  0           RESUME                   0

  1           LOAD_CONST               0 (0)
              LOAD_CONST               1 (None)
              IMPORT_NAME              0 (customtkinter)
              STORE_NAME               1 (ctk)

  2           LOAD_CONST               0 (0)
              LOAD_CONST               1 (None)
              IMPORT_NAME              2 (tkinter)
              STORE_NAME               3 (tk)

  3           LOAD_CONST               0 (0)
              LOAD_CONST               2 (('filedialog',))
              IMPORT_NAME              2 (tkinter)
              IMPORT_FROM              4 (filedialog)
              STORE_NAME               4 (filedialog)
              POP_TOP

  4           LOAD_CONST               0 (0)
              LOAD_CONST               1 (None)
              IMPORT_NAME              5 (os)
              STORE_NAME               5 (os)

  5           LOAD_CONST               0 (0)
              LOAD_CONST               3 (('datetime',))
              IMPORT_NAME              6 (datetime)
              IMPORT_FROM              6 (datetime)
              STORE_NAME               6 (datetime)
              POP_TOP

  7           LOAD_BUILD_CLASS
              PUSH_NULL
              LOAD_CONST               4 (<code object RangeEditorFrame at 0x0000028A6B375A10, file "src\ui\config_sellos.py", line 7>)
              MAKE_FUNCTION
              LOAD_CONST               5 ('RangeEditorFrame')
              LOAD_NAME                1 (ctk)
              LOAD_ATTR               14 (CTkFrame)
              CALL                     3
              STORE_NAME               8 (RangeEditorFrame)

 76           LOAD_BUILD_CLASS
              PUSH_NULL
              LOAD_CONST               6 (<code object ConfigSello1Window at 0x0000028A6B3761F0, file "src\ui\config_sellos.py", line 76>)
              MAKE_FUNCTION
              LOAD_CONST               7 ('ConfigSello1Window')
              LOAD_NAME                1 (ctk)
              LOAD_ATTR               18 (CTkToplevel)
              CALL                     3
              STORE_NAME              10 (ConfigSello1Window)

170           LOAD_BUILD_CLASS
              PUSH_NULL
              LOAD_CONST               8 (<code object ConfigSello2Window at 0x0000028A6B376670, file "src\ui\config_sellos.py", line 170>)
              MAKE_FUNCTION
              LOAD_CONST               9 ('ConfigSello2Window')
              LOAD_NAME                1 (ctk)
              LOAD_ATTR               18 (CTkToplevel)
              CALL                     3
              STORE_NAME              11 (ConfigSello2Window)
              RETURN_CONST             1 (None)

Disassembly of <code object RangeEditorFrame at 0x0000028A6B375A10, file "src\ui\config_sellos.py", line 7>:
  --           MAKE_CELL                0 (__class__)

   7           RESUME                   0
               LOAD_NAME                0 (__name__)
               STORE_NAME               1 (__module__)
               LOAD_CONST               0 ('RangeEditorFrame')
               STORE_NAME               2 (__qualname__)
               LOAD_CONST               1 (7)
               STORE_NAME               3 (__firstlineno__)

   8           LOAD_CONST               9 ((None, False))
               LOAD_FAST                0 (__class__)
               BUILD_TUPLE              1
               LOAD_CONST               2 (<code object __init__ at 0x0000028A6B3D1290, file "src\ui\config_sellos.py", line 8>)
               MAKE_FUNCTION
               SET_FUNCTION_ATTRIBUTE   8 (closure)
               SET_FUNCTION_ATTRIBUTE   1 (defaults)
               STORE_NAME               4 (__init__)

  30           LOAD_CONST              10 (('', ''))
               LOAD_CONST               3 (<code object add_rango at 0x0000028A6B3D2AA0, file "src\ui\config_sellos.py", line 30>)
               MAKE_FUNCTION
               SET_FUNCTION_ATTRIBUTE   1 (defaults)
               STORE_NAME               5 (add_rango)

  52           LOAD_CONST               4 (<code object del_rango at 0x0000028A6B3ACB70, file "src\ui\config_sellos.py", line 52>)
               MAKE_FUNCTION
               STORE_NAME               6 (del_rango)

  57           LOAD_CONST               5 (<code object get_ranges at 0x0000028A6B16E170, file "src\ui\config_sellos.py", line 57>)
               MAKE_FUNCTION
               STORE_NAME               7 (get_ranges)

  66           LOAD_CONST               6 (<code object get_exceptions at 0x0000028A6B3AD2F0, file "src\ui\config_sellos.py", line 66>)
               MAKE_FUNCTION
               STORE_NAME               8 (get_exceptions)

  71           LOAD_CONST               7 (<code object set_exceptions at 0x0000028A6B3AD430, file "src\ui\config_sellos.py", line 71>)
               MAKE_FUNCTION
               STORE_NAME               9 (set_exceptions)
               LOAD_CONST               8 (('entry_exceptions', 'frame_list', 'lista_entradas_rangos', 'show_exceptions'))
               STORE_NAME              10 (__static_attributes__)
               LOAD_FAST                0 (__class__)
               COPY                     1
               STORE_NAME              11 (__classcell__)
               RETURN_VALUE

Disassembly of <code object __init__ at 0x0000028A6B3D1290, file "src\ui\config_sellos.py", line 8>:
  --           COPY_FREE_VARS           1

   8           RESUME                   0

   9           LOAD_GLOBAL              0 (super)
               LOAD_DEREF               6 (__class__)
               LOAD_FAST                0 (self)
               LOAD_SUPER_ATTR          5 (__init__ + NULL|self)
               LOAD_FAST                1 (parent)
               LOAD_CONST               1 ('transparent')
               LOAD_CONST               2 (('fg_color',))
               CALL_KW                  2
               POP_TOP

  10           LOAD_FAST_LOAD_FAST     48 (show_exceptions, self)
               STORE_ATTR               2 (show_exceptions)

  11           BUILD_LIST               0
               LOAD_FAST                0 (self)
               STORE_ATTR               3 (lista_entradas_rangos)

  13           LOAD_GLOBAL              8 (ctk)
               LOAD_ATTR               10 (CTkFrame)
               PUSH_NULL
               LOAD_FAST                0 (self)
               LOAD_CONST               1 ('transparent')
               LOAD_CONST               2 (('fg_color',))
               CALL_KW                  2
               LOAD_FAST                0 (self)
               STORE_ATTR               6 (frame_list)

  14           LOAD_FAST                0 (self)
               LOAD_ATTR               12 (frame_list)
               LOAD_ATTR               15 (pack + NULL|self)
               LOAD_CONST               3 ('x')
               LOAD_CONST               4 (2)
               LOAD_CONST               5 (('fill', 'pady'))
               CALL_KW                  2
               POP_TOP

  16           LOAD_GLOBAL              8 (ctk)
               LOAD_ATTR               16 (CTkButton)
               PUSH_NULL
               LOAD_FAST                0 (self)
               LOAD_CONST               6 ('+ Nuevo Rango')
               LOAD_CONST               1 ('transparent')
               LOAD_CONST               7 (1)
               LOAD_FAST                0 (self)
               LOAD_ATTR               18 (add_rango)
               LOAD_CONST               8 (('text', 'fg_color', 'border_width', 'command'))
               CALL_KW                  5
               STORE_FAST               4 (btn_add)

  17           LOAD_FAST                4 (btn_add)
               LOAD_ATTR               15 (pack + NULL|self)
               LOAD_CONST               9 (5)
               LOAD_CONST              10 ('w')
               LOAD_CONST              11 (('pady', 'anchor'))
               CALL_KW                  2
               POP_TOP

  19           LOAD_FAST                0 (self)
               LOAD_ATTR                4 (show_exceptions)
               TO_BOOL
               POP_JUMP_IF_FALSE       87 (to L1)

  20           LOAD_GLOBAL              8 (ctk)
               LOAD_ATTR               20 (CTkLabel)
               PUSH_NULL
               LOAD_FAST                0 (self)
               LOAD_CONST              12 ('Páginas Excepción (Ej. 2, 5, 7-9):')
               LOAD_CONST              13 (('text',))
               CALL_KW                  2
               LOAD_ATTR               15 (pack + NULL|self)
               LOAD_CONST              10 ('w')
               LOAD_CONST              14 ((10, 0))
               LOAD_CONST              15 (('anchor', 'pady'))
               CALL_KW                  2
               POP_TOP

  21           LOAD_GLOBAL              8 (ctk)
               LOAD_ATTR               22 (CTkEntry)
               PUSH_NULL
               LOAD_FAST                0 (self)
               LOAD_CONST              16 ('Num. de páginas separadas por comas')
               LOAD_CONST              17 (('placeholder_text',))
               CALL_KW                  2
               LOAD_FAST                0 (self)
               STORE_ATTR              12 (entry_exceptions)

  22           LOAD_FAST                0 (self)
               LOAD_ATTR               24 (entry_exceptions)
               LOAD_ATTR               15 (pack + NULL|self)
               LOAD_CONST               3 ('x')
               LOAD_CONST               4 (2)
               LOAD_CONST               5 (('fill', 'pady'))
               CALL_KW                  2
               POP_TOP

  24   L1:     LOAD_FAST                2 (default_ranges)
               TO_BOOL
               POP_JUMP_IF_TRUE        28 (to L4)

  25           LOAD_FAST                0 (self)
               LOAD_ATTR               19 (add_rango + NULL|self)
               LOAD_CONST              18 ('1')
               LOAD_FAST                3 (show_exceptions)
               TO_BOOL
               POP_JUMP_IF_TRUE         2 (to L2)
               LOAD_CONST              18 ('1')
               JUMP_FORWARD             1 (to L3)
       L2:     LOAD_CONST              19 ('final')
       L3:     CALL                     2
               POP_TOP
               RETURN_CONST             0 (None)

  27   L4:     LOAD_FAST                2 (default_ranges)
               GET_ITER
       L5:     FOR_ITER                53 (to L6)
               STORE_FAST               5 (rng)

  28           LOAD_FAST                0 (self)
               LOAD_ATTR               19 (add_rango + NULL|self)
               LOAD_FAST                5 (rng)
               LOAD_ATTR               27 (get + NULL|self)
               LOAD_CONST              20 ('start')
               LOAD_CONST              21 ('')
               CALL                     2
               LOAD_FAST                5 (rng)
               LOAD_ATTR               27 (get + NULL|self)
               LOAD_CONST              22 ('end')
               LOAD_CONST              21 ('')
               CALL                     2
               CALL                     2
               POP_TOP
               JUMP_BACKWARD           55 (to L5)

  27   L6:     END_FOR
               POP_TOP
               RETURN_CONST             0 (None)

Disassembly of <code object add_rango at 0x0000028A6B3D2AA0, file "src\ui\config_sellos.py", line 30>:
  --           MAKE_CELL                0 (self)

  30           RESUME                   0

  31           LOAD_GLOBAL              0 (ctk)
               LOAD_ATTR                2 (CTkFrame)
               PUSH_NULL
               LOAD_DEREF               0 (self)
               LOAD_ATTR                4 (frame_list)
               LOAD_CONST               1 ('transparent')
               LOAD_CONST               2 (('fg_color',))
               CALL_KW                  2
               STORE_FAST               3 (f_rng)

  32           LOAD_FAST                3 (f_rng)
               LOAD_ATTR                7 (pack + NULL|self)
               LOAD_CONST               3 ('x')
               LOAD_CONST               4 (2)
               LOAD_CONST               5 (('fill', 'pady'))
               CALL_KW                  2
               POP_TOP

  34           LOAD_GLOBAL              0 (ctk)
               LOAD_ATTR                8 (CTkLabel)
               PUSH_NULL
               LOAD_FAST                3 (f_rng)
               LOAD_CONST               6 ('De pág:')
               LOAD_CONST               7 (('text',))
               CALL_KW                  2
               LOAD_ATTR               11 (grid + NULL|self)
               LOAD_CONST               8 (0)
               LOAD_CONST               8 (0)
               LOAD_CONST               9 ('w')
               LOAD_CONST               4 (2)
               LOAD_CONST              10 (('row', 'column', 'sticky', 'pady'))
               CALL_KW                  4
               POP_TOP

  35           LOAD_GLOBAL              0 (ctk)
               LOAD_ATTR               12 (CTkEntry)
               PUSH_NULL
               LOAD_FAST                3 (f_rng)
               LOAD_CONST              11 (45)
               LOAD_CONST              12 (('width',))
               CALL_KW                  2
               STORE_FAST               4 (entry_s)

  36           LOAD_FAST                4 (entry_s)
               LOAD_ATTR               11 (grid + NULL|self)
               LOAD_CONST               8 (0)
               LOAD_CONST              13 (1)
               LOAD_CONST               9 ('w')
               LOAD_CONST               4 (2)
               LOAD_CONST               4 (2)
               LOAD_CONST              14 (('row', 'column', 'sticky', 'padx', 'pady'))
               CALL_KW                  5
               POP_TOP

  37           LOAD_FAST                1 (def_start)
               TO_BOOL
               POP_JUMP_IF_FALSE       18 (to L1)
               LOAD_FAST                4 (entry_s)
               LOAD_ATTR               15 (insert + NULL|self)
               LOAD_CONST               8 (0)
               LOAD_FAST                1 (def_start)
               CALL                     2
               POP_TOP

  39   L1:     LOAD_GLOBAL              0 (ctk)
               LOAD_ATTR                8 (CTkLabel)
               PUSH_NULL
               LOAD_FAST                3 (f_rng)
               LOAD_CONST              15 ('a:')
               LOAD_CONST               7 (('text',))
               CALL_KW                  2
               LOAD_ATTR               11 (grid + NULL|self)
               LOAD_CONST               8 (0)
               LOAD_CONST               4 (2)
               LOAD_CONST               9 ('w')
               LOAD_CONST               4 (2)
               LOAD_CONST               4 (2)
               LOAD_CONST              14 (('row', 'column', 'sticky', 'padx', 'pady'))
               CALL_KW                  5
               POP_TOP

  40           LOAD_GLOBAL              0 (ctk)
               LOAD_ATTR               12 (CTkEntry)
               PUSH_NULL
               LOAD_FAST                3 (f_rng)
               LOAD_CONST              11 (45)
               LOAD_CONST              16 ('final')
               LOAD_CONST              17 (('width', 'placeholder_text'))
               CALL_KW                  3
               STORE_FAST               5 (entry_e)

  41           LOAD_FAST                5 (entry_e)
               LOAD_ATTR               11 (grid + NULL|self)
               LOAD_CONST               8 (0)
               LOAD_CONST              18 (3)
               LOAD_CONST               9 ('w')
               LOAD_CONST               4 (2)
               LOAD_CONST               4 (2)
               LOAD_CONST              14 (('row', 'column', 'sticky', 'padx', 'pady'))
               CALL_KW                  5
               POP_TOP

  42           LOAD_FAST                2 (def_end)
               TO_BOOL
               POP_JUMP_IF_FALSE       18 (to L2)
               LOAD_FAST                5 (entry_e)
               LOAD_ATTR               15 (insert + NULL|self)
               LOAD_CONST               8 (0)
               LOAD_FAST                2 (def_end)
               CALL                     2
               POP_TOP

  44   L2:     LOAD_FAST_LOAD_FAST     69 (entry_s, entry_e)
               BUILD_TUPLE              2
               STORE_FAST               6 (val_tuple)

  46           LOAD_GLOBAL              0 (ctk)
               LOAD_ATTR               16 (CTkButton)
               PUSH_NULL
               LOAD_FAST                3 (f_rng)
               LOAD_CONST              19 ('X')
               LOAD_CONST              20 (25)
               LOAD_CONST              21 ('red')
               LOAD_CONST              22 ('darkred')

  47           LOAD_FAST_LOAD_FAST     54 (f_rng, val_tuple)
               BUILD_TUPLE              2
               LOAD_FAST                0 (self)
               BUILD_TUPLE              1
               LOAD_CONST              23 (<code object <lambda> at 0x0000028A6B3584E0, file "src\ui\config_sellos.py", line 47>)
               MAKE_FUNCTION
               SET_FUNCTION_ATTRIBUTE   8 (closure)
               SET_FUNCTION_ATTRIBUTE   1 (defaults)

  46           LOAD_CONST              24 (('text', 'width', 'fg_color', 'hover_color', 'command'))
               CALL_KW                  6
               STORE_FAST               7 (btn_del)

  48           LOAD_FAST                7 (btn_del)
               LOAD_ATTR               11 (grid + NULL|self)
               LOAD_CONST               8 (0)
               LOAD_CONST              25 (4)
               LOAD_CONST              26 ((5, 0))
               LOAD_CONST              27 (('row', 'column', 'padx'))
               CALL_KW                  3
               POP_TOP

  50           LOAD_DEREF               0 (self)
               LOAD_ATTR               18 (lista_entradas_rangos)
               LOAD_ATTR               21 (append + NULL|self)
               LOAD_FAST                6 (val_tuple)
               CALL                     1
               POP_TOP
               RETURN_CONST             0 (None)

Disassembly of <code object <lambda> at 0x0000028A6B3584E0, file "src\ui\config_sellos.py", line 47>:
  --           COPY_FREE_VARS           1

  47           RESUME                   0
               LOAD_DEREF               2 (self)
               LOAD_ATTR                1 (del_rango + NULL|self)
               LOAD_FAST_LOAD_FAST      1 (f, e)
               CALL                     2
               RETURN_VALUE

Disassembly of <code object del_rango at 0x0000028A6B3ACB70, file "src\ui\config_sellos.py", line 52>:
 52           RESUME                   0

 53           LOAD_FAST_LOAD_FAST     32 (obj_tuple, self)
              LOAD_ATTR                0 (lista_entradas_rangos)
              CONTAINS_OP              0
              POP_JUMP_IF_FALSE       27 (to L1)

 54           LOAD_FAST                0 (self)
              LOAD_ATTR                0 (lista_entradas_rangos)
              LOAD_ATTR                3 (remove + NULL|self)
              LOAD_FAST                2 (obj_tuple)
              CALL                     1
              POP_TOP

 55   L1:     LOAD_FAST                1 (frame)
              LOAD_ATTR                5 (destroy + NULL|self)
              CALL                     0
              POP_TOP
              RETURN_CONST             0 (None)

Disassembly of <code object get_ranges at 0x0000028A6B16E170, file "src\ui\config_sellos.py", line 57>:
 57           RESUME                   0

 58           BUILD_LIST               0
              STORE_FAST               1 (ranges)

 59           LOAD_FAST                0 (self)
              LOAD_ATTR                0 (lista_entradas_rangos)
              GET_ITER
      L1:     FOR_ITER               102 (to L5)
              UNPACK_SEQUENCE          2
              STORE_FAST_STORE_FAST   35 (e_start, e_end)

 60           LOAD_FAST                2 (e_start)
              LOAD_ATTR                3 (get + NULL|self)
              CALL                     0
              LOAD_ATTR                5 (strip + NULL|self)
              CALL                     0
              STORE_FAST               4 (r_start)

 61           LOAD_FAST                3 (e_end)
              LOAD_ATTR                3 (get + NULL|self)
              CALL                     0
              LOAD_ATTR                5 (strip + NULL|self)
              CALL                     0
              STORE_FAST               5 (r_end)

 62           LOAD_FAST                4 (r_start)
              TO_BOOL
              POP_JUMP_IF_TRUE         2 (to L2)
              JUMP_BACKWARD           74 (to L1)

 63   L2:     LOAD_FAST                1 (ranges)
              LOAD_ATTR                7 (append + NULL|self)
              LOAD_FAST_LOAD_FAST     69 (r_start, r_end)
              TO_BOOL
              POP_JUMP_IF_FALSE        2 (to L3)
              LOAD_FAST                5 (r_end)
              JUMP_FORWARD             1 (to L4)
      L3:     LOAD_CONST               1 ('final')
      L4:     LOAD_CONST               2 (('start', 'end'))
              BUILD_CONST_KEY_MAP      2
              CALL                     1
              POP_TOP
              JUMP_BACKWARD          104 (to L1)

 59   L5:     END_FOR
              POP_TOP

 64           LOAD_FAST                1 (ranges)
              RETURN_VALUE

Disassembly of <code object get_exceptions at 0x0000028A6B3AD2F0, file "src\ui\config_sellos.py", line 66>:
 66           RESUME                   0

 67           LOAD_FAST                0 (self)
              LOAD_ATTR                0 (show_exceptions)
              TO_BOOL
              POP_JUMP_IF_FALSE       40 (to L1)

 68           LOAD_FAST                0 (self)
              LOAD_ATTR                2 (entry_exceptions)
              LOAD_ATTR                5 (get + NULL|self)
              CALL                     0
              LOAD_ATTR                7 (strip + NULL|self)
              CALL                     0
              RETURN_VALUE

 69   L1:     RETURN_CONST             1 ('')

Disassembly of <code object set_exceptions at 0x0000028A6B3AD430, file "src\ui\config_sellos.py", line 71>:
 71           RESUME                   0

 72           LOAD_FAST                0 (self)
              LOAD_ATTR                0 (show_exceptions)
              TO_BOOL
              POP_JUMP_IF_FALSE       37 (to L2)
              LOAD_FAST                1 (text)
              TO_BOOL
              POP_JUMP_IF_FALSE       29 (to L1)

 73           LOAD_FAST                0 (self)
              LOAD_ATTR                2 (entry_exceptions)
              LOAD_ATTR                5 (insert + NULL|self)
              LOAD_CONST               1 (0)
              LOAD_FAST                1 (text)
              CALL                     2
              POP_TOP
              RETURN_CONST             0 (None)

 72   L1:     RETURN_CONST             0 (None)
      L2:     RETURN_CONST             0 (None)

Disassembly of <code object ConfigSello1Window at 0x0000028A6B3761F0, file "src\ui\config_sellos.py", line 76>:
  --           MAKE_CELL                0 (__class__)

  76           RESUME                   0
               LOAD_NAME                0 (__name__)
               STORE_NAME               1 (__module__)
               LOAD_CONST               0 ('ConfigSello1Window')
               STORE_NAME               2 (__qualname__)
               LOAD_CONST               1 (76)
               STORE_NAME               3 (__firstlineno__)

  77           LOAD_CONST              10 ((None,))
               LOAD_FAST                0 (__class__)
               BUILD_TUPLE              1
               LOAD_CONST               2 (<code object __init__ at 0x0000028A6B171F30, file "src\ui\config_sellos.py", line 77>)
               MAKE_FUNCTION
               SET_FUNCTION_ATTRIBUTE   8 (closure)
               SET_FUNCTION_ATTRIBUTE   1 (defaults)
               STORE_NAME               4 (__init__)

  91           LOAD_CONST               3 (<code object setup_ui at 0x0000028A6B421FF0, file "src\ui\config_sellos.py", line 91>)
               MAKE_FUNCTION
               STORE_NAME               5 (setup_ui)

 124           LOAD_CONST               4 (<code object load_data at 0x0000028A6B424180, file "src\ui\config_sellos.py", line 124>)
               MAKE_FUNCTION
               STORE_NAME               6 (load_data)

 137           LOAD_CONST               5 (<code object load_signature at 0x0000028A6B11D420, file "src\ui\config_sellos.py", line 137>)
               MAKE_FUNCTION
               STORE_NAME               7 (load_signature)

 145           LOAD_CONST               6 (<code object edit_layout at 0x0000028A6B12A230, file "src\ui\config_sellos.py", line 145>)
               MAKE_FUNCTION
               STORE_NAME               8 (edit_layout)

 156           LOAD_CONST               7 (<code object preview_stamp at 0x0000028A6B3B1DE0, file "src\ui\config_sellos.py", line 156>)
               MAKE_FUNCTION
               STORE_NAME               9 (preview_stamp)

 161           LOAD_CONST               8 (<code object on_close at 0x0000028A6B3F3CC0, file "src\ui\config_sellos.py", line 161>)
               MAKE_FUNCTION
               STORE_NAME              10 (on_close)
               LOAD_CONST               9 (('config_manager', 'entry_scale', 'f_firma', 'lbl_sig_path', 'main_tab', 'on_close_callback', 'range_editor'))
               STORE_NAME              11 (__static_attributes__)
               LOAD_FAST                0 (__class__)
               COPY                     1
               STORE_NAME              12 (__classcell__)
               RETURN_VALUE

Disassembly of <code object __init__ at 0x0000028A6B171F30, file "src\ui\config_sellos.py", line 77>:
  --           COPY_FREE_VARS           1

  77           RESUME                   0

  78           LOAD_GLOBAL              0 (super)
               LOAD_DEREF               4 (__class__)
               LOAD_FAST                0 (self)
               LOAD_SUPER_ATTR          5 (__init__ + NULL|self)
               LOAD_FAST                1 (parent)
               CALL                     1
               POP_TOP

  79           LOAD_FAST                0 (self)
               LOAD_ATTR                5 (title + NULL|self)
               LOAD_CONST               1 ('Configuración Sello 1 (Carátula)')
               CALL                     1
               POP_TOP

  80           LOAD_FAST                0 (self)
               LOAD_ATTR                7 (geometry + NULL|self)
               LOAD_CONST               2 ('450x550')
               CALL                     1
               POP_TOP

  81           LOAD_FAST_LOAD_FAST     16 (parent, self)
               STORE_ATTR               4 (main_tab)

  82           LOAD_FAST_LOAD_FAST     32 (config_manager, self)
               STORE_ATTR               5 (config_manager)

  83           LOAD_FAST_LOAD_FAST     48 (on_close_callback, self)
               STORE_ATTR               6 (on_close_callback)

  85           LOAD_FAST                0 (self)
               LOAD_ATTR               15 (attributes + NULL|self)
               LOAD_CONST               3 ('-topmost')
               LOAD_CONST               4 (True)
               CALL                     2
               POP_TOP

  86           LOAD_FAST                0 (self)
               LOAD_ATTR               17 (protocol + NULL|self)
               LOAD_CONST               5 ('WM_DELETE_WINDOW')
               LOAD_FAST                0 (self)
               LOAD_ATTR               18 (on_close)
               CALL                     2
               POP_TOP

  88           LOAD_FAST                0 (self)
               LOAD_ATTR               21 (setup_ui + NULL|self)
               CALL                     0
               POP_TOP

  89           LOAD_FAST                0 (self)
               LOAD_ATTR               23 (load_data + NULL|self)
               CALL                     0
               POP_TOP
               RETURN_CONST             0 (None)

Disassembly of <code object setup_ui at 0x0000028A6B421FF0, file "src\ui\config_sellos.py", line 91>:
 91           RESUME                   0

 92           LOAD_FAST                0 (self)
              LOAD_ATTR                1 (grid_columnconfigure + NULL|self)
              LOAD_CONST               1 (0)
              LOAD_CONST               2 (1)
              LOAD_CONST               3 (('weight',))
              CALL_KW                  2
              POP_TOP

 93           LOAD_FAST                0 (self)
              LOAD_ATTR                3 (grid_rowconfigure + NULL|self)
              LOAD_CONST               4 (2)
              LOAD_CONST               2 (1)
              LOAD_CONST               3 (('weight',))
              CALL_KW                  2
              POP_TOP

 95           LOAD_GLOBAL              4 (ctk)
              LOAD_ATTR                6 (CTkFrame)
              PUSH_NULL
              LOAD_FAST                0 (self)
              LOAD_CONST               5 ('transparent')
              LOAD_CONST               6 (('fg_color',))
              CALL_KW                  2
              STORE_FAST               1 (f_top)

 96           LOAD_FAST                1 (f_top)
              LOAD_ATTR                9 (grid + NULL|self)
              LOAD_CONST               1 (0)
              LOAD_CONST               1 (0)
              LOAD_CONST               7 ('ew')
              LOAD_CONST               8 (20)
              LOAD_CONST               9 (10)
              LOAD_CONST              10 (('row', 'column', 'sticky', 'padx', 'pady'))
              CALL_KW                  5
              POP_TOP

 98           LOAD_GLOBAL              4 (ctk)
              LOAD_ATTR               10 (CTkLabel)
              PUSH_NULL
              LOAD_FAST                1 (f_top)
              LOAD_CONST              11 ('Escala (%):')
              LOAD_CONST              12 (('text',))
              CALL_KW                  2
              LOAD_ATTR                9 (grid + NULL|self)
              LOAD_CONST               2 (1)
              LOAD_CONST               1 (0)
              LOAD_CONST              13 ('w')
              LOAD_CONST              14 (5)
              LOAD_CONST              15 (('row', 'column', 'sticky', 'pady'))
              CALL_KW                  4
              POP_TOP

 99           LOAD_GLOBAL              4 (ctk)
              LOAD_ATTR               12 (CTkEntry)
              PUSH_NULL
              LOAD_FAST                1 (f_top)
              LOAD_CONST              16 (60)
              LOAD_CONST              17 (('width',))
              CALL_KW                  2
              LOAD_FAST                0 (self)
              STORE_ATTR               7 (entry_scale)

100           LOAD_FAST                0 (self)
              LOAD_ATTR               14 (entry_scale)
              LOAD_ATTR                9 (grid + NULL|self)
              LOAD_CONST               2 (1)
              LOAD_CONST               2 (1)
              LOAD_CONST              13 ('w')
              LOAD_CONST               9 (10)
              LOAD_CONST              14 (5)
              LOAD_CONST              10 (('row', 'column', 'sticky', 'padx', 'pady'))
              CALL_KW                  5
              POP_TOP

102           LOAD_GLOBAL              4 (ctk)
              LOAD_ATTR               10 (CTkLabel)
              PUSH_NULL
              LOAD_FAST                0 (self)
              LOAD_CONST              18 ('Rangos de Páginas para aplicar este sello:')
              LOAD_GLOBAL              4 (ctk)
              LOAD_ATTR               16 (CTkFont)
              PUSH_NULL
              LOAD_CONST              19 ('bold')
              LOAD_CONST               3 (('weight',))
              CALL_KW                  1
              LOAD_CONST              20 (('text', 'font'))
              CALL_KW                  3
              LOAD_ATTR                9 (grid + NULL|self)
              LOAD_CONST               2 (1)
              LOAD_CONST               1 (0)
              LOAD_CONST              13 ('w')
              LOAD_CONST               8 (20)
              LOAD_CONST              21 ((10, 0))
              LOAD_CONST              10 (('row', 'column', 'sticky', 'padx', 'pady'))
              CALL_KW                  5
              POP_TOP

104           LOAD_GLOBAL             19 (RangeEditorFrame + NULL)
              LOAD_FAST                0 (self)
              LOAD_CONST              22 (False)
              LOAD_CONST              23 (('show_exceptions',))
              CALL_KW                  2
              LOAD_FAST                0 (self)
              STORE_ATTR              10 (range_editor)

105           LOAD_FAST                0 (self)
              LOAD_ATTR               20 (range_editor)
              LOAD_ATTR                9 (grid + NULL|self)
              LOAD_CONST               4 (2)
              LOAD_CONST               1 (0)
              LOAD_CONST              24 ('nsew')
              LOAD_CONST               8 (20)
              LOAD_CONST              14 (5)
              LOAD_CONST              10 (('row', 'column', 'sticky', 'padx', 'pady'))
              CALL_KW                  5
              POP_TOP

107           LOAD_GLOBAL              4 (ctk)
              LOAD_ATTR                6 (CTkFrame)
              PUSH_NULL
              LOAD_FAST                0 (self)
              CALL                     1
              LOAD_FAST                0 (self)
              STORE_ATTR              11 (f_firma)

108           LOAD_FAST                0 (self)
              LOAD_ATTR               22 (f_firma)
              LOAD_ATTR                9 (grid + NULL|self)
              LOAD_CONST              25 (3)
              LOAD_CONST               1 (0)
              LOAD_CONST               7 ('ew')
              LOAD_CONST               8 (20)
              LOAD_CONST               9 (10)
              LOAD_CONST              10 (('row', 'column', 'sticky', 'padx', 'pady'))
              CALL_KW                  5
              POP_TOP

110           LOAD_GLOBAL              4 (ctk)
              LOAD_ATTR               24 (CTkButton)
              PUSH_NULL
              LOAD_FAST                0 (self)
              LOAD_ATTR               22 (f_firma)
              LOAD_CONST              26 ('Seleccionar Firma PNG')
              LOAD_FAST                0 (self)
              LOAD_ATTR               26 (load_signature)
              LOAD_CONST              27 (('text', 'command'))
              CALL_KW                  3
              STORE_FAST               2 (btn_load_sig)

111           LOAD_FAST                2 (btn_load_sig)
              LOAD_ATTR               29 (pack + NULL|self)
              LOAD_CONST              14 (5)
              LOAD_CONST              28 (('pady',))
              CALL_KW                  1
              POP_TOP

112           LOAD_GLOBAL              4 (ctk)
              LOAD_ATTR               10 (CTkLabel)
              PUSH_NULL
              LOAD_FAST                0 (self)
              LOAD_ATTR               22 (f_firma)
              LOAD_CONST              29 ('Sin firma')
              LOAD_CONST              30 ('gray')
              LOAD_CONST              31 (('text', 'text_color'))
              CALL_KW                  3
              LOAD_FAST                0 (self)
              STORE_ATTR              15 (lbl_sig_path)

113           LOAD_FAST                0 (self)
              LOAD_ATTR               30 (lbl_sig_path)
              LOAD_ATTR               29 (pack + NULL|self)
              CALL                     0
              POP_TOP

115           LOAD_GLOBAL              4 (ctk)
              LOAD_ATTR               24 (CTkButton)
              PUSH_NULL
              LOAD_FAST                0 (self)
              LOAD_ATTR               22 (f_firma)
              LOAD_CONST              32 ('Editar Layout Sello')
              LOAD_FAST                0 (self)
              LOAD_ATTR               32 (edit_layout)
              LOAD_CONST              27 (('text', 'command'))
              CALL_KW                  3
              STORE_FAST               3 (btn_edit_layout)

116           LOAD_FAST                3 (btn_edit_layout)
              LOAD_ATTR               29 (pack + NULL|self)
              LOAD_CONST              14 (5)
              LOAD_CONST              28 (('pady',))
              CALL_KW                  1
              POP_TOP

118           LOAD_GLOBAL              4 (ctk)
              LOAD_ATTR               24 (CTkButton)
              PUSH_NULL
              LOAD_FAST                0 (self)
              LOAD_ATTR               22 (f_firma)
              LOAD_CONST              33 ('👁️ Previsualizar Sello')
              LOAD_FAST                0 (self)
              LOAD_ATTR               34 (preview_stamp)
              LOAD_CONST              27 (('text', 'command'))
              CALL_KW                  3
              STORE_FAST               4 (btn_preview)

119           LOAD_FAST                4 (btn_preview)
              LOAD_ATTR               29 (pack + NULL|self)
              LOAD_CONST              14 (5)
              LOAD_CONST              28 (('pady',))
              CALL_KW                  1
              POP_TOP

121           LOAD_GLOBAL              4 (ctk)
              LOAD_ATTR               24 (CTkButton)
              PUSH_NULL
              LOAD_FAST                0 (self)
              LOAD_CONST              34 ('Guardar y Cerrar')
              LOAD_FAST                0 (self)
              LOAD_ATTR               36 (on_close)
              LOAD_CONST              27 (('text', 'command'))
              CALL_KW                  3
              STORE_FAST               5 (btn_save)

122           LOAD_FAST                5 (btn_save)
              LOAD_ATTR                9 (grid + NULL|self)
              LOAD_CONST              35 (4)
              LOAD_CONST               1 (0)
              LOAD_CONST               9 (10)
              LOAD_CONST              36 (('row', 'column', 'pady'))
              CALL_KW                  3
              POP_TOP
              RETURN_CONST             0 (None)

Disassembly of <code object load_data at 0x0000028A6B424180, file "src\ui\config_sellos.py", line 124>:
124           RESUME                   0

125           LOAD_FAST                0 (self)
              LOAD_ATTR                0 (entry_scale)
              LOAD_ATTR                3 (insert + NULL|self)
              LOAD_CONST               1 (0)
              LOAD_GLOBAL              5 (str + NULL)
              LOAD_FAST                0 (self)
              LOAD_ATTR                6 (config_manager)
              LOAD_ATTR                9 (get + NULL|self)
              LOAD_CONST               2 ('cover_scale')
              LOAD_CONST               3 ('100')
              CALL                     2
              CALL                     1
              CALL                     2
              POP_TOP

126           LOAD_FAST                0 (self)
              LOAD_ATTR                6 (config_manager)
              LOAD_ATTR                9 (get + NULL|self)
              LOAD_CONST               4 ('cover_ranges')
              LOAD_CONST               5 ('1')
              LOAD_CONST               5 ('1')
              LOAD_CONST               6 (('start', 'end'))
              BUILD_CONST_KEY_MAP      2
              BUILD_LIST               1
              CALL                     2
              STORE_FAST               1 (ranges)

128           LOAD_FAST                0 (self)
              LOAD_ATTR               10 (range_editor)
              LOAD_ATTR               12 (frame_list)
              LOAD_ATTR               15 (winfo_children + NULL|self)
              CALL                     0
              GET_ITER
      L1:     FOR_ITER                18 (to L2)
              STORE_FAST_LOAD_FAST    34 (w, w)
              LOAD_ATTR               17 (destroy + NULL|self)
              CALL                     0
              POP_TOP
              JUMP_BACKWARD           20 (to L1)
      L2:     END_FOR
              POP_TOP

129           LOAD_FAST                0 (self)
              LOAD_ATTR               10 (range_editor)
              LOAD_ATTR               18 (lista_entradas_rangos)
              LOAD_ATTR               21 (clear + NULL|self)
              CALL                     0
              POP_TOP

130           LOAD_FAST                1 (ranges)
              GET_ITER
      L3:     FOR_ITER                63 (to L4)
              STORE_FAST               3 (rng)

131           LOAD_FAST                0 (self)
              LOAD_ATTR               10 (range_editor)
              LOAD_ATTR               23 (add_rango + NULL|self)
              LOAD_FAST                3 (rng)
              LOAD_ATTR                9 (get + NULL|self)
              LOAD_CONST               7 ('start')
              LOAD_CONST               8 ('')
              CALL                     2
              LOAD_FAST                3 (rng)
              LOAD_ATTR                9 (get + NULL|self)
              LOAD_CONST               9 ('end')
              LOAD_CONST               8 ('')
              CALL                     2
              CALL                     2
              POP_TOP
              JUMP_BACKWARD           65 (to L3)

130   L4:     END_FOR
              POP_TOP

133           LOAD_FAST                0 (self)
              LOAD_ATTR                6 (config_manager)
              LOAD_ATTR                9 (get + NULL|self)
              LOAD_CONST              10 ('signature_path')
              LOAD_CONST               8 ('')
              CALL                     2
              STORE_FAST               4 (sig_path)

134           LOAD_FAST                4 (sig_path)
              TO_BOOL
              POP_JUMP_IF_FALSE       69 (to L6)
              LOAD_GLOBAL             24 (os)
              LOAD_ATTR               26 (path)
              LOAD_ATTR               29 (exists + NULL|self)
              LOAD_FAST                4 (sig_path)
              CALL                     1
              TO_BOOL
              POP_JUMP_IF_FALSE       32 (to L5)

135           LOAD_FAST                0 (self)
              LOAD_ATTR               30 (lbl_sig_path)
              LOAD_ATTR               33 (configure + NULL|self)
              LOAD_CONST              11 ('...')
              LOAD_FAST                4 (sig_path)
              LOAD_CONST              12 (-25)
              LOAD_CONST               0 (None)
              BINARY_SLICE
              FORMAT_SIMPLE
              BUILD_STRING             2
              LOAD_CONST              13 (('text',))
              CALL_KW                  1
              POP_TOP
              RETURN_CONST             0 (None)

134   L5:     RETURN_CONST             0 (None)
      L6:     RETURN_CONST             0 (None)

Disassembly of <code object load_signature at 0x0000028A6B11D420, file "src\ui\config_sellos.py", line 137>:
137           RESUME                   0

138           LOAD_FAST                0 (self)
              LOAD_ATTR                1 (attributes + NULL|self)
              LOAD_CONST               1 ('-topmost')
              LOAD_CONST               2 (False)
              CALL                     2
              POP_TOP

139           LOAD_GLOBAL              2 (filedialog)
              LOAD_ATTR                4 (askopenfilename)
              PUSH_NULL
              LOAD_CONST               3 ('Seleccionar Firma PNG')
              LOAD_CONST               4 (('PNG transparent', '*.png'))
              BUILD_LIST               1
              LOAD_CONST               5 (('title', 'filetypes'))
              CALL_KW                  2
              STORE_FAST               1 (path)

140           LOAD_FAST                0 (self)
              LOAD_ATTR                1 (attributes + NULL|self)
              LOAD_CONST               1 ('-topmost')
              LOAD_CONST               6 (True)
              CALL                     2
              POP_TOP

141           LOAD_FAST                1 (path)
              TO_BOOL
              POP_JUMP_IF_FALSE       60 (to L1)

142           LOAD_FAST                0 (self)
              LOAD_ATTR                6 (config_manager)
              LOAD_ATTR                9 (set + NULL|self)
              LOAD_CONST               7 ('signature_path')
              LOAD_FAST                1 (path)
              CALL                     2
              POP_TOP

143           LOAD_FAST                0 (self)
              LOAD_ATTR               10 (lbl_sig_path)
              LOAD_ATTR               13 (configure + NULL|self)
              LOAD_CONST               8 ('...')
              LOAD_FAST                1 (path)
              LOAD_CONST               9 (-25)
              LOAD_CONST               0 (None)
              BINARY_SLICE
              FORMAT_SIMPLE
              BUILD_STRING             2
              LOAD_CONST              10 (('text',))
              CALL_KW                  1
              POP_TOP
              RETURN_CONST             0 (None)

141   L1:     RETURN_CONST             0 (None)

Disassembly of <code object edit_layout at 0x0000028A6B12A230, file "src\ui\config_sellos.py", line 145>:
145           RESUME                   0

146           LOAD_CONST               1 (0)
              LOAD_CONST               2 (('LayoutEditorWindow',))
              IMPORT_NAME              0 (src.ui.layout_editor)
              IMPORT_FROM              1 (LayoutEditorWindow)
              STORE_FAST               1 (LayoutEditorWindow)
              POP_TOP

147           LOAD_FAST                0 (self)
              LOAD_ATTR                4 (main_tab)
              LOAD_ATTR                7 (get_resource_path + NULL|self)
              LOAD_CONST               3 ('assets/plantilla_caratula.png')
              CALL                     1
              STORE_FAST               2 (base_template)

148           LOAD_GLOBAL              8 (os)
              LOAD_ATTR               10 (path)
              LOAD_ATTR               13 (exists + NULL|self)
              LOAD_FAST                2 (base_template)
              CALL                     1
              TO_BOOL
              POP_JUMP_IF_TRUE        65 (to L1)

149           LOAD_FAST                0 (self)
              LOAD_ATTR               15 (attributes + NULL|self)
              LOAD_CONST               4 ('-topmost')
              LOAD_CONST               5 (False)
              CALL                     2
              POP_TOP

150           LOAD_CONST               1 (0)
              LOAD_CONST               0 (None)
              IMPORT_NAME              8 (tkinter.messagebox)
              IMPORT_FROM              9 (messagebox)
              STORE_FAST               3 (messagebox)
              POP_TOP

151           LOAD_FAST                3 (messagebox)
              LOAD_ATTR               21 (showwarning + NULL|self)
              LOAD_CONST               6 ('Atención')
              LOAD_CONST               7 ('No se encontró la plantilla default en ')
              LOAD_FAST                2 (base_template)
              FORMAT_SIMPLE
              LOAD_CONST               8 ('.')
              BUILD_STRING             3
              CALL                     2
              POP_TOP

152           LOAD_FAST                0 (self)
              LOAD_ATTR               15 (attributes + NULL|self)
              LOAD_CONST               4 ('-topmost')
              LOAD_CONST               9 (True)
              CALL                     2
              POP_TOP

153           RETURN_CONST             0 (None)

154   L1:     LOAD_FAST                1 (LayoutEditorWindow)
              PUSH_NULL
              LOAD_FAST_LOAD_FAST      0 (self, self)
              LOAD_ATTR               22 (config_manager)
              LOAD_FAST                2 (base_template)
              CALL                     3
              POP_TOP
              RETURN_CONST             0 (None)

Disassembly of <code object preview_stamp at 0x0000028A6B3B1DE0, file "src\ui\config_sellos.py", line 156>:
156           RESUME                   0

158           LOAD_GLOBAL              1 (int + NULL)
              LOAD_FAST                0 (self)
              LOAD_ATTR                2 (entry_scale)
              LOAD_ATTR                5 (get + NULL|self)
              CALL                     0
              COPY                     1
              TO_BOOL
              POP_JUMP_IF_TRUE         2 (to L1)
              POP_TOP
              LOAD_CONST               1 (100)
      L1:     CALL                     1
              LOAD_FAST                0 (self)
              LOAD_ATTR                6 (config_manager)
              LOAD_ATTR                8 (config)
              LOAD_CONST               2 ('cover_scale')
              STORE_SUBSCR

159           LOAD_FAST                0 (self)
              LOAD_ATTR               10 (main_tab)
              LOAD_ATTR               13 (action_preview_cover_stamp_from_popup + NULL|self)
              LOAD_FAST                0 (self)
              CALL                     1
              POP_TOP
              RETURN_CONST             0 (None)

Disassembly of <code object on_close at 0x0000028A6B3F3CC0, file "src\ui\config_sellos.py", line 161>:
161           RESUME                   0

162           LOAD_GLOBAL              1 (int + NULL)
              LOAD_FAST                0 (self)
              LOAD_ATTR                2 (entry_scale)
              LOAD_ATTR                5 (get + NULL|self)
              CALL                     0
              COPY                     1
              TO_BOOL
              POP_JUMP_IF_TRUE         2 (to L1)
              POP_TOP
              LOAD_CONST               1 (100)
      L1:     CALL                     1
              LOAD_FAST                0 (self)
              LOAD_ATTR                6 (config_manager)
              LOAD_ATTR                8 (config)
              LOAD_CONST               2 ('cover_scale')
              STORE_SUBSCR

163           LOAD_FAST                0 (self)
              LOAD_ATTR               10 (range_editor)
              LOAD_ATTR               13 (get_ranges + NULL|self)
              CALL                     0
              LOAD_FAST                0 (self)
              LOAD_ATTR                6 (config_manager)
              LOAD_ATTR                8 (config)
              LOAD_CONST               3 ('cover_ranges')
              STORE_SUBSCR

164           LOAD_FAST                0 (self)
              LOAD_ATTR                6 (config_manager)
              LOAD_ATTR               15 (save_config + NULL|self)
              CALL                     0
              POP_TOP

165           LOAD_FAST                0 (self)
              LOAD_ATTR               16 (on_close_callback)
              TO_BOOL
              POP_JUMP_IF_FALSE       16 (to L2)

166           LOAD_FAST                0 (self)
              LOAD_ATTR               17 (on_close_callback + NULL|self)
              CALL                     0
              POP_TOP

167   L2:     LOAD_FAST                0 (self)
              LOAD_ATTR               19 (destroy + NULL|self)
              CALL                     0
              POP_TOP
              RETURN_CONST             0 (None)

Disassembly of <code object ConfigSello2Window at 0x0000028A6B376670, file "src\ui\config_sellos.py", line 170>:
  --           MAKE_CELL                0 (__class__)

 170           RESUME                   0
               LOAD_NAME                0 (__name__)
               STORE_NAME               1 (__module__)
               LOAD_CONST               0 ('ConfigSello2Window')
               STORE_NAME               2 (__qualname__)
               LOAD_CONST               1 (170)
               STORE_NAME               3 (__firstlineno__)

 171           LOAD_CONST              10 ((None,))
               LOAD_FAST                0 (__class__)
               BUILD_TUPLE              1
               LOAD_CONST               2 (<code object __init__ at 0x0000028A6B4296A0, file "src\ui\config_sellos.py", line 171>)
               MAKE_FUNCTION
               SET_FUNCTION_ATTRIBUTE   8 (closure)
               SET_FUNCTION_ATTRIBUTE   1 (defaults)
               STORE_NAME               4 (__init__)

 185           LOAD_CONST               3 (<code object setup_ui at 0x0000028A6B46AB70, file "src\ui\config_sellos.py", line 185>)
               MAKE_FUNCTION
               STORE_NAME               5 (setup_ui)

 235           LOAD_CONST               4 (<code object update_mode_ui at 0x0000028A6B18A970, file "src\ui\config_sellos.py", line 235>)
               MAKE_FUNCTION
               STORE_NAME               6 (update_mode_ui)

 243           LOAD_CONST               5 (<code object load_custom_stamp at 0x0000028A6B11E9E0, file "src\ui\config_sellos.py", line 243>)
               MAKE_FUNCTION
               STORE_NAME               7 (load_custom_stamp)

 251           LOAD_CONST               6 (<code object load_signature at 0x0000028A6B11EBB0, file "src\ui\config_sellos.py", line 251>)
               MAKE_FUNCTION
               STORE_NAME               8 (load_signature)

 259           LOAD_CONST               7 (<code object load_data at 0x0000028A6B4265F0, file "src\ui\config_sellos.py", line 259>)
               MAKE_FUNCTION
               STORE_NAME               9 (load_data)

 281           LOAD_CONST               8 (<code object on_close at 0x0000028A6B46B4A0, file "src\ui\config_sellos.py", line 281>)
               MAKE_FUNCTION
               STORE_NAME              10 (on_close)
               LOAD_CONST               9 (('config_manager', 'entry_cip', 'entry_name', 'entry_scale', 'entry_tipo', 'f_custom', 'f_generate', 'lbl_custom_path', 'lbl_sig_path', 'mode_var', 'on_close_callback', 'range_editor'))
               STORE_NAME              11 (__static_attributes__)
               LOAD_FAST                0 (__class__)
               COPY                     1
               STORE_NAME              12 (__classcell__)
               RETURN_VALUE

Disassembly of <code object __init__ at 0x0000028A6B4296A0, file "src\ui\config_sellos.py", line 171>:
  --           COPY_FREE_VARS           1

 171           RESUME                   0

 172           LOAD_GLOBAL              0 (super)
               LOAD_DEREF               4 (__class__)
               LOAD_FAST                0 (self)
               LOAD_SUPER_ATTR          5 (__init__ + NULL|self)
               LOAD_FAST                1 (parent)
               CALL                     1
               POP_TOP

 173           LOAD_FAST                0 (self)
               LOAD_ATTR                5 (title + NULL|self)
               LOAD_CONST               1 ('Configuración Sello 2 (Cuerpo)')
               CALL                     1
               POP_TOP

 174           LOAD_FAST                0 (self)
               LOAD_ATTR                7 (geometry + NULL|self)
               LOAD_CONST               2 ('500x600')
               CALL                     1
               POP_TOP

 175           LOAD_FAST_LOAD_FAST     32 (config_manager, self)
               STORE_ATTR               4 (config_manager)

 176           LOAD_FAST_LOAD_FAST     48 (on_close_callback, self)
               STORE_ATTR               5 (on_close_callback)

 178           LOAD_FAST                0 (self)
               LOAD_ATTR               13 (attributes + NULL|self)
               LOAD_CONST               3 ('-topmost')
               LOAD_CONST               4 (True)
               CALL                     2
               POP_TOP

 179           LOAD_FAST                0 (self)
               LOAD_ATTR               15 (protocol + NULL|self)
               LOAD_CONST               5 ('WM_DELETE_WINDOW')
               LOAD_FAST                0 (self)
               LOAD_ATTR               16 (on_close)
               CALL                     2
               POP_TOP

 181           LOAD_FAST                0 (self)
               LOAD_ATTR               19 (setup_ui + NULL|self)
               CALL                     0
               POP_TOP

 182           LOAD_FAST                0 (self)
               LOAD_ATTR               21 (load_data + NULL|self)
               CALL                     0
               POP_TOP

 183           LOAD_FAST                0 (self)
               LOAD_ATTR               23 (update_mode_ui + NULL|self)
               CALL                     0
               POP_TOP
               RETURN_CONST             0 (None)

Disassembly of <code object setup_ui at 0x0000028A6B46AB70, file "src\ui\config_sellos.py", line 185>:
185           RESUME                   0

186           LOAD_FAST                0 (self)
              LOAD_ATTR                1 (grid_columnconfigure + NULL|self)
              LOAD_CONST               1 (0)
              LOAD_CONST               2 (1)
              LOAD_CONST               3 (('weight',))
              CALL_KW                  2
              POP_TOP

187           LOAD_FAST                0 (self)
              LOAD_ATTR                3 (grid_rowconfigure + NULL|self)
              LOAD_CONST               4 (2)
              LOAD_CONST               2 (1)
              LOAD_CONST               3 (('weight',))
              CALL_KW                  2
              POP_TOP

189           LOAD_GLOBAL              4 (ctk)
              LOAD_ATTR                6 (CTkFrame)
              PUSH_NULL
              LOAD_FAST                0 (self)
              LOAD_CONST               5 ('transparent')
              LOAD_CONST               6 (('fg_color',))
              CALL_KW                  2
              STORE_FAST               1 (f_top)

190           LOAD_FAST                1 (f_top)
              LOAD_ATTR                9 (grid + NULL|self)
              LOAD_CONST               1 (0)
              LOAD_CONST               1 (0)
              LOAD_CONST               7 ('ew')
              LOAD_CONST               8 (20)
              LOAD_CONST               9 (10)
              LOAD_CONST              10 (('row', 'column', 'sticky', 'padx', 'pady'))
              CALL_KW                  5
              POP_TOP

192           LOAD_GLOBAL             10 (tk)
              LOAD_ATTR               12 (StringVar)
              PUSH_NULL
              LOAD_FAST                0 (self)
              LOAD_ATTR               14 (config_manager)
              LOAD_ATTR               17 (get + NULL|self)
              LOAD_CONST              11 ('sello2_mode')
              LOAD_CONST              12 ('generate')
              CALL                     2
              LOAD_CONST              13 (('value',))
              CALL_KW                  1
              LOAD_FAST                0 (self)
              STORE_ATTR               9 (mode_var)

194           LOAD_GLOBAL              4 (ctk)
              LOAD_ATTR               20 (CTkRadioButton)
              PUSH_NULL
              LOAD_FAST                1 (f_top)
              LOAD_CONST              14 ('Generar Texto (Nombre y CIP)')
              LOAD_FAST                0 (self)
              LOAD_ATTR               18 (mode_var)
              LOAD_CONST              12 ('generate')
              LOAD_FAST                0 (self)
              LOAD_ATTR               22 (update_mode_ui)
              LOAD_CONST              15 (('text', 'variable', 'value', 'command'))
              CALL_KW                  5
              STORE_FAST               2 (r1)

195           LOAD_FAST                2 (r1)
              LOAD_ATTR                9 (grid + NULL|self)
              LOAD_CONST               1 (0)
              LOAD_CONST               1 (0)
              LOAD_CONST              16 ('w')
              LOAD_CONST              17 (5)
              LOAD_CONST              17 (5)
              LOAD_CONST              18 (('row', 'column', 'sticky', 'pady', 'padx'))
              CALL_KW                  5
              POP_TOP

196           LOAD_GLOBAL              4 (ctk)
              LOAD_ATTR               20 (CTkRadioButton)
              PUSH_NULL
              LOAD_FAST                1 (f_top)
              LOAD_CONST              19 ('Sello Pre-Diseñado (Solo Imagen)')
              LOAD_FAST                0 (self)
              LOAD_ATTR               18 (mode_var)
              LOAD_CONST              20 ('custom')
              LOAD_FAST                0 (self)
              LOAD_ATTR               22 (update_mode_ui)
              LOAD_CONST              15 (('text', 'variable', 'value', 'command'))
              CALL_KW                  5
              STORE_FAST               3 (r2)

197           LOAD_FAST                3 (r2)
              LOAD_ATTR                9 (grid + NULL|self)
              LOAD_CONST               1 (0)
              LOAD_CONST               2 (1)
              LOAD_CONST              16 ('w')
              LOAD_CONST              17 (5)
              LOAD_CONST              17 (5)
              LOAD_CONST              18 (('row', 'column', 'sticky', 'pady', 'padx'))
              CALL_KW                  5
              POP_TOP

199           LOAD_GLOBAL              4 (ctk)
              LOAD_ATTR                6 (CTkFrame)
              PUSH_NULL
              LOAD_FAST                1 (f_top)
              CALL                     1
              LOAD_FAST                0 (self)
              STORE_ATTR              12 (f_generate)

200           LOAD_FAST                0 (self)
              LOAD_ATTR               24 (f_generate)
              LOAD_ATTR                9 (grid + NULL|self)
              LOAD_CONST               2 (1)
              LOAD_CONST               1 (0)
              LOAD_CONST               4 (2)
              LOAD_CONST               7 ('ew')
              LOAD_CONST               9 (10)
              LOAD_CONST              21 (('row', 'column', 'columnspan', 'sticky', 'pady'))
              CALL_KW                  5
              POP_TOP

202           LOAD_GLOBAL              4 (ctk)
              LOAD_ATTR               26 (CTkButton)
              PUSH_NULL
              LOAD_FAST                0 (self)
              LOAD_ATTR               24 (f_generate)
              LOAD_CONST              22 ('Seleccionar Firma Base PNG')
              LOAD_FAST                0 (self)
              LOAD_ATTR               28 (load_signature)
              LOAD_CONST              23 (('text', 'command'))
              CALL_KW                  3
              STORE_FAST               4 (btn_load_sig2)

203           LOAD_FAST                4 (btn_load_sig2)
              LOAD_ATTR               31 (pack + NULL|self)
              LOAD_CONST              17 (5)
              LOAD_CONST              24 (('pady',))
              CALL_KW                  1
              POP_TOP

204           LOAD_GLOBAL              4 (ctk)
              LOAD_ATTR               32 (CTkLabel)
              PUSH_NULL
              LOAD_FAST                0 (self)
              LOAD_ATTR               24 (f_generate)
              LOAD_CONST              25 ('Sin firma')
              LOAD_CONST              26 ('gray')
              LOAD_CONST              27 (('text', 'text_color'))
              CALL_KW                  3
              LOAD_FAST                0 (self)
              STORE_ATTR              17 (lbl_sig_path)

205           LOAD_FAST                0 (self)
              LOAD_ATTR               34 (lbl_sig_path)
              LOAD_ATTR               31 (pack + NULL|self)
              CALL                     0
              POP_TOP

207           LOAD_GLOBAL              4 (ctk)
              LOAD_ATTR               36 (CTkEntry)
              PUSH_NULL
              LOAD_FAST                0 (self)
              LOAD_ATTR               24 (f_generate)
              LOAD_CONST              28 ('Nombre Completo')
              LOAD_CONST              29 (('placeholder_text',))
              CALL_KW                  2
              LOAD_FAST                0 (self)
              STORE_ATTR              19 (entry_name)

208           LOAD_FAST                0 (self)
              LOAD_ATTR               38 (entry_name)
              LOAD_ATTR               31 (pack + NULL|self)
              LOAD_CONST              30 ('x')
              LOAD_CONST               9 (10)
              LOAD_CONST              17 (5)
              LOAD_CONST              31 (('fill', 'padx', 'pady'))
              CALL_KW                  3
              POP_TOP

209           LOAD_GLOBAL              4 (ctk)
              LOAD_ATTR               36 (CTkEntry)
              PUSH_NULL
              LOAD_FAST                0 (self)
              LOAD_ATTR               24 (f_generate)
              LOAD_CONST              32 ('Número CIP')
              LOAD_CONST              29 (('placeholder_text',))
              CALL_KW                  2
              LOAD_FAST                0 (self)
              STORE_ATTR              20 (entry_cip)

210           LOAD_FAST                0 (self)
              LOAD_ATTR               40 (entry_cip)
              LOAD_ATTR               31 (pack + NULL|self)
              LOAD_CONST              30 ('x')
              LOAD_CONST               9 (10)
              LOAD_CONST              17 (5)
              LOAD_CONST              31 (('fill', 'padx', 'pady'))
              CALL_KW                  3
              POP_TOP

211           LOAD_GLOBAL              4 (ctk)
              LOAD_ATTR               36 (CTkEntry)
              PUSH_NULL
              LOAD_FAST                0 (self)
              LOAD_ATTR               24 (f_generate)
              LOAD_CONST              33 ('Tipo (Ej. Ing. Electricista)')
              LOAD_CONST              29 (('placeholder_text',))
              CALL_KW                  2
              LOAD_FAST                0 (self)
              STORE_ATTR              21 (entry_tipo)

212           LOAD_FAST                0 (self)
              LOAD_ATTR               42 (entry_tipo)
              LOAD_ATTR               31 (pack + NULL|self)
              LOAD_CONST              30 ('x')
              LOAD_CONST               9 (10)
              LOAD_CONST              17 (5)
              LOAD_CONST              31 (('fill', 'padx', 'pady'))
              CALL_KW                  3
              POP_TOP

214           LOAD_GLOBAL              4 (ctk)
              LOAD_ATTR                6 (CTkFrame)
              PUSH_NULL
              LOAD_FAST                1 (f_top)
              CALL                     1
              LOAD_FAST                0 (self)
              STORE_ATTR              22 (f_custom)

215           LOAD_FAST                0 (self)
              LOAD_ATTR               44 (f_custom)
              LOAD_ATTR                9 (grid + NULL|self)
              LOAD_CONST               4 (2)
              LOAD_CONST               1 (0)
              LOAD_CONST               4 (2)
              LOAD_CONST               7 ('ew')
              LOAD_CONST               9 (10)
              LOAD_CONST              21 (('row', 'column', 'columnspan', 'sticky', 'pady'))
              CALL_KW                  5
              POP_TOP

216           LOAD_GLOBAL              4 (ctk)
              LOAD_ATTR               26 (CTkButton)
              PUSH_NULL
              LOAD_FAST                0 (self)
              LOAD_ATTR               44 (f_custom)
              LOAD_CONST              34 ('Cargar Imagen del Sello')
              LOAD_FAST                0 (self)
              LOAD_ATTR               46 (load_custom_stamp)
              LOAD_CONST              23 (('text', 'command'))
              CALL_KW                  3
              STORE_FAST               5 (btn_load_custom)

217           LOAD_FAST                5 (btn_load_custom)
              LOAD_ATTR               31 (pack + NULL|self)
              LOAD_CONST              17 (5)
              LOAD_CONST              24 (('pady',))
              CALL_KW                  1
              POP_TOP

218           LOAD_GLOBAL              4 (ctk)
              LOAD_ATTR               32 (CTkLabel)
              PUSH_NULL
              LOAD_FAST                0 (self)
              LOAD_ATTR               44 (f_custom)
              LOAD_CONST              35 ('Ningún sello cargado')
              LOAD_CONST              26 ('gray')
              LOAD_CONST              36 (400)
              LOAD_CONST              37 (('text', 'text_color', 'wraplength'))
              CALL_KW                  4
              LOAD_FAST                0 (self)
              STORE_ATTR              24 (lbl_custom_path)

219           LOAD_FAST                0 (self)
              LOAD_ATTR               48 (lbl_custom_path)
              LOAD_ATTR               31 (pack + NULL|self)
              LOAD_CONST              17 (5)
              LOAD_CONST              24 (('pady',))
              CALL_KW                  1
              POP_TOP

221           LOAD_GLOBAL              4 (ctk)
              LOAD_ATTR                6 (CTkFrame)
              PUSH_NULL
              LOAD_FAST                0 (self)
              LOAD_CONST               5 ('transparent')
              LOAD_CONST               6 (('fg_color',))
              CALL_KW                  2
              STORE_FAST               6 (f_scale)

222           LOAD_FAST                6 (f_scale)
              LOAD_ATTR                9 (grid + NULL|self)
              LOAD_CONST               2 (1)
              LOAD_CONST               1 (0)
              LOAD_CONST               7 ('ew')
              LOAD_CONST               8 (20)
              LOAD_CONST              17 (5)
              LOAD_CONST              10 (('row', 'column', 'sticky', 'padx', 'pady'))
              CALL_KW                  5
              POP_TOP

223           LOAD_GLOBAL              4 (ctk)
              LOAD_ATTR               32 (CTkLabel)
              PUSH_NULL
              LOAD_FAST                6 (f_scale)
              LOAD_CONST              38 ('Escala (%):')
              LOAD_CONST              39 (('text',))
              CALL_KW                  2
              LOAD_ATTR               31 (pack + NULL|self)
              LOAD_CONST              40 ('left')
              LOAD_CONST              17 (5)
              LOAD_CONST              41 (('side', 'padx'))
              CALL_KW                  2
              POP_TOP

224           LOAD_GLOBAL              4 (ctk)
              LOAD_ATTR               36 (CTkEntry)
              PUSH_NULL
              LOAD_FAST                6 (f_scale)
              LOAD_CONST              42 (60)
              LOAD_CONST              43 (('width',))
              CALL_KW                  2
              LOAD_FAST                0 (self)
              STORE_ATTR              25 (entry_scale)

225           LOAD_FAST                0 (self)
              LOAD_ATTR               50 (entry_scale)
              LOAD_ATTR               31 (pack + NULL|self)
              LOAD_CONST              40 ('left')
              LOAD_CONST              17 (5)
              LOAD_CONST              41 (('side', 'padx'))
              CALL_KW                  2
              POP_TOP

227           LOAD_GLOBAL              4 (ctk)
              LOAD_ATTR               32 (CTkLabel)
              PUSH_NULL
              LOAD_FAST                0 (self)
              LOAD_CONST              44 ('Rangos y Excepciones para Sello 2:')
              LOAD_GLOBAL              4 (ctk)
              LOAD_ATTR               52 (CTkFont)
              PUSH_NULL
              LOAD_CONST              45 ('bold')
              LOAD_CONST               3 (('weight',))
              CALL_KW                  1
              LOAD_CONST              46 (('text', 'font'))
              CALL_KW                  3
              LOAD_ATTR                9 (grid + NULL|self)
              LOAD_CONST               4 (2)
              LOAD_CONST               1 (0)
              LOAD_CONST              16 ('w')
              LOAD_CONST               8 (20)
              LOAD_CONST              47 ((10, 0))
              LOAD_CONST              10 (('row', 'column', 'sticky', 'padx', 'pady'))
              CALL_KW                  5
              POP_TOP

229           LOAD_GLOBAL             55 (RangeEditorFrame + NULL)
              LOAD_FAST                0 (self)
              LOAD_CONST              48 (True)
              LOAD_CONST              49 (('show_exceptions',))
              CALL_KW                  2
              LOAD_FAST                0 (self)
              STORE_ATTR              28 (range_editor)

230           LOAD_FAST                0 (self)
              LOAD_ATTR               56 (range_editor)
              LOAD_ATTR                9 (grid + NULL|self)
              LOAD_CONST              50 (3)
              LOAD_CONST               1 (0)
              LOAD_CONST              51 ('nsew')
              LOAD_CONST               8 (20)
              LOAD_CONST              17 (5)
              LOAD_CONST              10 (('row', 'column', 'sticky', 'padx', 'pady'))
              CALL_KW                  5
              POP_TOP

232           LOAD_GLOBAL              4 (ctk)
              LOAD_ATTR               26 (CTkButton)
              PUSH_NULL
              LOAD_FAST                0 (self)
              LOAD_CONST              52 ('Guardar y Cerrar')
              LOAD_FAST                0 (self)
              LOAD_ATTR               58 (on_close)
              LOAD_CONST              23 (('text', 'command'))
              CALL_KW                  3
              STORE_FAST               7 (btn_save)

233           LOAD_FAST                7 (btn_save)
              LOAD_ATTR                9 (grid + NULL|self)
              LOAD_CONST              53 (4)
              LOAD_CONST               1 (0)
              LOAD_CONST               8 (20)
              LOAD_CONST              54 (('row', 'column', 'pady'))
              CALL_KW                  3
              POP_TOP
              RETURN_CONST             0 (None)

Disassembly of <code object update_mode_ui at 0x0000028A6B18A970, file "src\ui\config_sellos.py", line 235>:
235           RESUME                   0

236           LOAD_FAST                0 (self)
              LOAD_ATTR                0 (mode_var)
              LOAD_ATTR                3 (get + NULL|self)
              CALL                     0
              LOAD_CONST               1 ('generate')
              COMPARE_OP              88 (bool(==))
              POP_JUMP_IF_FALSE       53 (to L1)

237           LOAD_FAST                0 (self)
              LOAD_ATTR                4 (f_generate)
              LOAD_ATTR                7 (grid + NULL|self)
              CALL                     0
              POP_TOP

238           LOAD_FAST                0 (self)
              LOAD_ATTR                8 (f_custom)
              LOAD_ATTR               11 (grid_remove + NULL|self)
              CALL                     0
              POP_TOP
              RETURN_CONST             0 (None)

240   L1:     LOAD_FAST                0 (self)
              LOAD_ATTR                4 (f_generate)
              LOAD_ATTR               11 (grid_remove + NULL|self)
              CALL                     0
              POP_TOP

241           LOAD_FAST                0 (self)
              LOAD_ATTR                8 (f_custom)
              LOAD_ATTR                7 (grid + NULL|self)
              CALL                     0
              POP_TOP
              RETURN_CONST             0 (None)

Disassembly of <code object load_custom_stamp at 0x0000028A6B11E9E0, file "src\ui\config_sellos.py", line 243>:
243           RESUME                   0

244           LOAD_FAST                0 (self)
              LOAD_ATTR                1 (attributes + NULL|self)
              LOAD_CONST               1 ('-topmost')
              LOAD_CONST               2 (False)
              CALL                     2
              POP_TOP

245           LOAD_GLOBAL              2 (filedialog)
              LOAD_ATTR                4 (askopenfilename)
              PUSH_NULL
              LOAD_CONST               3 ('Seleccionar Sello Pre-Diseñado PNG')
              LOAD_CONST               4 (('PNG transparent', '*.png'))
              BUILD_LIST               1
              LOAD_CONST               5 (('title', 'filetypes'))
              CALL_KW                  2
              STORE_FAST               1 (path)

246           LOAD_FAST                0 (self)
              LOAD_ATTR                1 (attributes + NULL|self)
              LOAD_CONST               1 ('-topmost')
              LOAD_CONST               6 (True)
              CALL                     2
              POP_TOP

247           LOAD_FAST                1 (path)
              TO_BOOL
              POP_JUMP_IF_FALSE       60 (to L1)

248           LOAD_FAST                0 (self)
              LOAD_ATTR                6 (config_manager)
              LOAD_ATTR                9 (set + NULL|self)
              LOAD_CONST               7 ('sello2_custom_path')
              LOAD_FAST                1 (path)
              CALL                     2
              POP_TOP

249           LOAD_FAST                0 (self)
              LOAD_ATTR               10 (lbl_custom_path)
              LOAD_ATTR               13 (configure + NULL|self)
              LOAD_CONST               8 ('...')
              LOAD_FAST                1 (path)
              LOAD_CONST               9 (-35)
              LOAD_CONST               0 (None)
              BINARY_SLICE
              FORMAT_SIMPLE
              BUILD_STRING             2
              LOAD_CONST              10 (('text',))
              CALL_KW                  1
              POP_TOP
              RETURN_CONST             0 (None)

247   L1:     RETURN_CONST             0 (None)

Disassembly of <code object load_signature at 0x0000028A6B11EBB0, file "src\ui\config_sellos.py", line 251>:
251           RESUME                   0

252           LOAD_FAST                0 (self)
              LOAD_ATTR                1 (attributes + NULL|self)
              LOAD_CONST               1 ('-topmost')
              LOAD_CONST               2 (False)
              CALL                     2
              POP_TOP

253           LOAD_GLOBAL              2 (filedialog)
              LOAD_ATTR                4 (askopenfilename)
              PUSH_NULL
              LOAD_CONST               3 ('Seleccionar Firma Base PNG')
              LOAD_CONST               4 (('PNG transparent', '*.png'))
              BUILD_LIST               1
              LOAD_CONST               5 (('title', 'filetypes'))
              CALL_KW                  2
              STORE_FAST               1 (path)

254           LOAD_FAST                0 (self)
              LOAD_ATTR                1 (attributes + NULL|self)
              LOAD_CONST               1 ('-topmost')
              LOAD_CONST               6 (True)
              CALL                     2
              POP_TOP

255           LOAD_FAST                1 (path)
              TO_BOOL
              POP_JUMP_IF_FALSE       60 (to L1)

256           LOAD_FAST                0 (self)
              LOAD_ATTR                6 (config_manager)
              LOAD_ATTR                9 (set + NULL|self)
              LOAD_CONST               7 ('signature_path')
              LOAD_FAST                1 (path)
              CALL                     2
              POP_TOP

257           LOAD_FAST                0 (self)
              LOAD_ATTR               10 (lbl_sig_path)
              LOAD_ATTR               13 (configure + NULL|self)
              LOAD_CONST               8 ('...')
              LOAD_FAST                1 (path)
              LOAD_CONST               9 (-25)
              LOAD_CONST               0 (None)
              BINARY_SLICE
              FORMAT_SIMPLE
              BUILD_STRING             2
              LOAD_CONST              10 (('text',))
              CALL_KW                  1
              POP_TOP
              RETURN_CONST             0 (None)

255   L1:     RETURN_CONST             0 (None)

Disassembly of <code object load_data at 0x0000028A6B4265F0, file "src\ui\config_sellos.py", line 259>:
259           RESUME                   0

260           LOAD_FAST                0 (self)
              LOAD_ATTR                0 (entry_name)
              LOAD_ATTR                3 (insert + NULL|self)
              LOAD_CONST               1 (0)
              LOAD_FAST                0 (self)
              LOAD_ATTR                4 (config_manager)
              LOAD_ATTR                7 (get + NULL|self)
              LOAD_CONST               2 ('engineer_name')
              LOAD_CONST               3 ('')
              CALL                     2
              CALL                     2
              POP_TOP

261           LOAD_FAST                0 (self)
              LOAD_ATTR                8 (entry_cip)
              LOAD_ATTR                3 (insert + NULL|self)
              LOAD_CONST               1 (0)
              LOAD_FAST                0 (self)
              LOAD_ATTR                4 (config_manager)
              LOAD_ATTR                7 (get + NULL|self)
              LOAD_CONST               4 ('cip_number')
              LOAD_CONST               3 ('')
              CALL                     2
              CALL                     2
              POP_TOP

262           LOAD_FAST                0 (self)
              LOAD_ATTR               10 (entry_tipo)
              LOAD_ATTR                3 (insert + NULL|self)
              LOAD_CONST               1 (0)
              LOAD_FAST                0 (self)
              LOAD_ATTR                4 (config_manager)
              LOAD_ATTR                7 (get + NULL|self)
              LOAD_CONST               5 ('engineer_type')
              LOAD_CONST               6 ('Ingeniero Electricista')
              CALL                     2
              CALL                     2
              POP_TOP

264           LOAD_FAST                0 (self)
              LOAD_ATTR                4 (config_manager)
              LOAD_ATTR                7 (get + NULL|self)
              LOAD_CONST               7 ('signature_path')
              LOAD_CONST               3 ('')
              CALL                     2
              STORE_FAST               1 (s_path)

265           LOAD_FAST                1 (s_path)
              TO_BOOL
              POP_JUMP_IF_FALSE       67 (to L1)
              LOAD_GLOBAL             12 (os)
              LOAD_ATTR               14 (path)
              LOAD_ATTR               17 (exists + NULL|self)
              LOAD_FAST                1 (s_path)
              CALL                     1
              TO_BOOL
              POP_JUMP_IF_FALSE       31 (to L1)

266           LOAD_FAST                0 (self)
              LOAD_ATTR               18 (lbl_sig_path)
              LOAD_ATTR               21 (configure + NULL|self)
              LOAD_CONST               8 ('...')
              LOAD_FAST                1 (s_path)
              LOAD_CONST               9 (-25)
              LOAD_CONST               0 (None)
              BINARY_SLICE
              FORMAT_SIMPLE
              BUILD_STRING             2
              LOAD_CONST              10 (('text',))
              CALL_KW                  1
              POP_TOP

268   L1:     LOAD_FAST                0 (self)
              LOAD_ATTR                4 (config_manager)
              LOAD_ATTR                7 (get + NULL|self)
              LOAD_CONST              11 ('sello2_custom_path')
              LOAD_CONST               3 ('')
              CALL                     2
              STORE_FAST               2 (c_path)

269           LOAD_FAST                2 (c_path)
              TO_BOOL
              POP_JUMP_IF_FALSE       67 (to L2)
              LOAD_GLOBAL             12 (os)
              LOAD_ATTR               14 (path)
              LOAD_ATTR               17 (exists + NULL|self)
              LOAD_FAST                2 (c_path)
              CALL                     1
              TO_BOOL
              POP_JUMP_IF_FALSE       31 (to L2)

270           LOAD_FAST                0 (self)
              LOAD_ATTR               22 (lbl_custom_path)
              LOAD_ATTR               21 (configure + NULL|self)
              LOAD_CONST               8 ('...')
              LOAD_FAST                2 (c_path)
              LOAD_CONST              12 (-35)
              LOAD_CONST               0 (None)
              BINARY_SLICE
              FORMAT_SIMPLE
              BUILD_STRING             2
              LOAD_CONST              10 (('text',))
              CALL_KW                  1
              POP_TOP

272   L2:     LOAD_FAST                0 (self)
              LOAD_ATTR               24 (entry_scale)
              LOAD_ATTR                3 (insert + NULL|self)
              LOAD_CONST               1 (0)
              LOAD_GLOBAL             27 (str + NULL)
              LOAD_FAST                0 (self)
              LOAD_ATTR                4 (config_manager)
              LOAD_ATTR                7 (get + NULL|self)
              LOAD_CONST              13 ('body_scale')
              LOAD_CONST              14 ('100')
              CALL                     2
              CALL                     1
              CALL                     2
              POP_TOP

273           LOAD_FAST                0 (self)
              LOAD_ATTR                4 (config_manager)
              LOAD_ATTR                7 (get + NULL|self)
              LOAD_CONST              15 ('body_ranges')
              LOAD_CONST              16 ('2')
              LOAD_CONST              17 ('final')
              LOAD_CONST              18 (('start', 'end'))
              BUILD_CONST_KEY_MAP      2
              BUILD_LIST               1
              CALL                     2
              STORE_FAST               3 (ranges)

274           LOAD_FAST                0 (self)
              LOAD_ATTR               28 (range_editor)
              LOAD_ATTR               30 (frame_list)
              LOAD_ATTR               33 (winfo_children + NULL|self)
              CALL                     0
              GET_ITER
      L3:     FOR_ITER                18 (to L4)
              STORE_FAST_LOAD_FAST    68 (w, w)
              LOAD_ATTR               35 (destroy + NULL|self)
              CALL                     0
              POP_TOP
              JUMP_BACKWARD           20 (to L3)
      L4:     END_FOR
              POP_TOP

275           LOAD_FAST                0 (self)
              LOAD_ATTR               28 (range_editor)
              LOAD_ATTR               36 (lista_entradas_rangos)
              LOAD_ATTR               39 (clear + NULL|self)
              CALL                     0
              POP_TOP

276           LOAD_FAST                3 (ranges)
              GET_ITER
      L5:     FOR_ITER                63 (to L6)
              STORE_FAST               5 (rng)

277           LOAD_FAST                0 (self)
              LOAD_ATTR               28 (range_editor)
              LOAD_ATTR               41 (add_rango + NULL|self)
              LOAD_FAST                5 (rng)
              LOAD_ATTR                7 (get + NULL|self)
              LOAD_CONST              19 ('start')
              LOAD_CONST               3 ('')
              CALL                     2
              LOAD_FAST                5 (rng)
              LOAD_ATTR                7 (get + NULL|self)
              LOAD_CONST              20 ('end')
              LOAD_CONST               3 ('')
              CALL                     2
              CALL                     2
              POP_TOP
              JUMP_BACKWARD           65 (to L5)

276   L6:     END_FOR
              POP_TOP

279           LOAD_FAST                0 (self)
              LOAD_ATTR               28 (range_editor)
              LOAD_ATTR               43 (set_exceptions + NULL|self)
              LOAD_FAST                0 (self)
              LOAD_ATTR                4 (config_manager)
              LOAD_ATTR                7 (get + NULL|self)
              LOAD_CONST              21 ('body_exceptions')
              LOAD_CONST               3 ('')
              CALL                     2
              CALL                     1
              POP_TOP
              RETURN_CONST             0 (None)

Disassembly of <code object on_close at 0x0000028A6B46B4A0, file "src\ui\config_sellos.py", line 281>:
281           RESUME                   0

282           LOAD_FAST                0 (self)
              LOAD_ATTR                0 (entry_name)
              LOAD_ATTR                3 (get + NULL|self)
              CALL                     0
              LOAD_FAST                0 (self)
              LOAD_ATTR                4 (config_manager)
              LOAD_ATTR                6 (config)
              LOAD_CONST               1 ('engineer_name')
              STORE_SUBSCR

283           LOAD_FAST                0 (self)
              LOAD_ATTR                8 (entry_cip)
              LOAD_ATTR                3 (get + NULL|self)
              CALL                     0
              LOAD_FAST                0 (self)
              LOAD_ATTR                4 (config_manager)
              LOAD_ATTR                6 (config)
              LOAD_CONST               2 ('cip_number')
              STORE_SUBSCR

284           LOAD_FAST                0 (self)
              LOAD_ATTR               10 (entry_tipo)
              LOAD_ATTR                3 (get + NULL|self)
              CALL                     0
              LOAD_FAST                0 (self)
              LOAD_ATTR                4 (config_manager)
              LOAD_ATTR                6 (config)
              LOAD_CONST               3 ('engineer_type')
              STORE_SUBSCR

285           LOAD_FAST                0 (self)
              LOAD_ATTR               12 (mode_var)
              LOAD_ATTR                3 (get + NULL|self)
              CALL                     0
              LOAD_FAST                0 (self)
              LOAD_ATTR                4 (config_manager)
              LOAD_ATTR                6 (config)
              LOAD_CONST               4 ('sello2_mode')
              STORE_SUBSCR

286           LOAD_GLOBAL             15 (int + NULL)
              LOAD_FAST                0 (self)
              LOAD_ATTR               16 (entry_scale)
              LOAD_ATTR                3 (get + NULL|self)
              CALL                     0
              COPY                     1
              TO_BOOL
              POP_JUMP_IF_TRUE         2 (to L1)
              POP_TOP
              LOAD_CONST               5 (100)
      L1:     CALL                     1
              LOAD_FAST                0 (self)
              LOAD_ATTR                4 (config_manager)
              LOAD_ATTR                6 (config)
              LOAD_CONST               6 ('body_scale')
              STORE_SUBSCR

288           LOAD_FAST                0 (self)
              LOAD_ATTR               18 (range_editor)
              LOAD_ATTR               21 (get_ranges + NULL|self)
              CALL                     0
              LOAD_FAST                0 (self)
              LOAD_ATTR                4 (config_manager)
              LOAD_ATTR                6 (config)
              LOAD_CONST               7 ('body_ranges')
              STORE_SUBSCR

289           LOAD_FAST                0 (self)
              LOAD_ATTR               18 (range_editor)
              LOAD_ATTR               23 (get_exceptions + NULL|self)
              CALL                     0
              LOAD_FAST                0 (self)
              LOAD_ATTR                4 (config_manager)
              LOAD_ATTR                6 (config)
              LOAD_CONST               8 ('body_exceptions')
              STORE_SUBSCR

291           LOAD_FAST                0 (self)
              LOAD_ATTR                4 (config_manager)
              LOAD_ATTR               25 (save_config + NULL|self)
              CALL                     0
              POP_TOP

292           LOAD_FAST                0 (self)
              LOAD_ATTR               26 (on_close_callback)
              TO_BOOL
              POP_JUMP_IF_FALSE       16 (to L2)

293           LOAD_FAST                0 (self)
              LOAD_ATTR               27 (on_close_callback + NULL|self)
              CALL                     0
              POP_TOP

294   L2:     LOAD_FAST                0 (self)
              LOAD_ATTR               29 (destroy + NULL|self)
              CALL                     0
              POP_TOP
              RETURN_CONST             0 (None)
