  0           RESUME                   0

  1           LOAD_CONST               0 (0)
              LOAD_CONST               1 (None)
              IMPORT_NAME              0 (customtkinter)
              STORE_NAME               1 (ctk)

  2           LOAD_CONST               0 (0)
              LOAD_CONST               1 (None)
              IMPORT_NAME              2 (tkinter)
              STORE_NAME               3 (tk)

  3           LOAD_CONST               0 (0)
              LOAD_CONST               2 (('messagebox',))
              IMPORT_NAME              2 (tkinter)
              IMPORT_FROM              4 (messagebox)
              STORE_NAME               4 (messagebox)
              POP_TOP

  4           LOAD_CONST               0 (0)
              LOAD_CONST               3 (('Image', 'ImageTk'))
              IMPORT_NAME              5 (PIL)
              IMPORT_FROM              6 (Image)
              STORE_NAME               6 (Image)
              IMPORT_FROM              7 (ImageTk)
              STORE_NAME               7 (ImageTk)
              POP_TOP

  5           LOAD_CONST               0 (0)
              LOAD_CONST               1 (None)
              IMPORT_NAME              8 (os)
              STORE_NAME               8 (os)

  7           LOAD_BUILD_CLASS
              PUSH_NULL
              LOAD_CONST               4 (<code object LayoutEditorWindow at 0x0000028A6B18F990, file "src\ui\layout_editor.py", line 7>)
              MAKE_FUNCTION
              LOAD_CONST               5 ('LayoutEditorWindow')
              LOAD_NAME                1 (ctk)
              LOAD_ATTR               18 (CTkToplevel)
              CALL                     3
              STORE_NAME              10 (LayoutEditorWindow)
              RETURN_CONST             1 (None)

Disassembly of <code object LayoutEditorWindow at 0x0000028A6B18F990, file "src\ui\layout_editor.py", line 7>:
  --           MAKE_CELL                0 (__class__)

   7           RESUME                   0
               LOAD_NAME                0 (__name__)
               STORE_NAME               1 (__module__)
               LOAD_CONST               0 ('LayoutEditorWindow')
               STORE_NAME               2 (__qualname__)
               LOAD_CONST               1 (7)
               STORE_NAME               3 (__firstlineno__)

   8           LOAD_FAST                0 (__class__)
               BUILD_TUPLE              1
               LOAD_CONST               2 (<code object __init__ at 0x0000028A6B4155B0, file "src\ui\layout_editor.py", line 8>)
               MAKE_FUNCTION
               SET_FUNCTION_ATTRIBUTE   8 (closure)
               STORE_NAME               4 (__init__)

  26           LOAD_CONST               3 (<code object setup_ui at 0x0000028A6B45F130, file "src\ui\layout_editor.py", line 26>)
               MAKE_FUNCTION
               STORE_NAME               5 (setup_ui)

  70           LOAD_CONST               4 (<code object draw_markers at 0x0000028A6B46C650, file "src\ui\layout_editor.py", line 70>)
               MAKE_FUNCTION
               STORE_NAME               6 (draw_markers)

 118           LOAD_CONST               5 (<code object on_click at 0x0000028A6B1B69E0, file "src\ui\layout_editor.py", line 118>)
               MAKE_FUNCTION
               STORE_NAME               7 (on_click)

 123           LOAD_CONST               6 (<code object save_and_close at 0x0000028A6B45F9F0, file "src\ui\layout_editor.py", line 123>)
               MAKE_FUNCTION
               STORE_NAME               8 (save_and_close)
               LOAD_CONST               7 (('base_template', 'config', 'current_mode', 'cv', 'entry_date_scale', 'entry_sig_scale', 'img_pil', 'markers', 'temp_coords', 'tk_img'))
               STORE_NAME               9 (__static_attributes__)
               LOAD_FAST                0 (__class__)
               COPY                     1
               STORE_NAME              10 (__classcell__)
               RETURN_VALUE

Disassembly of <code object __init__ at 0x0000028A6B4155B0, file "src\ui\layout_editor.py", line 8>:
  --           COPY_FREE_VARS           1

   8           RESUME                   0

   9           LOAD_GLOBAL              0 (super)
               LOAD_DEREF               4 (__class__)
               LOAD_FAST                0 (self)
               LOAD_SUPER_ATTR          5 (__init__ + NULL|self)
               LOAD_FAST                1 (parent)
               CALL                     1
               POP_TOP

  10           LOAD_FAST_LOAD_FAST     32 (config_manager, self)
               STORE_ATTR               2 (config)

  11           LOAD_FAST_LOAD_FAST     48 (base_template, self)
               STORE_ATTR               3 (base_template)

  13           LOAD_FAST                0 (self)
               LOAD_ATTR                9 (title + NULL|self)
               LOAD_CONST               1 ('Editar Coordenadas Internas (Sello 1)')
               CALL                     1
               POP_TOP

  14           LOAD_FAST                0 (self)
               LOAD_ATTR               11 (geometry + NULL|self)
               LOAD_CONST               2 ('800x600')
               CALL                     1
               POP_TOP

  15           LOAD_FAST                0 (self)
               LOAD_ATTR               13 (attributes + NULL|self)
               LOAD_CONST               3 ('-topmost')
               LOAD_CONST               4 (True)
               CALL                     2
               POP_TOP

  18           LOAD_FAST                0 (self)
               LOAD_ATTR                4 (config)
               LOAD_ATTR               15 (get + NULL|self)
               LOAD_CONST               5 ('tpl_date1_coords')
               CALL                     1

  19           LOAD_FAST                0 (self)
               LOAD_ATTR                4 (config)
               LOAD_ATTR               15 (get + NULL|self)
               LOAD_CONST               6 ('tpl_date2_coords')
               CALL                     1

  20           LOAD_FAST                0 (self)
               LOAD_ATTR                4 (config)
               LOAD_ATTR               15 (get + NULL|self)
               LOAD_CONST               7 ('tpl_sig_coords')
               CALL                     1

  17           LOAD_CONST               8 (('date1', 'date2', 'sig'))
               BUILD_CONST_KEY_MAP      3
               LOAD_FAST                0 (self)
               STORE_ATTR               8 (temp_coords)

  23           BUILD_MAP                0
               LOAD_FAST                0 (self)
               STORE_ATTR               9 (markers)

  24           LOAD_FAST                0 (self)
               LOAD_ATTR               21 (setup_ui + NULL|self)
               CALL                     0
               POP_TOP
               RETURN_CONST             0 (None)

Disassembly of <code object setup_ui at 0x0000028A6B45F130, file "src\ui\layout_editor.py", line 26>:
 26           RESUME                   0

 27           LOAD_GLOBAL              0 (ctk)
              LOAD_ATTR                2 (CTkLabel)
              PUSH_NULL
              LOAD_FAST                0 (self)
              LOAD_CONST               1 ('Doble Clic directo en la imagen para capturar la posición del elemento seleccionado:')
              LOAD_CONST               2 (('text',))
              CALL_KW                  2
              STORE_FAST               1 (lbl_inst)

 28           LOAD_FAST                1 (lbl_inst)
              LOAD_ATTR                5 (pack + NULL|self)
              LOAD_CONST               3 (10)
              LOAD_CONST               4 (('pady',))
              CALL_KW                  1
              POP_TOP

 30           LOAD_GLOBAL              6 (tk)
              LOAD_ATTR                8 (StringVar)
              PUSH_NULL
              LOAD_CONST               5 ('date1')
              LOAD_CONST               6 (('value',))
              CALL_KW                  1
              LOAD_FAST                0 (self)
              STORE_ATTR               5 (current_mode)

 31           LOAD_GLOBAL              0 (ctk)
              LOAD_ATTR               12 (CTkFrame)
              PUSH_NULL
              LOAD_FAST                0 (self)
              LOAD_CONST               7 ('transparent')
              LOAD_CONST               8 (('fg_color',))
              CALL_KW                  2
              STORE_FAST               2 (frame_radio)

 32           LOAD_FAST                2 (frame_radio)
              LOAD_ATTR                5 (pack + NULL|self)
              LOAD_CONST               9 (5)
              LOAD_CONST               4 (('pady',))
              CALL_KW                  1
              POP_TOP

 34           LOAD_GLOBAL              0 (ctk)
              LOAD_ATTR               14 (CTkRadioButton)
              PUSH_NULL
              LOAD_FAST                2 (frame_radio)
              LOAD_CONST              10 ('Fecha Inicio')
              LOAD_FAST                0 (self)
              LOAD_ATTR               10 (current_mode)
              LOAD_CONST               5 ('date1')
              LOAD_CONST              11 (('text', 'variable', 'value'))
              CALL_KW                  4
              LOAD_ATTR                5 (pack + NULL|self)
              LOAD_CONST              12 ('left')
              LOAD_CONST               3 (10)
              LOAD_CONST              13 (('side', 'padx'))
              CALL_KW                  2
              POP_TOP

 35           LOAD_GLOBAL              0 (ctk)
              LOAD_ATTR               14 (CTkRadioButton)
              PUSH_NULL
              LOAD_FAST                2 (frame_radio)
              LOAD_CONST              14 ('Fecha Fin')
              LOAD_FAST                0 (self)
              LOAD_ATTR               10 (current_mode)
              LOAD_CONST              15 ('date2')
              LOAD_CONST              11 (('text', 'variable', 'value'))
              CALL_KW                  4
              LOAD_ATTR                5 (pack + NULL|self)
              LOAD_CONST              12 ('left')
              LOAD_CONST               3 (10)
              LOAD_CONST              13 (('side', 'padx'))
              CALL_KW                  2
              POP_TOP

 36           LOAD_GLOBAL              0 (ctk)
              LOAD_ATTR               14 (CTkRadioButton)
              PUSH_NULL
              LOAD_FAST                2 (frame_radio)
              LOAD_CONST              16 ('Firma')
              LOAD_FAST                0 (self)
              LOAD_ATTR               10 (current_mode)
              LOAD_CONST              17 ('sig')
              LOAD_CONST              11 (('text', 'variable', 'value'))
              CALL_KW                  4
              LOAD_ATTR                5 (pack + NULL|self)
              LOAD_CONST              12 ('left')
              LOAD_CONST               3 (10)
              LOAD_CONST              13 (('side', 'padx'))
              CALL_KW                  2
              POP_TOP

 38           LOAD_GLOBAL              0 (ctk)
              LOAD_ATTR               12 (CTkFrame)
              PUSH_NULL
              LOAD_FAST                0 (self)
              LOAD_CONST               7 ('transparent')
              LOAD_CONST               8 (('fg_color',))
              CALL_KW                  2
              STORE_FAST               3 (frame_scales)

 39           LOAD_FAST                3 (frame_scales)
              LOAD_ATTR                5 (pack + NULL|self)
              LOAD_CONST               9 (5)
              LOAD_CONST               4 (('pady',))
              CALL_KW                  1
              POP_TOP

 41           LOAD_GLOBAL              0 (ctk)
              LOAD_ATTR                2 (CTkLabel)
              PUSH_NULL
              LOAD_FAST                3 (frame_scales)
              LOAD_CONST              18 ('Escala Textos (%):')
              LOAD_CONST               2 (('text',))
              CALL_KW                  2
              LOAD_ATTR                5 (pack + NULL|self)
              LOAD_CONST              12 ('left')
              LOAD_CONST               9 (5)
              LOAD_CONST              13 (('side', 'padx'))
              CALL_KW                  2
              POP_TOP

 42           LOAD_GLOBAL              0 (ctk)
              LOAD_ATTR               16 (CTkEntry)
              PUSH_NULL
              LOAD_FAST                3 (frame_scales)
              LOAD_CONST              19 (50)
              LOAD_CONST              20 (('width',))
              CALL_KW                  2
              LOAD_FAST                0 (self)
              STORE_ATTR               9 (entry_date_scale)

 43           LOAD_FAST                0 (self)
              LOAD_ATTR               18 (entry_date_scale)
              LOAD_ATTR               21 (insert + NULL|self)
              LOAD_CONST              21 (0)
              LOAD_GLOBAL             23 (str + NULL)
              LOAD_FAST                0 (self)
              LOAD_ATTR               24 (config)
              LOAD_ATTR               27 (get + NULL|self)
              LOAD_CONST              22 ('tpl_date_scale')
              CALL                     1
              COPY                     1
              TO_BOOL
              POP_JUMP_IF_TRUE         2 (to L1)
              POP_TOP
              LOAD_CONST              23 (100)
      L1:     CALL                     1
              CALL                     2
              POP_TOP

 44           LOAD_FAST                0 (self)
              LOAD_ATTR               18 (entry_date_scale)
              LOAD_ATTR                5 (pack + NULL|self)
              LOAD_CONST              12 ('left')
              LOAD_CONST               9 (5)
              LOAD_CONST              13 (('side', 'padx'))
              CALL_KW                  2
              POP_TOP

 46           LOAD_GLOBAL              0 (ctk)
              LOAD_ATTR                2 (CTkLabel)
              PUSH_NULL
              LOAD_FAST                3 (frame_scales)
              LOAD_CONST              24 ('Escala Firma (%):')
              LOAD_CONST               2 (('text',))
              CALL_KW                  2
              LOAD_ATTR                5 (pack + NULL|self)
              LOAD_CONST              12 ('left')
              LOAD_CONST              25 ((15, 5))
              LOAD_CONST              13 (('side', 'padx'))
              CALL_KW                  2
              POP_TOP

 47           LOAD_GLOBAL              0 (ctk)
              LOAD_ATTR               16 (CTkEntry)
              PUSH_NULL
              LOAD_FAST                3 (frame_scales)
              LOAD_CONST              19 (50)
              LOAD_CONST              20 (('width',))
              CALL_KW                  2
              LOAD_FAST                0 (self)
              STORE_ATTR              14 (entry_sig_scale)

 48           LOAD_FAST                0 (self)
              LOAD_ATTR               28 (entry_sig_scale)
              LOAD_ATTR               21 (insert + NULL|self)
              LOAD_CONST              21 (0)
              LOAD_GLOBAL             23 (str + NULL)
              LOAD_FAST                0 (self)
              LOAD_ATTR               24 (config)
              LOAD_ATTR               27 (get + NULL|self)
              LOAD_CONST              26 ('tpl_sig_scale')
              CALL                     1
              COPY                     1
              TO_BOOL
              POP_JUMP_IF_TRUE         2 (to L2)
              POP_TOP
              LOAD_CONST              23 (100)
      L2:     CALL                     1
              CALL                     2
              POP_TOP

 49           LOAD_FAST                0 (self)
              LOAD_ATTR               28 (entry_sig_scale)
              LOAD_ATTR                5 (pack + NULL|self)
              LOAD_CONST              12 ('left')
              LOAD_CONST               9 (5)
              LOAD_CONST              13 (('side', 'padx'))
              CALL_KW                  2
              POP_TOP

 51           LOAD_GLOBAL              0 (ctk)
              LOAD_ATTR               30 (CTkScrollableFrame)
              PUSH_NULL
              LOAD_FAST                0 (self)
              CALL                     1
              STORE_FAST               4 (canvas_frame)

 52           LOAD_FAST                4 (canvas_frame)
              LOAD_ATTR                5 (pack + NULL|self)
              LOAD_CONST              27 ('both')
              LOAD_CONST              28 (True)
              LOAD_CONST              29 (20)
              LOAD_CONST               3 (10)
              LOAD_CONST              30 (('fill', 'expand', 'padx', 'pady'))
              CALL_KW                  4
              POP_TOP

 54           LOAD_GLOBAL             32 (Image)
              LOAD_ATTR               34 (open)
              PUSH_NULL
              LOAD_FAST                0 (self)
              LOAD_ATTR               36 (base_template)
              CALL                     1
              LOAD_FAST                0 (self)
              STORE_ATTR              19 (img_pil)

 55           LOAD_GLOBAL             40 (ImageTk)
              LOAD_ATTR               42 (PhotoImage)
              PUSH_NULL
              LOAD_FAST                0 (self)
              LOAD_ATTR               38 (img_pil)
              CALL                     1
              LOAD_FAST                0 (self)
              STORE_ATTR              22 (tk_img)

 57           LOAD_GLOBAL              6 (tk)
              LOAD_ATTR               46 (Canvas)
              PUSH_NULL
              LOAD_FAST_LOAD_FAST     64 (canvas_frame, self)
              LOAD_ATTR               38 (img_pil)
              LOAD_ATTR               48 (width)
              LOAD_FAST                0 (self)
              LOAD_ATTR               38 (img_pil)
              LOAD_ATTR               50 (height)
              LOAD_CONST              31 ('gray')
              LOAD_CONST              32 (('width', 'height', 'bg'))
              CALL_KW                  4
              LOAD_FAST                0 (self)
              STORE_ATTR              26 (cv)

 58           LOAD_FAST                0 (self)
              LOAD_ATTR               52 (cv)
              LOAD_ATTR                5 (pack + NULL|self)
              LOAD_CONST              28 (True)
              LOAD_CONST              33 (('expand',))
              CALL_KW                  1
              POP_TOP

 59           LOAD_FAST                0 (self)
              LOAD_ATTR               52 (cv)
              LOAD_ATTR               55 (create_image + NULL|self)
              LOAD_CONST              21 (0)
              LOAD_CONST              21 (0)
              LOAD_CONST              34 ('nw')
              LOAD_FAST                0 (self)
              LOAD_ATTR               44 (tk_img)
              LOAD_CONST              35 (('anchor', 'image'))
              CALL_KW                  4
              POP_TOP

 61           LOAD_FAST                0 (self)
              LOAD_ATTR               57 (draw_markers + NULL|self)
              CALL                     0
              POP_TOP

 63           LOAD_FAST                0 (self)
              LOAD_ATTR               52 (cv)
              LOAD_ATTR               59 (bind + NULL|self)
              LOAD_CONST              36 ('<Double-Button-1>')
              LOAD_FAST                0 (self)
              LOAD_ATTR               60 (on_click)
              CALL                     2
              POP_TOP

 64           LOAD_FAST                0 (self)
              LOAD_ATTR               18 (entry_date_scale)
              LOAD_ATTR               59 (bind + NULL|self)
              LOAD_CONST              37 ('<KeyRelease>')
              LOAD_FAST                0 (self)
              LOAD_ATTR               56 (draw_markers)
              CALL                     2
              POP_TOP

 65           LOAD_FAST                0 (self)
              LOAD_ATTR               28 (entry_sig_scale)
              LOAD_ATTR               59 (bind + NULL|self)
              LOAD_CONST              37 ('<KeyRelease>')
              LOAD_FAST                0 (self)
              LOAD_ATTR               56 (draw_markers)
              CALL                     2
              POP_TOP

 67           LOAD_GLOBAL              0 (ctk)
              LOAD_ATTR               62 (CTkButton)
              PUSH_NULL
              LOAD_FAST                0 (self)
              LOAD_CONST              38 ('Guardar Coordenadas')
              LOAD_CONST              39 ('blue')
              LOAD_FAST                0 (self)
              LOAD_ATTR               64 (save_and_close)
              LOAD_CONST              40 (('text', 'fg_color', 'command'))
              CALL_KW                  4
              STORE_FAST               5 (btn_save)

 68           LOAD_FAST                5 (btn_save)
              LOAD_ATTR                5 (pack + NULL|self)
              LOAD_CONST               3 (10)
              LOAD_CONST               4 (('pady',))
              CALL_KW                  1
              POP_TOP
              RETURN_CONST             0 (None)

Disassembly of <code object draw_markers at 0x0000028A6B46C650, file "src\ui\layout_editor.py", line 70>:
  70            RESUME                   0

  71            LOAD_GLOBAL              1 (list + NULL)
                LOAD_FAST                0 (self)
                LOAD_ATTR                2 (markers)
                LOAD_ATTR                5 (values + NULL|self)
                CALL                     0
                CALL                     1
                GET_ITER
        L1:     FOR_ITER                30 (to L2)
                STORE_FAST               2 (m)

  72            LOAD_FAST                0 (self)
                LOAD_ATTR                6 (cv)
                LOAD_ATTR                9 (delete + NULL|self)
                LOAD_FAST                2 (m)
                CALL                     1
                POP_TOP
                JUMP_BACKWARD           32 (to L1)

  71    L2:     END_FOR
                POP_TOP

  73            LOAD_FAST                0 (self)
                LOAD_ATTR                2 (markers)
                LOAD_ATTR               11 (clear + NULL|self)
                CALL                     0
                POP_TOP

  75    L3:     LOAD_GLOBAL             13 (int + NULL)
                LOAD_FAST                0 (self)
                LOAD_ATTR               14 (entry_date_scale)
                LOAD_ATTR               17 (get + NULL|self)
                CALL                     0
                COPY                     1
                TO_BOOL
                POP_JUMP_IF_TRUE         2 (to L4)
                POP_TOP
                LOAD_CONST               1 (100)
        L4:     CALL                     1
                STORE_FAST               3 (d_scale)

  78    L5:     LOAD_GLOBAL             13 (int + NULL)
                LOAD_FAST                0 (self)
                LOAD_ATTR               18 (entry_sig_scale)
                LOAD_ATTR               17 (get + NULL|self)
                CALL                     0
                COPY                     1
                TO_BOOL
                POP_JUMP_IF_TRUE         2 (to L6)
                POP_TOP
                LOAD_CONST               1 (100)
        L6:     CALL                     1
                STORE_FAST               4 (s_scale)

  81    L7:     LOAD_GLOBAL             13 (int + NULL)
                LOAD_FAST                0 (self)
                LOAD_ATTR               20 (img_pil)
                LOAD_ATTR               22 (height)
                LOAD_CONST               2 (0.08)
                BINARY_OP                5 (*)
                LOAD_FAST                3 (d_scale)
                LOAD_CONST               3 (100.0)
                BINARY_OP               11 (/)
                BINARY_OP                5 (*)
                CALL                     1
                STORE_FAST               5 (font_size)

  82            LOAD_FAST                5 (font_size)
                LOAD_CONST               4 (1)
                COMPARE_OP              18 (bool(<))
                POP_JUMP_IF_FALSE        2 (to L8)
                LOAD_CONST               5 (12)
                STORE_FAST               5 (font_size)

  84    L8:     LOAD_GLOBAL             13 (int + NULL)
                LOAD_FAST                0 (self)
                LOAD_ATTR               20 (img_pil)
                LOAD_ATTR               24 (width)
                LOAD_CONST               6 (0.35)
                BINARY_OP                5 (*)
                LOAD_FAST                4 (s_scale)
                LOAD_CONST               3 (100.0)
                BINARY_OP               11 (/)
                BINARY_OP                5 (*)
                CALL                     1
                STORE_FAST               6 (sig_w)

  85            LOAD_GLOBAL             13 (int + NULL)
                LOAD_FAST                6 (sig_w)
                LOAD_CONST               7 (0.4)
                BINARY_OP                5 (*)
                CALL                     1
                STORE_FAST               7 (sig_h)

  87            LOAD_FAST                0 (self)
                LOAD_ATTR               26 (temp_coords)
                LOAD_ATTR               29 (items + NULL|self)
                CALL                     0
                GET_ITER
        L9:     EXTENDED_ARG             2
                FOR_ITER               540 (to L19)
                UNPACK_SEQUENCE          2
                STORE_FAST_STORE_FAST  137 (key, val)

  88            LOAD_FAST                9 (val)
                TO_BOOL
                POP_JUMP_IF_TRUE         2 (to L10)
                JUMP_BACKWARD           15 (to L9)
       L10:     LOAD_GLOBAL             31 (isinstance + NULL)
                LOAD_FAST                9 (val)
                LOAD_GLOBAL              0 (list)
                LOAD_GLOBAL             32 (tuple)
                BUILD_TUPLE              2
                CALL                     2
                TO_BOOL
                POP_JUMP_IF_TRUE         2 (to L11)
                JUMP_BACKWARD           44 (to L9)
       L11:     LOAD_GLOBAL             35 (len + NULL)
                LOAD_FAST                9 (val)
                CALL                     1
                LOAD_CONST               8 (2)
                COMPARE_OP             188 (bool(>=))
                POP_JUMP_IF_TRUE         2 (to L12)
                JUMP_BACKWARD           61 (to L9)

  89   L12:     LOAD_FAST                9 (val)
                LOAD_CONST               9 (0)
                BINARY_SUBSCR
                LOAD_FAST                9 (val)
                LOAD_CONST               4 (1)
                BINARY_SUBSCR
                STORE_FAST_STORE_FAST  186 (y, x)

  90            LOAD_FAST                8 (key)
                LOAD_CONST              10 (('date1', 'date2'))
                CONTAINS_OP              0
                POP_JUMP_IF_FALSE      136 (to L16)

  91            LOAD_FAST                8 (key)
                LOAD_CONST              11 ('date1')
                COMPARE_OP              88 (bool(==))
                POP_JUMP_IF_FALSE        2 (to L13)
                LOAD_CONST              12 ('red')
                JUMP_FORWARD             1 (to L14)
       L13:     LOAD_CONST              13 ('blue')
       L14:     STORE_FAST              12 (color)

  92            LOAD_FAST                0 (self)
                LOAD_ATTR                6 (cv)
                LOAD_ATTR               37 (create_text + NULL|self)
                LOAD_FAST_LOAD_FAST    171 (x, y)
                LOAD_CONST              14 ('DD/MM/YYYY')
                LOAD_CONST              15 ('nw')
                LOAD_FAST               12 (color)
                LOAD_CONST              16 ('Arial')
                LOAD_FAST                5 (font_size)
                LOAD_CONST              17 ('bold')
                BUILD_TUPLE              3
                LOAD_CONST              18 (('text', 'anchor', 'fill', 'font'))
                CALL_KW                  6
                STORE_FAST              13 (m_text)

  93            LOAD_FAST                0 (self)
                LOAD_ATTR                6 (cv)
                LOAD_ATTR               39 (bbox + NULL|self)
                LOAD_FAST               13 (m_text)
                CALL                     1
                STORE_FAST              14 (bbox)

  94            LOAD_FAST               14 (bbox)
                TO_BOOL
                POP_JUMP_IF_FALSE       44 (to L15)

  95            LOAD_FAST                0 (self)
                LOAD_ATTR                6 (cv)
                LOAD_ATTR               41 (create_rectangle + NULL|self)
                LOAD_FAST_LOAD_FAST    236 (bbox, color)
                LOAD_CONST               8 (2)
                LOAD_CONST              19 ((4, 4))
                LOAD_CONST              20 (('outline', 'width', 'dash'))
                CALL_KW                  4
                STORE_FAST              15 (m_bg)

  96            LOAD_FAST_LOAD_FAST    240 (m_bg, self)
                LOAD_ATTR                2 (markers)
                LOAD_FAST                8 (key)
                FORMAT_SIMPLE
                LOAD_CONST              21 ('_bg')
                BUILD_STRING             2
                STORE_SUBSCR

  97   L15:     LOAD_FAST_LOAD_FAST    208 (m_text, self)
                LOAD_ATTR                2 (markers)
                LOAD_FAST                8 (key)
                STORE_SUBSCR
                JUMP_BACKWARD          212 (to L9)

  99   L16:     LOAD_CONST              22 ('green')
                STORE_FAST              12 (color)

 100            LOAD_FAST                6 (sig_w)
                STORE_FAST              16 (sig_w_calc)

 101            LOAD_FAST                7 (sig_h)
                STORE_FAST              17 (sig_h_calc)

 102            LOAD_CONST              23 ('ÁREA FIRMA')
                STORE_FAST              18 (sig_txt)

 104            NOP

 105   L17:     LOAD_FAST                0 (self)
                LOAD_ATTR               42 (config)
                LOAD_ATTR               17 (get + NULL|self)
                LOAD_CONST              24 ('signature_path')
                CALL                     1
                STORE_FAST              19 (s_path)

 106            LOAD_FAST               19 (s_path)
                TO_BOOL
                POP_JUMP_IF_FALSE      156 (to L18)
                LOAD_GLOBAL             44 (os)
                LOAD_ATTR               46 (path)
                LOAD_ATTR               49 (exists + NULL|self)
                LOAD_FAST               19 (s_path)
                CALL                     1
                TO_BOOL
                POP_JUMP_IF_FALSE      120 (to L18)

 107            LOAD_GLOBAL             50 (Image)
                LOAD_ATTR               52 (open)
                PUSH_NULL
                LOAD_FAST               19 (s_path)
                CALL                     1
                STORE_FAST              20 (tmp_s)

 108            LOAD_FAST                6 (sig_w)
                LOAD_GLOBAL             55 (float + NULL)
                LOAD_FAST               20 (tmp_s)
                LOAD_ATTR               56 (size)
                LOAD_CONST               9 (0)
                BINARY_SUBSCR
                CALL                     1
                BINARY_OP               11 (/)
                STORE_FAST              21 (r)

 109            LOAD_GLOBAL             13 (int + NULL)
                LOAD_GLOBAL             55 (float + NULL)
                LOAD_FAST               20 (tmp_s)
                LOAD_ATTR               56 (size)
                LOAD_CONST               4 (1)
                BINARY_SUBSCR
                CALL                     1
                LOAD_FAST               21 (r)
                BINARY_OP                5 (*)
                CALL                     1
                STORE_FAST              17 (sig_h_calc)

 110            LOAD_CONST              25 ('ÁREA FIRMA (')
                LOAD_FAST               20 (tmp_s)
                LOAD_ATTR               56 (size)
                LOAD_CONST               9 (0)
                BINARY_SUBSCR
                FORMAT_SIMPLE
                LOAD_CONST              26 ('x')
                LOAD_FAST               20 (tmp_s)
                LOAD_ATTR               56 (size)
                LOAD_CONST               4 (1)
                BINARY_SUBSCR
                FORMAT_SIMPLE
                LOAD_CONST              27 (')')
                BUILD_STRING             5
                STORE_FAST              18 (sig_txt)

 113   L18:     LOAD_FAST                0 (self)
                LOAD_ATTR                6 (cv)
                LOAD_ATTR               41 (create_rectangle + NULL|self)
                LOAD_FAST_LOAD_FAST    171 (x, y)
                LOAD_FAST               10 (x)
                LOAD_FAST               16 (sig_w_calc)
                BINARY_OP                0 (+)
                LOAD_FAST               11 (y)
                LOAD_FAST               17 (sig_h_calc)
                BINARY_OP                0 (+)
                LOAD_FAST               12 (color)
                LOAD_CONST               8 (2)
                LOAD_CONST              19 ((4, 4))
                LOAD_CONST              20 (('outline', 'width', 'dash'))
                CALL_KW                  7
                STORE_FAST              22 (m_rect)

 114            LOAD_FAST                0 (self)
                LOAD_ATTR                6 (cv)
                LOAD_ATTR               37 (create_text + NULL|self)
                LOAD_FAST               10 (x)
                LOAD_CONST              28 (5)
                BINARY_OP                0 (+)
                LOAD_FAST               11 (y)
                LOAD_CONST              28 (5)
                BINARY_OP                0 (+)
                LOAD_FAST               18 (sig_txt)
                LOAD_CONST              15 ('nw')
                LOAD_FAST               12 (color)
                LOAD_CONST              16 ('Arial')
                LOAD_GLOBAL             59 (max + NULL)
                LOAD_CONST              29 (10)
                LOAD_GLOBAL             13 (int + NULL)
                LOAD_FAST                5 (font_size)
                LOAD_CONST               8 (2)
                BINARY_OP               11 (/)
                CALL                     1
                CALL                     2
                LOAD_CONST              17 ('bold')
                BUILD_TUPLE              3
                LOAD_CONST              18 (('text', 'anchor', 'fill', 'font'))
                CALL_KW                  6
                STORE_FAST              13 (m_text)

 115            LOAD_FAST               22 (m_rect)
                LOAD_FAST                0 (self)
                LOAD_ATTR                2 (markers)
                LOAD_FAST                8 (key)
                STORE_SUBSCR

 116            LOAD_FAST_LOAD_FAST    208 (m_text, self)
                LOAD_ATTR                2 (markers)
                LOAD_FAST                8 (key)
                FORMAT_SIMPLE
                LOAD_CONST              30 ('_text')
                BUILD_STRING             2
                STORE_SUBSCR
                EXTENDED_ARG             2
                JUMP_BACKWARD          543 (to L9)

  87   L19:     END_FOR
                POP_TOP
                RETURN_CONST             0 (None)

  --   L20:     PUSH_EXC_INFO

  76            POP_TOP
                LOAD_CONST               1 (100)
                STORE_FAST               3 (d_scale)
       L21:     POP_EXCEPT
                EXTENDED_ARG             2
                JUMP_BACKWARD_NO_INTERRUPT 725 (to L5)

  --   L22:     COPY                     3
                POP_EXCEPT
                RERAISE                  1
       L23:     PUSH_EXC_INFO

  79            POP_TOP
                LOAD_CONST               1 (100)
                STORE_FAST               4 (s_scale)
       L24:     POP_EXCEPT
                EXTENDED_ARG             2
                JUMP_BACKWARD_NO_INTERRUPT 691 (to L7)

  --   L25:     COPY                     3
                POP_EXCEPT
                RERAISE                  1
       L26:     PUSH_EXC_INFO

 111            POP_TOP
       L27:     POP_EXCEPT
                JUMP_BACKWARD_NO_INTERRUPT 159 (to L18)

  --   L28:     COPY                     3
                POP_EXCEPT
                RERAISE                  1
ExceptionTable:
  L3 to L5 -> L20 [0]
  L5 to L7 -> L23 [0]
  L17 to L18 -> L26 [1]
  L20 to L21 -> L22 [1] lasti
  L23 to L24 -> L25 [1] lasti
  L26 to L27 -> L28 [2] lasti

Disassembly of <code object on_click at 0x0000028A6B1B69E0, file "src\ui\layout_editor.py", line 118>:
118           RESUME                   0

119           LOAD_FAST                0 (self)
              LOAD_ATTR                0 (current_mode)
              LOAD_ATTR                3 (get + NULL|self)
              CALL                     0
              STORE_FAST               2 (mode)

120           LOAD_FAST                1 (e)
              LOAD_ATTR                4 (x)
              LOAD_FAST                1 (e)
              LOAD_ATTR                6 (y)
              BUILD_LIST               2
              LOAD_FAST                0 (self)
              LOAD_ATTR                8 (temp_coords)
              LOAD_FAST                2 (mode)
              STORE_SUBSCR

121           LOAD_FAST                0 (self)
              LOAD_ATTR               11 (draw_markers + NULL|self)
              CALL                     0
              POP_TOP
              RETURN_CONST             0 (None)

Disassembly of <code object save_and_close at 0x0000028A6B45F9F0, file "src\ui\layout_editor.py", line 123>:
 123           RESUME                   0

 124           LOAD_FAST                0 (self)
               LOAD_ATTR                0 (config)
               LOAD_ATTR                3 (set + NULL|self)
               LOAD_CONST               1 ('tpl_date1_coords')
               LOAD_FAST                0 (self)
               LOAD_ATTR                4 (temp_coords)
               LOAD_CONST               2 ('date1')
               BINARY_SUBSCR
               CALL                     2
               POP_TOP

 125           LOAD_FAST                0 (self)
               LOAD_ATTR                0 (config)
               LOAD_ATTR                3 (set + NULL|self)
               LOAD_CONST               3 ('tpl_date2_coords')
               LOAD_FAST                0 (self)
               LOAD_ATTR                4 (temp_coords)
               LOAD_CONST               4 ('date2')
               BINARY_SUBSCR
               CALL                     2
               POP_TOP

 126           LOAD_FAST                0 (self)
               LOAD_ATTR                0 (config)
               LOAD_ATTR                3 (set + NULL|self)
               LOAD_CONST               5 ('tpl_sig_coords')
               LOAD_FAST                0 (self)
               LOAD_ATTR                4 (temp_coords)
               LOAD_CONST               6 ('sig')
               BINARY_SUBSCR
               CALL                     2
               POP_TOP

 127           NOP

 128   L1:     LOAD_FAST                0 (self)
               LOAD_ATTR                0 (config)
               LOAD_ATTR                3 (set + NULL|self)
               LOAD_CONST               7 ('tpl_date_scale')
               LOAD_GLOBAL              7 (int + NULL)
               LOAD_FAST                0 (self)
               LOAD_ATTR                8 (entry_date_scale)
               LOAD_ATTR               11 (get + NULL|self)
               CALL                     0
               COPY                     1
               TO_BOOL
               POP_JUMP_IF_TRUE         2 (to L2)
               POP_TOP
               LOAD_CONST               8 (100)
       L2:     CALL                     1
               CALL                     2
               POP_TOP

 129           LOAD_FAST                0 (self)
               LOAD_ATTR                0 (config)
               LOAD_ATTR                3 (set + NULL|self)
               LOAD_CONST               9 ('tpl_sig_scale')
               LOAD_GLOBAL              7 (int + NULL)
               LOAD_FAST                0 (self)
               LOAD_ATTR               12 (entry_sig_scale)
               LOAD_ATTR               11 (get + NULL|self)
               CALL                     0
               COPY                     1
               TO_BOOL
               POP_JUMP_IF_TRUE         2 (to L3)
               POP_TOP
               LOAD_CONST               8 (100)
       L3:     CALL                     1
               CALL                     2
               POP_TOP

 132   L4:     LOAD_FAST                0 (self)
               LOAD_ATTR               15 (destroy + NULL|self)
               CALL                     0
               POP_TOP

 135           LOAD_GLOBAL             17 (hasattr + NULL)
               LOAD_FAST                0 (self)
               LOAD_ATTR               18 (master)
               LOAD_CONST              10 ('attributes')
               CALL                     2
               TO_BOOL
               POP_JUMP_IF_FALSE       28 (to L5)

 136           LOAD_FAST                0 (self)
               LOAD_ATTR               18 (master)
               LOAD_ATTR               21 (attributes + NULL|self)
               LOAD_CONST              11 ('-topmost')
               LOAD_CONST              12 (False)
               CALL                     2
               POP_TOP

 137   L5:     LOAD_GLOBAL             22 (messagebox)
               LOAD_ATTR               24 (showinfo)
               PUSH_NULL
               LOAD_CONST              13 ('Guardado')
               LOAD_CONST              14 ('Coordenadas guardadas correctamente.')
               CALL                     2
               POP_TOP

 138           LOAD_GLOBAL             17 (hasattr + NULL)
               LOAD_FAST                0 (self)
               LOAD_ATTR               18 (master)
               LOAD_CONST              10 ('attributes')
               CALL                     2
               TO_BOOL
               POP_JUMP_IF_FALSE       29 (to L6)

 139           LOAD_FAST                0 (self)
               LOAD_ATTR               18 (master)
               LOAD_ATTR               21 (attributes + NULL|self)
               LOAD_CONST              11 ('-topmost')
               LOAD_CONST              15 (True)
               CALL                     2
               POP_TOP
               RETURN_CONST             0 (None)

 138   L6:     RETURN_CONST             0 (None)

  --   L7:     PUSH_EXC_INFO

 130           POP_TOP
       L8:     POP_EXCEPT
               JUMP_BACKWARD_NO_INTERRUPT 155 (to L4)

  --   L9:     COPY                     3
               POP_EXCEPT
               RERAISE                  1
ExceptionTable:
  L1 to L4 -> L7 [0]
  L7 to L8 -> L9 [1] lasti
