  0           RESUME                   0

  1           LOAD_CONST               0 (0)
              LOAD_CONST               1 (None)
              IMPORT_NAME              0 (customtkinter)
              STORE_NAME               1 (ctk)

  2           LOAD_CONST               0 (0)
              LOAD_CONST               1 (None)
              IMPORT_NAME              2 (tkinter)
              STORE_NAME               3 (tk)

  3           LOAD_CONST               0 (0)
              LOAD_CONST               2 (('filedialog', 'messagebox'))
              IMPORT_NAME              2 (tkinter)
              IMPORT_FROM              4 (filedialog)
              STORE_NAME               4 (filedialog)
              IMPORT_FROM              5 (messagebox)
              STORE_NAME               5 (messagebox)
              POP_TOP

  4           LOAD_CONST               0 (0)
              LOAD_CONST               3 (('Image', 'ImageTk'))
              IMPORT_NAME              6 (PIL)
              IMPORT_FROM              7 (Image)
              STORE_NAME               7 (Image)
              IMPORT_FROM              8 (ImageTk)
              STORE_NAME               8 (ImageTk)
              POP_TOP

  5           LOAD_CONST               0 (0)
              LOAD_CONST               1 (None)
              IMPORT_NAME              9 (os)
              STORE_NAME               9 (os)

  7           LOAD_CONST               0 (0)
              LOAD_CONST               4 (('LayoutEditorWindow',))
              IMPORT_NAME             10 (src.ui.layout_editor)
              IMPORT_FROM             11 (LayoutEditorWindow)
              STORE_NAME              11 (LayoutEditorWindow)
              POP_TOP

  8           LOAD_CONST               0 (0)
              LOAD_CONST               5 (('ConfigSello1Window', 'ConfigSello2Window'))
              IMPORT_NAME             12 (src.ui.config_sellos)
              IMPORT_FROM             13 (ConfigSello1Window)
              STORE_NAME              13 (ConfigSello1Window)
              IMPORT_FROM             14 (ConfigSello2Window)
              STORE_NAME              14 (ConfigSello2Window)
              POP_TOP

 10           LOAD_BUILD_CLASS
              PUSH_NULL
              LOAD_CONST               6 (<code object TabAutofirma at 0x0000028A6B186BB0, file "src\ui\tab_autofirma.py", line 10>)
              MAKE_FUNCTION
              LOAD_CONST               7 ('TabAutofirma')
              LOAD_NAME                1 (ctk)
              LOAD_ATTR               30 (CTkFrame)
              CALL                     3
              STORE_NAME              16 (TabAutofirma)
              RETURN_CONST             1 (None)

Disassembly of <code object TabAutofirma at 0x0000028A6B186BB0, file "src\ui\tab_autofirma.py", line 10>:
  --           MAKE_CELL                0 (__class__)

  10           RESUME                   0
               LOAD_NAME                0 (__name__)
               STORE_NAME               1 (__module__)
               LOAD_CONST               0 ('TabAutofirma')
               STORE_NAME               2 (__qualname__)
               LOAD_CONST               1 (10)
               STORE_NAME               3 (__firstlineno__)

  11           LOAD_FAST                0 (__class__)
               BUILD_TUPLE              1
               LOAD_CONST               2 (<code object __init__ at 0x0000028A6B400F50, file "src\ui\tab_autofirma.py", line 11>)
               MAKE_FUNCTION
               SET_FUNCTION_ATTRIBUTE   8 (closure)
               STORE_NAME               4 (__init__)

  35           LOAD_CONST               3 (<code object setup_ui at 0x0000028A6B47D5A0, file "src\ui\tab_autofirma.py", line 35>)
               MAKE_FUNCTION
               STORE_NAME               5 (setup_ui)

 147           LOAD_CONST               4 (<code object open_config_sello1 at 0x0000028A6B18F330, file "src\ui\tab_autofirma.py", line 147>)
               MAKE_FUNCTION
               STORE_NAME               6 (open_config_sello1)

 150           LOAD_CONST               5 (<code object open_config_sello2 at 0x0000028A6B36F880, file "src\ui\tab_autofirma.py", line 150>)
               MAKE_FUNCTION
               STORE_NAME               7 (open_config_sello2)

 153           LOAD_CONST               6 (<code object on_toggle_sellos at 0x0000028A6B171F30, file "src\ui\tab_autofirma.py", line 153>)
               MAKE_FUNCTION
               STORE_NAME               8 (on_toggle_sellos)

 159           LOAD_CONST               7 (<code object set_today at 0x0000028A6B3B1DE0, file "src\ui\tab_autofirma.py", line 159>)
               MAKE_FUNCTION
               STORE_NAME               9 (set_today)

 164           LOAD_CONST               8 (<code object load_profile at 0x0000028A6B13DBD0, file "src\ui\tab_autofirma.py", line 164>)
               MAKE_FUNCTION
               STORE_NAME              10 (load_profile)

 169           LOAD_CONST               9 (<code object save_profile at 0x0000028A6B172120, file "src\ui\tab_autofirma.py", line 169>)
               MAKE_FUNCTION
               STORE_NAME              11 (save_profile)

 175           LOAD_CONST              10 (<code object get_resource_path at 0x0000028A6B4296A0, file "src\ui\tab_autofirma.py", line 175>)
               MAKE_FUNCTION
               STORE_NAME              12 (get_resource_path)

 186           LOAD_CONST              11 (<code object action_load_template at 0x0000028A6B382B40, file "src\ui\tab_autofirma.py", line 186>)
               MAKE_FUNCTION
               STORE_NAME              13 (action_load_template)

 189           LOAD_CONST              12 (<code object action_edit_template_layout at 0x0000028A6B13DF10, file "src\ui\tab_autofirma.py", line 189>)
               MAKE_FUNCTION
               STORE_NAME              14 (action_edit_template_layout)

 196           LOAD_CONST              13 (<code object action_load_signature at 0x0000028A6B185830, file "src\ui\tab_autofirma.py", line 196>)
               MAKE_FUNCTION
               STORE_NAME              15 (action_load_signature)

 202           LOAD_CONST              14 (<code object load_pdf_from_path at 0x0000028A6B4167B0, file "src\ui\tab_autofirma.py", line 202>)
               MAKE_FUNCTION
               STORE_NAME              16 (load_pdf_from_path)

 214           LOAD_CONST              15 (<code object action_load_pdf at 0x0000028A6B6543C0, file "src\ui\tab_autofirma.py", line 214>)
               MAKE_FUNCTION
               STORE_NAME              17 (action_load_pdf)

 219           LOAD_CONST              16 (<code object action_prev_page at 0x0000028A6B143CB0, file "src\ui\tab_autofirma.py", line 219>)
               MAKE_FUNCTION
               STORE_NAME              18 (action_prev_page)

 224           LOAD_CONST              17 (<code object action_next_page at 0x0000028A6B185B30, file "src\ui\tab_autofirma.py", line 224>)
               MAKE_FUNCTION
               STORE_NAME              19 (action_next_page)

 229           LOAD_CONST              18 (<code object action_zoom_in at 0x0000028A6B167E10, file "src\ui\tab_autofirma.py", line 229>)
               MAKE_FUNCTION
               STORE_NAME              20 (action_zoom_in)

 233           LOAD_CONST              19 (<code object action_zoom_out at 0x0000028A6B3AC7B0, file "src\ui\tab_autofirma.py", line 233>)
               MAKE_FUNCTION
               STORE_NAME              21 (action_zoom_out)

 238           LOAD_CONST              20 (<code object action_preview_cover_stamp_from_popup at 0x0000028A6B423910, file "src\ui\tab_autofirma.py", line 238>)
               MAKE_FUNCTION
               STORE_NAME              22 (action_preview_cover_stamp_from_popup)

 274           LOAD_CONST              21 (<code object update_preview at 0x0000028A6B422810, file "src\ui\tab_autofirma.py", line 274>)
               MAKE_FUNCTION
               STORE_NAME              23 (update_preview)

 287           LOAD_CONST              22 (<code object on_canvas_click at 0x0000028A6B42F740, file "src\ui\tab_autofirma.py", line 287>)
               MAKE_FUNCTION
               STORE_NAME              24 (on_canvas_click)

 297           LOAD_CONST              23 (<code object get_stamp_size at 0x0000028A6B4265F0, file "src\ui\tab_autofirma.py", line 297>)
               MAKE_FUNCTION
               STORE_NAME              25 (get_stamp_size)

 332           LOAD_CONST              24 (<code object draw_ghost_rect at 0x0000028A6B426B90, file "src\ui\tab_autofirma.py", line 332>)
               MAKE_FUNCTION
               STORE_NAME              26 (draw_ghost_rect)

 343           LOAD_CONST              25 (<code object action_export at 0x0000028A6B498260, file "src\ui\tab_autofirma.py", line 343>)
               MAKE_FUNCTION
               STORE_NAME              27 (action_export)
               LOAD_CONST              26 (('body_coords', 'btn_export', 'btn_load_pdf', 'btn_next_page', 'btn_prev_page', 'btn_zoom_in', 'btn_zoom_out', 'canvas', 'canvas_panel', 'canvas_scale', 'config_manager', 'cover_coords', 'current_preview_page', 'current_stamp_type', 'entry_start_date', 'lbl_page_num', 'lbl_pdf_info', 'lbl_watermark', 'left_panel', 'pdf_doc', 'pdf_manager', 'pdf_path', 'preview_image_pil', 'preview_image_tk', 'radio_body', 'radio_cover', 'rect_id', 'right_panel', 'stamp_engine', 'total_pages', 'var_apply_sello1', 'var_apply_sello2'))
               STORE_NAME              28 (__static_attributes__)
               LOAD_FAST                0 (__class__)
               COPY                     1
               STORE_NAME              29 (__classcell__)
               RETURN_VALUE

Disassembly of <code object __init__ at 0x0000028A6B400F50, file "src\ui\tab_autofirma.py", line 11>:
  --           COPY_FREE_VARS           1

  11           RESUME                   0

  12           LOAD_GLOBAL              0 (super)
               LOAD_DEREF               5 (__class__)
               LOAD_FAST                0 (self)
               LOAD_SUPER_ATTR          5 (__init__ + NULL|self)
               LOAD_FAST                1 (parent)
               LOAD_CONST               1 ('transparent')
               LOAD_CONST               2 (('fg_color',))
               CALL_KW                  2
               POP_TOP

  14           LOAD_FAST_LOAD_FAST     32 (config_manager, self)
               STORE_ATTR               2 (config_manager)

  15           LOAD_FAST_LOAD_FAST     48 (stamp_engine, self)
               STORE_ATTR               3 (stamp_engine)

  16           LOAD_FAST_LOAD_FAST     64 (pdf_manager, self)
               STORE_ATTR               4 (pdf_manager)

  18           LOAD_CONST               0 (None)
               LOAD_FAST                0 (self)
               STORE_ATTR               5 (pdf_path)

  19           LOAD_CONST               0 (None)
               LOAD_FAST                0 (self)
               STORE_ATTR               6 (pdf_doc)

  20           LOAD_CONST               3 (0)
               LOAD_FAST                0 (self)
               STORE_ATTR               7 (total_pages)

  21           LOAD_CONST               3 (0)
               LOAD_FAST                0 (self)
               STORE_ATTR               8 (current_preview_page)

  23           LOAD_CONST               0 (None)
               LOAD_FAST                0 (self)
               STORE_ATTR               9 (preview_image_pil)

  24           LOAD_CONST               0 (None)
               LOAD_FAST                0 (self)
               STORE_ATTR              10 (preview_image_tk)

  25           LOAD_CONST               4 (1.0)
               LOAD_FAST                0 (self)
               STORE_ATTR              11 (canvas_scale)

  26           LOAD_CONST               0 (None)
               LOAD_FAST                0 (self)
               STORE_ATTR              12 (rect_id)

  27           LOAD_GLOBAL             26 (tk)
               LOAD_ATTR               28 (StringVar)
               PUSH_NULL
               LOAD_CONST               5 ('cover')
               LOAD_CONST               6 (('value',))
               CALL_KW                  1
               LOAD_FAST                0 (self)
               STORE_ATTR              15 (current_stamp_type)

  29           LOAD_FAST                0 (self)
               LOAD_ATTR                4 (config_manager)
               LOAD_ATTR               33 (get + NULL|self)
               LOAD_CONST               7 ('cover_coords')
               LOAD_CONST               8 (100)
               LOAD_CONST               8 (100)
               BUILD_LIST               2
               CALL                     2
               LOAD_FAST                0 (self)
               STORE_ATTR              17 (cover_coords)

  30           LOAD_FAST                0 (self)
               LOAD_ATTR                4 (config_manager)
               LOAD_ATTR               33 (get + NULL|self)
               LOAD_CONST               9 ('body_coords')
               LOAD_CONST               8 (100)
               LOAD_CONST               8 (100)
               BUILD_LIST               2
               CALL                     2
               LOAD_FAST                0 (self)
               STORE_ATTR              18 (body_coords)

  32           LOAD_FAST                0 (self)
               LOAD_ATTR               39 (setup_ui + NULL|self)
               CALL                     0
               POP_TOP

  33           LOAD_FAST                0 (self)
               LOAD_ATTR               41 (load_profile + NULL|self)
               CALL                     0
               POP_TOP
               RETURN_CONST             0 (None)

Disassembly of <code object setup_ui at 0x0000028A6B47D5A0, file "src\ui\tab_autofirma.py", line 35>:
  --           MAKE_CELL                0 (self)
               MAKE_CELL               15 (on_drop)
               MAKE_CELL               16 (windnd)

  35           RESUME                   0

  36           LOAD_DEREF               0 (self)
               LOAD_ATTR                1 (grid_rowconfigure + NULL|self)
               LOAD_CONST               1 (0)
               LOAD_CONST               2 (1)
               LOAD_CONST               3 (('weight',))
               CALL_KW                  2
               POP_TOP

  37           LOAD_DEREF               0 (self)
               LOAD_ATTR                3 (grid_columnconfigure + NULL|self)
               LOAD_CONST               1 (0)
               LOAD_CONST               1 (0)
               LOAD_CONST               3 (('weight',))
               CALL_KW                  2
               POP_TOP

  38           LOAD_DEREF               0 (self)
               LOAD_ATTR                3 (grid_columnconfigure + NULL|self)
               LOAD_CONST               2 (1)
               LOAD_CONST               2 (1)
               LOAD_CONST               3 (('weight',))
               CALL_KW                  2
               POP_TOP

  41           LOAD_GLOBAL              4 (ctk)
               LOAD_ATTR                6 (CTkScrollableFrame)
               PUSH_NULL
               LOAD_DEREF               0 (self)
               LOAD_CONST               4 (350)
               LOAD_CONST               1 (0)
               LOAD_CONST               5 (('width', 'corner_radius'))
               CALL_KW                  3
               LOAD_DEREF               0 (self)
               STORE_ATTR               4 (left_panel)

  42           LOAD_DEREF               0 (self)
               LOAD_ATTR                8 (left_panel)
               LOAD_ATTR               11 (grid + NULL|self)
               LOAD_CONST               1 (0)
               LOAD_CONST               1 (0)
               LOAD_CONST               6 ('nsew')
               LOAD_CONST               7 (('row', 'column', 'sticky'))
               CALL_KW                  3
               POP_TOP

  44           LOAD_GLOBAL              4 (ctk)
               LOAD_ATTR               12 (CTkLabel)
               PUSH_NULL
               LOAD_DEREF               0 (self)
               LOAD_ATTR                8 (left_panel)
               LOAD_CONST               8 ('CONFIGURACIÓN (PDF)')
               LOAD_GLOBAL              4 (ctk)
               LOAD_ATTR               14 (CTkFont)
               PUSH_NULL
               LOAD_CONST               9 (20)
               LOAD_CONST              10 ('bold')
               LOAD_CONST              11 (('size', 'weight'))
               CALL_KW                  2
               LOAD_CONST              12 (('text', 'font'))
               CALL_KW                  3
               STORE_FAST               1 (lbl_title)

  45           LOAD_FAST                1 (lbl_title)
               LOAD_ATTR               17 (pack + NULL|self)
               LOAD_CONST              13 ((20, 10))
               LOAD_CONST               9 (20)
               LOAD_CONST              14 (('pady', 'padx'))
               CALL_KW                  2
               POP_TOP

  47           LOAD_GLOBAL              4 (ctk)
               LOAD_ATTR               12 (CTkLabel)
               PUSH_NULL
               LOAD_DEREF               0 (self)
               LOAD_ATTR                8 (left_panel)
               LOAD_CONST              15 ('(Puedes arrastrar tu PDF aquí)')
               LOAD_GLOBAL              4 (ctk)
               LOAD_ATTR               14 (CTkFont)
               PUSH_NULL
               LOAD_CONST              16 (12)
               LOAD_CONST              17 ('italic')
               LOAD_CONST              18 (('size', 'slant'))
               CALL_KW                  2
               LOAD_CONST              19 ('gray')
               LOAD_CONST              20 (('text', 'font', 'text_color'))
               CALL_KW                  4
               STORE_FAST               2 (lbl_dnd_hint)

  48           LOAD_FAST                2 (lbl_dnd_hint)
               LOAD_ATTR               17 (pack + NULL|self)
               LOAD_CONST              21 ((0, 10))
               LOAD_CONST              22 (('pady',))
               CALL_KW                  1
               POP_TOP

  51           LOAD_GLOBAL              4 (ctk)
               LOAD_ATTR               18 (CTkFrame)
               PUSH_NULL
               LOAD_DEREF               0 (self)
               LOAD_ATTR                8 (left_panel)
               LOAD_CONST              23 ('transparent')
               LOAD_CONST              24 (('fg_color',))
               CALL_KW                  2
               STORE_FAST               3 (frame_files)

  52           LOAD_FAST                3 (frame_files)
               LOAD_ATTR               17 (pack + NULL|self)
               LOAD_CONST              25 ('x')
               LOAD_CONST               9 (20)
               LOAD_CONST              26 (5)
               LOAD_CONST              27 (('fill', 'padx', 'pady'))
               CALL_KW                  3
               POP_TOP

  54           LOAD_GLOBAL              4 (ctk)
               LOAD_ATTR               20 (CTkButton)
               PUSH_NULL
               LOAD_FAST                3 (frame_files)
               LOAD_CONST              28 ('Cargar Archivo PDF')
               LOAD_DEREF               0 (self)
               LOAD_ATTR               22 (action_load_pdf)
               LOAD_CONST              29 (('text', 'command'))
               CALL_KW                  3
               LOAD_DEREF               0 (self)
               STORE_ATTR              12 (btn_load_pdf)

  55           LOAD_DEREF               0 (self)
               LOAD_ATTR               24 (btn_load_pdf)
               LOAD_ATTR               17 (pack + NULL|self)
               LOAD_CONST              25 ('x')
               LOAD_CONST              26 (5)
               LOAD_CONST              30 (('fill', 'pady'))
               CALL_KW                  2
               POP_TOP

  56           LOAD_GLOBAL              4 (ctk)
               LOAD_ATTR               12 (CTkLabel)
               PUSH_NULL
               LOAD_FAST                3 (frame_files)
               LOAD_CONST              31 ('Ningún PDF cargado (0 págs)')
               LOAD_CONST              19 ('gray')
               LOAD_CONST              32 (('text', 'text_color'))
               CALL_KW                  3
               LOAD_DEREF               0 (self)
               STORE_ATTR              13 (lbl_pdf_info)

  57           LOAD_DEREF               0 (self)
               LOAD_ATTR               26 (lbl_pdf_info)
               LOAD_ATTR               17 (pack + NULL|self)
               LOAD_CONST              21 ((0, 10))
               LOAD_CONST              22 (('pady',))
               CALL_KW                  1
               POP_TOP

  60           LOAD_GLOBAL              4 (ctk)
               LOAD_ATTR               18 (CTkFrame)
               PUSH_NULL
               LOAD_FAST                3 (frame_files)
               LOAD_CONST              23 ('transparent')
               LOAD_CONST              24 (('fg_color',))
               CALL_KW                  2
               STORE_FAST               4 (f_date)

  61           LOAD_FAST                4 (f_date)
               LOAD_ATTR               17 (pack + NULL|self)
               LOAD_CONST              25 ('x')
               LOAD_CONST              26 (5)
               LOAD_CONST              30 (('fill', 'pady'))
               CALL_KW                  2
               POP_TOP

  62           LOAD_GLOBAL              4 (ctk)
               LOAD_ATTR               12 (CTkLabel)
               PUSH_NULL
               LOAD_FAST                4 (f_date)
               LOAD_CONST              33 ('Fecha Sello 1 (DD/MM/YYYY):')
               LOAD_CONST              34 (('text',))
               CALL_KW                  2
               LOAD_ATTR               17 (pack + NULL|self)
               LOAD_CONST              35 ('w')
               LOAD_CONST              36 (('anchor',))
               CALL_KW                  1
               POP_TOP

  64           LOAD_GLOBAL              4 (ctk)
               LOAD_ATTR               18 (CTkFrame)
               PUSH_NULL
               LOAD_FAST                4 (f_date)
               LOAD_CONST              23 ('transparent')
               LOAD_CONST              24 (('fg_color',))
               CALL_KW                  2
               STORE_FAST               5 (f_date_inner)

  65           LOAD_FAST                5 (f_date_inner)
               LOAD_ATTR               17 (pack + NULL|self)
               LOAD_CONST              25 ('x')
               LOAD_CONST              37 (('fill',))
               CALL_KW                  1
               POP_TOP

  66           LOAD_GLOBAL              4 (ctk)
               LOAD_ATTR               28 (CTkEntry)
               PUSH_NULL
               LOAD_FAST                5 (f_date_inner)
               LOAD_CONST              38 (120)
               LOAD_CONST              39 (('width',))
               CALL_KW                  2
               LOAD_DEREF               0 (self)
               STORE_ATTR              15 (entry_start_date)

  67           LOAD_DEREF               0 (self)
               LOAD_ATTR               30 (entry_start_date)
               LOAD_ATTR               17 (pack + NULL|self)
               LOAD_CONST              40 ('left')
               LOAD_CONST              41 ((0, 5))
               LOAD_CONST              42 (('side', 'padx'))
               CALL_KW                  2
               POP_TOP

  69           LOAD_GLOBAL              4 (ctk)
               LOAD_ATTR               20 (CTkButton)
               PUSH_NULL
               LOAD_FAST                5 (f_date_inner)
               LOAD_CONST              43 ('Hoy')
               LOAD_CONST              44 (40)
               LOAD_DEREF               0 (self)
               LOAD_ATTR               32 (set_today)
               LOAD_CONST              45 (('text', 'width', 'command'))
               CALL_KW                  4
               STORE_FAST               6 (btn_today)

  70           LOAD_FAST                6 (btn_today)
               LOAD_ATTR               17 (pack + NULL|self)
               LOAD_CONST              40 ('left')
               LOAD_CONST              46 (('side',))
               CALL_KW                  1
               POP_TOP

  73           LOAD_GLOBAL              4 (ctk)
               LOAD_ATTR               12 (CTkLabel)
               PUSH_NULL
               LOAD_DEREF               0 (self)
               LOAD_ATTR                8 (left_panel)
               LOAD_CONST              47 ('Aplicación de Sellos')
               LOAD_GLOBAL              4 (ctk)
               LOAD_ATTR               14 (CTkFont)
               PUSH_NULL
               LOAD_CONST              10 ('bold')
               LOAD_CONST               3 (('weight',))
               CALL_KW                  1
               LOAD_CONST              12 (('text', 'font'))
               CALL_KW                  3
               LOAD_ATTR               17 (pack + NULL|self)
               LOAD_CONST              48 ((15, 0))
               LOAD_CONST               9 (20)
               LOAD_CONST              35 ('w')
               LOAD_CONST              49 (('pady', 'padx', 'anchor'))
               CALL_KW                  3
               POP_TOP

  76           LOAD_GLOBAL              4 (ctk)
               LOAD_ATTR               18 (CTkFrame)
               PUSH_NULL
               LOAD_DEREF               0 (self)
               LOAD_ATTR                8 (left_panel)
               LOAD_CONST              23 ('transparent')
               LOAD_CONST              24 (('fg_color',))
               CALL_KW                  2
               STORE_FAST               7 (f_sello1)

  77           LOAD_FAST                7 (f_sello1)
               LOAD_ATTR               17 (pack + NULL|self)
               LOAD_CONST              25 ('x')
               LOAD_CONST               9 (20)
               LOAD_CONST              26 (5)
               LOAD_CONST              27 (('fill', 'padx', 'pady'))
               CALL_KW                  3
               POP_TOP

  78           LOAD_GLOBAL              4 (ctk)
               LOAD_ATTR               34 (BooleanVar)
               PUSH_NULL
               LOAD_DEREF               0 (self)
               LOAD_ATTR               36 (config_manager)
               LOAD_ATTR               39 (get + NULL|self)
               LOAD_CONST              50 ('apply_sello1')
               LOAD_CONST              51 (True)
               CALL                     2
               LOAD_CONST              52 (('value',))
               CALL_KW                  1
               LOAD_DEREF               0 (self)
               STORE_ATTR              20 (var_apply_sello1)

  79           LOAD_GLOBAL              4 (ctk)
               LOAD_ATTR               42 (CTkCheckBox)
               PUSH_NULL
               LOAD_FAST                7 (f_sello1)
               LOAD_CONST              53 ('Aplicar Sello 1 (Carátula/V°B°)')
               LOAD_DEREF               0 (self)
               LOAD_ATTR               40 (var_apply_sello1)
               LOAD_DEREF               0 (self)
               LOAD_ATTR               44 (on_toggle_sellos)
               LOAD_CONST              54 (('text', 'variable', 'command'))
               CALL_KW                  4
               STORE_FAST               8 (chk1)

  80           LOAD_FAST                8 (chk1)
               LOAD_ATTR               17 (pack + NULL|self)
               LOAD_CONST              40 ('left')
               LOAD_CONST              26 (5)
               LOAD_CONST              55 (('side', 'pady'))
               CALL_KW                  2
               POP_TOP

  81           LOAD_GLOBAL              4 (ctk)
               LOAD_ATTR               20 (CTkButton)
               PUSH_NULL
               LOAD_FAST                7 (f_sello1)
               LOAD_CONST              56 ('⚙️ Configurar')
               LOAD_CONST              57 (80)
               LOAD_CONST              58 ('gray30')
               LOAD_DEREF               0 (self)
               LOAD_ATTR               46 (open_config_sello1)
               LOAD_CONST              59 (('text', 'width', 'fg_color', 'command'))
               CALL_KW                  5
               STORE_FAST               9 (btn_cfg1)

  82           LOAD_FAST                9 (btn_cfg1)
               LOAD_ATTR               17 (pack + NULL|self)
               LOAD_CONST              60 ('right')
               LOAD_CONST              46 (('side',))
               CALL_KW                  1
               POP_TOP

  85           LOAD_GLOBAL              4 (ctk)
               LOAD_ATTR               18 (CTkFrame)
               PUSH_NULL
               LOAD_DEREF               0 (self)
               LOAD_ATTR                8 (left_panel)
               LOAD_CONST              23 ('transparent')
               LOAD_CONST              24 (('fg_color',))
               CALL_KW                  2
               STORE_FAST              10 (f_sello2)

  86           LOAD_FAST               10 (f_sello2)
               LOAD_ATTR               17 (pack + NULL|self)
               LOAD_CONST              25 ('x')
               LOAD_CONST               9 (20)
               LOAD_CONST              26 (5)
               LOAD_CONST              27 (('fill', 'padx', 'pady'))
               CALL_KW                  3
               POP_TOP

  87           LOAD_GLOBAL              4 (ctk)
               LOAD_ATTR               34 (BooleanVar)
               PUSH_NULL
               LOAD_DEREF               0 (self)
               LOAD_ATTR               36 (config_manager)
               LOAD_ATTR               39 (get + NULL|self)
               LOAD_CONST              61 ('apply_sello2')
               LOAD_CONST              51 (True)
               CALL                     2
               LOAD_CONST              52 (('value',))
               CALL_KW                  1
               LOAD_DEREF               0 (self)
               STORE_ATTR              24 (var_apply_sello2)

  88           LOAD_GLOBAL              4 (ctk)
               LOAD_ATTR               42 (CTkCheckBox)
               PUSH_NULL
               LOAD_FAST               10 (f_sello2)
               LOAD_CONST              62 ('Aplicar Sello 2 (Cuerpo)')
               LOAD_DEREF               0 (self)
               LOAD_ATTR               48 (var_apply_sello2)
               LOAD_DEREF               0 (self)
               LOAD_ATTR               44 (on_toggle_sellos)
               LOAD_CONST              54 (('text', 'variable', 'command'))
               CALL_KW                  4
               STORE_FAST              11 (chk2)

  89           LOAD_FAST               11 (chk2)
               LOAD_ATTR               17 (pack + NULL|self)
               LOAD_CONST              40 ('left')
               LOAD_CONST              26 (5)
               LOAD_CONST              55 (('side', 'pady'))
               CALL_KW                  2
               POP_TOP

  90           LOAD_GLOBAL              4 (ctk)
               LOAD_ATTR               20 (CTkButton)
               PUSH_NULL
               LOAD_FAST               10 (f_sello2)
               LOAD_CONST              56 ('⚙️ Configurar')
               LOAD_CONST              57 (80)
               LOAD_CONST              58 ('gray30')
               LOAD_DEREF               0 (self)
               LOAD_ATTR               50 (open_config_sello2)
               LOAD_CONST              59 (('text', 'width', 'fg_color', 'command'))
               CALL_KW                  5
               STORE_FAST              12 (btn_cfg2)

  91           LOAD_FAST               12 (btn_cfg2)
               LOAD_ATTR               17 (pack + NULL|self)
               LOAD_CONST              60 ('right')
               LOAD_CONST              46 (('side',))
               CALL_KW                  1
               POP_TOP

  94           LOAD_GLOBAL              4 (ctk)
               LOAD_ATTR               12 (CTkLabel)
               PUSH_NULL
               LOAD_DEREF               0 (self)
               LOAD_ATTR                8 (left_panel)
               LOAD_CONST              63 ('Modo Previsualización')
               LOAD_GLOBAL              4 (ctk)
               LOAD_ATTR               14 (CTkFont)
               PUSH_NULL
               LOAD_CONST              10 ('bold')
               LOAD_CONST               3 (('weight',))
               CALL_KW                  1
               LOAD_CONST              12 (('text', 'font'))
               CALL_KW                  3
               LOAD_ATTR               17 (pack + NULL|self)
               LOAD_CONST              64 ((15, 5))
               LOAD_CONST               9 (20)
               LOAD_CONST              35 ('w')
               LOAD_CONST              49 (('pady', 'padx', 'anchor'))
               CALL_KW                  3
               POP_TOP

  95           LOAD_GLOBAL              4 (ctk)
               LOAD_ATTR               18 (CTkFrame)
               PUSH_NULL
               LOAD_DEREF               0 (self)
               LOAD_ATTR                8 (left_panel)
               LOAD_CONST              23 ('transparent')
               LOAD_CONST              24 (('fg_color',))
               CALL_KW                  2
               STORE_FAST              13 (frame_radio)

  96           LOAD_FAST               13 (frame_radio)
               LOAD_ATTR               17 (pack + NULL|self)
               LOAD_CONST              25 ('x')
               LOAD_CONST               9 (20)
               LOAD_CONST               1 (0)
               LOAD_CONST              27 (('fill', 'padx', 'pady'))
               CALL_KW                  3
               POP_TOP

  97           LOAD_GLOBAL              4 (ctk)
               LOAD_ATTR               52 (CTkRadioButton)
               PUSH_NULL
               LOAD_FAST               13 (frame_radio)
               LOAD_CONST              65 ('Posicionar Carátula')
               LOAD_DEREF               0 (self)
               LOAD_ATTR               54 (current_stamp_type)
               LOAD_CONST              66 ('cover')
               LOAD_DEREF               0 (self)
               LOAD_ATTR               56 (update_preview)
               LOAD_CONST              67 (('text', 'variable', 'value', 'command'))
               CALL_KW                  5
               LOAD_DEREF               0 (self)
               STORE_ATTR              29 (radio_cover)

  98           LOAD_DEREF               0 (self)
               LOAD_ATTR               58 (radio_cover)
               LOAD_ATTR               17 (pack + NULL|self)
               LOAD_CONST              26 (5)
               LOAD_CONST              35 ('w')
               LOAD_CONST              68 (('pady', 'anchor'))
               CALL_KW                  2
               POP_TOP

  99           LOAD_GLOBAL              4 (ctk)
               LOAD_ATTR               52 (CTkRadioButton)
               PUSH_NULL
               LOAD_FAST               13 (frame_radio)
               LOAD_CONST              69 ('Posicionar Cuerpo')
               LOAD_DEREF               0 (self)
               LOAD_ATTR               54 (current_stamp_type)
               LOAD_CONST              70 ('body')
               LOAD_DEREF               0 (self)
               LOAD_ATTR               56 (update_preview)
               LOAD_CONST              67 (('text', 'variable', 'value', 'command'))
               CALL_KW                  5
               LOAD_DEREF               0 (self)
               STORE_ATTR              30 (radio_body)

 100           LOAD_DEREF               0 (self)
               LOAD_ATTR               60 (radio_body)
               LOAD_ATTR               17 (pack + NULL|self)
               LOAD_CONST              26 (5)
               LOAD_CONST              35 ('w')
               LOAD_CONST              68 (('pady', 'anchor'))
               CALL_KW                  2
               POP_TOP

 103           LOAD_GLOBAL              4 (ctk)
               LOAD_ATTR               20 (CTkButton)
               PUSH_NULL
               LOAD_DEREF               0 (self)
               LOAD_ATTR                8 (left_panel)
               LOAD_CONST              71 ('Procesar y Exportar')
               LOAD_CONST              72 ('green')
               LOAD_CONST              73 ('darkgreen')
               LOAD_CONST              44 (40)
               LOAD_GLOBAL              4 (ctk)
               LOAD_ATTR               14 (CTkFont)
               PUSH_NULL
               LOAD_CONST              10 ('bold')
               LOAD_CONST               3 (('weight',))
               CALL_KW                  1
               LOAD_DEREF               0 (self)
               LOAD_ATTR               62 (action_export)
               LOAD_CONST              74 (('text', 'fg_color', 'hover_color', 'height', 'font', 'command'))
               CALL_KW                  7
               LOAD_DEREF               0 (self)
               STORE_ATTR              32 (btn_export)

 104           LOAD_DEREF               0 (self)
               LOAD_ATTR               64 (btn_export)
               LOAD_ATTR               17 (pack + NULL|self)
               LOAD_CONST              25 ('x')
               LOAD_CONST               9 (20)
               LOAD_CONST              75 ((20, 5))
               LOAD_CONST              27 (('fill', 'padx', 'pady'))
               CALL_KW                  3
               POP_TOP

 105           LOAD_GLOBAL              4 (ctk)
               LOAD_ATTR               12 (CTkLabel)
               PUSH_NULL
               LOAD_DEREF               0 (self)
               LOAD_ATTR                8 (left_panel)
               LOAD_CONST              76 ('© L.Navarrete')
               LOAD_CONST              19 ('gray')
               LOAD_GLOBAL              4 (ctk)
               LOAD_ATTR               14 (CTkFont)
               PUSH_NULL
               LOAD_CONST              77 (10)
               LOAD_CONST              17 ('italic')
               LOAD_CONST              18 (('size', 'slant'))
               CALL_KW                  2
               LOAD_CONST              78 (('text', 'text_color', 'font'))
               CALL_KW                  4
               LOAD_DEREF               0 (self)
               STORE_ATTR              33 (lbl_watermark)

 106           LOAD_DEREF               0 (self)
               LOAD_ATTR               66 (lbl_watermark)
               LOAD_ATTR               17 (pack + NULL|self)
               LOAD_CONST              79 ((0, 20))
               LOAD_CONST              22 (('pady',))
               CALL_KW                  1
               POP_TOP

 109           LOAD_GLOBAL              4 (ctk)
               LOAD_ATTR               18 (CTkFrame)
               PUSH_NULL
               LOAD_DEREF               0 (self)
               LOAD_CONST               1 (0)
               LOAD_CONST              80 (('corner_radius',))
               CALL_KW                  2
               LOAD_DEREF               0 (self)
               STORE_ATTR              34 (right_panel)

 110           LOAD_DEREF               0 (self)
               LOAD_ATTR               68 (right_panel)
               LOAD_ATTR               11 (grid + NULL|self)
               LOAD_CONST               1 (0)
               LOAD_CONST               2 (1)
               LOAD_CONST               6 ('nsew')
               LOAD_CONST              77 (10)
               LOAD_CONST              77 (10)
               LOAD_CONST              81 (('row', 'column', 'sticky', 'padx', 'pady'))
               CALL_KW                  5
               POP_TOP

 112           LOAD_GLOBAL              4 (ctk)
               LOAD_ATTR               18 (CTkFrame)
               PUSH_NULL
               LOAD_DEREF               0 (self)
               LOAD_ATTR               68 (right_panel)
               LOAD_CONST              44 (40)
               LOAD_CONST              82 (('height',))
               CALL_KW                  2
               STORE_FAST              14 (frame_paginator)

 113           LOAD_FAST               14 (frame_paginator)
               LOAD_ATTR               17 (pack + NULL|self)
               LOAD_CONST              25 ('x')
               LOAD_CONST              83 ('top')
               LOAD_CONST              21 ((0, 10))
               LOAD_CONST              84 (('fill', 'side', 'pady'))
               CALL_KW                  3
               POP_TOP

 114           LOAD_GLOBAL              4 (ctk)
               LOAD_ATTR               20 (CTkButton)
               PUSH_NULL
               LOAD_FAST               14 (frame_paginator)
               LOAD_CONST              85 ('<')
               LOAD_CONST              44 (40)
               LOAD_DEREF               0 (self)
               LOAD_ATTR               70 (action_prev_page)
               LOAD_CONST              45 (('text', 'width', 'command'))
               CALL_KW                  4
               LOAD_DEREF               0 (self)
               STORE_ATTR              36 (btn_prev_page)

 115           LOAD_DEREF               0 (self)
               LOAD_ATTR               72 (btn_prev_page)
               LOAD_ATTR               17 (pack + NULL|self)
               LOAD_CONST              40 ('left')
               LOAD_CONST              26 (5)
               LOAD_CONST              26 (5)
               LOAD_CONST              86 (('side', 'padx', 'pady'))
               CALL_KW                  3
               POP_TOP

 116           LOAD_GLOBAL              4 (ctk)
               LOAD_ATTR               12 (CTkLabel)
               PUSH_NULL
               LOAD_FAST               14 (frame_paginator)
               LOAD_CONST              87 ('Página 0 / 0')
               LOAD_CONST              34 (('text',))
               CALL_KW                  2
               LOAD_DEREF               0 (self)
               STORE_ATTR              37 (lbl_page_num)

 117           LOAD_DEREF               0 (self)
               LOAD_ATTR               74 (lbl_page_num)
               LOAD_ATTR               17 (pack + NULL|self)
               LOAD_CONST              40 ('left')
               LOAD_CONST              77 (10)
               LOAD_CONST              26 (5)
               LOAD_CONST              86 (('side', 'padx', 'pady'))
               CALL_KW                  3
               POP_TOP

 118           LOAD_GLOBAL              4 (ctk)
               LOAD_ATTR               20 (CTkButton)
               PUSH_NULL
               LOAD_FAST               14 (frame_paginator)
               LOAD_CONST              88 ('>')
               LOAD_CONST              44 (40)
               LOAD_DEREF               0 (self)
               LOAD_ATTR               76 (action_next_page)
               LOAD_CONST              45 (('text', 'width', 'command'))
               CALL_KW                  4
               LOAD_DEREF               0 (self)
               STORE_ATTR              39 (btn_next_page)

 119           LOAD_DEREF               0 (self)
               LOAD_ATTR               78 (btn_next_page)
               LOAD_ATTR               17 (pack + NULL|self)
               LOAD_CONST              40 ('left')
               LOAD_CONST              26 (5)
               LOAD_CONST              26 (5)
               LOAD_CONST              86 (('side', 'padx', 'pady'))
               CALL_KW                  3
               POP_TOP

 120           LOAD_GLOBAL              4 (ctk)
               LOAD_ATTR               20 (CTkButton)
               PUSH_NULL
               LOAD_FAST               14 (frame_paginator)
               LOAD_CONST              89 ('Zoom +')
               LOAD_CONST              90 (60)
               LOAD_DEREF               0 (self)
               LOAD_ATTR               80 (action_zoom_in)
               LOAD_CONST              45 (('text', 'width', 'command'))
               CALL_KW                  4
               LOAD_DEREF               0 (self)
               STORE_ATTR              41 (btn_zoom_in)

 121           LOAD_DEREF               0 (self)
               LOAD_ATTR               82 (btn_zoom_in)
               LOAD_ATTR               17 (pack + NULL|self)
               LOAD_CONST              60 ('right')
               LOAD_CONST              26 (5)
               LOAD_CONST              26 (5)
               LOAD_CONST              86 (('side', 'padx', 'pady'))
               CALL_KW                  3
               POP_TOP

 122           LOAD_GLOBAL              4 (ctk)
               LOAD_ATTR               20 (CTkButton)
               PUSH_NULL
               LOAD_FAST               14 (frame_paginator)
               LOAD_CONST              91 ('Zoom -')
               LOAD_CONST              90 (60)
               LOAD_DEREF               0 (self)
               LOAD_ATTR               84 (action_zoom_out)
               LOAD_CONST              45 (('text', 'width', 'command'))
               CALL_KW                  4
               LOAD_DEREF               0 (self)
               STORE_ATTR              43 (btn_zoom_out)

 123           LOAD_DEREF               0 (self)
               LOAD_ATTR               86 (btn_zoom_out)
               LOAD_ATTR               17 (pack + NULL|self)
               LOAD_CONST              60 ('right')
               LOAD_CONST              26 (5)
               LOAD_CONST              26 (5)
               LOAD_CONST              86 (('side', 'padx', 'pady'))
               CALL_KW                  3
               POP_TOP

 125           LOAD_GLOBAL              4 (ctk)
               LOAD_ATTR               18 (CTkFrame)
               PUSH_NULL
               LOAD_DEREF               0 (self)
               LOAD_ATTR               68 (right_panel)
               CALL                     1
               LOAD_DEREF               0 (self)
               STORE_ATTR              44 (canvas_panel)

 126           LOAD_DEREF               0 (self)
               LOAD_ATTR               88 (canvas_panel)
               LOAD_ATTR               17 (pack + NULL|self)
               LOAD_CONST              92 ('both')
               LOAD_CONST              51 (True)
               LOAD_CONST              93 (('fill', 'expand'))
               CALL_KW                  2
               POP_TOP

 127           LOAD_GLOBAL             90 (tk)
               LOAD_ATTR               92 (Canvas)
               PUSH_NULL
               LOAD_DEREF               0 (self)
               LOAD_ATTR               88 (canvas_panel)
               LOAD_CONST              94 ('gray20')
               LOAD_CONST               1 (0)
               LOAD_CONST              95 (('bg', 'highlightthickness'))
               CALL_KW                  3
               LOAD_DEREF               0 (self)
               STORE_ATTR              47 (canvas)

 128           LOAD_DEREF               0 (self)
               LOAD_ATTR               94 (canvas)
               LOAD_ATTR               17 (pack + NULL|self)
               LOAD_CONST              92 ('both')
               LOAD_CONST              51 (True)
               LOAD_CONST              93 (('fill', 'expand'))
               CALL_KW                  2
               POP_TOP

 129           LOAD_DEREF               0 (self)
               LOAD_ATTR               94 (canvas)
               LOAD_ATTR               97 (bind + NULL|self)
               LOAD_CONST              96 ('<Button-1>')
               LOAD_DEREF               0 (self)
               LOAD_ATTR               98 (on_canvas_click)
               CALL                     2
               POP_TOP

 132           NOP

 133   L1:     LOAD_CONST               1 (0)
               LOAD_CONST               0 (None)
               IMPORT_NAME             50 (windnd)
               STORE_DEREF             16 (windnd)

 134           LOAD_FAST                0 (self)
               BUILD_TUPLE              1
               LOAD_CONST              97 (<code object on_drop at 0x0000028A6B13D6F0, file "src\ui\tab_autofirma.py", line 134>)
               MAKE_FUNCTION
               SET_FUNCTION_ATTRIBUTE   8 (closure)
               STORE_DEREF             15 (on_drop)

 142           LOAD_DEREF               0 (self)
               LOAD_ATTR              103 (after + NULL|self)
               LOAD_CONST              98 (500)
               LOAD_FAST               15 (on_drop)
               LOAD_FAST                0 (self)
               LOAD_FAST               16 (windnd)
               BUILD_TUPLE              3
               LOAD_CONST              99 (<code object <lambda> at 0x0000028A6B654290, file "src\ui\tab_autofirma.py", line 142>)
               MAKE_FUNCTION
               SET_FUNCTION_ATTRIBUTE   8 (closure)
               CALL                     2
               POP_TOP
       L2:     RETURN_CONST             0 (None)

  --   L3:     PUSH_EXC_INFO

 143           LOAD_GLOBAL            104 (ImportError)
               CHECK_EXC_MATCH
               POP_JUMP_IF_FALSE        3 (to L5)
               POP_TOP

 144   L4:     POP_EXCEPT
               RETURN_CONST             0 (None)

 143   L5:     RERAISE                  0

  --   L6:     COPY                     3
               POP_EXCEPT
               RERAISE                  1
ExceptionTable:
  L1 to L2 -> L3 [0]
  L3 to L4 -> L6 [1] lasti
  L5 to L6 -> L6 [1] lasti

Disassembly of <code object on_drop at 0x0000028A6B13D6F0, file "src\ui\tab_autofirma.py", line 134>:
  --           COPY_FREE_VARS           1

 134           RESUME                   0

 135           LOAD_FAST                0 (files)
               TO_BOOL
               POP_JUMP_IF_TRUE         1 (to L1)
               RETURN_CONST             0 (None)

 136   L1:     LOAD_FAST                0 (files)
               LOAD_CONST               1 (0)
               BINARY_SUBSCR
               LOAD_ATTR                1 (decode + NULL|self)
               LOAD_CONST               2 ('gbk')
               LOAD_CONST               3 ('ignore')
               LOAD_CONST               4 (('errors',))
               CALL_KW                  2
               STORE_FAST               1 (path)

 137           LOAD_FAST                1 (path)
               LOAD_ATTR                3 (lower + NULL|self)
               CALL                     0
               LOAD_ATTR                5 (endswith + NULL|self)
               LOAD_CONST               5 ('.pdf')
               CALL                     1
               TO_BOOL
               POP_JUMP_IF_FALSE       18 (to L2)

 138           LOAD_DEREF               2 (self)
               LOAD_ATTR                7 (load_pdf_from_path + NULL|self)
               LOAD_FAST                1 (path)
               CALL                     1
               POP_TOP
               RETURN_CONST             0 (None)

 140   L2:     LOAD_GLOBAL              8 (messagebox)
               LOAD_ATTR               10 (showwarning)
               PUSH_NULL
               LOAD_CONST               6 ('Formato Inválido')
               LOAD_CONST               7 ('Por favor arrastra un archivo PDF.')
               CALL                     2
               POP_TOP
               RETURN_CONST             0 (None)

Disassembly of <code object <lambda> at 0x0000028A6B654290, file "src\ui\tab_autofirma.py", line 142>:
  --           COPY_FREE_VARS           3

 142           RESUME                   0
               LOAD_DEREF               2 (windnd)
               LOAD_ATTR                1 (hook_dropfiles + NULL|self)
               LOAD_DEREF               1 (self)
               LOAD_ATTR                3 (winfo_toplevel + NULL|self)
               CALL                     0
               LOAD_ATTR                5 (winfo_id + NULL|self)
               CALL                     0
               LOAD_DEREF               0 (on_drop)
               LOAD_CONST               1 (('func',))
               CALL_KW                  2
               RETURN_VALUE

Disassembly of <code object open_config_sello1 at 0x0000028A6B18F330, file "src\ui\tab_autofirma.py", line 147>:
147           RESUME                   0

148           LOAD_GLOBAL              1 (ConfigSello1Window + NULL)
              LOAD_FAST_LOAD_FAST      0 (self, self)
              LOAD_ATTR                2 (config_manager)
              LOAD_FAST                0 (self)
              LOAD_ATTR                4 (update_preview)
              LOAD_CONST               1 (('on_close_callback',))
              CALL_KW                  3
              POP_TOP
              RETURN_CONST             0 (None)

Disassembly of <code object open_config_sello2 at 0x0000028A6B36F880, file "src\ui\tab_autofirma.py", line 150>:
150           RESUME                   0

151           LOAD_GLOBAL              1 (ConfigSello2Window + NULL)
              LOAD_FAST_LOAD_FAST      0 (self, self)
              LOAD_ATTR                2 (config_manager)
              LOAD_FAST                0 (self)
              LOAD_ATTR                4 (update_preview)
              LOAD_CONST               1 (('on_close_callback',))
              CALL_KW                  3
              POP_TOP
              RETURN_CONST             0 (None)

Disassembly of <code object on_toggle_sellos at 0x0000028A6B171F30, file "src\ui\tab_autofirma.py", line 153>:
153           RESUME                   0

154           LOAD_FAST                0 (self)
              LOAD_ATTR                0 (var_apply_sello1)
              LOAD_ATTR                3 (get + NULL|self)
              CALL                     0
              LOAD_FAST                0 (self)
              LOAD_ATTR                4 (config_manager)
              LOAD_ATTR                6 (config)
              LOAD_CONST               1 ('apply_sello1')
              STORE_SUBSCR

155           LOAD_FAST                0 (self)
              LOAD_ATTR                8 (var_apply_sello2)
              LOAD_ATTR                3 (get + NULL|self)
              CALL                     0
              LOAD_FAST                0 (self)
              LOAD_ATTR                4 (config_manager)
              LOAD_ATTR                6 (config)
              LOAD_CONST               2 ('apply_sello2')
              STORE_SUBSCR

156           LOAD_FAST                0 (self)
              LOAD_ATTR                4 (config_manager)
              LOAD_ATTR               11 (save_config + NULL|self)
              CALL                     0
              POP_TOP

157           LOAD_FAST                0 (self)
              LOAD_ATTR               13 (update_preview + NULL|self)
              CALL                     0
              POP_TOP
              RETURN_CONST             0 (None)

Disassembly of <code object set_today at 0x0000028A6B3B1DE0, file "src\ui\tab_autofirma.py", line 159>:
159           RESUME                   0

160           LOAD_CONST               1 (0)
              LOAD_CONST               2 (('datetime',))
              IMPORT_NAME              0 (datetime)
              IMPORT_FROM              0 (datetime)
              STORE_FAST               1 (datetime)
              POP_TOP

161           LOAD_FAST                0 (self)
              LOAD_ATTR                2 (entry_start_date)
              LOAD_ATTR                5 (delete + NULL|self)
              LOAD_CONST               1 (0)
              LOAD_CONST               3 ('end')
              CALL                     2
              POP_TOP

162           LOAD_FAST                0 (self)
              LOAD_ATTR                2 (entry_start_date)
              LOAD_ATTR                7 (insert + NULL|self)
              LOAD_CONST               1 (0)
              LOAD_FAST                1 (datetime)
              LOAD_ATTR                9 (today + NULL|self)
              CALL                     0
              LOAD_ATTR               11 (strftime + NULL|self)
              LOAD_CONST               4 ('%d/%m/%Y')
              CALL                     1
              CALL                     2
              POP_TOP
              RETURN_CONST             0 (None)

Disassembly of <code object load_profile at 0x0000028A6B13DBD0, file "src\ui\tab_autofirma.py", line 164>:
164           RESUME                   0

165           LOAD_FAST                0 (self)
              LOAD_ATTR                1 (get_resource_path + NULL|self)
              LOAD_CONST               1 ('assets/plantilla_caratula.png')
              CALL                     1
              STORE_FAST               1 (tpl_path)

166           LOAD_FAST                0 (self)
              LOAD_ATTR                2 (config_manager)
              LOAD_ATTR                5 (set + NULL|self)
              LOAD_CONST               2 ('template_path')
              LOAD_FAST                1 (tpl_path)
              CALL                     2
              POP_TOP

167           LOAD_FAST                0 (self)
              LOAD_ATTR                6 (entry_start_date)
              LOAD_ATTR                9 (insert + NULL|self)
              LOAD_CONST               3 (0)
              LOAD_FAST                0 (self)
              LOAD_ATTR                2 (config_manager)
              LOAD_ATTR               11 (get + NULL|self)
              LOAD_CONST               4 ('start_date')
              LOAD_CONST               5 ('')
              CALL                     2
              CALL                     2
              POP_TOP
              RETURN_CONST             0 (None)

Disassembly of <code object save_profile at 0x0000028A6B172120, file "src\ui\tab_autofirma.py", line 169>:
169           RESUME                   0

170           LOAD_FAST                0 (self)
              LOAD_ATTR                0 (entry_start_date)
              LOAD_ATTR                3 (get + NULL|self)
              CALL                     0
              LOAD_FAST                0 (self)
              LOAD_ATTR                4 (config_manager)
              LOAD_ATTR                6 (config)
              LOAD_CONST               1 ('start_date')
              STORE_SUBSCR

171           LOAD_FAST                0 (self)
              LOAD_ATTR                8 (cover_coords)
              LOAD_FAST                0 (self)
              LOAD_ATTR                4 (config_manager)
              LOAD_ATTR                6 (config)
              LOAD_CONST               2 ('cover_coords')
              STORE_SUBSCR

172           LOAD_FAST                0 (self)
              LOAD_ATTR               10 (body_coords)
              LOAD_FAST                0 (self)
              LOAD_ATTR                4 (config_manager)
              LOAD_ATTR                6 (config)
              LOAD_CONST               3 ('body_coords')
              STORE_SUBSCR

173           LOAD_FAST                0 (self)
              LOAD_ATTR                4 (config_manager)
              LOAD_ATTR               13 (save_config + NULL|self)
              CALL                     0
              POP_TOP
              RETURN_CONST             0 (None)

Disassembly of <code object get_resource_path at 0x0000028A6B4296A0, file "src\ui\tab_autofirma.py", line 175>:
 175           RESUME                   0

 177           LOAD_CONST               1 (0)
               LOAD_CONST               2 (None)
               IMPORT_NAME              0 (sys)
               STORE_FAST               2 (sys)

 178           NOP

 180   L1:     LOAD_FAST                2 (sys)
               LOAD_ATTR                2 (_MEIPASS)
               STORE_FAST               3 (base_path)

 184   L2:     LOAD_GLOBAL              6 (os)
               LOAD_ATTR                8 (path)
               LOAD_ATTR               13 (join + NULL|self)
               LOAD_FAST_LOAD_FAST     49 (base_path, relative_path)
               CALL                     2
               RETURN_VALUE

  --   L3:     PUSH_EXC_INFO

 181           LOAD_GLOBAL              4 (Exception)
               CHECK_EXC_MATCH
               POP_JUMP_IF_FALSE       98 (to L5)
               POP_TOP

 182           LOAD_GLOBAL              6 (os)
               LOAD_ATTR                8 (path)
               LOAD_ATTR               11 (abspath + NULL|self)
               LOAD_GLOBAL              6 (os)
               LOAD_ATTR                8 (path)
               LOAD_ATTR               13 (join + NULL|self)
               LOAD_GLOBAL              6 (os)
               LOAD_ATTR                8 (path)
               LOAD_ATTR               15 (dirname + NULL|self)
               LOAD_GLOBAL             16 (__file__)
               CALL                     1
               LOAD_CONST               3 ('..')
               LOAD_CONST               3 ('..')
               CALL                     3
               CALL                     1
               STORE_FAST               3 (base_path)
       L4:     POP_EXCEPT
               JUMP_BACKWARD_NO_INTERRUPT 138 (to L2)

 181   L5:     RERAISE                  0

  --   L6:     COPY                     3
               POP_EXCEPT
               RERAISE                  1
ExceptionTable:
  L1 to L2 -> L3 [0]
  L3 to L4 -> L6 [1] lasti
  L5 to L6 -> L6 [1] lasti

Disassembly of <code object action_load_template at 0x0000028A6B382B40, file "src\ui\tab_autofirma.py", line 186>:
186           RESUME                   0

187           RETURN_CONST             0 (None)

Disassembly of <code object action_edit_template_layout at 0x0000028A6B13DF10, file "src\ui\tab_autofirma.py", line 189>:
189           RESUME                   0

190           LOAD_FAST                0 (self)
              LOAD_ATTR                1 (get_resource_path + NULL|self)
              LOAD_CONST               1 ('assets/plantilla_caratula.png')
              CALL                     1
              STORE_FAST               1 (base_template)

191           LOAD_GLOBAL              2 (os)
              LOAD_ATTR                4 (path)
              LOAD_ATTR                7 (exists + NULL|self)
              LOAD_FAST                1 (base_template)
              CALL                     1
              TO_BOOL
              POP_JUMP_IF_TRUE        28 (to L1)

192           LOAD_GLOBAL              8 (messagebox)
              LOAD_ATTR               10 (showwarning)
              PUSH_NULL
              LOAD_CONST               2 ('Atención')
              LOAD_CONST               3 ('No se encontró la plantilla default en ')
              LOAD_FAST                1 (base_template)
              FORMAT_SIMPLE
              LOAD_CONST               4 ('.')
              BUILD_STRING             3
              CALL                     2
              POP_TOP

193           RETURN_CONST             0 (None)

194   L1:     LOAD_GLOBAL             13 (LayoutEditorWindow + NULL)
              LOAD_FAST_LOAD_FAST      0 (self, self)
              LOAD_ATTR               14 (config_manager)
              LOAD_FAST                1 (base_template)
              CALL                     3
              POP_TOP
              RETURN_CONST             0 (None)

Disassembly of <code object action_load_signature at 0x0000028A6B185830, file "src\ui\tab_autofirma.py", line 196>:
196           RESUME                   0

197           LOAD_GLOBAL              0 (filedialog)
              LOAD_ATTR                2 (askopenfilename)
              PUSH_NULL
              LOAD_CONST               1 ('Seleccionar Firma PNG')
              LOAD_CONST               2 (('PNG transparent', '*.png'))
              BUILD_LIST               1
              LOAD_CONST               3 (('title', 'filetypes'))
              CALL_KW                  2
              STORE_FAST               1 (path)

198           LOAD_FAST                1 (path)
              TO_BOOL
              POP_JUMP_IF_FALSE       60 (to L1)

199           LOAD_FAST                0 (self)
              LOAD_ATTR                4 (config_manager)
              LOAD_ATTR                7 (set + NULL|self)
              LOAD_CONST               4 ('signature_path')
              LOAD_FAST                1 (path)
              CALL                     2
              POP_TOP

200           LOAD_FAST                0 (self)
              LOAD_ATTR                8 (lbl_sig_path)
              LOAD_ATTR               11 (configure + NULL|self)
              LOAD_CONST               5 ('...')
              LOAD_FAST                1 (path)
              LOAD_CONST               6 (-25)
              LOAD_CONST               0 (None)
              BINARY_SLICE
              FORMAT_SIMPLE
              BUILD_STRING             2
              LOAD_CONST               7 (('text',))
              CALL_KW                  1
              POP_TOP
              RETURN_CONST             0 (None)

198   L1:     RETURN_CONST             0 (None)

Disassembly of <code object load_pdf_from_path at 0x0000028A6B4167B0, file "src\ui\tab_autofirma.py", line 202>:
202           RESUME                   0

203           LOAD_FAST                1 (path)
              TO_BOOL
              POP_JUMP_IF_FALSE      218 (to L3)
              LOAD_GLOBAL              0 (os)
              LOAD_ATTR                2 (path)
              LOAD_ATTR                5 (exists + NULL|self)
              LOAD_FAST                1 (path)
              CALL                     1
              TO_BOOL
              POP_JUMP_IF_FALSE      181 (to L2)

204           LOAD_FAST_LOAD_FAST     16 (path, self)
              STORE_ATTR               3 (pdf_path)

205           LOAD_FAST                0 (self)
              LOAD_ATTR                8 (pdf_manager)
              LOAD_ATTR               11 (load_pdf + NULL|self)
              LOAD_FAST                1 (path)
              CALL                     1
              UNPACK_SEQUENCE          2
              LOAD_FAST                0 (self)
              STORE_ATTR               6 (pdf_doc)
              LOAD_FAST                0 (self)
              STORE_ATTR               7 (total_pages)

207           LOAD_FAST                0 (self)
              LOAD_ATTR               14 (total_pages)
              LOAD_CONST               1 (0)
              COMPARE_OP             148 (bool(>))
              POP_JUMP_IF_FALSE       95 (to L1)

208           LOAD_FAST                0 (self)
              LOAD_ATTR               16 (lbl_pdf_info)
              LOAD_ATTR               19 (configure + NULL|self)
              LOAD_CONST               2 ('Cargado: ')
              LOAD_GLOBAL              0 (os)
              LOAD_ATTR                2 (path)
              LOAD_ATTR               21 (basename + NULL|self)
              LOAD_FAST                1 (path)
              CALL                     1
              FORMAT_SIMPLE
              LOAD_CONST               3 (' (')
              LOAD_FAST                0 (self)
              LOAD_ATTR               14 (total_pages)
              FORMAT_SIMPLE
              LOAD_CONST               4 (' págs)')
              BUILD_STRING             5
              LOAD_CONST               5 (('text',))
              CALL_KW                  1
              POP_TOP

209           LOAD_CONST               1 (0)
              LOAD_FAST                0 (self)
              STORE_ATTR              11 (current_preview_page)

210           LOAD_FAST                0 (self)
              LOAD_ATTR               25 (update_preview + NULL|self)
              CALL                     0
              POP_TOP
              RETURN_CONST             0 (None)

212   L1:     LOAD_GLOBAL             26 (messagebox)
              LOAD_ATTR               28 (showerror)
              PUSH_NULL
              LOAD_CONST               6 ('Error')
              LOAD_CONST               7 ('No se pudo cargar el archivo PDF.')
              CALL                     2
              POP_TOP
              RETURN_CONST             0 (None)

203   L2:     RETURN_CONST             0 (None)
      L3:     RETURN_CONST             0 (None)

Disassembly of <code object action_load_pdf at 0x0000028A6B6543C0, file "src\ui\tab_autofirma.py", line 214>:
214           RESUME                   0

215           LOAD_GLOBAL              0 (filedialog)
              LOAD_ATTR                2 (askopenfilename)
              PUSH_NULL
              LOAD_CONST               1 ('Seleccionar PDF a sellar')
              LOAD_CONST               2 (('Archivos PDF', '*.pdf'))
              BUILD_LIST               1
              LOAD_CONST               3 (('title', 'filetypes'))
              CALL_KW                  2
              STORE_FAST               1 (path)

216           LOAD_FAST                1 (path)
              TO_BOOL
              POP_JUMP_IF_FALSE       18 (to L1)

217           LOAD_FAST                0 (self)
              LOAD_ATTR                5 (load_pdf_from_path + NULL|self)
              LOAD_FAST                1 (path)
              CALL                     1
              POP_TOP
              RETURN_CONST             0 (None)

216   L1:     RETURN_CONST             0 (None)

Disassembly of <code object action_prev_page at 0x0000028A6B143CB0, file "src\ui\tab_autofirma.py", line 219>:
219           RESUME                   0

220           LOAD_FAST                0 (self)
              LOAD_ATTR                0 (total_pages)
              LOAD_CONST               1 (0)
              COMPARE_OP             148 (bool(>))
              POP_JUMP_IF_FALSE       55 (to L2)
              LOAD_FAST                0 (self)
              LOAD_ATTR                2 (current_preview_page)
              LOAD_CONST               1 (0)
              COMPARE_OP             148 (bool(>))
              POP_JUMP_IF_FALSE       38 (to L1)

221           LOAD_FAST                0 (self)
              COPY                     1
              LOAD_ATTR                2 (current_preview_page)
              LOAD_CONST               2 (1)
              BINARY_OP               23 (-=)
              SWAP                     2
              STORE_ATTR               1 (current_preview_page)

222           LOAD_FAST                0 (self)
              LOAD_ATTR                5 (update_preview + NULL|self)
              CALL                     0
              POP_TOP
              RETURN_CONST             0 (None)

220   L1:     RETURN_CONST             0 (None)
      L2:     RETURN_CONST             0 (None)

Disassembly of <code object action_next_page at 0x0000028A6B185B30, file "src\ui\tab_autofirma.py", line 224>:
224           RESUME                   0

225           LOAD_FAST                0 (self)
              LOAD_ATTR                0 (total_pages)
              LOAD_CONST               1 (0)
              COMPARE_OP             148 (bool(>))
              POP_JUMP_IF_FALSE       68 (to L2)
              LOAD_FAST                0 (self)
              LOAD_ATTR                2 (current_preview_page)
              LOAD_FAST                0 (self)
              LOAD_ATTR                0 (total_pages)
              LOAD_CONST               2 (1)
              BINARY_OP               10 (-)
              COMPARE_OP              18 (bool(<))
              POP_JUMP_IF_FALSE       38 (to L1)

226           LOAD_FAST                0 (self)
              COPY                     1
              LOAD_ATTR                2 (current_preview_page)
              LOAD_CONST               2 (1)
              BINARY_OP               13 (+=)
              SWAP                     2
              STORE_ATTR               1 (current_preview_page)

227           LOAD_FAST                0 (self)
              LOAD_ATTR                5 (update_preview + NULL|self)
              CALL                     0
              POP_TOP
              RETURN_CONST             0 (None)

225   L1:     RETURN_CONST             0 (None)
      L2:     RETURN_CONST             0 (None)

Disassembly of <code object action_zoom_in at 0x0000028A6B167E10, file "src\ui\tab_autofirma.py", line 229>:
229           RESUME                   0

230           LOAD_FAST                0 (self)
              COPY                     1
              LOAD_ATTR                0 (canvas_scale)
              LOAD_CONST               1 (0.2)
              BINARY_OP               13 (+=)
              SWAP                     2
              STORE_ATTR               0 (canvas_scale)

231           LOAD_FAST                0 (self)
              LOAD_ATTR                3 (update_preview + NULL|self)
              CALL                     0
              POP_TOP
              RETURN_CONST             0 (None)

Disassembly of <code object action_zoom_out at 0x0000028A6B3AC7B0, file "src\ui\tab_autofirma.py", line 233>:
233           RESUME                   0

234           LOAD_FAST                0 (self)
              LOAD_ATTR                0 (canvas_scale)
              LOAD_CONST               1 (0.4)
              COMPARE_OP             148 (bool(>))
              POP_JUMP_IF_FALSE       38 (to L1)

235           LOAD_FAST                0 (self)
              COPY                     1
              LOAD_ATTR                0 (canvas_scale)
              LOAD_CONST               2 (0.2)
              BINARY_OP               23 (-=)
              SWAP                     2
              STORE_ATTR               0 (canvas_scale)

236           LOAD_FAST                0 (self)
              LOAD_ATTR                3 (update_preview + NULL|self)
              CALL                     0
              POP_TOP
              RETURN_CONST             0 (None)

234   L1:     RETURN_CONST             0 (None)

Disassembly of <code object action_preview_cover_stamp_from_popup at 0x0000028A6B423910, file "src\ui\tab_autofirma.py", line 238>:
 238           RESUME                   0

 239           LOAD_FAST                0 (self)
               LOAD_ATTR                1 (save_profile + NULL|self)
               CALL                     0
               POP_TOP

 240           LOAD_FAST                0 (self)
               LOAD_ATTR                2 (config_manager)
               LOAD_ATTR                5 (get + NULL|self)
               LOAD_CONST               1 ('signature_path')
               CALL                     1
               STORE_FAST               2 (sig_path)

 241           LOAD_FAST                0 (self)
               LOAD_ATTR                2 (config_manager)
               LOAD_ATTR                5 (get + NULL|self)
               LOAD_CONST               2 ('start_date')
               LOAD_CONST               3 ('')
               CALL                     2
               STORE_FAST               3 (start_date)

 242           LOAD_FAST                0 (self)
               LOAD_ATTR                7 (get_resource_path + NULL|self)
               LOAD_CONST               4 ('assets/plantilla_caratula.png')
               CALL                     1
               STORE_FAST               4 (base_template)

 244           LOAD_GLOBAL              8 (os)
               LOAD_ATTR               10 (path)
               LOAD_ATTR               13 (exists + NULL|self)
               LOAD_FAST                4 (base_template)
               CALL                     1
               TO_BOOL
               POP_JUMP_IF_TRUE        63 (to L1)

 245           LOAD_FAST                1 (popup)
               LOAD_ATTR               15 (attributes + NULL|self)
               LOAD_CONST               5 ('-topmost')
               LOAD_CONST               6 (False)
               CALL                     2
               POP_TOP

 246           LOAD_GLOBAL             16 (messagebox)
               LOAD_ATTR               18 (showwarning)
               PUSH_NULL
               LOAD_CONST               7 ('Falta Plantilla')
               LOAD_CONST               8 ('Falta plantilla principal en: ')
               LOAD_FAST                4 (base_template)
               FORMAT_SIMPLE
               BUILD_STRING             2
               CALL                     2
               POP_TOP

 247           LOAD_FAST                1 (popup)
               LOAD_ATTR               15 (attributes + NULL|self)
               LOAD_CONST               5 ('-topmost')
               LOAD_CONST               9 (True)
               CALL                     2
               POP_TOP

 248           RETURN_CONST             0 (None)

 250   L1:     NOP

 252   L2:     LOAD_FAST                0 (self)
               LOAD_ATTR                2 (config_manager)
               LOAD_ATTR                5 (get + NULL|self)
               LOAD_CONST              10 ('tpl_date1_coords')
               CALL                     1

 253           LOAD_FAST                0 (self)
               LOAD_ATTR                2 (config_manager)
               LOAD_ATTR                5 (get + NULL|self)
               LOAD_CONST              11 ('tpl_date2_coords')
               CALL                     1

 254           LOAD_FAST                0 (self)
               LOAD_ATTR                2 (config_manager)
               LOAD_ATTR                5 (get + NULL|self)
               LOAD_CONST              12 ('tpl_sig_coords')
               CALL                     1

 255           LOAD_FAST                0 (self)
               LOAD_ATTR                2 (config_manager)
               LOAD_ATTR                5 (get + NULL|self)
               LOAD_CONST              13 ('tpl_date_scale')
               LOAD_CONST              14 (100)
               CALL                     2

 256           LOAD_FAST                0 (self)
               LOAD_ATTR                2 (config_manager)
               LOAD_ATTR                5 (get + NULL|self)
               LOAD_CONST              15 ('tpl_sig_scale')
               LOAD_CONST              14 (100)
               CALL                     2

 251           LOAD_CONST              16 (('date1', 'date2', 'sig', 'date_scale', 'sig_scale'))
               BUILD_CONST_KEY_MAP      5
               STORE_FAST               5 (layout_cfg)

 258           LOAD_FAST                0 (self)
               LOAD_ATTR               20 (stamp_engine)
               LOAD_ATTR               23 (generate_cover_stamp + NULL|self)
               LOAD_FAST_LOAD_FAST     66 (base_template, sig_path)
               LOAD_FAST_LOAD_FAST     53 (start_date, layout_cfg)
               LOAD_CONST              17 (('layout_coords',))
               CALL_KW                  4
               STORE_FAST               6 (cover_img)

 260           LOAD_GLOBAL             24 (ctk)
               LOAD_ATTR               26 (CTkToplevel)
               PUSH_NULL
               LOAD_FAST                0 (self)
               CALL                     1
               STORE_FAST               7 (top)

 261           LOAD_FAST                7 (top)
               LOAD_ATTR               29 (title + NULL|self)
               LOAD_CONST              18 ('Previsualización Sello Carátula')
               CALL                     1
               POP_TOP

 262           LOAD_FAST                7 (top)
               LOAD_ATTR               31 (geometry + NULL|self)
               LOAD_CONST              19 ('600x400')
               CALL                     1
               POP_TOP

 263           LOAD_FAST                7 (top)
               LOAD_ATTR               15 (attributes + NULL|self)
               LOAD_CONST               5 ('-topmost')
               LOAD_CONST               9 (True)
               CALL                     2
               POP_TOP

 265           LOAD_GLOBAL             32 (ImageTk)
               LOAD_ATTR               34 (PhotoImage)
               PUSH_NULL
               LOAD_FAST                6 (cover_img)
               CALL                     1
               STORE_FAST               8 (tk_img)

 266           LOAD_GLOBAL             24 (ctk)
               LOAD_ATTR               36 (CTkLabel)
               PUSH_NULL
               LOAD_FAST_LOAD_FAST    120 (top, tk_img)
               LOAD_CONST               3 ('')
               LOAD_CONST              20 (('image', 'text'))
               CALL_KW                  3
               STORE_FAST               9 (lbl)

 267           LOAD_FAST                9 (lbl)
               LOAD_ATTR               39 (pack + NULL|self)
               LOAD_CONST               9 (True)
               LOAD_CONST              21 (20)
               LOAD_CONST              21 (20)
               LOAD_CONST              22 (('expand', 'padx', 'pady'))
               CALL_KW                  3
               POP_TOP
       L3:     RETURN_CONST             0 (None)

  --   L4:     PUSH_EXC_INFO

 269           LOAD_GLOBAL             40 (Exception)
               CHECK_EXC_MATCH
               POP_JUMP_IF_FALSE       72 (to L8)
               STORE_FAST              10 (e)

 270   L5:     LOAD_FAST                1 (popup)
               LOAD_ATTR               15 (attributes + NULL|self)
               LOAD_CONST               5 ('-topmost')
               LOAD_CONST               6 (False)
               CALL                     2
               POP_TOP

 271           LOAD_GLOBAL             16 (messagebox)
               LOAD_ATTR               42 (showerror)
               PUSH_NULL
               LOAD_CONST              23 ('Error')
               LOAD_CONST              24 ('No se pudo generar el sello: ')
               LOAD_FAST               10 (e)
               FORMAT_SIMPLE
               BUILD_STRING             2
               CALL                     2
               POP_TOP

 272           LOAD_FAST                1 (popup)
               LOAD_ATTR               15 (attributes + NULL|self)
               LOAD_CONST               5 ('-topmost')
               LOAD_CONST               9 (True)
               CALL                     2
               POP_TOP
       L6:     POP_EXCEPT
               LOAD_CONST               0 (None)
               STORE_FAST              10 (e)
               DELETE_FAST             10 (e)
               RETURN_CONST             0 (None)

  --   L7:     LOAD_CONST               0 (None)
               STORE_FAST              10 (e)
               DELETE_FAST             10 (e)
               RERAISE                  1

 269   L8:     RERAISE                  0

  --   L9:     COPY                     3
               POP_EXCEPT
               RERAISE                  1
ExceptionTable:
  L2 to L3 -> L4 [0]
  L4 to L5 -> L9 [1] lasti
  L5 to L6 -> L7 [1] lasti
  L7 to L9 -> L9 [1] lasti

Disassembly of <code object update_preview at 0x0000028A6B422810, file "src\ui\tab_autofirma.py", line 274>:
274           RESUME                   0

275           LOAD_FAST                0 (self)
              LOAD_ATTR                0 (pdf_doc)
              TO_BOOL
              POP_JUMP_IF_TRUE         1 (to L1)
              RETURN_CONST             0 (None)

276   L1:     LOAD_FAST                0 (self)
              LOAD_ATTR                2 (lbl_page_num)
              LOAD_ATTR                5 (configure + NULL|self)
              LOAD_CONST               1 ('Página ')
              LOAD_FAST                0 (self)
              LOAD_ATTR                6 (current_preview_page)
              LOAD_CONST               2 (1)
              BINARY_OP                0 (+)
              FORMAT_SIMPLE
              LOAD_CONST               3 (' / ')
              LOAD_FAST                0 (self)
              LOAD_ATTR                8 (total_pages)
              FORMAT_SIMPLE
              BUILD_STRING             4
              LOAD_CONST               4 (('text',))
              CALL_KW                  1
              POP_TOP

278           LOAD_FAST                0 (self)
              LOAD_ATTR               10 (pdf_manager)
              LOAD_ATTR               13 (get_page_image + NULL|self)
              LOAD_FAST                0 (self)
              LOAD_ATTR                0 (pdf_doc)
              LOAD_FAST                0 (self)
              LOAD_ATTR                6 (current_preview_page)
              LOAD_FAST                0 (self)
              LOAD_ATTR               14 (canvas_scale)
              LOAD_CONST               5 (('zoom',))
              CALL_KW                  3
              LOAD_FAST                0 (self)
              STORE_ATTR               8 (preview_image_pil)

279           LOAD_FAST                0 (self)
              LOAD_ATTR               16 (preview_image_pil)
              TO_BOOL
              POP_JUMP_IF_TRUE         1 (to L2)
              RETURN_CONST             0 (None)

281   L2:     LOAD_GLOBAL             18 (ImageTk)
              LOAD_ATTR               20 (PhotoImage)
              PUSH_NULL
              LOAD_FAST                0 (self)
              LOAD_ATTR               16 (preview_image_pil)
              CALL                     1
              LOAD_FAST                0 (self)
              STORE_ATTR              11 (preview_image_tk)

282           LOAD_FAST                0 (self)
              LOAD_ATTR               24 (canvas)
              LOAD_ATTR               27 (delete + NULL|self)
              LOAD_CONST               6 ('all')
              CALL                     1
              POP_TOP

283           LOAD_FAST                0 (self)
              LOAD_ATTR               24 (canvas)
              LOAD_ATTR               29 (create_image + NULL|self)
              LOAD_CONST               7 (0)
              LOAD_CONST               7 (0)
              LOAD_CONST               8 ('nw')
              LOAD_FAST                0 (self)
              LOAD_ATTR               22 (preview_image_tk)
              LOAD_CONST               9 (('anchor', 'image'))
              CALL_KW                  4
              POP_TOP

284           LOAD_FAST                0 (self)
              LOAD_ATTR               24 (canvas)
              LOAD_ATTR               31 (config + NULL|self)
              LOAD_FAST                0 (self)
              LOAD_ATTR               24 (canvas)
              LOAD_ATTR               33 (bbox + NULL|self)
              LOAD_CONST               6 ('all')
              CALL                     1
              LOAD_CONST              10 (('scrollregion',))
              CALL_KW                  1
              POP_TOP

285           LOAD_FAST                0 (self)
              LOAD_ATTR               35 (draw_ghost_rect + NULL|self)
              CALL                     0
              POP_TOP
              RETURN_CONST             0 (None)

Disassembly of <code object on_canvas_click at 0x0000028A6B42F740, file "src\ui\tab_autofirma.py", line 287>:
287           RESUME                   0

288           LOAD_FAST                0 (self)
              LOAD_ATTR                0 (pdf_doc)
              TO_BOOL
              POP_JUMP_IF_TRUE         1 (to L1)
              RETURN_CONST             0 (None)

289   L1:     LOAD_GLOBAL              3 (int + NULL)
              LOAD_FAST                1 (event)
              LOAD_ATTR                4 (x)
              LOAD_FAST                0 (self)
              LOAD_ATTR                6 (canvas_scale)
              BINARY_OP               11 (/)
              CALL                     1
              STORE_FAST               2 (real_x)

290           LOAD_GLOBAL              3 (int + NULL)
              LOAD_FAST                1 (event)
              LOAD_ATTR                8 (y)
              LOAD_FAST                0 (self)
              LOAD_ATTR                6 (canvas_scale)
              BINARY_OP               11 (/)
              CALL                     1
              STORE_FAST               3 (real_y)

291           LOAD_FAST                0 (self)
              LOAD_ATTR               10 (current_stamp_type)
              LOAD_ATTR               13 (get + NULL|self)
              CALL                     0
              STORE_FAST               4 (mode)

292           LOAD_FAST                4 (mode)
              LOAD_CONST               1 ('cover')
              COMPARE_OP              88 (bool(==))
              POP_JUMP_IF_FALSE        9 (to L2)
              LOAD_FAST_LOAD_FAST     35 (real_x, real_y)
              BUILD_LIST               2
              LOAD_FAST                0 (self)
              STORE_ATTR               7 (cover_coords)
              JUMP_FORWARD             8 (to L3)

293   L2:     LOAD_FAST_LOAD_FAST     35 (real_x, real_y)
              BUILD_LIST               2
              LOAD_FAST                0 (self)
              STORE_ATTR               8 (body_coords)

294   L3:     LOAD_FAST                0 (self)
              LOAD_ATTR               19 (save_profile + NULL|self)
              CALL                     0
              POP_TOP

295           LOAD_FAST                0 (self)
              LOAD_ATTR               21 (draw_ghost_rect + NULL|self)
              CALL                     0
              POP_TOP
              RETURN_CONST             0 (None)

Disassembly of <code object get_stamp_size at 0x0000028A6B4265F0, file "src\ui\tab_autofirma.py", line 297>:
 297            RESUME                   0

 298            LOAD_GLOBAL              1 (int + NULL)
                LOAD_FAST                0 (self)
                LOAD_ATTR                2 (config_manager)
                LOAD_ATTR                5 (get + NULL|self)
                LOAD_CONST               1 ('cover_scale')
                LOAD_CONST               2 (100)
                CALL                     2
                CALL                     1
                STORE_FAST               2 (cover_scale)

 299            LOAD_GLOBAL              1 (int + NULL)
                LOAD_FAST                0 (self)
                LOAD_ATTR                2 (config_manager)
                LOAD_ATTR                5 (get + NULL|self)
                LOAD_CONST               3 ('body_scale')
                LOAD_CONST               2 (100)
                CALL                     2
                CALL                     1
                STORE_FAST               3 (body_scale)

 301            LOAD_CONST               4 (0.35)
                STORE_FAST               4 (BASE_FACTOR)

 303            LOAD_FAST                1 (mode)
                LOAD_CONST               5 ('cover')
                COMPARE_OP              88 (bool(==))
                POP_JUMP_IF_FALSE      141 (to L5)

 304            LOAD_FAST                0 (self)
                LOAD_ATTR                7 (get_resource_path + NULL|self)
                LOAD_CONST               6 ('assets/plantilla_caratula.png')
                CALL                     1
                STORE_FAST               5 (tpl_path)

 305            LOAD_CONST               7 ((300, 150))
                UNPACK_SEQUENCE          2
                STORE_FAST_STORE_FAST  103 (w, h)

 306            LOAD_GLOBAL              8 (os)
                LOAD_ATTR               10 (path)
                LOAD_ATTR               13 (exists + NULL|self)
                LOAD_FAST                5 (tpl_path)
                CALL                     1
                TO_BOOL
                POP_JUMP_IF_FALSE       46 (to L4)

 307            NOP

 308    L1:     LOAD_GLOBAL             14 (Image)
                LOAD_ATTR               16 (open)
                PUSH_NULL
                LOAD_FAST                5 (tpl_path)
                CALL                     1
                BEFORE_WITH
        L2:     STORE_FAST               8 (img)

 309            LOAD_FAST                8 (img)
                LOAD_ATTR               18 (size)
                UNPACK_SEQUENCE          2
                STORE_FAST_STORE_FAST  103 (w, h)

 308    L3:     LOAD_CONST               0 (None)
                LOAD_CONST               0 (None)
                LOAD_CONST               0 (None)
                CALL                     2
                POP_TOP

 311    L4:     LOAD_GLOBAL              1 (int + NULL)
                LOAD_FAST_LOAD_FAST    100 (w, BASE_FACTOR)
                BINARY_OP                5 (*)
                LOAD_FAST                2 (cover_scale)
                LOAD_CONST               8 (100.0)
                BINARY_OP               11 (/)
                BINARY_OP                5 (*)
                CALL                     1
                LOAD_GLOBAL              1 (int + NULL)
                LOAD_FAST_LOAD_FAST    116 (h, BASE_FACTOR)
                BINARY_OP                5 (*)
                LOAD_FAST                2 (cover_scale)
                LOAD_CONST               8 (100.0)
                BINARY_OP               11 (/)
                BINARY_OP                5 (*)
                CALL                     1
                BUILD_TUPLE              2
                RETURN_VALUE

 313    L5:     LOAD_FAST                0 (self)
                LOAD_ATTR                2 (config_manager)
                LOAD_ATTR                5 (get + NULL|self)
                LOAD_CONST               9 ('sello2_mode')
                CALL                     1
                LOAD_CONST              10 ('custom')
                COMPARE_OP              88 (bool(==))
                POP_JUMP_IF_FALSE      123 (to L10)

 314            LOAD_FAST                0 (self)
                LOAD_ATTR                2 (config_manager)
                LOAD_ATTR                5 (get + NULL|self)
                LOAD_CONST              11 ('sello2_custom_path')
                LOAD_CONST              12 ('')
                CALL                     2
                STORE_FAST               9 (c_path)

 315            LOAD_CONST               7 ((300, 150))
                UNPACK_SEQUENCE          2
                STORE_FAST_STORE_FAST  171 (cw, ch)

 316            LOAD_FAST                9 (c_path)
                TO_BOOL
                POP_JUMP_IF_FALSE       81 (to L9)
                LOAD_GLOBAL              8 (os)
                LOAD_ATTR               10 (path)
                LOAD_ATTR               13 (exists + NULL|self)
                LOAD_FAST                9 (c_path)
                CALL                     1
                TO_BOOL
                POP_JUMP_IF_FALSE       45 (to L9)

 317            NOP

 318    L6:     LOAD_GLOBAL             14 (Image)
                LOAD_ATTR               16 (open)
                PUSH_NULL
                LOAD_FAST                9 (c_path)
                CALL                     1
                BEFORE_WITH
        L7:     STORE_FAST_LOAD_FAST   136 (img, img)
                LOAD_ATTR               18 (size)
                UNPACK_SEQUENCE          2
                STORE_FAST_STORE_FAST  171 (cw, ch)
        L8:     LOAD_CONST               0 (None)
                LOAD_CONST               0 (None)
                LOAD_CONST               0 (None)
                CALL                     2
                POP_TOP

 320    L9:     LOAD_FAST_LOAD_FAST    171 (cw, ch)
                STORE_FAST_STORE_FAST  118 (h, w)
                JUMP_FORWARD           136 (to L12)

 322   L10:     NOP

 323   L11:     LOAD_FAST                0 (self)
                LOAD_ATTR               20 (stamp_engine)
                LOAD_ATTR               23 (get_body_stamp_size + NULL|self)

 324            LOAD_FAST                0 (self)
                LOAD_ATTR                2 (config_manager)
                LOAD_ATTR                5 (get + NULL|self)
                LOAD_CONST              13 ('signature_path')
                CALL                     1

 325            LOAD_FAST                0 (self)
                LOAD_ATTR                2 (config_manager)
                LOAD_ATTR                5 (get + NULL|self)
                LOAD_CONST              14 ('engineer_name')
                LOAD_CONST              12 ('')
                CALL                     2

 326            LOAD_FAST                0 (self)
                LOAD_ATTR                2 (config_manager)
                LOAD_ATTR                5 (get + NULL|self)
                LOAD_CONST              15 ('cip_number')
                LOAD_CONST              12 ('')
                CALL                     2

 327            LOAD_FAST                0 (self)
                LOAD_ATTR                2 (config_manager)
                LOAD_ATTR                5 (get + NULL|self)
                LOAD_CONST              16 ('engineer_type')
                LOAD_CONST              12 ('')
                CALL                     2

 323            CALL                     4
                UNPACK_SEQUENCE          2
                STORE_FAST_STORE_FAST  103 (w, h)

 330   L12:     LOAD_GLOBAL              1 (int + NULL)
                LOAD_FAST_LOAD_FAST    100 (w, BASE_FACTOR)
                BINARY_OP                5 (*)
                LOAD_FAST                3 (body_scale)
                LOAD_CONST               8 (100.0)
                BINARY_OP               11 (/)
                BINARY_OP                5 (*)
                CALL                     1
                LOAD_GLOBAL              1 (int + NULL)
                LOAD_FAST_LOAD_FAST    116 (h, BASE_FACTOR)
                BINARY_OP                5 (*)
                LOAD_FAST                3 (body_scale)
                LOAD_CONST               8 (100.0)
                BINARY_OP               11 (/)
                BINARY_OP                5 (*)
                CALL                     1
                BUILD_TUPLE              2
                RETURN_VALUE

 308   L13:     PUSH_EXC_INFO
                WITH_EXCEPT_START
                TO_BOOL
                POP_JUMP_IF_TRUE         1 (to L14)
                RERAISE                  2
       L14:     POP_TOP
       L15:     POP_EXCEPT
                POP_TOP
                POP_TOP
       L16:     EXTENDED_ARG             1
                JUMP_BACKWARD_NO_INTERRUPT 381 (to L4)

  --   L17:     COPY                     3
                POP_EXCEPT
                RERAISE                  1
       L18:     PUSH_EXC_INFO

 310            POP_TOP
       L19:     POP_EXCEPT
                EXTENDED_ARG             1
                JUMP_BACKWARD_NO_INTERRUPT 389 (to L4)

  --   L20:     COPY                     3
                POP_EXCEPT
                RERAISE                  1

 318   L21:     PUSH_EXC_INFO
                WITH_EXCEPT_START
                TO_BOOL
                POP_JUMP_IF_TRUE         1 (to L22)
                RERAISE                  2
       L22:     POP_TOP
       L23:     POP_EXCEPT
                POP_TOP
                POP_TOP
       L24:     JUMP_BACKWARD_NO_INTERRUPT 217 (to L9)

  --   L25:     COPY                     3
                POP_EXCEPT
                RERAISE                  1
       L26:     PUSH_EXC_INFO

 319            POP_TOP
       L27:     POP_EXCEPT
                JUMP_BACKWARD_NO_INTERRUPT 224 (to L9)

  --   L28:     COPY                     3
                POP_EXCEPT
                RERAISE                  1
       L29:     PUSH_EXC_INFO

 329            POP_TOP
                LOAD_CONST              17 ((400, 250))
                UNPACK_SEQUENCE          2
                STORE_FAST_STORE_FAST  103 (w, h)
       L30:     POP_EXCEPT
                JUMP_BACKWARD_NO_INTERRUPT 96 (to L12)

  --   L31:     COPY                     3
                POP_EXCEPT
                RERAISE                  1
ExceptionTable:
  L1 to L2 -> L18 [0]
  L2 to L3 -> L13 [1] lasti
  L3 to L4 -> L18 [0]
  L6 to L7 -> L26 [0]
  L7 to L8 -> L21 [1] lasti
  L8 to L9 -> L26 [0]
  L11 to L12 -> L29 [0]
  L13 to L15 -> L17 [3] lasti
  L15 to L16 -> L18 [0]
  L17 to L18 -> L18 [0]
  L18 to L19 -> L20 [1] lasti
  L21 to L23 -> L25 [3] lasti
  L23 to L24 -> L26 [0]
  L25 to L26 -> L26 [0]
  L26 to L27 -> L28 [1] lasti
  L29 to L30 -> L31 [1] lasti

Disassembly of <code object draw_ghost_rect at 0x0000028A6B426B90, file "src\ui\tab_autofirma.py", line 332>:
332           RESUME                   0

333           LOAD_FAST                0 (self)
              LOAD_ATTR                0 (rect_id)
              TO_BOOL
              POP_JUMP_IF_FALSE       37 (to L1)
              LOAD_FAST                0 (self)
              LOAD_ATTR                2 (canvas)
              LOAD_ATTR                5 (delete + NULL|self)
              LOAD_FAST                0 (self)
              LOAD_ATTR                0 (rect_id)
              CALL                     1
              POP_TOP

334   L1:     LOAD_FAST                0 (self)
              LOAD_ATTR                6 (current_stamp_type)
              LOAD_ATTR                9 (get + NULL|self)
              CALL                     0
              STORE_FAST               1 (mode)

335           LOAD_FAST                0 (self)
              LOAD_ATTR               11 (get_stamp_size + NULL|self)
              LOAD_FAST                1 (mode)
              CALL                     1
              UNPACK_SEQUENCE          2
              STORE_FAST_STORE_FAST   35 (w, h)

337           LOAD_FAST                1 (mode)
              LOAD_CONST               1 ('cover')
              COMPARE_OP              88 (bool(==))
              POP_JUMP_IF_FALSE       12 (to L2)
              LOAD_FAST                0 (self)
              LOAD_ATTR               12 (cover_coords)
              JUMP_FORWARD            11 (to L3)
      L2:     LOAD_FAST                0 (self)
              LOAD_ATTR               14 (body_coords)
      L3:     UNPACK_SEQUENCE          2
              STORE_FAST_STORE_FAST   69 (cx, cy)

338           LOAD_FAST                1 (mode)
              LOAD_CONST               1 ('cover')
              COMPARE_OP              88 (bool(==))
              POP_JUMP_IF_FALSE        2 (to L4)
              LOAD_CONST               2 ('blue')
              JUMP_FORWARD             1 (to L5)
      L4:     LOAD_CONST               3 ('red')
      L5:     STORE_FAST               6 (color)

340           LOAD_FAST_LOAD_FAST     64 (cx, self)
              LOAD_ATTR               16 (canvas_scale)
              BINARY_OP                5 (*)
              LOAD_FAST_LOAD_FAST     80 (cy, self)
              LOAD_ATTR               16 (canvas_scale)
              BINARY_OP                5 (*)
              LOAD_FAST_LOAD_FAST     32 (w, self)
              LOAD_ATTR               16 (canvas_scale)
              BINARY_OP                5 (*)
              LOAD_FAST_LOAD_FAST     48 (h, self)
              LOAD_ATTR               16 (canvas_scale)
              BINARY_OP                5 (*)
              BUILD_TUPLE              4
              UNPACK_SEQUENCE          4
              STORE_FAST_STORE_FAST  120 (x, y)
              STORE_FAST_STORE_FAST   35 (w, h)

341           LOAD_FAST                0 (self)
              LOAD_ATTR                2 (canvas)
              LOAD_ATTR               19 (create_rectangle + NULL|self)
              LOAD_FAST_LOAD_FAST    120 (x, y)
              LOAD_FAST_LOAD_FAST    114 (x, w)
              BINARY_OP                0 (+)
              LOAD_FAST_LOAD_FAST    131 (y, h)
              BINARY_OP                0 (+)
              LOAD_FAST                6 (color)
              LOAD_CONST               4 (2)
              LOAD_CONST               5 ((4, 4))
              LOAD_CONST               6 (('outline', 'width', 'dash'))
              CALL_KW                  7
              LOAD_FAST                0 (self)
              STORE_ATTR               0 (rect_id)
              RETURN_CONST             0 (None)

Disassembly of <code object action_export at 0x0000028A6B498260, file "src\ui\tab_autofirma.py", line 343>:
 343            RESUME                   0

 344            LOAD_FAST                0 (self)
                LOAD_ATTR                0 (pdf_doc)
                TO_BOOL
                POP_JUMP_IF_FALSE       17 (to L1)
                LOAD_FAST                0 (self)
                LOAD_ATTR                2 (pdf_path)
                TO_BOOL
                POP_JUMP_IF_TRUE        24 (to L2)

 345    L1:     LOAD_GLOBAL              4 (messagebox)
                LOAD_ATTR                6 (showwarning)
                PUSH_NULL
                LOAD_CONST               1 ('Atención')
                LOAD_CONST               2 ('Cargue un PDF primero.')
                CALL                     2
                POP_TOP

 346            RETURN_CONST             0 (None)

 348    L2:     LOAD_FAST                0 (self)
                LOAD_ATTR                9 (save_profile + NULL|self)
                CALL                     0
                POP_TOP

 350            LOAD_GLOBAL             10 (os)
                LOAD_ATTR               12 (path)
                LOAD_ATTR               15 (splitext + NULL|self)
                LOAD_FAST                0 (self)
                LOAD_ATTR                2 (pdf_path)
                CALL                     1
                UNPACK_SEQUENCE          2
                STORE_FAST_STORE_FAST   18 (base, ext)

 351            LOAD_FAST                1 (base)
                FORMAT_SIMPLE
                LOAD_CONST               3 ('_firmado')
                LOAD_FAST                2 (ext)
                FORMAT_SIMPLE
                BUILD_STRING             3
                STORE_FAST               3 (out_path)

 353            NOP

 354    L3:     LOAD_FAST                0 (self)
                LOAD_ATTR               16 (config_manager)
                LOAD_ATTR               19 (get + NULL|self)
                LOAD_CONST               4 ('signature_path')
                CALL                     1
                STORE_FAST               4 (sig_path)

 355            LOAD_FAST                0 (self)
                LOAD_ATTR               16 (config_manager)
                LOAD_ATTR               19 (get + NULL|self)
                LOAD_CONST               5 ('engineer_name')
                LOAD_CONST               6 ('')
                CALL                     2
                STORE_FAST               5 (name)

 356            LOAD_FAST                0 (self)
                LOAD_ATTR               16 (config_manager)
                LOAD_ATTR               19 (get + NULL|self)
                LOAD_CONST               7 ('cip_number')
                LOAD_CONST               6 ('')
                CALL                     2
                STORE_FAST               6 (cip)

 357            LOAD_FAST                0 (self)
                LOAD_ATTR               16 (config_manager)
                LOAD_ATTR               19 (get + NULL|self)
                LOAD_CONST               8 ('engineer_type')
                LOAD_CONST               6 ('')
                CALL                     2
                STORE_FAST               7 (tipo)

 358            LOAD_FAST                0 (self)
                LOAD_ATTR               16 (config_manager)
                LOAD_ATTR               19 (get + NULL|self)
                LOAD_CONST               9 ('start_date')
                LOAD_CONST               6 ('')
                CALL                     2
                STORE_FAST               8 (start_date)

 360            LOAD_FAST                0 (self)
                LOAD_ATTR               21 (get_resource_path + NULL|self)
                LOAD_CONST              10 ('assets/plantilla_caratula.png')
                CALL                     1
                STORE_FAST               9 (base_template)

 361            LOAD_GLOBAL             10 (os)
                LOAD_ATTR               12 (path)
                LOAD_ATTR               23 (exists + NULL|self)
                LOAD_FAST                9 (base_template)
                CALL                     1
                TO_BOOL
                POP_JUMP_IF_TRUE       150 (to L4)

 362            LOAD_GLOBAL             10 (os)
                LOAD_ATTR               24 (makedirs)
                PUSH_NULL
                LOAD_GLOBAL             10 (os)
                LOAD_ATTR               12 (path)
                LOAD_ATTR               27 (dirname + NULL|self)
                LOAD_FAST                9 (base_template)
                CALL                     1
                LOAD_CONST              11 (True)
                LOAD_CONST              12 (('exist_ok',))
                CALL_KW                  2
                POP_TOP

 363            LOAD_GLOBAL             28 (Image)
                LOAD_ATTR               30 (new)
                PUSH_NULL
                LOAD_CONST              13 ('RGBA')
                LOAD_CONST              14 ((300, 150))
                LOAD_CONST              15 ('white')
                CALL                     3
                STORE_FAST              10 (tmp_img)

 364            LOAD_CONST              16 (0)
                LOAD_CONST              17 (('ImageDraw',))
                IMPORT_NAME             16 (PIL)
                IMPORT_FROM             17 (ImageDraw)
                STORE_FAST              11 (ImageDraw)
                POP_TOP

 365            LOAD_FAST               11 (ImageDraw)
                LOAD_ATTR               37 (Draw + NULL|self)
                LOAD_FAST               10 (tmp_img)
                CALL                     1
                STORE_FAST              12 (d)

 366            LOAD_FAST               12 (d)
                LOAD_ATTR               39 (rectangle + NULL|self)
                BUILD_LIST               0
                LOAD_CONST              18 ((0, 0, 299, 149))
                LIST_EXTEND              1
                LOAD_CONST              19 ('black')
                LOAD_CONST              20 (2)
                LOAD_CONST              21 (('outline', 'width'))
                CALL_KW                  3
                POP_TOP

 367            LOAD_FAST               12 (d)
                LOAD_ATTR               41 (text + NULL|self)
                LOAD_CONST              22 ((10, 120))
                LOAD_CONST              23 ('V°B° ________________')
                LOAD_CONST              19 ('black')
                LOAD_CONST              24 (('fill',))
                CALL_KW                  3
                POP_TOP

 368            LOAD_FAST               10 (tmp_img)
                LOAD_ATTR               43 (save + NULL|self)
                LOAD_FAST                9 (base_template)
                CALL                     1
                POP_TOP

 371    L4:     LOAD_FAST                0 (self)
                LOAD_ATTR               16 (config_manager)
                LOAD_ATTR               19 (get + NULL|self)
                LOAD_CONST              25 ('tpl_date1_coords')
                CALL                     1

 372            LOAD_FAST                0 (self)
                LOAD_ATTR               16 (config_manager)
                LOAD_ATTR               19 (get + NULL|self)
                LOAD_CONST              26 ('tpl_date2_coords')
                CALL                     1

 373            LOAD_FAST                0 (self)
                LOAD_ATTR               16 (config_manager)
                LOAD_ATTR               19 (get + NULL|self)
                LOAD_CONST              27 ('tpl_sig_coords')
                CALL                     1

 374            LOAD_FAST                0 (self)
                LOAD_ATTR               16 (config_manager)
                LOAD_ATTR               19 (get + NULL|self)
                LOAD_CONST              28 ('tpl_date_scale')
                LOAD_CONST              29 (100)
                CALL                     2

 375            LOAD_FAST                0 (self)
                LOAD_ATTR               16 (config_manager)
                LOAD_ATTR               19 (get + NULL|self)
                LOAD_CONST              30 ('tpl_sig_scale')
                LOAD_CONST              29 (100)
                CALL                     2

 370            LOAD_CONST              31 (('date1', 'date2', 'sig', 'date_scale', 'sig_scale'))
                BUILD_CONST_KEY_MAP      5
                STORE_FAST              13 (layout_cfg)

 378            LOAD_CONST               0 (None)
                STORE_FAST              14 (cover_img)

 379            LOAD_FAST                0 (self)
                LOAD_ATTR               16 (config_manager)
                LOAD_ATTR               19 (get + NULL|self)
                LOAD_CONST              32 ('apply_sello1')
                LOAD_CONST              11 (True)
                CALL                     2
                TO_BOOL
                POP_JUMP_IF_FALSE       26 (to L5)

 380            LOAD_FAST                0 (self)
                LOAD_ATTR               44 (stamp_engine)
                LOAD_ATTR               47 (generate_cover_stamp + NULL|self)
                LOAD_FAST_LOAD_FAST    148 (base_template, sig_path)
                LOAD_FAST_LOAD_FAST    141 (start_date, layout_cfg)
                LOAD_CONST              33 (('layout_coords',))
                CALL_KW                  4
                STORE_FAST              14 (cover_img)

 382    L5:     LOAD_CONST               0 (None)
                STORE_FAST              15 (body_img)

 383            LOAD_FAST                0 (self)
                LOAD_ATTR               16 (config_manager)
                LOAD_ATTR               19 (get + NULL|self)
                LOAD_CONST              34 ('apply_sello2')
                LOAD_CONST              11 (True)
                CALL                     2
                TO_BOOL
                POP_JUMP_IF_FALSE      168 (to L8)

 384            LOAD_FAST                0 (self)
                LOAD_ATTR               16 (config_manager)
                LOAD_ATTR               19 (get + NULL|self)
                LOAD_CONST              35 ('sello2_mode')
                CALL                     1
                LOAD_CONST              36 ('custom')
                COMPARE_OP              88 (bool(==))
                POP_JUMP_IF_FALSE      109 (to L7)

 385            LOAD_FAST                0 (self)
                LOAD_ATTR               16 (config_manager)
                LOAD_ATTR               19 (get + NULL|self)
                LOAD_CONST              37 ('sello2_custom_path')
                LOAD_CONST               6 ('')
                CALL                     2
                STORE_FAST              16 (c_path)

 386            LOAD_FAST               16 (c_path)
                TO_BOOL
                POP_JUMP_IF_FALSE       73 (to L6)
                LOAD_GLOBAL             10 (os)
                LOAD_ATTR               12 (path)
                LOAD_ATTR               23 (exists + NULL|self)
                LOAD_FAST               16 (c_path)
                CALL                     1
                TO_BOOL
                POP_JUMP_IF_FALSE       37 (to L6)

 387            LOAD_GLOBAL             28 (Image)
                LOAD_ATTR               48 (open)
                PUSH_NULL
                LOAD_FAST               16 (c_path)
                CALL                     1
                LOAD_ATTR               51 (convert + NULL|self)
                LOAD_CONST              13 ('RGBA')
                CALL                     1
                STORE_FAST              15 (body_img)

  --    L6:     JUMP_FORWARD            28 (to L8)

 389    L7:     LOAD_FAST                0 (self)
                LOAD_ATTR               44 (stamp_engine)
                LOAD_ATTR               53 (generate_body_stamp + NULL|self)
                LOAD_FAST_LOAD_FAST     69 (sig_path, name)
                LOAD_FAST_LOAD_FAST    103 (cip, tipo)
                CALL                     4
                STORE_FAST              15 (body_img)

 391    L8:     LOAD_FAST                0 (self)
                LOAD_ATTR               54 (pdf_manager)
                LOAD_ATTR               57 (process_and_save + NULL|self)
                LOAD_FAST                0 (self)
                LOAD_ATTR                0 (pdf_doc)
                LOAD_FAST_LOAD_FAST    239 (cover_img, body_img)
                LOAD_FAST                0 (self)
                LOAD_ATTR               16 (config_manager)
                LOAD_ATTR               58 (config)
                LOAD_FAST                3 (out_path)
                CALL                     5
                UNPACK_SEQUENCE          2
                STORE_FAST              17 (success)
                STORE_FAST              18 (msg)

 392            LOAD_FAST               17 (success)
                TO_BOOL
                POP_JUMP_IF_FALSE       27 (to L10)
                LOAD_GLOBAL              4 (messagebox)
                LOAD_ATTR               60 (showinfo)
                PUSH_NULL
                LOAD_CONST              38 ('Éxito')
                LOAD_CONST              39 ('¡Documento firmado exitosamente!\nGuardado en:\n')
                LOAD_FAST                3 (out_path)
                FORMAT_SIMPLE
                BUILD_STRING             2
                CALL                     2
                POP_TOP
        L9:     RETURN_CONST             0 (None)

 393   L10:     LOAD_GLOBAL              4 (messagebox)
                LOAD_ATTR               62 (showerror)
                PUSH_NULL
                LOAD_CONST              40 ('Error')
                LOAD_FAST               18 (msg)
                CALL                     2
                POP_TOP
       L11:     RETURN_CONST             0 (None)

  --   L12:     PUSH_EXC_INFO

 394            LOAD_GLOBAL             64 (Exception)
                CHECK_EXC_MATCH
                POP_JUMP_IF_FALSE       42 (to L16)
                STORE_FAST              19 (e)

 395   L13:     LOAD_GLOBAL              4 (messagebox)
                LOAD_ATTR               62 (showerror)
                PUSH_NULL
                LOAD_CONST              41 ('Error Severo')
                LOAD_GLOBAL             67 (str + NULL)
                LOAD_FAST               19 (e)
                CALL                     1
                CALL                     2
                POP_TOP
       L14:     POP_EXCEPT
                LOAD_CONST               0 (None)
                STORE_FAST              19 (e)
                DELETE_FAST             19 (e)
                RETURN_CONST             0 (None)

  --   L15:     LOAD_CONST               0 (None)
                STORE_FAST              19 (e)
                DELETE_FAST             19 (e)
                RERAISE                  1

 394   L16:     RERAISE                  0

  --   L17:     COPY                     3
                POP_EXCEPT
                RERAISE                  1
ExceptionTable:
  L3 to L9 -> L12 [0]
  L10 to L11 -> L12 [0]
  L12 to L13 -> L17 [1] lasti
  L13 to L14 -> L15 [1] lasti
  L15 to L17 -> L17 [1] lasti
