  0           RESUME                   0

  1           LOAD_CONST               0 (0)
              LOAD_CONST               1 (None)
              IMPORT_NAME              0 (customtkinter)
              STORE_NAME               1 (ctk)

  2           LOAD_CONST               0 (0)
              LOAD_CONST               1 (None)
              IMPORT_NAME              2 (datetime)
              STORE_NAME               2 (datetime)

  3           LOAD_CONST               0 (0)
              LOAD_CONST               1 (None)
              IMPORT_NAME              3 (json)
              STORE_NAME               3 (json)

  4           LOAD_CONST               0 (0)
              LOAD_CONST               1 (None)
              IMPORT_NAME              4 (os)
              STORE_NAME               4 (os)

  6           LOAD_BUILD_CLASS
              PUSH_NULL
              LOAD_CONST               2 (<code object TabCarta at 0x0000028A6B16E4F0, file "src\ui\tab_carta.py", line 6>)
              MAKE_FUNCTION
              LOAD_CONST               3 ('TabCarta')
              LOAD_NAME                1 (ctk)
              LOAD_ATTR               10 (CTkFrame)
              CALL                     3
              STORE_NAME               6 (TabCarta)
              RETURN_CONST             1 (None)

Disassembly of <code object TabCarta at 0x0000028A6B16E4F0, file "src\ui\tab_carta.py", line 6>:
  --           MAKE_CELL                0 (__class__)

   6           RESUME                   0
               LOAD_NAME                0 (__name__)
               STORE_NAME               1 (__module__)
               LOAD_CONST               0 ('TabCarta')
               STORE_NAME               2 (__qualname__)
               LOAD_CONST               1 (6)
               STORE_NAME               3 (__firstlineno__)

   7           LOAD_FAST                0 (__class__)
               BUILD_TUPLE              1
               LOAD_CONST               2 (<code object __init__ at 0x0000028A6B1418F0, file "src\ui\tab_carta.py", line 7>)
               MAKE_FUNCTION
               SET_FUNCTION_ATTRIBUTE   8 (closure)
               STORE_NAME               4 (__init__)

  18           LOAD_CONST               3 (<code object setup_logic at 0x0000028A6B400510, file "src\ui\tab_carta.py", line 18>)
               MAKE_FUNCTION
               STORE_NAME               5 (setup_logic)

  37           LOAD_CONST               4 (<code object load_databases at 0x0000028A6B45E1C0, file "src\ui\tab_carta.py", line 37>)
               MAKE_FUNCTION
               STORE_NAME               6 (load_databases)

  71           LOAD_CONST               5 (<code object on_date_typing at 0x0000028A6B4993B0, file "src\ui\tab_carta.py", line 71>)
               MAKE_FUNCTION
               STORE_NAME               7 (on_date_typing)

  89           LOAD_CONST               6 (<code object setup_ui at 0x0000028A6B496780, file "src\ui\tab_carta.py", line 89>)
               MAKE_FUNCTION
               STORE_NAME               8 (setup_ui)

 132           LOAD_CONST               7 (<code object build_bloque_generales at 0x0000028A6B496CA0, file "src\ui\tab_carta.py", line 132>)
               MAKE_FUNCTION
               STORE_NAME               9 (build_bloque_generales)

 151           LOAD_CONST               8 (<code object build_bloque_ubicacion at 0x0000028A6B46A2E0, file "src\ui\tab_carta.py", line 151>)
               MAKE_FUNCTION
               STORE_NAME              10 (build_bloque_ubicacion)

 195           LOAD_CONST               9 (<code object build_bloque_fechas at 0x0000028A6B497C90, file "src\ui\tab_carta.py", line 195>)
               MAKE_FUNCTION
               STORE_NAME              11 (build_bloque_fechas)

 220           LOAD_CONST              10 (<code object build_bloque_ingenieros at 0x0000028A6B46C1D0, file "src\ui\tab_carta.py", line 220>)
               MAKE_FUNCTION
               STORE_NAME              12 (build_bloque_ingenieros)

 297           LOAD_CONST              11 (<code object build_bloque_planos at 0x0000028A6B3FFFF0, file "src\ui\tab_carta.py", line 297>)
               MAKE_FUNCTION
               STORE_NAME              13 (build_bloque_planos)

 311           LOAD_CONST              12 (<code object on_chk_cliente at 0x0000028A6B45E7B0, file "src\ui\tab_carta.py", line 311>)
               MAKE_FUNCTION
               STORE_NAME              14 (on_chk_cliente)

 319           LOAD_CONST              13 (<code object on_chk_dir at 0x0000028A6B4243B0, file "src\ui\tab_carta.py", line 319>)
               MAKE_FUNCTION
               STORE_NAME              15 (on_chk_dir)

 327           LOAD_CONST              14 (<code object on_chk_civil_rev at 0x0000028A6B186EB0, file "src\ui\tab_carta.py", line 327>)
               MAKE_FUNCTION
               STORE_NAME              16 (on_chk_civil_rev)

 333           LOAD_CONST              15 (<code object on_chk_civil_proy at 0x0000028A6B187030, file "src\ui\tab_carta.py", line 333>)
               MAKE_FUNCTION
               STORE_NAME              17 (on_chk_civil_proy)

 339           LOAD_CONST              16 (<code object on_chk_fecha_hoy at 0x0000028A6B468590, file "src\ui\tab_carta.py", line 339>)
               MAKE_FUNCTION
               STORE_NAME              18 (on_chk_fecha_hoy)

 348           LOAD_CONST              17 (<code object on_fecha_inicio_change at 0x0000028A6B376790, file "src\ui\tab_carta.py", line 348>)
               MAKE_FUNCTION
               STORE_NAME              19 (on_fecha_inicio_change)

 351           LOAD_CONST              18 (<code object calcular_fecha_fin at 0x0000028A6B46CE80, file "src\ui\tab_carta.py", line 351>)
               MAKE_FUNCTION
               STORE_NAME              20 (calcular_fecha_fin)

 370           LOAD_CONST              19 (<code object on_distrito_type at 0x0000028A6B3982D0, file "src\ui\tab_carta.py", line 370>)
               MAKE_FUNCTION
               STORE_NAME              21 (on_distrito_type)

 376           LOAD_CONST              20 (<code object on_distrito_change at 0x0000028A6B1871B0, file "src\ui\tab_carta.py", line 376>)
               MAKE_FUNCTION
               STORE_NAME              22 (on_distrito_change)

 382           LOAD_CONST              21 (<code object save_new_ubicacion_cache at 0x0000028A6B3F3CC0, file "src\ui\tab_carta.py", line 382>)
               MAKE_FUNCTION
               STORE_NAME              23 (save_new_ubicacion_cache)

 394           LOAD_CONST              22 (<code object on_revisor_type at 0x0000028A6B187330, file "src\ui\tab_carta.py", line 394>)
               MAKE_FUNCTION
               STORE_NAME              24 (on_revisor_type)

 399           LOAD_CONST              23 (<code object on_revisor_change at 0x0000028A6B12A830, file "src\ui\tab_carta.py", line 399>)
               MAKE_FUNCTION
               STORE_NAME              25 (on_revisor_change)

 409           LOAD_CONST              24 (<code object on_proyectista_type at 0x0000028A6B1874B0, file "src\ui\tab_carta.py", line 409>)
               MAKE_FUNCTION
               STORE_NAME              26 (on_proyectista_type)

 414           LOAD_CONST              25 (<code object on_proyectista_change at 0x0000028A6B187630, file "src\ui\tab_carta.py", line 414>)
               MAKE_FUNCTION
               STORE_NAME              27 (on_proyectista_change)

 421           LOAD_CONST              26 (<code object on_civil_rev_type at 0x0000028A6B1877B0, file "src\ui\tab_carta.py", line 421>)
               MAKE_FUNCTION
               STORE_NAME              28 (on_civil_rev_type)

 426           LOAD_CONST              27 (<code object on_civil_rev_change at 0x0000028A6B187930, file "src\ui\tab_carta.py", line 426>)
               MAKE_FUNCTION
               STORE_NAME              29 (on_civil_rev_change)

 433           LOAD_CONST              28 (<code object on_civil_proy_type at 0x0000028A6B187AB0, file "src\ui\tab_carta.py", line 433>)
               MAKE_FUNCTION
               STORE_NAME              30 (on_civil_proy_type)

 438           LOAD_CONST              29 (<code object on_civil_proy_change at 0x0000028A6B187C30, file "src\ui\tab_carta.py", line 438>)
               MAKE_FUNCTION
               STORE_NAME              31 (on_civil_proy_change)

 445           LOAD_CONST              36 (('',))
               LOAD_CONST              30 (<code object save_new_ingenieros_cache at 0x0000028A6B46D120, file "src\ui\tab_carta.py", line 445>)
               MAKE_FUNCTION
               SET_FUNCTION_ATTRIBUTE   1 (defaults)
               STORE_NAME              32 (save_new_ingenieros_cache)

 461           LOAD_CONST              31 (<code object agregar_cajon_plano at 0x0000028A6B468320, file "src\ui\tab_carta.py", line 461>)
               MAKE_FUNCTION
               STORE_NAME              33 (agregar_cajon_plano)

 478           LOAD_CONST              32 (<code object eliminar_cajon_plano at 0x0000028A6B3AD430, file "src\ui\tab_carta.py", line 478>)
               MAKE_FUNCTION
               STORE_NAME              34 (eliminar_cajon_plano)

 484           LOAD_CONST              33 (<code object get_resource_path at 0x0000028A6B42A390, file "src\ui\tab_carta.py", line 484>)
               MAKE_FUNCTION
               STORE_NAME              35 (get_resource_path)

 495           LOAD_CONST              34 (<code object action_generar_word at 0x0000028A6B49DE60, file "src\ui\tab_carta.py", line 495>)
               MAKE_FUNCTION
               STORE_NAME              36 (action_generar_word)
               LOAD_CONST              35 (('btn_export', 'chk_civil_proy', 'chk_civil_rev', 'chk_cliente', 'chk_direccion', 'chk_f_hoy', 'combo_civil_proy', 'combo_civil_rev', 'combo_distrito', 'combo_proyectista', 'combo_revisor', 'config_manager', 'entry_atc', 'entry_civil_proy_cip', 'entry_civil_rev_cip', 'entry_civil_rev_planos', 'entry_cliente', 'entry_departamento', 'entry_direccion', 'entry_direccion_proyecto', 'entry_dirigido', 'entry_fecha_carta', 'entry_fecha_fin', 'entry_fecha_inicio', 'entry_fecha_sys', 'entry_proyectista_cip', 'entry_referencia', 'entry_revisor_cip', 'entry_revisor_tipo', 'entry_solicitud', 'f_civil_proy', 'f_civil_rev', 'frame_planos_list', 'ingenieros_cache', 'lbl_watermark', 'left_panel', 'lista_entradas_planos', 'right_panel', 'ubicaciones_cache', 'var_misma_dir', 'var_mismo_cliente', 'var_tiene_civil_proy', 'var_tiene_civil_rev', 'var_usar_f_hoy', 'word_engine'))
               STORE_NAME              37 (__static_attributes__)
               LOAD_FAST                0 (__class__)
               COPY                     1
               STORE_NAME              38 (__classcell__)
               RETURN_VALUE

Disassembly of <code object __init__ at 0x0000028A6B1418F0, file "src\ui\tab_carta.py", line 7>:
  --           COPY_FREE_VARS           1

   7           RESUME                   0

   8           LOAD_GLOBAL              0 (super)
               LOAD_DEREF               4 (__class__)
               LOAD_FAST                0 (self)
               LOAD_SUPER_ATTR          5 (__init__ + NULL|self)
               LOAD_FAST                1 (parent)
               LOAD_CONST               1 ('transparent')
               LOAD_CONST               2 (('fg_color',))
               CALL_KW                  2
               POP_TOP

   9           LOAD_FAST_LOAD_FAST     32 (config_manager, self)
               STORE_ATTR               2 (config_manager)

  10           LOAD_FAST_LOAD_FAST     48 (word_engine, self)
               STORE_ATTR               3 (word_engine)

  12           BUILD_MAP                0
               LOAD_FAST                0 (self)
               STORE_ATTR               4 (ubicaciones_cache)

  13           BUILD_LIST               0
               LOAD_FAST                0 (self)
               STORE_ATTR               5 (ingenieros_cache)

  15           LOAD_FAST                0 (self)
               LOAD_ATTR               13 (setup_ui + NULL|self)
               CALL                     0
               POP_TOP

  16           LOAD_FAST                0 (self)
               LOAD_ATTR               15 (setup_logic + NULL|self)
               CALL                     0
               POP_TOP
               RETURN_CONST             0 (None)

Disassembly of <code object setup_logic at 0x0000028A6B400510, file "src\ui\tab_carta.py", line 18>:
  --           MAKE_CELL                0 (self)

  18           RESUME                   0

  19           LOAD_GLOBAL              0 (datetime)
               LOAD_ATTR                0 (datetime)
               LOAD_ATTR                3 (now + NULL|self)
               CALL                     0
               STORE_FAST               1 (hoy)

  20           LOAD_FAST                1 (hoy)
               LOAD_ATTR                4 (day)
               LOAD_CONST               1 ('02d')
               FORMAT_WITH_SPEC
               LOAD_CONST               2 ('/')
               LOAD_FAST                1 (hoy)
               LOAD_ATTR                6 (month)
               LOAD_CONST               1 ('02d')
               FORMAT_WITH_SPEC
               LOAD_CONST               2 ('/')
               LOAD_FAST                1 (hoy)
               LOAD_ATTR                8 (year)
               FORMAT_SIMPLE
               BUILD_STRING             5
               STORE_FAST               2 (fecha_str)

  21           LOAD_DEREF               0 (self)
               LOAD_ATTR               10 (entry_fecha_sys)
               LOAD_ATTR               13 (insert + NULL|self)
               LOAD_CONST               3 (0)
               LOAD_FAST                2 (fecha_str)
               CALL                     2
               POP_TOP

  24           LOAD_DEREF               0 (self)
               LOAD_ATTR               15 (load_databases + NULL|self)
               CALL                     0
               POP_TOP

  28           LOAD_DEREF               0 (self)
               LOAD_ATTR               10 (entry_fecha_sys)
               LOAD_ATTR               17 (bind + NULL|self)
               LOAD_CONST               4 ('<KeyRelease>')
               LOAD_FAST                0 (self)
               BUILD_TUPLE              1
               LOAD_CONST               5 (<code object <lambda> at 0x0000028A6B36F990, file "src\ui\tab_carta.py", line 28>)
               MAKE_FUNCTION
               SET_FUNCTION_ATTRIBUTE   8 (closure)
               CALL                     2
               POP_TOP

  29           LOAD_DEREF               0 (self)
               LOAD_ATTR               18 (entry_fecha_carta)
               LOAD_ATTR               17 (bind + NULL|self)
               LOAD_CONST               4 ('<KeyRelease>')
               LOAD_FAST                0 (self)
               BUILD_TUPLE              1
               LOAD_CONST               6 (<code object <lambda> at 0x0000028A6B36FAA0, file "src\ui\tab_carta.py", line 29>)
               MAKE_FUNCTION
               SET_FUNCTION_ATTRIBUTE   8 (closure)
               CALL                     2
               POP_TOP

  31           LOAD_FAST                0 (self)
               BUILD_TUPLE              1
               LOAD_CONST               7 (<code object on_inicio_change at 0x0000028A6B1AB340, file "src\ui\tab_carta.py", line 31>)
               MAKE_FUNCTION
               SET_FUNCTION_ATTRIBUTE   8 (closure)
               STORE_FAST               3 (on_inicio_change)

  35           LOAD_DEREF               0 (self)
               LOAD_ATTR               20 (entry_fecha_inicio)
               LOAD_ATTR               17 (bind + NULL|self)
               LOAD_CONST               4 ('<KeyRelease>')
               LOAD_FAST                3 (on_inicio_change)
               CALL                     2
               POP_TOP
               RETURN_CONST             0 (None)

Disassembly of <code object <lambda> at 0x0000028A6B36F990, file "src\ui\tab_carta.py", line 28>:
  --           COPY_FREE_VARS           1

  28           RESUME                   0
               LOAD_DEREF               1 (self)
               LOAD_ATTR                1 (on_date_typing + NULL|self)
               LOAD_FAST                0 (e)
               LOAD_DEREF               1 (self)
               LOAD_ATTR                2 (entry_fecha_sys)
               CALL                     2
               RETURN_VALUE

Disassembly of <code object <lambda> at 0x0000028A6B36FAA0, file "src\ui\tab_carta.py", line 29>:
  --           COPY_FREE_VARS           1

  29           RESUME                   0
               LOAD_DEREF               1 (self)
               LOAD_ATTR                1 (on_date_typing + NULL|self)
               LOAD_FAST                0 (e)
               LOAD_DEREF               1 (self)
               LOAD_ATTR                2 (entry_fecha_carta)
               CALL                     2
               RETURN_VALUE

Disassembly of <code object on_inicio_change at 0x0000028A6B1AB340, file "src\ui\tab_carta.py", line 31>:
  --           COPY_FREE_VARS           1

  31           RESUME                   0

  32           LOAD_DEREF               1 (self)
               LOAD_ATTR                1 (on_date_typing + NULL|self)
               LOAD_FAST                0 (e)
               LOAD_DEREF               1 (self)
               LOAD_ATTR                2 (entry_fecha_inicio)
               CALL                     2
               POP_TOP

  33           LOAD_DEREF               1 (self)
               LOAD_ATTR                5 (on_fecha_inicio_change + NULL|self)
               LOAD_FAST                0 (e)
               CALL                     1
               POP_TOP
               RETURN_CONST             0 (None)

Disassembly of <code object load_databases at 0x0000028A6B45E1C0, file "src\ui\tab_carta.py", line 37>:
  37            RESUME                   0

  39            LOAD_CONST               1 ('ubicaciones.json')
                STORE_FAST               1 (ubi_path)

  40            LOAD_GLOBAL              0 (os)
                LOAD_ATTR                2 (path)
                LOAD_ATTR                5 (exists + NULL|self)
                LOAD_FAST                1 (ubi_path)
                CALL                     1
                TO_BOOL
                POP_JUMP_IF_FALSE       48 (to L4)

  41            NOP

  42    L1:     LOAD_GLOBAL              7 (open + NULL)
                LOAD_FAST                1 (ubi_path)
                LOAD_CONST               2 ('r')
                LOAD_CONST               3 ('utf-8')
                LOAD_CONST               4 (('encoding',))
                CALL_KW                  3
                BEFORE_WITH
        L2:     STORE_FAST               2 (f)

  43            LOAD_GLOBAL              8 (json)
                LOAD_ATTR               10 (load)
                PUSH_NULL
                LOAD_FAST                2 (f)
                CALL                     1
                LOAD_FAST                0 (self)
                STORE_ATTR               6 (ubicaciones_cache)

  42    L3:     LOAD_CONST               0 (None)
                LOAD_CONST               0 (None)
                LOAD_CONST               0 (None)
                CALL                     2
                POP_TOP

  45    L4:     LOAD_FAST                0 (self)
                LOAD_ATTR               12 (ubicaciones_cache)
                TO_BOOL
                POP_JUMP_IF_FALSE       61 (to L5)

  46            LOAD_GLOBAL             15 (list + NULL)
                LOAD_FAST                0 (self)
                LOAD_ATTR               12 (ubicaciones_cache)
                LOAD_ATTR               17 (keys + NULL|self)
                CALL                     0
                CALL                     1
                STORE_FAST               3 (dists)

  47            LOAD_FAST                0 (self)
                LOAD_ATTR               18 (combo_distrito)
                LOAD_ATTR               21 (configure + NULL|self)
                LOAD_FAST                3 (dists)
                LOAD_CONST               5 (('values',))
                CALL_KW                  1
                POP_TOP
                JUMP_FORWARD            53 (to L6)

  49    L5:     LOAD_FAST                0 (self)
                LOAD_ATTR               18 (combo_distrito)
                LOAD_ATTR               21 (configure + NULL|self)
                LOAD_CONST               6 ('Ej. Lima')
                BUILD_LIST               1
                LOAD_CONST               5 (('values',))
                CALL_KW                  1
                POP_TOP

  50            LOAD_FAST                0 (self)
                LOAD_ATTR               18 (combo_distrito)
                LOAD_ATTR               23 (set + NULL|self)
                LOAD_CONST               7 ('')
                CALL                     1
                POP_TOP

  53    L6:     LOAD_CONST               8 ('ingenieros.json')
                STORE_FAST               4 (ing_path)

  54            LOAD_GLOBAL              0 (os)
                LOAD_ATTR                2 (path)
                LOAD_ATTR                5 (exists + NULL|self)
                LOAD_FAST                4 (ing_path)
                CALL                     1
                TO_BOOL
                POP_JUMP_IF_FALSE       48 (to L10)

  55            NOP

  56    L7:     LOAD_GLOBAL              7 (open + NULL)
                LOAD_FAST                4 (ing_path)
                LOAD_CONST               2 ('r')
                LOAD_CONST               3 ('utf-8')
                LOAD_CONST               4 (('encoding',))
                CALL_KW                  3
                BEFORE_WITH
        L8:     STORE_FAST               2 (f)

  57            LOAD_GLOBAL              8 (json)
                LOAD_ATTR               10 (load)
                PUSH_NULL
                LOAD_FAST                2 (f)
                CALL                     1
                LOAD_FAST                0 (self)
                STORE_ATTR              12 (ingenieros_cache)

  56    L9:     LOAD_CONST               0 (None)
                LOAD_CONST               0 (None)
                LOAD_CONST               0 (None)
                CALL                     2
                POP_TOP

  60   L10:     LOAD_FAST                0 (self)
                LOAD_ATTR               24 (ingenieros_cache)
                TO_BOOL
                POP_JUMP_IF_FALSE       31 (to L15)
                LOAD_FAST                0 (self)
                LOAD_ATTR               24 (ingenieros_cache)
                GET_ITER
                LOAD_FAST_AND_CLEAR      5 (ing)
                SWAP                     2
       L11:     BUILD_LIST               0
                SWAP                     2
                GET_ITER
       L12:     FOR_ITER                 7 (to L13)
                STORE_FAST_LOAD_FAST    85 (ing, ing)
                LOAD_CONST               9 ('nombre')
                BINARY_SUBSCR
                LIST_APPEND              2
                JUMP_BACKWARD            9 (to L12)
       L13:     END_FOR
                POP_TOP
       L14:     SWAP                     2
                STORE_FAST               5 (ing)
                JUMP_FORWARD             2 (to L16)
       L15:     LOAD_CONST              10 ('- Vacío -')
                BUILD_LIST               1
       L16:     STORE_FAST               6 (nombres)

  61            LOAD_FAST                0 (self)
                LOAD_ATTR               26 (combo_revisor)
                LOAD_ATTR               21 (configure + NULL|self)
                LOAD_FAST                6 (nombres)
                LOAD_CONST               5 (('values',))
                CALL_KW                  1
                POP_TOP

  62            LOAD_FAST                0 (self)
                LOAD_ATTR               28 (combo_proyectista)
                LOAD_ATTR               21 (configure + NULL|self)
                LOAD_FAST                6 (nombres)
                LOAD_CONST               5 (('values',))
                CALL_KW                  1
                POP_TOP

  63            LOAD_FAST                0 (self)
                LOAD_ATTR               24 (ingenieros_cache)
                TO_BOOL
                POP_JUMP_IF_FALSE       31 (to L21)
                LOAD_FAST                0 (self)
                LOAD_ATTR               24 (ingenieros_cache)
                GET_ITER
                LOAD_FAST_AND_CLEAR      5 (ing)
                SWAP                     2
       L17:     BUILD_LIST               0
                SWAP                     2
                GET_ITER
       L18:     FOR_ITER                 7 (to L19)
                STORE_FAST_LOAD_FAST    85 (ing, ing)
                LOAD_CONST               9 ('nombre')
                BINARY_SUBSCR
                LIST_APPEND              2
                JUMP_BACKWARD            9 (to L18)
       L19:     END_FOR
                POP_TOP
       L20:     SWAP                     2
                STORE_FAST               5 (ing)
                JUMP_FORWARD             2 (to L22)
       L21:     LOAD_CONST              10 ('- Vacío -')
                BUILD_LIST               1
       L22:     STORE_FAST               6 (nombres)

  64            LOAD_FAST                0 (self)
                LOAD_ATTR               26 (combo_revisor)
                LOAD_ATTR               21 (configure + NULL|self)
                LOAD_FAST                6 (nombres)
                LOAD_CONST               5 (('values',))
                CALL_KW                  1
                POP_TOP

  65            LOAD_FAST                0 (self)
                LOAD_ATTR               28 (combo_proyectista)
                LOAD_ATTR               21 (configure + NULL|self)
                LOAD_FAST                6 (nombres)
                LOAD_CONST               5 (('values',))
                CALL_KW                  1
                POP_TOP

  66            LOAD_GLOBAL             31 (hasattr + NULL)
                LOAD_FAST                0 (self)
                LOAD_CONST              11 ('combo_civil_rev')
                CALL                     2
                TO_BOOL
                POP_JUMP_IF_FALSE       25 (to L23)

  67            LOAD_FAST                0 (self)
                LOAD_ATTR               32 (combo_civil_rev)
                LOAD_ATTR               21 (configure + NULL|self)
                LOAD_FAST                6 (nombres)
                LOAD_CONST               5 (('values',))
                CALL_KW                  1
                POP_TOP

  68   L23:     LOAD_GLOBAL             31 (hasattr + NULL)
                LOAD_FAST                0 (self)
                LOAD_CONST              12 ('combo_civil_proy')
                CALL                     2
                TO_BOOL
                POP_JUMP_IF_FALSE       26 (to L24)

  69            LOAD_FAST                0 (self)
                LOAD_ATTR               34 (combo_civil_proy)
                LOAD_ATTR               21 (configure + NULL|self)
                LOAD_FAST                6 (nombres)
                LOAD_CONST               5 (('values',))
                CALL_KW                  1
                POP_TOP
                RETURN_CONST             0 (None)

  68   L24:     RETURN_CONST             0 (None)

  42   L25:     PUSH_EXC_INFO
                WITH_EXCEPT_START
                TO_BOOL
                POP_JUMP_IF_TRUE         1 (to L26)
                RERAISE                  2
       L26:     POP_TOP
       L27:     POP_EXCEPT
                POP_TOP
                POP_TOP
       L28:     EXTENDED_ARG             2
                JUMP_BACKWARD_NO_INTERRUPT 520 (to L4)

  --   L29:     COPY                     3
                POP_EXCEPT
                RERAISE                  1
       L30:     PUSH_EXC_INFO

  44            POP_TOP
       L31:     POP_EXCEPT
                EXTENDED_ARG             2
                JUMP_BACKWARD_NO_INTERRUPT 528 (to L4)

  --   L32:     COPY                     3
                POP_EXCEPT
                RERAISE                  1

  56   L33:     PUSH_EXC_INFO
                WITH_EXCEPT_START
                TO_BOOL
                POP_JUMP_IF_TRUE         1 (to L34)
                RERAISE                  2
       L34:     POP_TOP
       L35:     POP_EXCEPT
                POP_TOP
                POP_TOP
       L36:     EXTENDED_ARG             1
                JUMP_BACKWARD_NO_INTERRUPT 329 (to L10)

  --   L37:     COPY                     3
                POP_EXCEPT
                RERAISE                  1
       L38:     PUSH_EXC_INFO

  58            POP_TOP
       L39:     POP_EXCEPT
                EXTENDED_ARG             1
                JUMP_BACKWARD_NO_INTERRUPT 337 (to L10)

  --   L40:     COPY                     3
                POP_EXCEPT
                RERAISE                  1
       L41:     SWAP                     2
                POP_TOP

  60            SWAP                     2
                STORE_FAST               5 (ing)
                RERAISE                  0

  --   L42:     SWAP                     2
                POP_TOP

  63            SWAP                     2
                STORE_FAST               5 (ing)
                RERAISE                  0
ExceptionTable:
  L1 to L2 -> L30 [0]
  L2 to L3 -> L25 [1] lasti
  L3 to L4 -> L30 [0]
  L7 to L8 -> L38 [0]
  L8 to L9 -> L33 [1] lasti
  L9 to L10 -> L38 [0]
  L11 to L14 -> L41 [2]
  L17 to L20 -> L42 [2]
  L25 to L27 -> L29 [3] lasti
  L27 to L28 -> L30 [0]
  L29 to L30 -> L30 [0]
  L30 to L31 -> L32 [1] lasti
  L33 to L35 -> L37 [3] lasti
  L35 to L36 -> L38 [0]
  L37 to L38 -> L38 [0]
  L38 to L39 -> L40 [1] lasti

Disassembly of <code object on_date_typing at 0x0000028A6B4993B0, file "src\ui\tab_carta.py", line 71>:
 71           RESUME                   0

 72           LOAD_FAST                1 (event)
              LOAD_ATTR                0 (keysym)
              LOAD_CONST               1 (('BackSpace', 'Delete', 'Left', 'Right'))
              CONTAINS_OP              0
              POP_JUMP_IF_FALSE        1 (to L1)
              RETURN_CONST             0 (None)

 73   L1:     LOAD_FAST                2 (entry_widget)
              LOAD_ATTR                3 (get + NULL|self)
              CALL                     0
              LOAD_ATTR                5 (replace + NULL|self)
              LOAD_CONST               2 ('/')
              LOAD_CONST               3 ('')
              CALL                     2
              STORE_FAST               3 (texto)

 74           LOAD_FAST                3 (texto)
              LOAD_ATTR                7 (isdigit + NULL|self)
              CALL                     0
              TO_BOOL
              POP_JUMP_IF_TRUE        55 (to L4)
              LOAD_FAST                3 (texto)
              LOAD_CONST               3 ('')
              COMPARE_OP             119 (bool(!=))
              POP_JUMP_IF_FALSE       49 (to L4)

 75           LOAD_FAST                2 (entry_widget)
              LOAD_ATTR                9 (delete + NULL|self)
              LOAD_CONST               4 (0)
              LOAD_CONST               5 ('end')
              CALL                     2
              POP_TOP

 76           LOAD_FAST                2 (entry_widget)
              LOAD_ATTR               11 (insert + NULL|self)
              LOAD_CONST               4 (0)
              LOAD_FAST                3 (texto)
              TO_BOOL
              POP_JUMP_IF_FALSE        5 (to L2)
              LOAD_FAST                3 (texto)
              LOAD_CONST               0 (None)
              LOAD_CONST               6 (-1)
              BINARY_SLICE
              JUMP_FORWARD             1 (to L3)
      L2:     LOAD_CONST               3 ('')
      L3:     CALL                     2
              POP_TOP

 77           RETURN_CONST             0 (None)

 79   L4:     LOAD_GLOBAL             13 (len + NULL)
              LOAD_FAST                3 (texto)
              CALL                     1
              LOAD_CONST               7 (8)
              COMPARE_OP             148 (bool(>))
              POP_JUMP_IF_FALSE        5 (to L5)
              LOAD_FAST                3 (texto)
              LOAD_CONST               0 (None)
              LOAD_CONST               7 (8)
              BINARY_SLICE
              STORE_FAST               3 (texto)

 80   L5:     LOAD_CONST               3 ('')
              STORE_FAST               4 (formateado)

 81           LOAD_GLOBAL             15 (enumerate + NULL)
              LOAD_GLOBAL             17 (str + NULL)
              LOAD_FAST                3 (texto)
              CALL                     1
              CALL                     1
              GET_ITER
      L6:     FOR_ITER                26 (to L9)
              UNPACK_SEQUENCE          2
              STORE_FAST_STORE_FAST   86 (i, char)

 82           LOAD_FAST                5 (i)
              LOAD_CONST               8 (2)
              COMPARE_OP              88 (bool(==))
              POP_JUMP_IF_TRUE         6 (to L7)
              LOAD_FAST                5 (i)
              LOAD_CONST               9 (4)
              COMPARE_OP              88 (bool(==))
              POP_JUMP_IF_FALSE        5 (to L8)

 83   L7:     LOAD_FAST                4 (formateado)
              LOAD_CONST               2 ('/')
              BINARY_OP               13 (+=)
              STORE_FAST               4 (formateado)

 84   L8:     LOAD_FAST_LOAD_FAST     70 (formateado, char)
              BINARY_OP               13 (+=)
              STORE_FAST               4 (formateado)
              JUMP_BACKWARD           28 (to L6)

 81   L9:     END_FOR
              POP_TOP

 86           LOAD_FAST                2 (entry_widget)
              LOAD_ATTR                9 (delete + NULL|self)
              LOAD_CONST               4 (0)
              LOAD_CONST               5 ('end')
              CALL                     2
              POP_TOP

 87           LOAD_FAST                2 (entry_widget)
              LOAD_ATTR               11 (insert + NULL|self)
              LOAD_CONST               4 (0)
              LOAD_FAST                4 (formateado)
              CALL                     2
              POP_TOP
              RETURN_CONST             0 (None)

Disassembly of <code object setup_ui at 0x0000028A6B496780, file "src\ui\tab_carta.py", line 89>:
 89           RESUME                   0

 92           LOAD_FAST                0 (self)
              LOAD_ATTR                1 (grid_rowconfigure + NULL|self)
              LOAD_CONST               1 (0)
              LOAD_CONST               2 (1)
              LOAD_CONST               3 (('weight',))
              CALL_KW                  2
              POP_TOP

 93           LOAD_FAST                0 (self)
              LOAD_ATTR                3 (grid_columnconfigure + NULL|self)
              LOAD_CONST               1 (0)
              LOAD_CONST               4 (4)
              LOAD_CONST               3 (('weight',))
              CALL_KW                  2
              POP_TOP

 94           LOAD_FAST                0 (self)
              LOAD_ATTR                3 (grid_columnconfigure + NULL|self)
              LOAD_CONST               2 (1)
              LOAD_CONST               2 (1)
              LOAD_CONST               3 (('weight',))
              CALL_KW                  2
              POP_TOP

 97           LOAD_GLOBAL              4 (ctk)
              LOAD_ATTR                6 (CTkScrollableFrame)
              PUSH_NULL
              LOAD_FAST                0 (self)
              LOAD_CONST               1 (0)
              LOAD_CONST               5 (('corner_radius',))
              CALL_KW                  2
              LOAD_FAST                0 (self)
              STORE_ATTR               4 (left_panel)

 98           LOAD_FAST                0 (self)
              LOAD_ATTR                8 (left_panel)
              LOAD_ATTR               11 (grid + NULL|self)
              LOAD_CONST               1 (0)
              LOAD_CONST               1 (0)
              LOAD_CONST               6 ('nsew')
              LOAD_CONST               7 ((0, 5))
              LOAD_CONST               8 (('row', 'column', 'sticky', 'padx'))
              CALL_KW                  4
              POP_TOP

100           LOAD_GLOBAL              4 (ctk)
              LOAD_ATTR               12 (CTkLabel)
              PUSH_NULL
              LOAD_FAST                0 (self)
              LOAD_ATTR                8 (left_panel)
              LOAD_CONST               9 ('ASISTENTE DE CARTA DE APROBACIÓN')
              LOAD_GLOBAL              4 (ctk)
              LOAD_ATTR               14 (CTkFont)
              PUSH_NULL
              LOAD_CONST              10 (20)
              LOAD_CONST              11 ('bold')
              LOAD_CONST              12 (('size', 'weight'))
              CALL_KW                  2
              LOAD_CONST              13 (('text', 'font'))
              CALL_KW                  3
              STORE_FAST               1 (lbl_title)

101           LOAD_FAST                1 (lbl_title)
              LOAD_ATTR               17 (pack + NULL|self)
              LOAD_CONST              14 ((20, 10))
              LOAD_CONST              10 (20)
              LOAD_CONST              15 (('pady', 'padx'))
              CALL_KW                  2
              POP_TOP

104           LOAD_FAST                0 (self)
              LOAD_ATTR               19 (build_bloque_generales + NULL|self)
              CALL                     0
              POP_TOP

107           LOAD_FAST                0 (self)
              LOAD_ATTR               21 (build_bloque_ubicacion + NULL|self)
              CALL                     0
              POP_TOP

110           LOAD_FAST                0 (self)
              LOAD_ATTR               23 (build_bloque_fechas + NULL|self)
              CALL                     0
              POP_TOP

113           LOAD_FAST                0 (self)
              LOAD_ATTR               25 (build_bloque_ingenieros + NULL|self)
              CALL                     0
              POP_TOP

116           LOAD_FAST                0 (self)
              LOAD_ATTR               27 (build_bloque_planos + NULL|self)
              CALL                     0
              POP_TOP

119           LOAD_GLOBAL              4 (ctk)
              LOAD_ATTR               28 (CTkFrame)
              PUSH_NULL
              LOAD_FAST                0 (self)
              LOAD_CONST               1 (0)
              LOAD_CONST               5 (('corner_radius',))
              CALL_KW                  2
              LOAD_FAST                0 (self)
              STORE_ATTR              15 (right_panel)

120           LOAD_FAST                0 (self)
              LOAD_ATTR               30 (right_panel)
              LOAD_ATTR               11 (grid + NULL|self)
              LOAD_CONST               1 (0)
              LOAD_CONST               2 (1)
              LOAD_CONST               6 ('nsew')
              LOAD_CONST              16 ((5, 0))
              LOAD_CONST               8 (('row', 'column', 'sticky', 'padx'))
              CALL_KW                  4
              POP_TOP

122           LOAD_GLOBAL              4 (ctk)
              LOAD_ATTR               12 (CTkLabel)
              PUSH_NULL
              LOAD_FAST                0 (self)
              LOAD_ATTR               30 (right_panel)
              LOAD_CONST              17 ('ACCIONES')
              LOAD_GLOBAL              4 (ctk)
              LOAD_ATTR               14 (CTkFont)
              PUSH_NULL
              LOAD_CONST              18 (18)
              LOAD_CONST              11 ('bold')
              LOAD_CONST              12 (('size', 'weight'))
              CALL_KW                  2
              LOAD_CONST              13 (('text', 'font'))
              CALL_KW                  3
              STORE_FAST               2 (lbl_resume)

123           LOAD_FAST                2 (lbl_resume)
              LOAD_ATTR               17 (pack + NULL|self)
              LOAD_CONST              14 ((20, 10))
              LOAD_CONST              10 (20)
              LOAD_CONST              15 (('pady', 'padx'))
              CALL_KW                  2
              POP_TOP

126           LOAD_GLOBAL              4 (ctk)
              LOAD_ATTR               32 (CTkButton)
              PUSH_NULL
              LOAD_FAST                0 (self)
              LOAD_ATTR               30 (right_panel)
              LOAD_CONST              19 ('Generar Documento Word')
              LOAD_CONST              20 ('blue')
              LOAD_CONST              21 ('darkblue')
              LOAD_CONST              22 (50)
              LOAD_GLOBAL              4 (ctk)
              LOAD_ATTR               14 (CTkFont)
              PUSH_NULL
              LOAD_CONST              11 ('bold')
              LOAD_CONST               3 (('weight',))
              CALL_KW                  1
              LOAD_FAST                0 (self)
              LOAD_ATTR               34 (action_generar_word)
              LOAD_CONST              23 (('text', 'fg_color', 'hover_color', 'height', 'font', 'command'))
              CALL_KW                  7
              LOAD_FAST                0 (self)
              STORE_ATTR              18 (btn_export)

127           LOAD_FAST                0 (self)
              LOAD_ATTR               36 (btn_export)
              LOAD_ATTR               17 (pack + NULL|self)
              LOAD_CONST              24 ('x')
              LOAD_CONST              10 (20)
              LOAD_CONST              14 ((20, 10))
              LOAD_CONST              25 (('fill', 'padx', 'pady'))
              CALL_KW                  3
              POP_TOP

129           LOAD_GLOBAL              4 (ctk)
              LOAD_ATTR               12 (CTkLabel)
              PUSH_NULL
              LOAD_FAST                0 (self)
              LOAD_ATTR               30 (right_panel)
              LOAD_CONST              26 ('© L.Navarrete')
              LOAD_CONST              27 ('gray')
              LOAD_GLOBAL              4 (ctk)
              LOAD_ATTR               14 (CTkFont)
              PUSH_NULL
              LOAD_CONST              28 (10)
              LOAD_CONST              29 ('italic')
              LOAD_CONST              30 (('size', 'slant'))
              CALL_KW                  2
              LOAD_CONST              31 (('text', 'text_color', 'font'))
              CALL_KW                  4
              LOAD_FAST                0 (self)
              STORE_ATTR              19 (lbl_watermark)

130           LOAD_FAST                0 (self)
              LOAD_ATTR               38 (lbl_watermark)
              LOAD_ATTR               17 (pack + NULL|self)
              LOAD_CONST              32 ((0, 20))
              LOAD_CONST              33 (('pady',))
              CALL_KW                  1
              POP_TOP
              RETURN_CONST             0 (None)

Disassembly of <code object build_bloque_generales at 0x0000028A6B496CA0, file "src\ui\tab_carta.py", line 132>:
132           RESUME                   0

133           LOAD_GLOBAL              0 (ctk)
              LOAD_ATTR                2 (CTkLabel)
              PUSH_NULL
              LOAD_FAST                0 (self)
              LOAD_ATTR                4 (left_panel)
              LOAD_CONST               1 ('1. Datos Generales y Fechas')
              LOAD_GLOBAL              0 (ctk)
              LOAD_ATTR                6 (CTkFont)
              PUSH_NULL
              LOAD_CONST               2 ('bold')
              LOAD_CONST               3 (14)
              LOAD_CONST               4 (('weight', 'size'))
              CALL_KW                  2
              LOAD_CONST               5 (('text', 'font'))
              CALL_KW                  3
              STORE_FAST               1 (lbl)

134           LOAD_FAST                1 (lbl)
              LOAD_ATTR                9 (pack + NULL|self)
              LOAD_CONST               6 ((15, 5))
              LOAD_CONST               7 (20)
              LOAD_CONST               8 ('w')
              LOAD_CONST               9 (('pady', 'padx', 'anchor'))
              CALL_KW                  3
              POP_TOP

136           LOAD_GLOBAL              0 (ctk)
              LOAD_ATTR               10 (CTkFrame)
              PUSH_NULL
              LOAD_FAST                0 (self)
              LOAD_ATTR                4 (left_panel)
              CALL                     1
              STORE_FAST               2 (f_generales)

137           LOAD_FAST                2 (f_generales)
              LOAD_ATTR                9 (pack + NULL|self)
              LOAD_CONST              10 ('x')
              LOAD_CONST               7 (20)
              LOAD_CONST              11 (5)
              LOAD_CONST              12 (('fill', 'padx', 'pady'))
              CALL_KW                  3
              POP_TOP

139           LOAD_GLOBAL              0 (ctk)
              LOAD_ATTR               12 (CTkEntry)
              PUSH_NULL
              LOAD_FAST                2 (f_generales)
              LOAD_CONST              13 ('Num ATC (Ej. 0100)')
              LOAD_CONST              14 (('placeholder_text',))
              CALL_KW                  2
              LOAD_FAST                0 (self)
              STORE_ATTR               7 (entry_atc)

140           LOAD_FAST                0 (self)
              LOAD_ATTR               14 (entry_atc)
              LOAD_ATTR               17 (grid + NULL|self)
              LOAD_CONST              15 (0)
              LOAD_CONST              15 (0)
              LOAD_CONST              16 ('ew')
              LOAD_CONST              17 (10)
              LOAD_CONST              17 (10)
              LOAD_CONST              18 (('row', 'column', 'sticky', 'padx', 'pady'))
              CALL_KW                  5
              POP_TOP

142           LOAD_GLOBAL              0 (ctk)
              LOAD_ATTR               12 (CTkEntry)
              PUSH_NULL
              LOAD_FAST                2 (f_generales)
              LOAD_CONST              19 ('Referencia')
              LOAD_CONST              14 (('placeholder_text',))
              CALL_KW                  2
              LOAD_FAST                0 (self)
              STORE_ATTR               9 (entry_referencia)

143           LOAD_FAST                0 (self)
              LOAD_ATTR               18 (entry_referencia)
              LOAD_ATTR               17 (grid + NULL|self)
              LOAD_CONST              15 (0)
              LOAD_CONST              20 (1)
              LOAD_CONST              16 ('ew')
              LOAD_CONST              17 (10)
              LOAD_CONST              17 (10)
              LOAD_CONST              18 (('row', 'column', 'sticky', 'padx', 'pady'))
              CALL_KW                  5
              POP_TOP

145           LOAD_GLOBAL              0 (ctk)
              LOAD_ATTR               12 (CTkEntry)
              PUSH_NULL
              LOAD_FAST                2 (f_generales)
              LOAD_CONST              21 ('Fecha Emisión (DD/MM/AAAA)')
              LOAD_CONST              14 (('placeholder_text',))
              CALL_KW                  2
              LOAD_FAST                0 (self)
              STORE_ATTR              10 (entry_fecha_sys)

146           LOAD_FAST                0 (self)
              LOAD_ATTR               20 (entry_fecha_sys)
              LOAD_ATTR               17 (grid + NULL|self)
              LOAD_CONST              20 (1)
              LOAD_CONST              15 (0)
              LOAD_CONST              22 (2)
              LOAD_CONST              16 ('ew')
              LOAD_CONST              17 (10)
              LOAD_CONST              17 (10)
              LOAD_CONST              23 (('row', 'column', 'columnspan', 'sticky', 'padx', 'pady'))
              CALL_KW                  6
              POP_TOP

148           LOAD_FAST                2 (f_generales)
              LOAD_ATTR               23 (grid_columnconfigure + NULL|self)
              LOAD_CONST              15 (0)
              LOAD_CONST              20 (1)
              LOAD_CONST              24 (('weight',))
              CALL_KW                  2
              POP_TOP

149           LOAD_FAST                2 (f_generales)
              LOAD_ATTR               23 (grid_columnconfigure + NULL|self)
              LOAD_CONST              20 (1)
              LOAD_CONST              20 (1)
              LOAD_CONST              24 (('weight',))
              CALL_KW                  2
              POP_TOP
              RETURN_CONST             0 (None)

Disassembly of <code object build_bloque_ubicacion at 0x0000028A6B46A2E0, file "src\ui\tab_carta.py", line 151>:
151           RESUME                   0

152           LOAD_GLOBAL              0 (ctk)
              LOAD_ATTR                2 (CTkLabel)
              PUSH_NULL
              LOAD_FAST                0 (self)
              LOAD_ATTR                4 (left_panel)
              LOAD_CONST               1 ('2. Solicitud, Cliente y Ubicación')
              LOAD_GLOBAL              0 (ctk)
              LOAD_ATTR                6 (CTkFont)
              PUSH_NULL
              LOAD_CONST               2 ('bold')
              LOAD_CONST               3 (14)
              LOAD_CONST               4 (('weight', 'size'))
              CALL_KW                  2
              LOAD_CONST               5 (('text', 'font'))
              CALL_KW                  3
              STORE_FAST               1 (lbl)

153           LOAD_FAST                1 (lbl)
              LOAD_ATTR                9 (pack + NULL|self)
              LOAD_CONST               6 ((15, 5))
              LOAD_CONST               7 (20)
              LOAD_CONST               8 ('w')
              LOAD_CONST               9 (('pady', 'padx', 'anchor'))
              CALL_KW                  3
              POP_TOP

155           LOAD_GLOBAL              0 (ctk)
              LOAD_ATTR               10 (CTkFrame)
              PUSH_NULL
              LOAD_FAST                0 (self)
              LOAD_ATTR                4 (left_panel)
              CALL                     1
              STORE_FAST               2 (f_ubi)

156           LOAD_FAST                2 (f_ubi)
              LOAD_ATTR                9 (pack + NULL|self)
              LOAD_CONST              10 ('x')
              LOAD_CONST               7 (20)
              LOAD_CONST              11 (5)
              LOAD_CONST              12 (('fill', 'padx', 'pady'))
              CALL_KW                  3
              POP_TOP

158           LOAD_GLOBAL              0 (ctk)
              LOAD_ATTR               12 (CTkEntry)
              PUSH_NULL
              LOAD_FAST                2 (f_ubi)
              LOAD_CONST              13 ('Solicitud (Ej. Aprobación de Subsistema...)')
              LOAD_CONST              14 (('placeholder_text',))
              CALL_KW                  2
              LOAD_FAST                0 (self)
              STORE_ATTR               7 (entry_solicitud)

159           LOAD_FAST                0 (self)
              LOAD_ATTR               14 (entry_solicitud)
              LOAD_ATTR               17 (grid + NULL|self)
              LOAD_CONST              15 (0)
              LOAD_CONST              15 (0)
              LOAD_CONST              16 (2)
              LOAD_CONST              17 ('ew')
              LOAD_CONST              18 (10)
              LOAD_CONST              18 (10)
              LOAD_CONST              19 (('row', 'column', 'columnspan', 'sticky', 'padx', 'pady'))
              CALL_KW                  6
              POP_TOP

161           LOAD_GLOBAL              0 (ctk)
              LOAD_ATTR               12 (CTkEntry)
              PUSH_NULL
              LOAD_FAST                2 (f_ubi)
              LOAD_CONST              20 ('Dirigido A (Empresa o Persona)')
              LOAD_CONST              14 (('placeholder_text',))
              CALL_KW                  2
              LOAD_FAST                0 (self)
              STORE_ATTR               9 (entry_dirigido)

162           LOAD_FAST                0 (self)
              LOAD_ATTR               18 (entry_dirigido)
              LOAD_ATTR               17 (grid + NULL|self)
              LOAD_CONST              21 (1)
              LOAD_CONST              15 (0)
              LOAD_CONST              17 ('ew')
              LOAD_CONST              18 (10)
              LOAD_CONST              22 ((10, 2))
              LOAD_CONST              23 (('row', 'column', 'sticky', 'padx', 'pady'))
              CALL_KW                  5
              POP_TOP

164           LOAD_GLOBAL              0 (ctk)
              LOAD_ATTR               12 (CTkEntry)
              PUSH_NULL
              LOAD_FAST                2 (f_ubi)
              LOAD_CONST              24 ('Cliente (Propietario)')
              LOAD_CONST              14 (('placeholder_text',))
              CALL_KW                  2
              LOAD_FAST                0 (self)
              STORE_ATTR              10 (entry_cliente)

165           LOAD_FAST                0 (self)
              LOAD_ATTR               20 (entry_cliente)
              LOAD_ATTR               17 (grid + NULL|self)
              LOAD_CONST              21 (1)
              LOAD_CONST              21 (1)
              LOAD_CONST              17 ('ew')
              LOAD_CONST              18 (10)
              LOAD_CONST              22 ((10, 2))
              LOAD_CONST              23 (('row', 'column', 'sticky', 'padx', 'pady'))
              CALL_KW                  5
              POP_TOP

168           LOAD_GLOBAL              0 (ctk)
              LOAD_ATTR               22 (BooleanVar)
              PUSH_NULL
              LOAD_CONST              25 (False)
              LOAD_CONST              26 (('value',))
              CALL_KW                  1
              LOAD_FAST                0 (self)
              STORE_ATTR              12 (var_mismo_cliente)

169           LOAD_GLOBAL              0 (ctk)
              LOAD_ATTR               26 (CTkCheckBox)
              PUSH_NULL
              LOAD_FAST                2 (f_ubi)
              LOAD_CONST              27 ('Mismo que Dirigido')
              LOAD_FAST                0 (self)
              LOAD_ATTR               24 (var_mismo_cliente)
              LOAD_FAST                0 (self)
              LOAD_ATTR               28 (on_chk_cliente)
              LOAD_CONST              28 (('text', 'variable', 'command'))
              CALL_KW                  4
              LOAD_FAST                0 (self)
              STORE_ATTR              15 (chk_cliente)

170           LOAD_FAST                0 (self)
              LOAD_ATTR               30 (chk_cliente)
              LOAD_ATTR               17 (grid + NULL|self)
              LOAD_CONST              16 (2)
              LOAD_CONST              21 (1)
              LOAD_CONST               8 ('w')
              LOAD_CONST              18 (10)
              LOAD_CONST              29 ((0, 10))
              LOAD_CONST              23 (('row', 'column', 'sticky', 'padx', 'pady'))
              CALL_KW                  5
              POP_TOP

173           LOAD_GLOBAL              0 (ctk)
              LOAD_ATTR               12 (CTkEntry)
              PUSH_NULL
              LOAD_FAST                2 (f_ubi)
              LOAD_CONST              30 ('Dirección de la Carta')
              LOAD_CONST              14 (('placeholder_text',))
              CALL_KW                  2
              LOAD_FAST                0 (self)
              STORE_ATTR              16 (entry_direccion)

174           LOAD_FAST                0 (self)
              LOAD_ATTR               32 (entry_direccion)
              LOAD_ATTR               17 (grid + NULL|self)
              LOAD_CONST              31 (3)
              LOAD_CONST              15 (0)
              LOAD_CONST              17 ('ew')
              LOAD_CONST              18 (10)
              LOAD_CONST              22 ((10, 2))
              LOAD_CONST              23 (('row', 'column', 'sticky', 'padx', 'pady'))
              CALL_KW                  5
              POP_TOP

176           LOAD_GLOBAL              0 (ctk)
              LOAD_ATTR               12 (CTkEntry)
              PUSH_NULL
              LOAD_FAST                2 (f_ubi)
              LOAD_CONST              32 ('Dirección Real del Proyecto')
              LOAD_CONST              14 (('placeholder_text',))
              CALL_KW                  2
              LOAD_FAST                0 (self)
              STORE_ATTR              17 (entry_direccion_proyecto)

177           LOAD_FAST                0 (self)
              LOAD_ATTR               34 (entry_direccion_proyecto)
              LOAD_ATTR               17 (grid + NULL|self)
              LOAD_CONST              31 (3)
              LOAD_CONST              21 (1)
              LOAD_CONST              17 ('ew')
              LOAD_CONST              18 (10)
              LOAD_CONST              22 ((10, 2))
              LOAD_CONST              23 (('row', 'column', 'sticky', 'padx', 'pady'))
              CALL_KW                  5
              POP_TOP

180           LOAD_GLOBAL              0 (ctk)
              LOAD_ATTR               22 (BooleanVar)
              PUSH_NULL
              LOAD_CONST              25 (False)
              LOAD_CONST              26 (('value',))
              CALL_KW                  1
              LOAD_FAST                0 (self)
              STORE_ATTR              18 (var_misma_dir)

181           LOAD_GLOBAL              0 (ctk)
              LOAD_ATTR               26 (CTkCheckBox)
              PUSH_NULL
              LOAD_FAST                2 (f_ubi)
              LOAD_CONST              33 ('Misma Dirección')
              LOAD_FAST                0 (self)
              LOAD_ATTR               36 (var_misma_dir)
              LOAD_FAST                0 (self)
              LOAD_ATTR               38 (on_chk_dir)
              LOAD_CONST              28 (('text', 'variable', 'command'))
              CALL_KW                  4
              LOAD_FAST                0 (self)
              STORE_ATTR              20 (chk_direccion)

182           LOAD_FAST                0 (self)
              LOAD_ATTR               40 (chk_direccion)
              LOAD_ATTR               17 (grid + NULL|self)
              LOAD_CONST              34 (4)
              LOAD_CONST              21 (1)
              LOAD_CONST               8 ('w')
              LOAD_CONST              18 (10)
              LOAD_CONST              29 ((0, 10))
              LOAD_CONST              23 (('row', 'column', 'sticky', 'padx', 'pady'))
              CALL_KW                  5
              POP_TOP

185           LOAD_GLOBAL              0 (ctk)
              LOAD_ATTR               42 (CTkComboBox)
              PUSH_NULL
              LOAD_FAST                2 (f_ubi)
              LOAD_CONST              35 ('Cargando...')
              BUILD_LIST               1
              LOAD_FAST                0 (self)
              LOAD_ATTR               44 (on_distrito_change)
              LOAD_CONST              36 (('values', 'command'))
              CALL_KW                  3
              LOAD_FAST                0 (self)
              STORE_ATTR              23 (combo_distrito)

186           LOAD_FAST                0 (self)
              LOAD_ATTR               46 (combo_distrito)
              LOAD_ATTR               17 (grid + NULL|self)
              LOAD_CONST              11 (5)
              LOAD_CONST              15 (0)
              LOAD_CONST              17 ('ew')
              LOAD_CONST              18 (10)
              LOAD_CONST              18 (10)
              LOAD_CONST              23 (('row', 'column', 'sticky', 'padx', 'pady'))
              CALL_KW                  5
              POP_TOP

187           LOAD_FAST                0 (self)
              LOAD_ATTR               46 (combo_distrito)
              LOAD_ATTR               49 (bind + NULL|self)
              LOAD_CONST              37 ('<KeyRelease>')
              LOAD_FAST                0 (self)
              LOAD_ATTR               50 (on_distrito_type)
              CALL                     2
              POP_TOP

189           LOAD_GLOBAL              0 (ctk)
              LOAD_ATTR               12 (CTkEntry)
              PUSH_NULL
              LOAD_FAST                2 (f_ubi)
              LOAD_CONST              38 ('Departamento (Ej. Lima)')
              LOAD_CONST              14 (('placeholder_text',))
              CALL_KW                  2
              LOAD_FAST                0 (self)
              STORE_ATTR              26 (entry_departamento)

190           LOAD_FAST                0 (self)
              LOAD_ATTR               52 (entry_departamento)
              LOAD_ATTR               17 (grid + NULL|self)
              LOAD_CONST              11 (5)
              LOAD_CONST              21 (1)
              LOAD_CONST              17 ('ew')
              LOAD_CONST              18 (10)
              LOAD_CONST              18 (10)
              LOAD_CONST              23 (('row', 'column', 'sticky', 'padx', 'pady'))
              CALL_KW                  5
              POP_TOP

192           LOAD_FAST                2 (f_ubi)
              LOAD_ATTR               55 (grid_columnconfigure + NULL|self)
              LOAD_CONST              15 (0)
              LOAD_CONST              21 (1)
              LOAD_CONST              39 (('weight',))
              CALL_KW                  2
              POP_TOP

193           LOAD_FAST                2 (f_ubi)
              LOAD_ATTR               55 (grid_columnconfigure + NULL|self)
              LOAD_CONST              21 (1)
              LOAD_CONST              21 (1)
              LOAD_CONST              39 (('weight',))
              CALL_KW                  2
              POP_TOP
              RETURN_CONST             0 (None)

Disassembly of <code object build_bloque_fechas at 0x0000028A6B497C90, file "src\ui\tab_carta.py", line 195>:
195           RESUME                   0

196           LOAD_GLOBAL              0 (ctk)
              LOAD_ATTR                2 (CTkLabel)
              PUSH_NULL
              LOAD_FAST                0 (self)
              LOAD_ATTR                4 (left_panel)
              LOAD_CONST               1 ('3. Fechas del Proyecto (Carta e Inicio)')
              LOAD_GLOBAL              0 (ctk)
              LOAD_ATTR                6 (CTkFont)
              PUSH_NULL
              LOAD_CONST               2 ('bold')
              LOAD_CONST               3 (14)
              LOAD_CONST               4 (('weight', 'size'))
              CALL_KW                  2
              LOAD_CONST               5 (('text', 'font'))
              CALL_KW                  3
              STORE_FAST               1 (lbl)

197           LOAD_FAST                1 (lbl)
              LOAD_ATTR                9 (pack + NULL|self)
              LOAD_CONST               6 ((15, 5))
              LOAD_CONST               7 (20)
              LOAD_CONST               8 ('w')
              LOAD_CONST               9 (('pady', 'padx', 'anchor'))
              CALL_KW                  3
              POP_TOP

199           LOAD_GLOBAL              0 (ctk)
              LOAD_ATTR               10 (CTkFrame)
              PUSH_NULL
              LOAD_FAST                0 (self)
              LOAD_ATTR                4 (left_panel)
              CALL                     1
              STORE_FAST               2 (f_fec)

200           LOAD_FAST                2 (f_fec)
              LOAD_ATTR                9 (pack + NULL|self)
              LOAD_CONST              10 ('x')
              LOAD_CONST               7 (20)
              LOAD_CONST              11 (5)
              LOAD_CONST              12 (('fill', 'padx', 'pady'))
              CALL_KW                  3
              POP_TOP

202           LOAD_GLOBAL              0 (ctk)
              LOAD_ATTR               12 (CTkEntry)
              PUSH_NULL
              LOAD_FAST                2 (f_fec)
              LOAD_CONST              13 ('Fecha Carta (DD/MM/YYYY)')
              LOAD_CONST              14 (('placeholder_text',))
              CALL_KW                  2
              LOAD_FAST                0 (self)
              STORE_ATTR               7 (entry_fecha_carta)

203           LOAD_FAST                0 (self)
              LOAD_ATTR               14 (entry_fecha_carta)
              LOAD_ATTR               17 (grid + NULL|self)
              LOAD_CONST              15 (0)
              LOAD_CONST              15 (0)
              LOAD_CONST              16 ('ew')
              LOAD_CONST              17 (10)
              LOAD_CONST              17 (10)
              LOAD_CONST              18 (('row', 'column', 'sticky', 'padx', 'pady'))
              CALL_KW                  5
              POP_TOP

205           LOAD_GLOBAL              0 (ctk)
              LOAD_ATTR               12 (CTkEntry)
              PUSH_NULL
              LOAD_FAST                2 (f_fec)
              LOAD_CONST              19 ('Fecha Inicio (DD/MM/YYYY)')
              LOAD_CONST              14 (('placeholder_text',))
              CALL_KW                  2
              LOAD_FAST                0 (self)
              STORE_ATTR               9 (entry_fecha_inicio)

206           LOAD_FAST                0 (self)
              LOAD_ATTR               18 (entry_fecha_inicio)
              LOAD_ATTR               17 (grid + NULL|self)
              LOAD_CONST              15 (0)
              LOAD_CONST              20 (1)
              LOAD_CONST              16 ('ew')
              LOAD_CONST              17 (10)
              LOAD_CONST              21 ((10, 2))
              LOAD_CONST              18 (('row', 'column', 'sticky', 'padx', 'pady'))
              CALL_KW                  5
              POP_TOP

208           LOAD_GLOBAL              0 (ctk)
              LOAD_ATTR               12 (CTkEntry)
              PUSH_NULL
              LOAD_FAST                2 (f_fec)
              LOAD_CONST              22 ('Fecha Fin (Automático)')
              LOAD_CONST              23 ('disabled')
              LOAD_CONST              24 (('placeholder_text', 'state'))
              CALL_KW                  3
              LOAD_FAST                0 (self)
              STORE_ATTR              10 (entry_fecha_fin)

209           LOAD_FAST                0 (self)
              LOAD_ATTR               20 (entry_fecha_fin)
              LOAD_ATTR               17 (grid + NULL|self)
              LOAD_CONST              15 (0)
              LOAD_CONST              25 (2)
              LOAD_CONST              16 ('ew')
              LOAD_CONST              17 (10)
              LOAD_CONST              17 (10)
              LOAD_CONST              18 (('row', 'column', 'sticky', 'padx', 'pady'))
              CALL_KW                  5
              POP_TOP

212           LOAD_GLOBAL              0 (ctk)
              LOAD_ATTR               22 (BooleanVar)
              PUSH_NULL
              LOAD_CONST              26 (False)
              LOAD_CONST              27 (('value',))
              CALL_KW                  1
              LOAD_FAST                0 (self)
              STORE_ATTR              12 (var_usar_f_hoy)

213           LOAD_GLOBAL              0 (ctk)
              LOAD_ATTR               26 (CTkCheckBox)
              PUSH_NULL
              LOAD_FAST                2 (f_fec)
              LOAD_CONST              28 ('Igualar a Fecha Emisión')
              LOAD_FAST                0 (self)
              LOAD_ATTR               24 (var_usar_f_hoy)
              LOAD_FAST                0 (self)
              LOAD_ATTR               28 (on_chk_fecha_hoy)
              LOAD_CONST              29 (('text', 'variable', 'command'))
              CALL_KW                  4
              LOAD_FAST                0 (self)
              STORE_ATTR              15 (chk_f_hoy)

214           LOAD_FAST                0 (self)
              LOAD_ATTR               30 (chk_f_hoy)
              LOAD_ATTR               17 (grid + NULL|self)
              LOAD_CONST              20 (1)
              LOAD_CONST              20 (1)
              LOAD_CONST               8 ('w')
              LOAD_CONST              17 (10)
              LOAD_CONST              30 ((0, 10))
              LOAD_CONST              18 (('row', 'column', 'sticky', 'padx', 'pady'))
              CALL_KW                  5
              POP_TOP

216           LOAD_FAST                2 (f_fec)
              LOAD_ATTR               33 (grid_columnconfigure + NULL|self)
              LOAD_CONST              15 (0)
              LOAD_CONST              20 (1)
              LOAD_CONST              31 (('weight',))
              CALL_KW                  2
              POP_TOP

217           LOAD_FAST                2 (f_fec)
              LOAD_ATTR               33 (grid_columnconfigure + NULL|self)
              LOAD_CONST              20 (1)
              LOAD_CONST              20 (1)
              LOAD_CONST              31 (('weight',))
              CALL_KW                  2
              POP_TOP

218           LOAD_FAST                2 (f_fec)
              LOAD_ATTR               33 (grid_columnconfigure + NULL|self)
              LOAD_CONST              25 (2)
              LOAD_CONST              20 (1)
              LOAD_CONST              31 (('weight',))
              CALL_KW                  2
              POP_TOP
              RETURN_CONST             0 (None)

Disassembly of <code object build_bloque_ingenieros at 0x0000028A6B46C1D0, file "src\ui\tab_carta.py", line 220>:
220           RESUME                   0

221           LOAD_GLOBAL              0 (ctk)
              LOAD_ATTR                2 (CTkLabel)
              PUSH_NULL
              LOAD_FAST                0 (self)
              LOAD_ATTR                4 (left_panel)
              LOAD_CONST               1 ('4. Base de Ingenieros')
              LOAD_GLOBAL              0 (ctk)
              LOAD_ATTR                6 (CTkFont)
              PUSH_NULL
              LOAD_CONST               2 ('bold')
              LOAD_CONST               3 (14)
              LOAD_CONST               4 (('weight', 'size'))
              CALL_KW                  2
              LOAD_CONST               5 (('text', 'font'))
              CALL_KW                  3
              STORE_FAST               1 (lbl)

222           LOAD_FAST                1 (lbl)
              LOAD_ATTR                9 (pack + NULL|self)
              LOAD_CONST               6 ((15, 5))
              LOAD_CONST               7 (20)
              LOAD_CONST               8 ('w')
              LOAD_CONST               9 (('pady', 'padx', 'anchor'))
              CALL_KW                  3
              POP_TOP

224           LOAD_GLOBAL              0 (ctk)
              LOAD_ATTR               10 (CTkFrame)
              PUSH_NULL
              LOAD_FAST                0 (self)
              LOAD_ATTR                4 (left_panel)
              CALL                     1
              STORE_FAST               2 (f_ing)

225           LOAD_FAST                2 (f_ing)
              LOAD_ATTR                9 (pack + NULL|self)
              LOAD_CONST              10 ('x')
              LOAD_CONST               7 (20)
              LOAD_CONST              11 (5)
              LOAD_CONST              12 (('fill', 'padx', 'pady'))
              CALL_KW                  3
              POP_TOP

228           LOAD_GLOBAL              0 (ctk)
              LOAD_ATTR               10 (CTkFrame)
              PUSH_NULL
              LOAD_FAST                2 (f_ing)
              LOAD_CONST              13 ('transparent')
              LOAD_CONST              14 (('fg_color',))
              CALL_KW                  2
              STORE_FAST               3 (f_rev)

229           LOAD_FAST                3 (f_rev)
              LOAD_ATTR                9 (pack + NULL|self)
              LOAD_CONST              10 ('x')
              LOAD_CONST              15 (10)
              LOAD_CONST              16 ((10, 5))
              LOAD_CONST              12 (('fill', 'padx', 'pady'))
              CALL_KW                  3
              POP_TOP

230           LOAD_FAST                3 (f_rev)
              LOAD_ATTR               13 (grid_columnconfigure + NULL|self)
              LOAD_CONST              17 (0)
              LOAD_CONST              18 (2)
              LOAD_CONST              19 (('weight',))
              CALL_KW                  2
              POP_TOP

231           LOAD_FAST                3 (f_rev)
              LOAD_ATTR               13 (grid_columnconfigure + NULL|self)
              LOAD_CONST              20 (1)
              LOAD_CONST              20 (1)
              LOAD_CONST              19 (('weight',))
              CALL_KW                  2
              POP_TOP

232           LOAD_FAST                3 (f_rev)
              LOAD_ATTR               13 (grid_columnconfigure + NULL|self)
              LOAD_CONST              18 (2)
              LOAD_CONST              20 (1)
              LOAD_CONST              19 (('weight',))
              CALL_KW                  2
              POP_TOP

234           LOAD_GLOBAL              0 (ctk)
              LOAD_ATTR               14 (CTkComboBox)
              PUSH_NULL
              LOAD_FAST                3 (f_rev)
              LOAD_CONST              21 ('')
              BUILD_LIST               1
              LOAD_FAST                0 (self)
              LOAD_ATTR               16 (on_revisor_change)
              LOAD_CONST              22 (('values', 'command'))
              CALL_KW                  3
              LOAD_FAST                0 (self)
              STORE_ATTR               9 (combo_revisor)

235           LOAD_FAST                0 (self)
              LOAD_ATTR               18 (combo_revisor)
              LOAD_ATTR               21 (grid + NULL|self)
              LOAD_CONST              17 (0)
              LOAD_CONST              17 (0)
              LOAD_CONST              23 ('ew')
              LOAD_CONST              24 ((0, 5))
              LOAD_CONST              25 (('row', 'column', 'sticky', 'padx'))
              CALL_KW                  4
              POP_TOP

236           LOAD_FAST                0 (self)
              LOAD_ATTR               18 (combo_revisor)
              LOAD_ATTR               23 (bind + NULL|self)
              LOAD_CONST              26 ('<KeyRelease>')
              LOAD_FAST                0 (self)
              LOAD_ATTR               24 (on_revisor_type)
              CALL                     2
              POP_TOP

238           LOAD_GLOBAL              0 (ctk)
              LOAD_ATTR               26 (CTkEntry)
              PUSH_NULL
              LOAD_FAST                3 (f_rev)
              LOAD_CONST              27 ('CIP Revisor')
              LOAD_CONST              28 (('placeholder_text',))
              CALL_KW                  2
              LOAD_FAST                0 (self)
              STORE_ATTR              14 (entry_revisor_cip)

239           LOAD_FAST                0 (self)
              LOAD_ATTR               28 (entry_revisor_cip)
              LOAD_ATTR               21 (grid + NULL|self)
              LOAD_CONST              17 (0)
              LOAD_CONST              20 (1)
              LOAD_CONST              23 ('ew')
              LOAD_CONST              24 ((0, 5))
              LOAD_CONST              25 (('row', 'column', 'sticky', 'padx'))
              CALL_KW                  4
              POP_TOP

241           LOAD_GLOBAL              0 (ctk)
              LOAD_ATTR               26 (CTkEntry)
              PUSH_NULL
              LOAD_FAST                3 (f_rev)
              LOAD_CONST              29 ('Tipo (Ej. Ing. Electricista)')
              LOAD_CONST              28 (('placeholder_text',))
              CALL_KW                  2
              LOAD_FAST                0 (self)
              STORE_ATTR              15 (entry_revisor_tipo)

242           LOAD_FAST                0 (self)
              LOAD_ATTR               30 (entry_revisor_tipo)
              LOAD_ATTR               21 (grid + NULL|self)
              LOAD_CONST              17 (0)
              LOAD_CONST              18 (2)
              LOAD_CONST              23 ('ew')
              LOAD_CONST              30 (('row', 'column', 'sticky'))
              CALL_KW                  3
              POP_TOP

245           LOAD_GLOBAL              0 (ctk)
              LOAD_ATTR               10 (CTkFrame)
              PUSH_NULL
              LOAD_FAST                2 (f_ing)
              LOAD_CONST              13 ('transparent')
              LOAD_CONST              14 (('fg_color',))
              CALL_KW                  2
              STORE_FAST               4 (f_proy)

246           LOAD_FAST                4 (f_proy)
              LOAD_ATTR                9 (pack + NULL|self)
              LOAD_CONST              10 ('x')
              LOAD_CONST              15 (10)
              LOAD_CONST              31 ((5, 10))
              LOAD_CONST              12 (('fill', 'padx', 'pady'))
              CALL_KW                  3
              POP_TOP

247           LOAD_FAST                4 (f_proy)
              LOAD_ATTR               13 (grid_columnconfigure + NULL|self)
              LOAD_CONST              17 (0)
              LOAD_CONST              18 (2)
              LOAD_CONST              19 (('weight',))
              CALL_KW                  2
              POP_TOP

248           LOAD_FAST                4 (f_proy)
              LOAD_ATTR               13 (grid_columnconfigure + NULL|self)
              LOAD_CONST              20 (1)
              LOAD_CONST              20 (1)
              LOAD_CONST              19 (('weight',))
              CALL_KW                  2
              POP_TOP

250           LOAD_GLOBAL              0 (ctk)
              LOAD_ATTR               14 (CTkComboBox)
              PUSH_NULL
              LOAD_FAST                4 (f_proy)
              LOAD_CONST              21 ('')
              BUILD_LIST               1
              LOAD_FAST                0 (self)
              LOAD_ATTR               32 (on_proyectista_change)
              LOAD_CONST              22 (('values', 'command'))
              CALL_KW                  3
              LOAD_FAST                0 (self)
              STORE_ATTR              17 (combo_proyectista)

251           LOAD_FAST                0 (self)
              LOAD_ATTR               34 (combo_proyectista)
              LOAD_ATTR               21 (grid + NULL|self)
              LOAD_CONST              17 (0)
              LOAD_CONST              17 (0)
              LOAD_CONST              23 ('ew')
              LOAD_CONST              24 ((0, 5))
              LOAD_CONST              25 (('row', 'column', 'sticky', 'padx'))
              CALL_KW                  4
              POP_TOP

252           LOAD_FAST                0 (self)
              LOAD_ATTR               34 (combo_proyectista)
              LOAD_ATTR               23 (bind + NULL|self)
              LOAD_CONST              26 ('<KeyRelease>')
              LOAD_FAST                0 (self)
              LOAD_ATTR               36 (on_proyectista_type)
              CALL                     2
              POP_TOP

254           LOAD_GLOBAL              0 (ctk)
              LOAD_ATTR               26 (CTkEntry)
              PUSH_NULL
              LOAD_FAST                4 (f_proy)
              LOAD_CONST              32 ('CIP Proyectista')
              LOAD_CONST              28 (('placeholder_text',))
              CALL_KW                  2
              LOAD_FAST                0 (self)
              STORE_ATTR              19 (entry_proyectista_cip)

255           LOAD_FAST                0 (self)
              LOAD_ATTR               38 (entry_proyectista_cip)
              LOAD_ATTR               21 (grid + NULL|self)
              LOAD_CONST              17 (0)
              LOAD_CONST              20 (1)
              LOAD_CONST              23 ('ew')
              LOAD_CONST              30 (('row', 'column', 'sticky'))
              CALL_KW                  3
              POP_TOP

258           LOAD_GLOBAL              0 (ctk)
              LOAD_ATTR               10 (CTkFrame)
              PUSH_NULL
              LOAD_FAST                2 (f_ing)
              LOAD_CONST              13 ('transparent')
              LOAD_CONST              14 (('fg_color',))
              CALL_KW                  2
              STORE_FAST               5 (f_chk_civil_rev)

259           LOAD_FAST                5 (f_chk_civil_rev)
              LOAD_ATTR                9 (pack + NULL|self)
              LOAD_CONST              10 ('x')
              LOAD_CONST              15 (10)
              LOAD_CONST              33 ((5, 5))
              LOAD_CONST              12 (('fill', 'padx', 'pady'))
              CALL_KW                  3
              POP_TOP

260           LOAD_GLOBAL              0 (ctk)
              LOAD_ATTR               40 (BooleanVar)
              PUSH_NULL
              LOAD_CONST              34 (False)
              LOAD_CONST              35 (('value',))
              CALL_KW                  1
              LOAD_FAST                0 (self)
              STORE_ATTR              21 (var_tiene_civil_rev)

261           LOAD_GLOBAL              0 (ctk)
              LOAD_ATTR               44 (CTkCheckBox)
              PUSH_NULL
              LOAD_FAST                5 (f_chk_civil_rev)
              LOAD_CONST              36 ('Incluir Ingeniero Civil (Revisor)')
              LOAD_FAST                0 (self)
              LOAD_ATTR               42 (var_tiene_civil_rev)
              LOAD_FAST                0 (self)
              LOAD_ATTR               46 (on_chk_civil_rev)
              LOAD_CONST              37 (('text', 'variable', 'command'))
              CALL_KW                  4
              LOAD_FAST                0 (self)
              STORE_ATTR              24 (chk_civil_rev)

262           LOAD_FAST                0 (self)
              LOAD_ATTR               48 (chk_civil_rev)
              LOAD_ATTR                9 (pack + NULL|self)
              LOAD_CONST               8 ('w')
              LOAD_CONST              38 (('anchor',))
              CALL_KW                  1
              POP_TOP

264           LOAD_GLOBAL              0 (ctk)
              LOAD_ATTR               10 (CTkFrame)
              PUSH_NULL
              LOAD_FAST                2 (f_ing)
              LOAD_CONST              13 ('transparent')
              LOAD_CONST              14 (('fg_color',))
              CALL_KW                  2
              LOAD_FAST                0 (self)
              STORE_ATTR              25 (f_civil_rev)

265           LOAD_FAST                0 (self)
              LOAD_ATTR               50 (f_civil_rev)
              LOAD_ATTR               13 (grid_columnconfigure + NULL|self)
              LOAD_CONST              17 (0)
              LOAD_CONST              18 (2)
              LOAD_CONST              19 (('weight',))
              CALL_KW                  2
              POP_TOP

266           LOAD_FAST                0 (self)
              LOAD_ATTR               50 (f_civil_rev)
              LOAD_ATTR               13 (grid_columnconfigure + NULL|self)
              LOAD_CONST              20 (1)
              LOAD_CONST              20 (1)
              LOAD_CONST              19 (('weight',))
              CALL_KW                  2
              POP_TOP

267           LOAD_FAST                0 (self)
              LOAD_ATTR               50 (f_civil_rev)
              LOAD_ATTR               13 (grid_columnconfigure + NULL|self)
              LOAD_CONST              18 (2)
              LOAD_CONST              20 (1)
              LOAD_CONST              19 (('weight',))
              CALL_KW                  2
              POP_TOP

269           LOAD_GLOBAL              0 (ctk)
              LOAD_ATTR               14 (CTkComboBox)
              PUSH_NULL
              LOAD_FAST                0 (self)
              LOAD_ATTR               50 (f_civil_rev)
              LOAD_CONST              21 ('')
              BUILD_LIST               1
              LOAD_FAST                0 (self)
              LOAD_ATTR               52 (on_civil_rev_change)
              LOAD_CONST              22 (('values', 'command'))
              CALL_KW                  3
              LOAD_FAST                0 (self)
              STORE_ATTR              27 (combo_civil_rev)

270           LOAD_FAST                0 (self)
              LOAD_ATTR               54 (combo_civil_rev)
              LOAD_ATTR               21 (grid + NULL|self)
              LOAD_CONST              17 (0)
              LOAD_CONST              17 (0)
              LOAD_CONST              23 ('ew')
              LOAD_CONST              24 ((0, 5))
              LOAD_CONST              25 (('row', 'column', 'sticky', 'padx'))
              CALL_KW                  4
              POP_TOP

271           LOAD_FAST                0 (self)
              LOAD_ATTR               54 (combo_civil_rev)
              LOAD_ATTR               23 (bind + NULL|self)
              LOAD_CONST              26 ('<KeyRelease>')
              LOAD_FAST                0 (self)
              LOAD_ATTR               56 (on_civil_rev_type)
              CALL                     2
              POP_TOP

273           LOAD_GLOBAL              0 (ctk)
              LOAD_ATTR               26 (CTkEntry)
              PUSH_NULL
              LOAD_FAST                0 (self)
              LOAD_ATTR               50 (f_civil_rev)
              LOAD_CONST              39 ('CIP Ing. Civil (Rev)')
              LOAD_CONST              28 (('placeholder_text',))
              CALL_KW                  2
              LOAD_FAST                0 (self)
              STORE_ATTR              29 (entry_civil_rev_cip)

274           LOAD_FAST                0 (self)
              LOAD_ATTR               58 (entry_civil_rev_cip)
              LOAD_ATTR               21 (grid + NULL|self)
              LOAD_CONST              17 (0)
              LOAD_CONST              20 (1)
              LOAD_CONST              23 ('ew')
              LOAD_CONST              24 ((0, 5))
              LOAD_CONST              25 (('row', 'column', 'sticky', 'padx'))
              CALL_KW                  4
              POP_TOP

276           LOAD_GLOBAL              0 (ctk)
              LOAD_ATTR               26 (CTkEntry)
              PUSH_NULL
              LOAD_FAST                0 (self)
              LOAD_ATTR               50 (f_civil_rev)
              LOAD_CONST              40 ('Planos Civiles (Ej. OC-01)')
              LOAD_CONST              28 (('placeholder_text',))
              CALL_KW                  2
              LOAD_FAST                0 (self)
              STORE_ATTR              30 (entry_civil_rev_planos)

277           LOAD_FAST                0 (self)
              LOAD_ATTR               60 (entry_civil_rev_planos)
              LOAD_ATTR               21 (grid + NULL|self)
              LOAD_CONST              17 (0)
              LOAD_CONST              18 (2)
              LOAD_CONST              23 ('ew')
              LOAD_CONST              30 (('row', 'column', 'sticky'))
              CALL_KW                  3
              POP_TOP

280           LOAD_GLOBAL              0 (ctk)
              LOAD_ATTR               10 (CTkFrame)
              PUSH_NULL
              LOAD_FAST                2 (f_ing)
              LOAD_CONST              13 ('transparent')
              LOAD_CONST              14 (('fg_color',))
              CALL_KW                  2
              STORE_FAST               6 (f_chk_civil_proy)

281           LOAD_FAST                6 (f_chk_civil_proy)
              LOAD_ATTR                9 (pack + NULL|self)
              LOAD_CONST              10 ('x')
              LOAD_CONST              15 (10)
              LOAD_CONST              33 ((5, 5))
              LOAD_CONST              12 (('fill', 'padx', 'pady'))
              CALL_KW                  3
              POP_TOP

282           LOAD_GLOBAL              0 (ctk)
              LOAD_ATTR               40 (BooleanVar)
              PUSH_NULL
              LOAD_CONST              34 (False)
              LOAD_CONST              35 (('value',))
              CALL_KW                  1
              LOAD_FAST                0 (self)
              STORE_ATTR              31 (var_tiene_civil_proy)

283           LOAD_GLOBAL              0 (ctk)
              LOAD_ATTR               44 (CTkCheckBox)
              PUSH_NULL
              LOAD_FAST                6 (f_chk_civil_proy)
              LOAD_CONST              41 ('Incluir Ingeniero Civil (Proyectista)')
              LOAD_FAST                0 (self)
              LOAD_ATTR               62 (var_tiene_civil_proy)
              LOAD_FAST                0 (self)
              LOAD_ATTR               64 (on_chk_civil_proy)
              LOAD_CONST              37 (('text', 'variable', 'command'))
              CALL_KW                  4
              LOAD_FAST                0 (self)
              STORE_ATTR              33 (chk_civil_proy)

284           LOAD_FAST                0 (self)
              LOAD_ATTR               66 (chk_civil_proy)
              LOAD_ATTR                9 (pack + NULL|self)
              LOAD_CONST               8 ('w')
              LOAD_CONST              38 (('anchor',))
              CALL_KW                  1
              POP_TOP

286           LOAD_GLOBAL              0 (ctk)
              LOAD_ATTR               10 (CTkFrame)
              PUSH_NULL
              LOAD_FAST                2 (f_ing)
              LOAD_CONST              13 ('transparent')
              LOAD_CONST              14 (('fg_color',))
              CALL_KW                  2
              LOAD_FAST                0 (self)
              STORE_ATTR              34 (f_civil_proy)

287           LOAD_FAST                0 (self)
              LOAD_ATTR               68 (f_civil_proy)
              LOAD_ATTR               13 (grid_columnconfigure + NULL|self)
              LOAD_CONST              17 (0)
              LOAD_CONST              18 (2)
              LOAD_CONST              19 (('weight',))
              CALL_KW                  2
              POP_TOP

288           LOAD_FAST                0 (self)
              LOAD_ATTR               68 (f_civil_proy)
              LOAD_ATTR               13 (grid_columnconfigure + NULL|self)
              LOAD_CONST              20 (1)
              LOAD_CONST              20 (1)
              LOAD_CONST              19 (('weight',))
              CALL_KW                  2
              POP_TOP

290           LOAD_GLOBAL              0 (ctk)
              LOAD_ATTR               14 (CTkComboBox)
              PUSH_NULL
              LOAD_FAST                0 (self)
              LOAD_ATTR               68 (f_civil_proy)
              LOAD_CONST              21 ('')
              BUILD_LIST               1
              LOAD_FAST                0 (self)
              LOAD_ATTR               70 (on_civil_proy_change)
              LOAD_CONST              22 (('values', 'command'))
              CALL_KW                  3
              LOAD_FAST                0 (self)
              STORE_ATTR              36 (combo_civil_proy)

291           LOAD_FAST                0 (self)
              LOAD_ATTR               72 (combo_civil_proy)
              LOAD_ATTR               21 (grid + NULL|self)
              LOAD_CONST              17 (0)
              LOAD_CONST              17 (0)
              LOAD_CONST              23 ('ew')
              LOAD_CONST              24 ((0, 5))
              LOAD_CONST              25 (('row', 'column', 'sticky', 'padx'))
              CALL_KW                  4
              POP_TOP

292           LOAD_FAST                0 (self)
              LOAD_ATTR               72 (combo_civil_proy)
              LOAD_ATTR               23 (bind + NULL|self)
              LOAD_CONST              26 ('<KeyRelease>')
              LOAD_FAST                0 (self)
              LOAD_ATTR               74 (on_civil_proy_type)
              CALL                     2
              POP_TOP

294           LOAD_GLOBAL              0 (ctk)
              LOAD_ATTR               26 (CTkEntry)
              PUSH_NULL
              LOAD_FAST                0 (self)
              LOAD_ATTR               68 (f_civil_proy)
              LOAD_CONST              42 ('CIP Ing. Civil (Proy)')
              LOAD_CONST              28 (('placeholder_text',))
              CALL_KW                  2
              LOAD_FAST                0 (self)
              STORE_ATTR              38 (entry_civil_proy_cip)

295           LOAD_FAST                0 (self)
              LOAD_ATTR               76 (entry_civil_proy_cip)
              LOAD_ATTR               21 (grid + NULL|self)
              LOAD_CONST              17 (0)
              LOAD_CONST              20 (1)
              LOAD_CONST              23 ('ew')
              LOAD_CONST              24 ((0, 5))
              LOAD_CONST              25 (('row', 'column', 'sticky', 'padx'))
              CALL_KW                  4
              POP_TOP
              RETURN_CONST             0 (None)

Disassembly of <code object build_bloque_planos at 0x0000028A6B3FFFF0, file "src\ui\tab_carta.py", line 297>:
297           RESUME                   0

298           LOAD_GLOBAL              0 (ctk)
              LOAD_ATTR                2 (CTkLabel)
              PUSH_NULL
              LOAD_FAST                0 (self)
              LOAD_ATTR                4 (left_panel)
              LOAD_CONST               1 ('5. Listado de Planos')
              LOAD_GLOBAL              0 (ctk)
              LOAD_ATTR                6 (CTkFont)
              PUSH_NULL
              LOAD_CONST               2 ('bold')
              LOAD_CONST               3 (14)
              LOAD_CONST               4 (('weight', 'size'))
              CALL_KW                  2
              LOAD_CONST               5 (('text', 'font'))
              CALL_KW                  3
              STORE_FAST               1 (lbl)

299           LOAD_FAST                1 (lbl)
              LOAD_ATTR                9 (pack + NULL|self)
              LOAD_CONST               6 ((15, 5))
              LOAD_CONST               7 (20)
              LOAD_CONST               8 ('w')
              LOAD_CONST               9 (('pady', 'padx', 'anchor'))
              CALL_KW                  3
              POP_TOP

301           LOAD_GLOBAL              0 (ctk)
              LOAD_ATTR               10 (CTkFrame)
              PUSH_NULL
              LOAD_FAST                0 (self)
              LOAD_ATTR                4 (left_panel)
              LOAD_CONST              10 ('transparent')
              LOAD_CONST              11 (('fg_color',))
              CALL_KW                  2
              LOAD_FAST                0 (self)
              STORE_ATTR               6 (frame_planos_list)

302           LOAD_FAST                0 (self)
              LOAD_ATTR               12 (frame_planos_list)
              LOAD_ATTR                9 (pack + NULL|self)
              LOAD_CONST              12 ('x')
              LOAD_CONST               7 (20)
              LOAD_CONST              13 (0)
              LOAD_CONST              14 (('fill', 'padx', 'pady'))
              CALL_KW                  3
              POP_TOP

304           BUILD_LIST               0
              LOAD_FAST                0 (self)
              STORE_ATTR               7 (lista_entradas_planos)

305           LOAD_FAST                0 (self)
              LOAD_ATTR               17 (agregar_cajon_plano + NULL|self)
              CALL                     0
              POP_TOP

307           LOAD_GLOBAL              0 (ctk)
              LOAD_ATTR               18 (CTkButton)
              PUSH_NULL
              LOAD_FAST                0 (self)
              LOAD_ATTR                4 (left_panel)
              LOAD_CONST              15 ('+ Agregar Plano Adicional')
              LOAD_CONST              10 ('transparent')
              LOAD_CONST              16 (1)
              LOAD_FAST                0 (self)
              LOAD_ATTR               16 (agregar_cajon_plano)
              LOAD_CONST              17 (('text', 'fg_color', 'border_width', 'command'))
              CALL_KW                  5
              STORE_FAST               2 (btn_add)

308           LOAD_FAST                2 (btn_add)
              LOAD_ATTR                9 (pack + NULL|self)
              LOAD_CONST              18 (10)
              LOAD_CONST               7 (20)
              LOAD_CONST               8 ('w')
              LOAD_CONST               9 (('pady', 'padx', 'anchor'))
              CALL_KW                  3
              POP_TOP
              RETURN_CONST             0 (None)

Disassembly of <code object on_chk_cliente at 0x0000028A6B45E7B0, file "src\ui\tab_carta.py", line 311>:
311           RESUME                   0

312           LOAD_FAST                0 (self)
              LOAD_ATTR                0 (var_mismo_cliente)
              LOAD_ATTR                3 (get + NULL|self)
              CALL                     0
              TO_BOOL
              POP_JUMP_IF_FALSE      106 (to L1)

313           LOAD_FAST                0 (self)
              LOAD_ATTR                4 (entry_cliente)
              LOAD_ATTR                7 (delete + NULL|self)
              LOAD_CONST               1 (0)
              LOAD_CONST               2 ('end')
              CALL                     2
              POP_TOP

314           LOAD_FAST                0 (self)
              LOAD_ATTR                4 (entry_cliente)
              LOAD_ATTR                9 (insert + NULL|self)
              LOAD_CONST               1 (0)
              LOAD_FAST                0 (self)
              LOAD_ATTR               10 (entry_dirigido)
              LOAD_ATTR                3 (get + NULL|self)
              CALL                     0
              CALL                     2
              POP_TOP

315           LOAD_FAST                0 (self)
              LOAD_ATTR                4 (entry_cliente)
              LOAD_ATTR               13 (configure + NULL|self)
              LOAD_CONST               3 ('disabled')
              LOAD_CONST               4 (('state',))
              CALL_KW                  1
              POP_TOP
              RETURN_CONST             0 (None)

317   L1:     LOAD_FAST                0 (self)
              LOAD_ATTR                4 (entry_cliente)
              LOAD_ATTR               13 (configure + NULL|self)
              LOAD_CONST               5 ('normal')
              LOAD_CONST               4 (('state',))
              CALL_KW                  1
              POP_TOP
              RETURN_CONST             0 (None)

Disassembly of <code object on_chk_dir at 0x0000028A6B4243B0, file "src\ui\tab_carta.py", line 319>:
319           RESUME                   0

320           LOAD_FAST                0 (self)
              LOAD_ATTR                0 (var_misma_dir)
              LOAD_ATTR                3 (get + NULL|self)
              CALL                     0
              TO_BOOL
              POP_JUMP_IF_FALSE      106 (to L1)

321           LOAD_FAST                0 (self)
              LOAD_ATTR                4 (entry_direccion_proyecto)
              LOAD_ATTR                7 (delete + NULL|self)
              LOAD_CONST               1 (0)
              LOAD_CONST               2 ('end')
              CALL                     2
              POP_TOP

322           LOAD_FAST                0 (self)
              LOAD_ATTR                4 (entry_direccion_proyecto)
              LOAD_ATTR                9 (insert + NULL|self)
              LOAD_CONST               1 (0)
              LOAD_FAST                0 (self)
              LOAD_ATTR               10 (entry_direccion)
              LOAD_ATTR                3 (get + NULL|self)
              CALL                     0
              CALL                     2
              POP_TOP

323           LOAD_FAST                0 (self)
              LOAD_ATTR                4 (entry_direccion_proyecto)
              LOAD_ATTR               13 (configure + NULL|self)
              LOAD_CONST               3 ('disabled')
              LOAD_CONST               4 (('state',))
              CALL_KW                  1
              POP_TOP
              RETURN_CONST             0 (None)

325   L1:     LOAD_FAST                0 (self)
              LOAD_ATTR                4 (entry_direccion_proyecto)
              LOAD_ATTR               13 (configure + NULL|self)
              LOAD_CONST               5 ('normal')
              LOAD_CONST               4 (('state',))
              CALL_KW                  1
              POP_TOP
              RETURN_CONST             0 (None)

Disassembly of <code object on_chk_civil_rev at 0x0000028A6B186EB0, file "src\ui\tab_carta.py", line 327>:
327           RESUME                   0

328           LOAD_FAST                0 (self)
              LOAD_ATTR                0 (var_tiene_civil_rev)
              LOAD_ATTR                3 (get + NULL|self)
              CALL                     0
              TO_BOOL
              POP_JUMP_IF_FALSE       28 (to L1)

329           LOAD_FAST                0 (self)
              LOAD_ATTR                4 (f_civil_rev)
              LOAD_ATTR                7 (pack + NULL|self)
              LOAD_CONST               1 ('x')
              LOAD_CONST               2 (10)
              LOAD_CONST               3 ((0, 10))
              LOAD_CONST               4 (('fill', 'padx', 'pady'))
              CALL_KW                  3
              POP_TOP
              RETURN_CONST             0 (None)

331   L1:     LOAD_FAST                0 (self)
              LOAD_ATTR                4 (f_civil_rev)
              LOAD_ATTR                9 (pack_forget + NULL|self)
              CALL                     0
              POP_TOP
              RETURN_CONST             0 (None)

Disassembly of <code object on_chk_civil_proy at 0x0000028A6B187030, file "src\ui\tab_carta.py", line 333>:
333           RESUME                   0

334           LOAD_FAST                0 (self)
              LOAD_ATTR                0 (var_tiene_civil_proy)
              LOAD_ATTR                3 (get + NULL|self)
              CALL                     0
              TO_BOOL
              POP_JUMP_IF_FALSE       28 (to L1)

335           LOAD_FAST                0 (self)
              LOAD_ATTR                4 (f_civil_proy)
              LOAD_ATTR                7 (pack + NULL|self)
              LOAD_CONST               1 ('x')
              LOAD_CONST               2 (10)
              LOAD_CONST               3 ((0, 10))
              LOAD_CONST               4 (('fill', 'padx', 'pady'))
              CALL_KW                  3
              POP_TOP
              RETURN_CONST             0 (None)

337   L1:     LOAD_FAST                0 (self)
              LOAD_ATTR                4 (f_civil_proy)
              LOAD_ATTR                9 (pack_forget + NULL|self)
              CALL                     0
              POP_TOP
              RETURN_CONST             0 (None)

Disassembly of <code object on_chk_fecha_hoy at 0x0000028A6B468590, file "src\ui\tab_carta.py", line 339>:
339           RESUME                   0

340           LOAD_FAST                0 (self)
              LOAD_ATTR                0 (var_usar_f_hoy)
              LOAD_ATTR                3 (get + NULL|self)
              CALL                     0
              TO_BOOL
              POP_JUMP_IF_FALSE      147 (to L1)

341           LOAD_FAST                0 (self)
              LOAD_ATTR                4 (entry_fecha_inicio)
              LOAD_ATTR                7 (delete + NULL|self)
              LOAD_CONST               1 (0)
              LOAD_CONST               2 ('end')
              CALL                     2
              POP_TOP

342           LOAD_FAST                0 (self)
              LOAD_ATTR                4 (entry_fecha_inicio)
              LOAD_ATTR                9 (insert + NULL|self)
              LOAD_CONST               1 (0)
              LOAD_FAST                0 (self)
              LOAD_ATTR               10 (entry_fecha_sys)
              LOAD_ATTR                3 (get + NULL|self)
              CALL                     0
              CALL                     2
              POP_TOP

343           LOAD_FAST                0 (self)
              LOAD_ATTR                4 (entry_fecha_inicio)
              LOAD_ATTR               13 (configure + NULL|self)
              LOAD_CONST               3 ('disabled')
              LOAD_CONST               4 (('state',))
              CALL_KW                  1
              POP_TOP

344           LOAD_FAST                0 (self)
              LOAD_ATTR               15 (calcular_fecha_fin + NULL|self)
              LOAD_FAST                0 (self)
              LOAD_ATTR               10 (entry_fecha_sys)
              LOAD_ATTR                3 (get + NULL|self)
              CALL                     0
              CALL                     1
              POP_TOP
              RETURN_CONST             0 (None)

346   L1:     LOAD_FAST                0 (self)
              LOAD_ATTR                4 (entry_fecha_inicio)
              LOAD_ATTR               13 (configure + NULL|self)
              LOAD_CONST               5 ('normal')
              LOAD_CONST               4 (('state',))
              CALL_KW                  1
              POP_TOP
              RETURN_CONST             0 (None)

Disassembly of <code object on_fecha_inicio_change at 0x0000028A6B376790, file "src\ui\tab_carta.py", line 348>:
348           RESUME                   0

349           LOAD_FAST                0 (self)
              LOAD_ATTR                1 (calcular_fecha_fin + NULL|self)
              LOAD_FAST                0 (self)
              LOAD_ATTR                2 (entry_fecha_inicio)
              LOAD_ATTR                5 (get + NULL|self)
              CALL                     0
              CALL                     1
              POP_TOP
              RETURN_CONST             0 (None)

Disassembly of <code object calcular_fecha_fin at 0x0000028A6B46CE80, file "src\ui\tab_carta.py", line 351>:
 351           RESUME                   0

 352           LOAD_CONST               1 (0)
               LOAD_CONST               0 (None)
               IMPORT_NAME              0 (re)
               STORE_FAST               2 (re)

 353           LOAD_CONST               1 (0)
               LOAD_CONST               2 (('relativedelta',))
               IMPORT_NAME              1 (dateutil.relativedelta)
               IMPORT_FROM              2 (relativedelta)
               STORE_FAST               3 (relativedelta)
               POP_TOP

 354           LOAD_FAST                0 (self)
               LOAD_ATTR                6 (entry_fecha_fin)
               LOAD_ATTR                9 (configure + NULL|self)
               LOAD_CONST               3 ('normal')
               LOAD_CONST               4 (('state',))
               CALL_KW                  1
               POP_TOP

 355           LOAD_FAST                0 (self)
               LOAD_ATTR                6 (entry_fecha_fin)
               LOAD_ATTR               11 (delete + NULL|self)
               LOAD_CONST               1 (0)
               LOAD_CONST               5 ('end')
               CALL                     2
               POP_TOP

 357           LOAD_FAST                2 (re)
               LOAD_ATTR               13 (search + NULL|self)
               LOAD_CONST               6 ('(\\d{2})[-/](\\d{2})[-/](\\d{4})')
               LOAD_FAST                1 (str_fecha_inicio)
               CALL                     2
               STORE_FAST               4 (match)

 358           LOAD_FAST                4 (match)
               TO_BOOL
               POP_JUMP_IF_FALSE      108 (to L2)

 359           NOP

 361   L1:     LOAD_GLOBAL             15 (map + NULL)
               LOAD_GLOBAL             16 (int)
               LOAD_FAST                4 (match)
               LOAD_ATTR               19 (groups + NULL|self)
               CALL                     0
               CALL                     2
               UNPACK_SEQUENCE          3
               STORE_FAST_STORE_FAST   86 (d, m)
               STORE_FAST               7 (y)

 362           LOAD_GLOBAL             20 (datetime)
               LOAD_ATTR               20 (datetime)
               PUSH_NULL
               LOAD_FAST_LOAD_FAST    118 (y, m)
               LOAD_FAST                5 (d)
               CALL                     3
               STORE_FAST               8 (dt_inicio)

 363           LOAD_FAST_LOAD_FAST    131 (dt_inicio, relativedelta)
               PUSH_NULL
               LOAD_CONST               7 (2)
               LOAD_CONST               8 (('years',))
               CALL_KW                  1
               BINARY_OP                0 (+)
               STORE_FAST               9 (dt_fin)

 364           LOAD_FAST                0 (self)
               LOAD_ATTR                6 (entry_fecha_fin)
               LOAD_ATTR               23 (insert + NULL|self)
               LOAD_CONST               1 (0)
               LOAD_FAST                9 (dt_fin)
               LOAD_ATTR               25 (strftime + NULL|self)
               LOAD_CONST               9 ('%d/%m/%Y')
               CALL                     1
               CALL                     2
               POP_TOP

 367   L2:     LOAD_FAST                0 (self)
               LOAD_ATTR                6 (entry_fecha_fin)
               LOAD_ATTR                9 (configure + NULL|self)
               LOAD_CONST              10 ('disabled')
               LOAD_CONST               4 (('state',))
               CALL_KW                  1
               POP_TOP
               RETURN_CONST             0 (None)

  --   L3:     PUSH_EXC_INFO

 365           POP_TOP
       L4:     POP_EXCEPT
               JUMP_BACKWARD_NO_INTERRUPT 30 (to L2)

  --   L5:     COPY                     3
               POP_EXCEPT
               RERAISE                  1
ExceptionTable:
  L1 to L2 -> L3 [0]
  L3 to L4 -> L5 [1] lasti

Disassembly of <code object on_distrito_type at 0x0000028A6B3982D0, file "src\ui\tab_carta.py", line 370>:
370           RESUME                   0

372           LOAD_FAST                0 (self)
              LOAD_ATTR                0 (combo_distrito)
              LOAD_ATTR                3 (get + NULL|self)
              CALL                     0
              STORE_FAST               2 (current_text)

373           LOAD_FAST_LOAD_FAST     32 (current_text, self)
              LOAD_ATTR                4 (ubicaciones_cache)
              CONTAINS_OP              0
              POP_JUMP_IF_FALSE       18 (to L1)

374           LOAD_FAST                0 (self)
              LOAD_ATTR                7 (on_distrito_change + NULL|self)
              LOAD_FAST                2 (current_text)
              CALL                     1
              POP_TOP
              RETURN_CONST             0 (None)

373   L1:     RETURN_CONST             0 (None)

Disassembly of <code object on_distrito_change at 0x0000028A6B1871B0, file "src\ui\tab_carta.py", line 376>:
376           RESUME                   0

378           LOAD_FAST_LOAD_FAST     16 (choice, self)
              LOAD_ATTR                0 (ubicaciones_cache)
              CONTAINS_OP              0
              POP_JUMP_IF_FALSE       70 (to L1)

379           LOAD_FAST                0 (self)
              LOAD_ATTR                2 (entry_departamento)
              LOAD_ATTR                5 (delete + NULL|self)
              LOAD_CONST               1 (0)
              LOAD_CONST               2 ('end')
              CALL                     2
              POP_TOP

380           LOAD_FAST                0 (self)
              LOAD_ATTR                2 (entry_departamento)
              LOAD_ATTR                7 (insert + NULL|self)
              LOAD_CONST               1 (0)
              LOAD_FAST                0 (self)
              LOAD_ATTR                0 (ubicaciones_cache)
              LOAD_FAST                1 (choice)
              BINARY_SUBSCR
              CALL                     2
              POP_TOP
              RETURN_CONST             0 (None)

378   L1:     RETURN_CONST             0 (None)

Disassembly of <code object save_new_ubicacion_cache at 0x0000028A6B3F3CC0, file "src\ui\tab_carta.py", line 382>:
 382            RESUME                   0

 383            LOAD_FAST                0 (self)
                LOAD_ATTR                0 (combo_distrito)
                LOAD_ATTR                3 (get + NULL|self)
                CALL                     0
                STORE_FAST               1 (dist_actual)

 384            LOAD_FAST                0 (self)
                LOAD_ATTR                4 (entry_departamento)
                LOAD_ATTR                3 (get + NULL|self)
                CALL                     0
                STORE_FAST               2 (dep_actual)

 386            LOAD_FAST                1 (dist_actual)
                TO_BOOL
                POP_JUMP_IF_FALSE      112 (to L8)
                LOAD_FAST                2 (dep_actual)
                TO_BOOL
                POP_JUMP_IF_FALSE      104 (to L7)
                LOAD_FAST_LOAD_FAST     16 (dist_actual, self)
                LOAD_ATTR                6 (ubicaciones_cache)
                CONTAINS_OP              1
                POP_JUMP_IF_TRUE        19 (to L1)
                LOAD_FAST                0 (self)
                LOAD_ATTR                6 (ubicaciones_cache)
                LOAD_FAST                1 (dist_actual)
                BINARY_SUBSCR
                LOAD_FAST                2 (dep_actual)
                COMPARE_OP             119 (bool(!=))
                POP_JUMP_IF_FALSE       69 (to L6)

 387    L1:     LOAD_FAST_LOAD_FAST     32 (dep_actual, self)
                LOAD_ATTR                6 (ubicaciones_cache)
                LOAD_FAST                1 (dist_actual)
                STORE_SUBSCR

 388            NOP

 389    L2:     LOAD_GLOBAL              9 (open + NULL)
                LOAD_CONST               1 ('ubicaciones.json')
                LOAD_CONST               2 ('w')
                LOAD_CONST               3 ('utf-8')
                LOAD_CONST               4 (('encoding',))
                CALL_KW                  3
                BEFORE_WITH
        L3:     STORE_FAST               3 (f)

 390            LOAD_GLOBAL             10 (json)
                LOAD_ATTR               12 (dump)
                PUSH_NULL
                LOAD_FAST                0 (self)
                LOAD_ATTR                6 (ubicaciones_cache)
                LOAD_FAST                3 (f)
                LOAD_CONST               5 (4)
                LOAD_CONST               6 (False)
                LOAD_CONST               7 (('indent', 'ensure_ascii'))
                CALL_KW                  4
                POP_TOP

 389    L4:     LOAD_CONST               0 (None)
                LOAD_CONST               0 (None)
                LOAD_CONST               0 (None)
                CALL                     2
                POP_TOP
        L5:     RETURN_CONST             0 (None)

 386    L6:     RETURN_CONST             0 (None)
        L7:     RETURN_CONST             0 (None)
        L8:     RETURN_CONST             0 (None)

 389    L9:     PUSH_EXC_INFO
                WITH_EXCEPT_START
                TO_BOOL
                POP_JUMP_IF_TRUE         1 (to L10)
                RERAISE                  2
       L10:     POP_TOP
       L11:     POP_EXCEPT
                POP_TOP
                POP_TOP
       L12:     RETURN_CONST             0 (None)

  --   L13:     COPY                     3
                POP_EXCEPT
                RERAISE                  1
       L14:     PUSH_EXC_INFO

 391            POP_TOP
       L15:     POP_EXCEPT
                RETURN_CONST             0 (None)

  --   L16:     COPY                     3
                POP_EXCEPT
                RERAISE                  1
ExceptionTable:
  L2 to L3 -> L14 [0]
  L3 to L4 -> L9 [1] lasti
  L4 to L5 -> L14 [0]
  L9 to L11 -> L13 [3] lasti
  L11 to L12 -> L14 [0]
  L13 to L14 -> L14 [0]
  L14 to L15 -> L16 [1] lasti

Disassembly of <code object on_revisor_type at 0x0000028A6B187330, file "src\ui\tab_carta.py", line 394>:
 394           RESUME                   0

 395           LOAD_FAST                0 (self)
               LOAD_ATTR                0 (combo_revisor)
               LOAD_ATTR                3 (get + NULL|self)
               CALL                     0
               STORE_FAST               2 (nm)

 396           LOAD_FAST_LOAD_FAST     32 (nm, self)
               LOAD_ATTR                4 (ingenieros_cache)
               GET_ITER
               LOAD_FAST_AND_CLEAR      3 (i)
               SWAP                     2
       L1:     BUILD_LIST               0
               SWAP                     2
               GET_ITER
       L2:     FOR_ITER                 7 (to L3)
               STORE_FAST_LOAD_FAST    51 (i, i)
               LOAD_CONST               1 ('nombre')
               BINARY_SUBSCR
               LIST_APPEND              2
               JUMP_BACKWARD            9 (to L2)
       L3:     END_FOR
               POP_TOP
       L4:     SWAP                     2
               STORE_FAST               3 (i)
               CONTAINS_OP              0
               POP_JUMP_IF_FALSE       18 (to L5)

 397           LOAD_FAST                0 (self)
               LOAD_ATTR                7 (on_revisor_change + NULL|self)
               LOAD_FAST                2 (nm)
               CALL                     1
               POP_TOP
               RETURN_CONST             0 (None)

 396   L5:     RETURN_CONST             0 (None)

  --   L6:     SWAP                     2
               POP_TOP

 396           SWAP                     2
               STORE_FAST               3 (i)
               RERAISE                  0
ExceptionTable:
  L1 to L4 -> L6 [3]

Disassembly of <code object on_revisor_change at 0x0000028A6B12A830, file "src\ui\tab_carta.py", line 399>:
399           RESUME                   0

400           LOAD_FAST                0 (self)
              LOAD_ATTR                0 (ingenieros_cache)
              GET_ITER
      L1:     FOR_ITER               138 (to L4)
              STORE_FAST               2 (ing)

401           LOAD_FAST                2 (ing)
              LOAD_CONST               1 ('nombre')
              BINARY_SUBSCR
              LOAD_FAST                1 (choice)
              COMPARE_OP              88 (bool(==))
              POP_JUMP_IF_TRUE         2 (to L2)
              JUMP_BACKWARD           14 (to L1)

402   L2:     LOAD_FAST                0 (self)
              LOAD_ATTR                2 (entry_revisor_cip)
              LOAD_ATTR                5 (delete + NULL|self)
              LOAD_CONST               2 (0)
              LOAD_CONST               3 ('end')
              CALL                     2
              POP_TOP

403           LOAD_FAST                0 (self)
              LOAD_ATTR                2 (entry_revisor_cip)
              LOAD_ATTR                7 (insert + NULL|self)
              LOAD_CONST               2 (0)
              LOAD_FAST                2 (ing)
              LOAD_CONST               4 ('cip')
              BINARY_SUBSCR
              CALL                     2
              POP_TOP

404           LOAD_CONST               5 ('tipo')
              LOAD_FAST                2 (ing)
              CONTAINS_OP              0
              POP_JUMP_IF_FALSE       59 (to L3)

405           LOAD_FAST                0 (self)
              LOAD_ATTR                8 (entry_revisor_tipo)
              LOAD_ATTR                5 (delete + NULL|self)
              LOAD_CONST               2 (0)
              LOAD_CONST               3 ('end')
              CALL                     2
              POP_TOP

406           LOAD_FAST                0 (self)
              LOAD_ATTR                8 (entry_revisor_tipo)
              LOAD_ATTR                7 (insert + NULL|self)
              LOAD_CONST               2 (0)
              LOAD_FAST                2 (ing)
              LOAD_CONST               5 ('tipo')
              BINARY_SUBSCR
              CALL                     2
              POP_TOP

407   L3:     POP_TOP
              RETURN_CONST             0 (None)

400   L4:     END_FOR
              POP_TOP
              RETURN_CONST             0 (None)

Disassembly of <code object on_proyectista_type at 0x0000028A6B1874B0, file "src\ui\tab_carta.py", line 409>:
 409           RESUME                   0

 410           LOAD_FAST                0 (self)
               LOAD_ATTR                0 (combo_proyectista)
               LOAD_ATTR                3 (get + NULL|self)
               CALL                     0
               STORE_FAST               2 (nm)

 411           LOAD_FAST_LOAD_FAST     32 (nm, self)
               LOAD_ATTR                4 (ingenieros_cache)
               GET_ITER
               LOAD_FAST_AND_CLEAR      3 (i)
               SWAP                     2
       L1:     BUILD_LIST               0
               SWAP                     2
               GET_ITER
       L2:     FOR_ITER                 7 (to L3)
               STORE_FAST_LOAD_FAST    51 (i, i)
               LOAD_CONST               1 ('nombre')
               BINARY_SUBSCR
               LIST_APPEND              2
               JUMP_BACKWARD            9 (to L2)
       L3:     END_FOR
               POP_TOP
       L4:     SWAP                     2
               STORE_FAST               3 (i)
               CONTAINS_OP              0
               POP_JUMP_IF_FALSE       18 (to L5)

 412           LOAD_FAST                0 (self)
               LOAD_ATTR                7 (on_proyectista_change + NULL|self)
               LOAD_FAST                2 (nm)
               CALL                     1
               POP_TOP
               RETURN_CONST             0 (None)

 411   L5:     RETURN_CONST             0 (None)

  --   L6:     SWAP                     2
               POP_TOP

 411           SWAP                     2
               STORE_FAST               3 (i)
               RERAISE                  0
ExceptionTable:
  L1 to L4 -> L6 [3]

Disassembly of <code object on_proyectista_change at 0x0000028A6B187630, file "src\ui\tab_carta.py", line 414>:
414           RESUME                   0

415           LOAD_FAST                0 (self)
              LOAD_ATTR                0 (ingenieros_cache)
              GET_ITER
      L1:     FOR_ITER                73 (to L3)
              STORE_FAST               2 (ing)

416           LOAD_FAST                2 (ing)
              LOAD_CONST               1 ('nombre')
              BINARY_SUBSCR
              LOAD_FAST                1 (choice)
              COMPARE_OP              88 (bool(==))
              POP_JUMP_IF_TRUE         2 (to L2)
              JUMP_BACKWARD           14 (to L1)

417   L2:     LOAD_FAST                0 (self)
              LOAD_ATTR                2 (entry_proyectista_cip)
              LOAD_ATTR                5 (delete + NULL|self)
              LOAD_CONST               2 (0)
              LOAD_CONST               3 ('end')
              CALL                     2
              POP_TOP

418           LOAD_FAST                0 (self)
              LOAD_ATTR                2 (entry_proyectista_cip)
              LOAD_ATTR                7 (insert + NULL|self)
              LOAD_CONST               2 (0)
              LOAD_FAST                2 (ing)
              LOAD_CONST               4 ('cip')
              BINARY_SUBSCR
              CALL                     2
              POP_TOP

419           POP_TOP
              RETURN_CONST             0 (None)

415   L3:     END_FOR
              POP_TOP
              RETURN_CONST             0 (None)

Disassembly of <code object on_civil_rev_type at 0x0000028A6B1877B0, file "src\ui\tab_carta.py", line 421>:
 421           RESUME                   0

 422           LOAD_FAST                0 (self)
               LOAD_ATTR                0 (combo_civil_rev)
               LOAD_ATTR                3 (get + NULL|self)
               CALL                     0
               STORE_FAST               2 (nm)

 423           LOAD_FAST_LOAD_FAST     32 (nm, self)
               LOAD_ATTR                4 (ingenieros_cache)
               GET_ITER
               LOAD_FAST_AND_CLEAR      3 (i)
               SWAP                     2
       L1:     BUILD_LIST               0
               SWAP                     2
               GET_ITER
       L2:     FOR_ITER                 7 (to L3)
               STORE_FAST_LOAD_FAST    51 (i, i)
               LOAD_CONST               1 ('nombre')
               BINARY_SUBSCR
               LIST_APPEND              2
               JUMP_BACKWARD            9 (to L2)
       L3:     END_FOR
               POP_TOP
       L4:     SWAP                     2
               STORE_FAST               3 (i)
               CONTAINS_OP              0
               POP_JUMP_IF_FALSE       18 (to L5)

 424           LOAD_FAST                0 (self)
               LOAD_ATTR                7 (on_civil_rev_change + NULL|self)
               LOAD_FAST                2 (nm)
               CALL                     1
               POP_TOP
               RETURN_CONST             0 (None)

 423   L5:     RETURN_CONST             0 (None)

  --   L6:     SWAP                     2
               POP_TOP

 423           SWAP                     2
               STORE_FAST               3 (i)
               RERAISE                  0
ExceptionTable:
  L1 to L4 -> L6 [3]

Disassembly of <code object on_civil_rev_change at 0x0000028A6B187930, file "src\ui\tab_carta.py", line 426>:
426           RESUME                   0

427           LOAD_FAST                0 (self)
              LOAD_ATTR                0 (ingenieros_cache)
              GET_ITER
      L1:     FOR_ITER                73 (to L3)
              STORE_FAST               2 (ing)

428           LOAD_FAST                2 (ing)
              LOAD_CONST               1 ('nombre')
              BINARY_SUBSCR
              LOAD_FAST                1 (choice)
              COMPARE_OP              88 (bool(==))
              POP_JUMP_IF_TRUE         2 (to L2)
              JUMP_BACKWARD           14 (to L1)

429   L2:     LOAD_FAST                0 (self)
              LOAD_ATTR                2 (entry_civil_rev_cip)
              LOAD_ATTR                5 (delete + NULL|self)
              LOAD_CONST               2 (0)
              LOAD_CONST               3 ('end')
              CALL                     2
              POP_TOP

430           LOAD_FAST                0 (self)
              LOAD_ATTR                2 (entry_civil_rev_cip)
              LOAD_ATTR                7 (insert + NULL|self)
              LOAD_CONST               2 (0)
              LOAD_FAST                2 (ing)
              LOAD_CONST               4 ('cip')
              BINARY_SUBSCR
              CALL                     2
              POP_TOP

431           POP_TOP
              RETURN_CONST             0 (None)

427   L3:     END_FOR
              POP_TOP
              RETURN_CONST             0 (None)

Disassembly of <code object on_civil_proy_type at 0x0000028A6B187AB0, file "src\ui\tab_carta.py", line 433>:
 433           RESUME                   0

 434           LOAD_FAST                0 (self)
               LOAD_ATTR                0 (combo_civil_proy)
               LOAD_ATTR                3 (get + NULL|self)
               CALL                     0
               STORE_FAST               2 (nm)

 435           LOAD_FAST_LOAD_FAST     32 (nm, self)
               LOAD_ATTR                4 (ingenieros_cache)
               GET_ITER
               LOAD_FAST_AND_CLEAR      3 (i)
               SWAP                     2
       L1:     BUILD_LIST               0
               SWAP                     2
               GET_ITER
       L2:     FOR_ITER                 7 (to L3)
               STORE_FAST_LOAD_FAST    51 (i, i)
               LOAD_CONST               1 ('nombre')
               BINARY_SUBSCR
               LIST_APPEND              2
               JUMP_BACKWARD            9 (to L2)
       L3:     END_FOR
               POP_TOP
       L4:     SWAP                     2
               STORE_FAST               3 (i)
               CONTAINS_OP              0
               POP_JUMP_IF_FALSE       18 (to L5)

 436           LOAD_FAST                0 (self)
               LOAD_ATTR                7 (on_civil_proy_change + NULL|self)
               LOAD_FAST                2 (nm)
               CALL                     1
               POP_TOP
               RETURN_CONST             0 (None)

 435   L5:     RETURN_CONST             0 (None)

  --   L6:     SWAP                     2
               POP_TOP

 435           SWAP                     2
               STORE_FAST               3 (i)
               RERAISE                  0
ExceptionTable:
  L1 to L4 -> L6 [3]

Disassembly of <code object on_civil_proy_change at 0x0000028A6B187C30, file "src\ui\tab_carta.py", line 438>:
438           RESUME                   0

439           LOAD_FAST                0 (self)
              LOAD_ATTR                0 (ingenieros_cache)
              GET_ITER
      L1:     FOR_ITER                73 (to L3)
              STORE_FAST               2 (ing)

440           LOAD_FAST                2 (ing)
              LOAD_CONST               1 ('nombre')
              BINARY_SUBSCR
              LOAD_FAST                1 (choice)
              COMPARE_OP              88 (bool(==))
              POP_JUMP_IF_TRUE         2 (to L2)
              JUMP_BACKWARD           14 (to L1)

441   L2:     LOAD_FAST                0 (self)
              LOAD_ATTR                2 (entry_civil_proy_cip)
              LOAD_ATTR                5 (delete + NULL|self)
              LOAD_CONST               2 (0)
              LOAD_CONST               3 ('end')
              CALL                     2
              POP_TOP

442           LOAD_FAST                0 (self)
              LOAD_ATTR                2 (entry_civil_proy_cip)
              LOAD_ATTR                7 (insert + NULL|self)
              LOAD_CONST               2 (0)
              LOAD_FAST                2 (ing)
              LOAD_CONST               4 ('cip')
              BINARY_SUBSCR
              CALL                     2
              POP_TOP

443           POP_TOP
              RETURN_CONST             0 (None)

439   L3:     END_FOR
              POP_TOP
              RETURN_CONST             0 (None)

Disassembly of <code object save_new_ingenieros_cache at 0x0000028A6B46D120, file "src\ui\tab_carta.py", line 445>:
  --            MAKE_CELL                1 (nombre)

 445            RESUME                   0

 446            LOAD_DEREF               1 (nombre)
                TO_BOOL
                POP_JUMP_IF_FALSE        7 (to L1)
                LOAD_FAST                2 (cip)
                TO_BOOL
                POP_JUMP_IF_TRUE         1 (to L2)
        L1:     RETURN_CONST             0 (None)

 447    L2:     LOAD_GLOBAL              1 (next + NULL)
                LOAD_FAST                1 (nombre)
                BUILD_TUPLE              1
                LOAD_CONST               1 (<code object <genexpr> at 0x0000028A6B36FCC0, file "src\ui\tab_carta.py", line 447>)
                MAKE_FUNCTION
                SET_FUNCTION_ATTRIBUTE   8 (closure)
                LOAD_FAST                0 (self)
                LOAD_ATTR                2 (ingenieros_cache)
                GET_ITER
                CALL                     0
                LOAD_CONST               0 (None)
                CALL                     2
                STORE_FAST               5 (exist)

 448            LOAD_FAST                5 (exist)
                TO_BOOL
                POP_JUMP_IF_FALSE       16 (to L4)

 449            LOAD_FAST_LOAD_FAST     37 (cip, exist)
                LOAD_CONST               2 ('cip')
                STORE_SUBSCR

 450            LOAD_FAST                4 (tipo)
                TO_BOOL
                POP_JUMP_IF_FALSE        4 (to L3)
                LOAD_FAST_LOAD_FAST     69 (tipo, exist)
                LOAD_CONST               3 ('tipo')
                STORE_SUBSCR

  --    L3:     JUMP_FORWARD            49 (to L8)

 452    L4:     LOAD_FAST                4 (tipo)
                TO_BOOL
                POP_JUMP_IF_FALSE        2 (to L5)
                LOAD_FAST                4 (tipo)
                JUMP_FORWARD             9 (to L7)
        L5:     LOAD_FAST                3 (rev_or_proy)
                LOAD_CONST               4 ('revisor')
                COMPARE_OP              88 (bool(==))
                POP_JUMP_IF_FALSE        2 (to L6)
                LOAD_CONST               5 ('Ingeniero')
                JUMP_FORWARD             1 (to L7)
        L6:     LOAD_CONST               6 ('Ingeniero Proyectista')
        L7:     STORE_FAST               6 (tipo_final)

 453            LOAD_FAST                0 (self)
                LOAD_ATTR                2 (ingenieros_cache)
                LOAD_ATTR                5 (append + NULL|self)
                LOAD_DEREF               1 (nombre)
                LOAD_FAST_LOAD_FAST     38 (cip, tipo_final)
                LOAD_CONST               7 (('nombre', 'cip', 'tipo'))
                BUILD_CONST_KEY_MAP      3
                CALL                     1
                POP_TOP

 455    L8:     NOP

 456    L9:     LOAD_GLOBAL              7 (open + NULL)
                LOAD_CONST               8 ('ingenieros.json')
                LOAD_CONST               9 ('w')
                LOAD_CONST              10 ('utf-8')
                LOAD_CONST              11 (('encoding',))
                CALL_KW                  3
                BEFORE_WITH
       L10:     STORE_FAST               7 (f)

 457            LOAD_GLOBAL              8 (json)
                LOAD_ATTR               10 (dump)
                PUSH_NULL
                LOAD_FAST                0 (self)
                LOAD_ATTR                2 (ingenieros_cache)
                LOAD_FAST                7 (f)
                LOAD_CONST              12 (4)
                LOAD_CONST              13 (False)
                LOAD_CONST              14 (('indent', 'ensure_ascii'))
                CALL_KW                  4
                POP_TOP

 456   L11:     LOAD_CONST               0 (None)
                LOAD_CONST               0 (None)
                LOAD_CONST               0 (None)
                CALL                     2
                POP_TOP
       L12:     RETURN_CONST             0 (None)
       L13:     PUSH_EXC_INFO
                WITH_EXCEPT_START
                TO_BOOL
                POP_JUMP_IF_TRUE         1 (to L14)
                RERAISE                  2
       L14:     POP_TOP
       L15:     POP_EXCEPT
                POP_TOP
                POP_TOP
       L16:     RETURN_CONST             0 (None)

  --   L17:     COPY                     3
                POP_EXCEPT
                RERAISE                  1
       L18:     PUSH_EXC_INFO

 458            POP_TOP
       L19:     POP_EXCEPT
                RETURN_CONST             0 (None)

  --   L20:     COPY                     3
                POP_EXCEPT
                RERAISE                  1
ExceptionTable:
  L9 to L10 -> L18 [0]
  L10 to L11 -> L13 [1] lasti
  L11 to L12 -> L18 [0]
  L13 to L15 -> L17 [3] lasti
  L15 to L16 -> L18 [0]
  L17 to L18 -> L18 [0]
  L18 to L19 -> L20 [1] lasti

Disassembly of <code object <genexpr> at 0x0000028A6B36FCC0, file "src\ui\tab_carta.py", line 447>:
  --           COPY_FREE_VARS           1

 447           RETURN_GENERATOR
               POP_TOP
       L1:     RESUME                   0
               LOAD_FAST                0 (.0)
               GET_ITER
       L2:     FOR_ITER                17 (to L5)
               STORE_FAST_LOAD_FAST    17 (i, i)
               LOAD_CONST               0 ('nombre')
               BINARY_SUBSCR
               LOAD_DEREF               2 (nombre)
               COMPARE_OP              88 (bool(==))
       L3:     POP_JUMP_IF_TRUE         2 (to L4)
               JUMP_BACKWARD           13 (to L2)
       L4:     LOAD_FAST                1 (i)
               YIELD_VALUE              0
               RESUME                   5
               POP_TOP
               JUMP_BACKWARD           19 (to L2)
       L5:     END_FOR
               POP_TOP
               RETURN_CONST             1 (None)

  --   L6:     CALL_INTRINSIC_1         3 (INTRINSIC_STOPITERATION_ERROR)
               RERAISE                  1
ExceptionTable:
  L1 to L3 -> L6 [0] lasti
  L4 to L6 -> L6 [0] lasti

Disassembly of <code object agregar_cajon_plano at 0x0000028A6B468320, file "src\ui\tab_carta.py", line 461>:
  --           MAKE_CELL                0 (self)

 461           RESUME                   0

 462           LOAD_GLOBAL              1 (len + NULL)
               LOAD_DEREF               0 (self)
               LOAD_ATTR                2 (lista_entradas_planos)
               CALL                     1
               LOAD_CONST               1 (1)
               BINARY_OP                0 (+)
               STORE_FAST               1 (num)

 465           LOAD_GLOBAL              4 (ctk)
               LOAD_ATTR                6 (CTkFrame)
               PUSH_NULL
               LOAD_DEREF               0 (self)
               LOAD_ATTR                8 (frame_planos_list)
               LOAD_CONST               2 ('transparent')
               LOAD_CONST               3 (('fg_color',))
               CALL_KW                  2
               STORE_FAST               2 (f_plano)

 466           LOAD_FAST                2 (f_plano)
               LOAD_ATTR               11 (pack + NULL|self)
               LOAD_CONST               4 ('x')
               LOAD_CONST               5 (2)
               LOAD_CONST               6 (('fill', 'pady'))
               CALL_KW                  2
               POP_TOP

 467           LOAD_FAST                2 (f_plano)
               LOAD_ATTR               13 (grid_columnconfigure + NULL|self)
               LOAD_CONST               7 (0)
               LOAD_CONST               1 (1)
               LOAD_CONST               8 (('weight',))
               CALL_KW                  2
               POP_TOP

 469           LOAD_GLOBAL              4 (ctk)
               LOAD_ATTR               14 (CTkEntry)
               PUSH_NULL
               LOAD_FAST                2 (f_plano)
               LOAD_CONST               9 ('Nombre del Plano ')
               LOAD_FAST                1 (num)
               FORMAT_SIMPLE
               LOAD_CONST              10 (' (Ej. IE-01)')
               BUILD_STRING             3
               LOAD_CONST              11 (('placeholder_text',))
               CALL_KW                  2
               STORE_FAST               3 (entry)

 470           LOAD_FAST                3 (entry)
               LOAD_ATTR               17 (grid + NULL|self)
               LOAD_CONST               7 (0)
               LOAD_CONST               7 (0)
               LOAD_CONST              12 ('ew')
               LOAD_CONST              13 ((0, 5))
               LOAD_CONST              14 (('row', 'column', 'sticky', 'padx'))
               CALL_KW                  4
               POP_TOP

 472           LOAD_GLOBAL              4 (ctk)
               LOAD_ATTR               18 (CTkButton)
               PUSH_NULL
               LOAD_FAST                2 (f_plano)
               LOAD_CONST              15 ('X')
               LOAD_CONST              16 (30)
               LOAD_CONST              17 ('red')
               LOAD_CONST              18 ('darkred')

 473           LOAD_FAST_LOAD_FAST     35 (f_plano, entry)
               BUILD_TUPLE              2
               LOAD_FAST                0 (self)
               BUILD_TUPLE              1
               LOAD_CONST              19 (<code object <lambda> at 0x0000028A6B35AC40, file "src\ui\tab_carta.py", line 473>)
               MAKE_FUNCTION
               SET_FUNCTION_ATTRIBUTE   8 (closure)
               SET_FUNCTION_ATTRIBUTE   1 (defaults)

 472           LOAD_CONST              20 (('text', 'width', 'fg_color', 'hover_color', 'command'))
               CALL_KW                  6
               STORE_FAST               4 (btn_del)

 474           LOAD_FAST                4 (btn_del)
               LOAD_ATTR               17 (grid + NULL|self)
               LOAD_CONST               7 (0)
               LOAD_CONST               1 (1)
               LOAD_CONST              21 (('row', 'column'))
               CALL_KW                  2
               POP_TOP

 476           LOAD_DEREF               0 (self)
               LOAD_ATTR                2 (lista_entradas_planos)
               LOAD_ATTR               21 (append + NULL|self)
               LOAD_FAST                3 (entry)
               CALL                     1
               POP_TOP
               RETURN_CONST             0 (None)

Disassembly of <code object <lambda> at 0x0000028A6B35AC40, file "src\ui\tab_carta.py", line 473>:
  --           COPY_FREE_VARS           1

 473           RESUME                   0
               LOAD_DEREF               2 (self)
               LOAD_ATTR                1 (eliminar_cajon_plano + NULL|self)
               LOAD_FAST_LOAD_FAST      1 (f, e)
               CALL                     2
               RETURN_VALUE

Disassembly of <code object eliminar_cajon_plano at 0x0000028A6B3AD430, file "src\ui\tab_carta.py", line 478>:
478           RESUME                   0

479           LOAD_FAST_LOAD_FAST     32 (entry, self)
              LOAD_ATTR                0 (lista_entradas_planos)
              CONTAINS_OP              0
              POP_JUMP_IF_FALSE       27 (to L1)

480           LOAD_FAST                0 (self)
              LOAD_ATTR                0 (lista_entradas_planos)
              LOAD_ATTR                3 (remove + NULL|self)
              LOAD_FAST                2 (entry)
              CALL                     1
              POP_TOP

481   L1:     LOAD_FAST                1 (frame)
              LOAD_ATTR                5 (destroy + NULL|self)
              CALL                     0
              POP_TOP
              RETURN_CONST             0 (None)

Disassembly of <code object get_resource_path at 0x0000028A6B42A390, file "src\ui\tab_carta.py", line 484>:
 484           RESUME                   0

 486           LOAD_CONST               1 (0)
               LOAD_CONST               2 (None)
               IMPORT_NAME              0 (sys)
               STORE_FAST               2 (sys)

 487           NOP

 489   L1:     LOAD_FAST                2 (sys)
               LOAD_ATTR                2 (_MEIPASS)
               STORE_FAST               3 (base_path)

 493   L2:     LOAD_GLOBAL              6 (os)
               LOAD_ATTR                8 (path)
               LOAD_ATTR               13 (join + NULL|self)
               LOAD_FAST_LOAD_FAST     49 (base_path, relative_path)
               CALL                     2
               RETURN_VALUE

  --   L3:     PUSH_EXC_INFO

 490           LOAD_GLOBAL              4 (Exception)
               CHECK_EXC_MATCH
               POP_JUMP_IF_FALSE       98 (to L5)
               POP_TOP

 491           LOAD_GLOBAL              6 (os)
               LOAD_ATTR                8 (path)
               LOAD_ATTR               11 (abspath + NULL|self)
               LOAD_GLOBAL              6 (os)
               LOAD_ATTR                8 (path)
               LOAD_ATTR               13 (join + NULL|self)
               LOAD_GLOBAL              6 (os)
               LOAD_ATTR                8 (path)
               LOAD_ATTR               15 (dirname + NULL|self)
               LOAD_GLOBAL             16 (__file__)
               CALL                     1
               LOAD_CONST               3 ('..')
               LOAD_CONST               3 ('..')
               CALL                     3
               CALL                     1
               STORE_FAST               3 (base_path)
       L4:     POP_EXCEPT
               JUMP_BACKWARD_NO_INTERRUPT 138 (to L2)

 490   L5:     RERAISE                  0

  --   L6:     COPY                     3
               POP_EXCEPT
               RERAISE                  1
ExceptionTable:
  L1 to L2 -> L3 [0]
  L3 to L4 -> L6 [1] lasti
  L5 to L6 -> L6 [1] lasti

Disassembly of <code object action_generar_word at 0x0000028A6B49DE60, file "src\ui\tab_carta.py", line 495>:
  --            MAKE_CELL                0 (self)
                MAKE_CELL               11 (messagebox)
                MAKE_CELL               12 (msg)

 495            RESUME                   0

 496            LOAD_CONST               1 (0)
                LOAD_CONST               2 (('filedialog', 'messagebox'))
                IMPORT_NAME              0 (tkinter)
                IMPORT_FROM              1 (filedialog)
                STORE_FAST               1 (filedialog)
                IMPORT_FROM              2 (messagebox)
                STORE_DEREF             11 (messagebox)
                POP_TOP

 499            LOAD_DEREF               0 (self)
                LOAD_ATTR                7 (save_new_ubicacion_cache + NULL|self)
                CALL                     0
                POP_TOP

 500            LOAD_DEREF               0 (self)
                LOAD_ATTR                9 (save_new_ingenieros_cache + NULL|self)
                LOAD_DEREF               0 (self)
                LOAD_ATTR               10 (combo_revisor)
                LOAD_ATTR               13 (get + NULL|self)
                CALL                     0
                LOAD_DEREF               0 (self)
                LOAD_ATTR               14 (entry_revisor_cip)
                LOAD_ATTR               13 (get + NULL|self)
                CALL                     0
                LOAD_CONST               3 ('revisor')
                LOAD_DEREF               0 (self)
                LOAD_ATTR               16 (entry_revisor_tipo)
                LOAD_ATTR               13 (get + NULL|self)
                CALL                     0
                CALL                     4
                POP_TOP

 501            LOAD_DEREF               0 (self)
                LOAD_ATTR                9 (save_new_ingenieros_cache + NULL|self)
                LOAD_DEREF               0 (self)
                LOAD_ATTR               18 (combo_proyectista)
                LOAD_ATTR               13 (get + NULL|self)
                CALL                     0
                LOAD_DEREF               0 (self)
                LOAD_ATTR               20 (entry_proyectista_cip)
                LOAD_ATTR               13 (get + NULL|self)
                CALL                     0
                LOAD_CONST               4 ('proyectista')
                CALL                     3
                POP_TOP

 503            LOAD_DEREF               0 (self)
                LOAD_ATTR               22 (var_tiene_civil_rev)
                LOAD_ATTR               13 (get + NULL|self)
                CALL                     0
                TO_BOOL
                POP_JUMP_IF_FALSE       68 (to L1)

 504            LOAD_DEREF               0 (self)
                LOAD_ATTR                9 (save_new_ingenieros_cache + NULL|self)
                LOAD_DEREF               0 (self)
                LOAD_ATTR               24 (combo_civil_rev)
                LOAD_ATTR               13 (get + NULL|self)
                CALL                     0
                LOAD_DEREF               0 (self)
                LOAD_ATTR               26 (entry_civil_rev_cip)
                LOAD_ATTR               13 (get + NULL|self)
                CALL                     0
                LOAD_CONST               3 ('revisor')
                LOAD_CONST               5 ('Ingeniero Civil')
                CALL                     4
                POP_TOP

 505    L1:     LOAD_DEREF               0 (self)
                LOAD_ATTR               28 (var_tiene_civil_proy)
                LOAD_ATTR               13 (get + NULL|self)
                CALL                     0
                TO_BOOL
                POP_JUMP_IF_FALSE       68 (to L2)

 506            LOAD_DEREF               0 (self)
                LOAD_ATTR                9 (save_new_ingenieros_cache + NULL|self)
                LOAD_DEREF               0 (self)
                LOAD_ATTR               30 (combo_civil_proy)
                LOAD_ATTR               13 (get + NULL|self)
                CALL                     0
                LOAD_DEREF               0 (self)
                LOAD_ATTR               32 (entry_civil_proy_cip)
                LOAD_ATTR               13 (get + NULL|self)
                CALL                     0
                LOAD_CONST               4 ('proyectista')
                LOAD_CONST               5 ('Ingeniero Civil')
                CALL                     4
                POP_TOP

 509    L2:     LOAD_DEREF               0 (self)
                LOAD_ATTR               35 (get_resource_path + NULL|self)
                LOAD_CONST               6 ('assets/plantilla_carta.docx')
                CALL                     1
                STORE_FAST               2 (template_base_path)

 510            LOAD_GLOBAL             36 (os)
                LOAD_ATTR               38 (path)
                LOAD_ATTR               41 (exists + NULL|self)
                LOAD_FAST                2 (template_base_path)
                CALL                     1
                TO_BOOL
                POP_JUMP_IF_TRUE        23 (to L3)

 511            LOAD_DEREF              11 (messagebox)
                LOAD_ATTR               43 (showwarning + NULL|self)
                LOAD_CONST               7 ('Falta Plantilla')
                LOAD_CONST               8 ('No se encontró la plantilla base en ')
                LOAD_FAST                2 (template_base_path)
                FORMAT_SIMPLE
                LOAD_CONST               9 ('. Por favor, asegúrate de colocarla antes de exportar.')
                BUILD_STRING             3
                CALL                     2
                POP_TOP

 512            RETURN_CONST             0 (None)

 515    L3:     LOAD_DEREF               0 (self)
                LOAD_ATTR               44 (lista_entradas_planos)
                GET_ITER
                LOAD_FAST_AND_CLEAR      3 (p)
                SWAP                     2
        L4:     BUILD_LIST               0
                SWAP                     2
                GET_ITER
        L5:     FOR_ITER                69 (to L8)
                STORE_FAST_LOAD_FAST    51 (p, p)
                LOAD_ATTR               13 (get + NULL|self)
                CALL                     0
                LOAD_ATTR               47 (strip + NULL|self)
                CALL                     0
                TO_BOOL
        L6:     POP_JUMP_IF_TRUE         2 (to L7)
                JUMP_BACKWARD           39 (to L5)
        L7:     LOAD_FAST                3 (p)
                LOAD_ATTR               13 (get + NULL|self)
                CALL                     0
                LOAD_ATTR               47 (strip + NULL|self)
                CALL                     0
                LIST_APPEND              2
                JUMP_BACKWARD           71 (to L5)
        L8:     END_FOR
                POP_TOP
        L9:     STORE_FAST               4 (planos)
                STORE_FAST               3 (p)

 516            LOAD_FAST                4 (planos)
                TO_BOOL
                POP_JUMP_IF_TRUE        19 (to L10)

 517            LOAD_DEREF              11 (messagebox)
                LOAD_ATTR               43 (showwarning + NULL|self)
                LOAD_CONST              10 ('Faltan Planos')
                LOAD_CONST              11 ('Debes ingresar al menos un (1) plano en la lista.')
                CALL                     2
                POP_TOP

 518            RETURN_CONST             0 (None)

 520   L10:     LOAD_DEREF               0 (self)
                LOAD_ATTR               48 (entry_atc)
                LOAD_ATTR               13 (get + NULL|self)
                CALL                     0
                LOAD_ATTR               47 (strip + NULL|self)
                CALL                     0
                STORE_FAST               5 (atc_val)

 521            LOAD_FAST                5 (atc_val)
                TO_BOOL
                POP_JUMP_IF_TRUE         2 (to L11)

 522            LOAD_CONST              12 ('0000')
                STORE_FAST               5 (atc_val)

 524   L11:     LOAD_FAST                1 (filedialog)
                LOAD_ATTR               51 (asksaveasfilename + NULL|self)

 525            LOAD_CONST              13 ('.docx')

 526            LOAD_CONST              14 ('PD-')
                LOAD_FAST                5 (atc_val)
                FORMAT_SIMPLE
                LOAD_CONST              15 ('-2026.docx')
                BUILD_STRING             3

 527            LOAD_CONST              16 (('Word Document', '*.docx'))
                BUILD_LIST               1

 524            LOAD_CONST              17 (('defaultextension', 'initialfile', 'filetypes'))
                CALL_KW                  3
                STORE_FAST               6 (export_path)

 529            LOAD_FAST                6 (export_path)
                TO_BOOL
                POP_JUMP_IF_TRUE         1 (to L12)

 530            RETURN_CONST             0 (None)

 535   L12:     BUILD_MAP                0

 536            LOAD_CONST              18 ('FECHA_HOY_CORTA')
                LOAD_DEREF               0 (self)
                LOAD_ATTR               52 (entry_fecha_sys)
                LOAD_ATTR               13 (get + NULL|self)
                CALL                     0

 535            MAP_ADD                  1

 537            LOAD_CONST              19 ('ATC')
                LOAD_FAST                5 (atc_val)

 535            MAP_ADD                  1

 538            LOAD_CONST              20 ('REFERENCIA')
                LOAD_DEREF               0 (self)
                LOAD_ATTR               54 (entry_referencia)
                LOAD_ATTR               13 (get + NULL|self)
                CALL                     0

 535            MAP_ADD                  1

 540            LOAD_CONST              21 ('SOLICITUD')
                LOAD_DEREF               0 (self)
                LOAD_ATTR               56 (entry_solicitud)
                LOAD_ATTR               13 (get + NULL|self)
                CALL                     0

 535            MAP_ADD                  1

 541            LOAD_CONST              22 ('DIRIGIDO')
                LOAD_DEREF               0 (self)
                LOAD_ATTR               58 (entry_dirigido)
                LOAD_ATTR               13 (get + NULL|self)
                CALL                     0

 535            MAP_ADD                  1

 542            LOAD_CONST              23 ('CLIENTE')
                LOAD_DEREF               0 (self)
                LOAD_ATTR               60 (entry_cliente)
                LOAD_ATTR               13 (get + NULL|self)
                CALL                     0

 535            MAP_ADD                  1

 544            LOAD_CONST              24 ('DIRECCION_CARTA')
                LOAD_DEREF               0 (self)
                LOAD_ATTR               62 (entry_direccion)
                LOAD_ATTR               13 (get + NULL|self)
                CALL                     0

 535            MAP_ADD                  1

 545            LOAD_CONST              25 ('DIRECCION_PROYECTO')
                LOAD_DEREF               0 (self)
                LOAD_ATTR               64 (entry_direccion_proyecto)
                LOAD_ATTR               13 (get + NULL|self)
                CALL                     0

 535            MAP_ADD                  1

 546            LOAD_CONST              26 ('DISTRITO')
                LOAD_DEREF               0 (self)
                LOAD_ATTR               66 (combo_distrito)
                LOAD_ATTR               13 (get + NULL|self)
                CALL                     0

 535            MAP_ADD                  1

 547            LOAD_CONST              27 ('DEPARTAMENTO')
                LOAD_DEREF               0 (self)
                LOAD_ATTR               68 (entry_departamento)
                LOAD_ATTR               13 (get + NULL|self)
                CALL                     0

 535            MAP_ADD                  1

 549            LOAD_CONST              28 ('FECHA_CARTA')
                LOAD_DEREF               0 (self)
                LOAD_ATTR               70 (entry_fecha_carta)
                LOAD_ATTR               13 (get + NULL|self)
                CALL                     0

 535            MAP_ADD                  1

 550            LOAD_CONST              29 ('FECHA_INICIO')
                LOAD_DEREF               0 (self)
                LOAD_ATTR               72 (entry_fecha_inicio)
                LOAD_ATTR               13 (get + NULL|self)
                CALL                     0

 535            MAP_ADD                  1

 551            LOAD_CONST              30 ('FECHA_FIN_CALCULADA')
                LOAD_DEREF               0 (self)
                LOAD_ATTR               74 (entry_fecha_fin)
                LOAD_ATTR               13 (get + NULL|self)
                CALL                     0

 535            MAP_ADD                  1

 553            LOAD_CONST              31 ('REVISOR_NOMBRE')
                LOAD_DEREF               0 (self)
                LOAD_ATTR               10 (combo_revisor)
                LOAD_ATTR               13 (get + NULL|self)
                CALL                     0

 535            MAP_ADD                  1

 554            LOAD_CONST              32 ('REVISOR_CIP')
                LOAD_DEREF               0 (self)
                LOAD_ATTR               14 (entry_revisor_cip)
                LOAD_ATTR               13 (get + NULL|self)
                CALL                     0

 535            MAP_ADD                  1

 555            LOAD_CONST              33 ('REVISOR_TIPO')
                LOAD_DEREF               0 (self)
                LOAD_ATTR               16 (entry_revisor_tipo)
                LOAD_ATTR               13 (get + NULL|self)
                CALL                     0

 535            MAP_ADD                  1

 556            LOAD_CONST              34 ('PROYECTISTA_NOMBRE')
                LOAD_DEREF               0 (self)
                LOAD_ATTR               18 (combo_proyectista)
                LOAD_ATTR               13 (get + NULL|self)
                CALL                     0

 535            MAP_ADD                  1

 557            LOAD_DEREF               0 (self)
                LOAD_ATTR               20 (entry_proyectista_cip)
                LOAD_ATTR               13 (get + NULL|self)
                CALL                     0

 559            LOAD_DEREF               0 (self)
                LOAD_ATTR               22 (var_tiene_civil_rev)
                LOAD_ATTR               13 (get + NULL|self)
                CALL                     0

 560            LOAD_DEREF               0 (self)
                LOAD_ATTR               22 (var_tiene_civil_rev)
                LOAD_ATTR               13 (get + NULL|self)
                CALL                     0
                TO_BOOL
                POP_JUMP_IF_FALSE       26 (to L13)
                LOAD_DEREF               0 (self)
                LOAD_ATTR               24 (combo_civil_rev)
                LOAD_ATTR               13 (get + NULL|self)
                CALL                     0
                JUMP_FORWARD             1 (to L14)
       L13:     LOAD_CONST              35 ('')

 561   L14:     LOAD_DEREF               0 (self)
                LOAD_ATTR               22 (var_tiene_civil_rev)
                LOAD_ATTR               13 (get + NULL|self)
                CALL                     0
                TO_BOOL
                POP_JUMP_IF_FALSE       26 (to L15)
                LOAD_DEREF               0 (self)
                LOAD_ATTR               26 (entry_civil_rev_cip)
                LOAD_ATTR               13 (get + NULL|self)
                CALL                     0
                JUMP_FORWARD             1 (to L16)
       L15:     LOAD_CONST              35 ('')

 562   L16:     LOAD_DEREF               0 (self)
                LOAD_ATTR               22 (var_tiene_civil_rev)
                LOAD_ATTR               13 (get + NULL|self)
                CALL                     0
                TO_BOOL
                POP_JUMP_IF_FALSE       26 (to L17)
                LOAD_DEREF               0 (self)
                LOAD_ATTR               76 (entry_civil_rev_planos)
                LOAD_ATTR               13 (get + NULL|self)
                CALL                     0
                JUMP_FORWARD             1 (to L18)
       L17:     LOAD_CONST              35 ('')

 564   L18:     LOAD_DEREF               0 (self)
                LOAD_ATTR               28 (var_tiene_civil_proy)
                LOAD_ATTR               13 (get + NULL|self)
                CALL                     0

 565            LOAD_DEREF               0 (self)
                LOAD_ATTR               28 (var_tiene_civil_proy)
                LOAD_ATTR               13 (get + NULL|self)
                CALL                     0
                TO_BOOL
                POP_JUMP_IF_FALSE       26 (to L19)
                LOAD_DEREF               0 (self)
                LOAD_ATTR               30 (combo_civil_proy)
                LOAD_ATTR               13 (get + NULL|self)
                CALL                     0
                JUMP_FORWARD             1 (to L20)
       L19:     LOAD_CONST              35 ('')

 566   L20:     LOAD_DEREF               0 (self)
                LOAD_ATTR               28 (var_tiene_civil_proy)
                LOAD_ATTR               13 (get + NULL|self)
                CALL                     0
                TO_BOOL
                POP_JUMP_IF_FALSE       26 (to L21)
                LOAD_DEREF               0 (self)
                LOAD_ATTR               32 (entry_civil_proy_cip)
                LOAD_ATTR               13 (get + NULL|self)
                CALL                     0
                JUMP_FORWARD             1 (to L22)
       L21:     LOAD_CONST              35 ('')

 568   L22:     LOAD_FAST                4 (planos)

 535            LOAD_CONST              36 (('PROYECTISTA_CIP', 'TIENE_ING_CIVIL_REV', 'NOMBRE_ING_CIVIL_REV', 'CIP_ING_CIVIL_REV', 'PLANOS_CIVILES', 'TIENE_ING_CIVIL_PROY', 'NOMBRE_ING_CIVIL_PROY', 'CIP_ING_CIVIL_PROY', 'LISTA_PLANOS'))
                BUILD_CONST_KEY_MAP      9
                DICT_UPDATE              1
                STORE_FAST               7 (context)

 572            LOAD_DEREF               0 (self)
                LOAD_ATTR               78 (word_engine)
                LOAD_ATTR               81 (generar_documento + NULL|self)
                LOAD_FAST_LOAD_FAST     38 (template_base_path, export_path)
                LOAD_FAST                7 (context)
                CALL                     3
                UNPACK_SEQUENCE          2
                STORE_FAST               8 (success)
                STORE_DEREF             12 (msg)

 574            LOAD_FAST                8 (success)
                TO_BOOL
                POP_JUMP_IF_FALSE       45 (to L25)

 575            NOP

 577   L23:     LOAD_CONST               1 (0)
                LOAD_CONST               0 (None)
                IMPORT_NAME             41 (threading)
                STORE_FAST               9 (threading)

 578            LOAD_FAST               11 (messagebox)
                LOAD_FAST               12 (msg)
                LOAD_FAST                0 (self)
                BUILD_TUPLE              3
                LOAD_CONST              37 (<code object convert_to_pdf at 0x0000028A6B12AA30, file "src\ui\tab_carta.py", line 578>)
                MAKE_FUNCTION
                SET_FUNCTION_ATTRIBUTE   8 (closure)
                STORE_FAST              10 (convert_to_pdf)

 593            LOAD_FAST                9 (threading)
                LOAD_ATTR               85 (Thread + NULL|self)
                LOAD_FAST_LOAD_FAST    166 (convert_to_pdf, export_path)
                BUILD_TUPLE              1
                LOAD_CONST              38 (True)
                LOAD_CONST              39 (('target', 'args', 'daemon'))
                CALL_KW                  3
                LOAD_ATTR               87 (start + NULL|self)
                CALL                     0
                POP_TOP
       L24:     RETURN_CONST             0 (None)

 597   L25:     LOAD_DEREF              11 (messagebox)
                LOAD_ATTR               91 (showerror + NULL|self)
                LOAD_CONST              41 ('Error')
                LOAD_DEREF              12 (msg)
                CALL                     2
                POP_TOP
                RETURN_CONST             0 (None)

  --   L26:     SWAP                     2
                POP_TOP

 515            SWAP                     2
                STORE_FAST               3 (p)
                RERAISE                  0

  --   L27:     PUSH_EXC_INFO

 594            POP_TOP

 595            LOAD_DEREF              11 (messagebox)
                LOAD_ATTR               89 (showinfo + NULL|self)
                LOAD_CONST              40 ('Éxito')
                LOAD_DEREF              12 (msg)
                CALL                     2
                POP_TOP
       L28:     POP_EXCEPT
                RETURN_CONST             0 (None)

  --   L29:     COPY                     3
                POP_EXCEPT
                RERAISE                  1
ExceptionTable:
  L4 to L6 -> L26 [2]
  L7 to L9 -> L26 [2]
  L23 to L24 -> L27 [0]
  L27 to L28 -> L29 [1] lasti

Disassembly of <code object convert_to_pdf at 0x0000028A6B12AA30, file "src\ui\tab_carta.py", line 578>:
  --            COPY_FREE_VARS           3

 578            RESUME                   0

 579            NOP

 580    L1:     LOAD_CONST               1 (0)
                LOAD_CONST               2 (('convert',))
                IMPORT_NAME              0 (docx2pdf)
                IMPORT_FROM              1 (convert)
                STORE_FAST               1 (convert)
                POP_TOP

 581            LOAD_FAST                0 (docx_path)
                LOAD_ATTR                5 (replace + NULL|self)
                LOAD_CONST               3 ('.docx')
                LOAD_CONST               4 ('.pdf')
                CALL                     2
                STORE_FAST               2 (pdf_path)

 582            LOAD_FAST                1 (convert)
                PUSH_NULL
                LOAD_FAST_LOAD_FAST      2 (docx_path, pdf_path)
                CALL                     2
                POP_TOP

 584            LOAD_DEREF               6 (self)
                LOAD_ATTR                7 (after + NULL|self)
                LOAD_CONST               1 (0)
                LOAD_FAST                4 (messagebox)
                LOAD_FAST                5 (msg)
                BUILD_TUPLE              2
                LOAD_CONST               5 (<code object <lambda> at 0x0000028A6B37AD30, file "src\ui\tab_carta.py", line 584>)
                MAKE_FUNCTION
                SET_FUNCTION_ATTRIBUTE   8 (closure)
                CALL                     2
                POP_TOP
        L2:     RETURN_CONST             0 (None)

  --    L3:     PUSH_EXC_INFO

 585            LOAD_GLOBAL              8 (ImportError)
                CHECK_EXC_MATCH
                POP_JUMP_IF_FALSE       26 (to L5)
                POP_TOP

 587            LOAD_DEREF               6 (self)
                LOAD_ATTR                7 (after + NULL|self)
                LOAD_CONST               1 (0)
                LOAD_FAST                4 (messagebox)
                LOAD_FAST                5 (msg)
                BUILD_TUPLE              2
                LOAD_CONST               6 (<code object <lambda> at 0x0000028A6B378830, file "src\ui\tab_carta.py", line 587>)
                MAKE_FUNCTION
                SET_FUNCTION_ATTRIBUTE   8 (closure)
                CALL                     2
                POP_TOP
        L4:     POP_EXCEPT
                RETURN_CONST             0 (None)

 588    L5:     LOAD_GLOBAL             10 (Exception)
                CHECK_EXC_MATCH
                POP_JUMP_IF_FALSE       47 (to L9)
                STORE_FAST               3 (e)

 589    L6:     LOAD_GLOBAL             13 (print + NULL)
                LOAD_CONST               7 ('Error convirtiendo a PDF: ')
                LOAD_FAST                3 (e)
                FORMAT_SIMPLE
                BUILD_STRING             2
                CALL                     1
                POP_TOP

 590            LOAD_DEREF               6 (self)
                LOAD_ATTR                7 (after + NULL|self)
                LOAD_CONST               1 (0)
                LOAD_FAST                4 (messagebox)
                LOAD_FAST                5 (msg)
                BUILD_TUPLE              2
                LOAD_CONST               8 (<code object <lambda> at 0x0000028A6B35AE20, file "src\ui\tab_carta.py", line 590>)
                MAKE_FUNCTION
                SET_FUNCTION_ATTRIBUTE   8 (closure)
                CALL                     2
                POP_TOP
        L7:     POP_EXCEPT
                LOAD_CONST               0 (None)
                STORE_FAST               3 (e)
                DELETE_FAST              3 (e)
                RETURN_CONST             0 (None)

  --    L8:     LOAD_CONST               0 (None)
                STORE_FAST               3 (e)
                DELETE_FAST              3 (e)
                RERAISE                  1

 588    L9:     RERAISE                  0

  --   L10:     COPY                     3
                POP_EXCEPT
                RERAISE                  1
ExceptionTable:
  L1 to L2 -> L3 [0]
  L3 to L4 -> L10 [1] lasti
  L5 to L6 -> L10 [1] lasti
  L6 to L7 -> L8 [1] lasti
  L8 to L10 -> L10 [1] lasti

Disassembly of <code object <lambda> at 0x0000028A6B37AD30, file "src\ui\tab_carta.py", line 584>:
  --           COPY_FREE_VARS           2

 584           RESUME                   0
               LOAD_DEREF               0 (messagebox)
               LOAD_ATTR                1 (showinfo + NULL|self)
               LOAD_CONST               1 ('Éxito')
               LOAD_DEREF               1 (msg)
               FORMAT_SIMPLE
               LOAD_CONST               2 ('\n\nTambién se ha generado automáticamente una versión PDF en la misma carpeta.')
               BUILD_STRING             2
               CALL                     2
               RETURN_VALUE

Disassembly of <code object <lambda> at 0x0000028A6B378830, file "src\ui\tab_carta.py", line 587>:
  --           COPY_FREE_VARS           2

 587           RESUME                   0
               LOAD_DEREF               0 (messagebox)
               LOAD_ATTR                1 (showinfo + NULL|self)
               LOAD_CONST               1 ('Éxito')
               LOAD_DEREF               1 (msg)
               FORMAT_SIMPLE
               LOAD_CONST               2 ("\n\nOpcional: Instala 'docx2pdf' (pip install docx2pdf) para habilitar la auto-exportación a PDF.")
               BUILD_STRING             2
               CALL                     2
               RETURN_VALUE

Disassembly of <code object <lambda> at 0x0000028A6B35AE20, file "src\ui\tab_carta.py", line 590>:
  --           COPY_FREE_VARS           2

 590           RESUME                   0
               LOAD_DEREF               0 (messagebox)
               LOAD_ATTR                1 (showinfo + NULL|self)
               LOAD_CONST               1 ('Éxito')
               LOAD_DEREF               1 (msg)
               CALL                     2
               RETURN_VALUE
