  0           RESUME                   0

  1           LOAD_CONST               0 (0)
              LOAD_CONST               1 (None)
              IMPORT_NAME              0 (sys)
              STORE_NAME               0 (sys)

  2           LOAD_CONST               0 (0)
              LOAD_CONST               1 (None)
              IMPORT_NAME              1 (os)
              STORE_NAME               1 (os)

  5           LOAD_NAME                0 (sys)
              LOAD_ATTR                4 (path)
              LOAD_ATTR                7 (insert + NULL|self)
              LOAD_CONST               0 (0)
              LOAD_NAME                1 (os)
              LOAD_ATTR                4 (path)
              LOAD_ATTR                9 (dirname + NULL|self)
              LOAD_NAME                1 (os)
              LOAD_ATTR                4 (path)
              LOAD_ATTR               11 (abspath + NULL|self)
              LOAD_NAME                6 (__file__)
              CALL                     1
              CALL                     1
              CALL                     2
              POP_TOP

  7           LOAD_CONST               0 (0)
              LOAD_CONST               2 (('MainApp',))
              IMPORT_NAME              7 (src.gui)
              IMPORT_FROM              8 (MainApp)
              STORE_NAME               8 (MainApp)
              POP_TOP

  9           LOAD_NAME                9 (__name__)
              LOAD_CONST               3 ('__main__')
              COMPARE_OP              88 (bool(==))
              POP_JUMP_IF_FALSE       24 (to L1)

 10           LOAD_NAME                8 (MainApp)
              PUSH_NULL
              CALL                     0
              STORE_NAME              10 (app)

 11           LOAD_NAME               10 (app)
              LOAD_ATTR               23 (mainloop + NULL|self)
              CALL                     0
              POP_TOP
              RETURN_CONST             1 (None)

  9   L1:     RETURN_CONST             1 (None)

  --- CODE OBJ: <module> ---
  CONSTANTS: (0, None, ('MainApp',), '__main__')
  NAMES: ('sys', 'os', 'path', 'insert', 'dirname', 'abspath', '__file__', 'src.gui', 'MainApp', '__name__', 'app', 'mainloop')
  VARNAMES: ()
  FREEVARS: ()
