  0           RESUME                   0

  1           LOAD_CONST               0 (0)
              LOAD_CONST               1 (None)
              IMPORT_NAME              0 (fitz)
              STORE_NAME               0 (fitz)

  2           LOAD_CONST               0 (0)
              LOAD_CONST               1 (None)
              IMPORT_NAME              1 (io)
              STORE_NAME               1 (io)

  3           LOAD_CONST               0 (0)
              LOAD_CONST               2 (('Image',))
              IMPORT_NAME              2 (PIL)
              IMPORT_FROM              3 (Image)
              STORE_NAME               3 (Image)
              POP_TOP

  5           LOAD_BUILD_CLASS
              PUSH_NULL
              LOAD_CONST               3 (<code object PDFManager at 0x000001FC0A712D30, file "src\pdf_manager.py", line 5>)
              MAKE_FUNCTION
              LOAD_CONST               4 ('PDFManager')
              CALL                     2
              STORE_NAME               4 (PDFManager)
              RETURN_CONST             1 (None)

Disassembly of <code object PDFManager at 0x000001FC0A712D30, file "src\pdf_manager.py", line 5>:
  5           RESUME                   0
              LOAD_NAME                0 (__name__)
              STORE_NAME               1 (__module__)
              LOAD_CONST               0 ('PDFManager')
              STORE_NAME               2 (__qualname__)
              LOAD_CONST               1 (5)
              STORE_NAME               3 (__firstlineno__)

  6           LOAD_CONST               2 (<code object __init__ at 0x000001FC0A734B90, file "src\pdf_manager.py", line 6>)
              MAKE_FUNCTION
              STORE_NAME               4 (__init__)

  9           LOAD_CONST               3 (<code object load_pdf at 0x000001FC0A5D2290, file "src\pdf_manager.py", line 9>)
              MAKE_FUNCTION
              STORE_NAME               5 (load_pdf)

 20           LOAD_CONST               9 ((1.0,))
              LOAD_CONST               4 (<code object get_page_image at 0x000001FC0A61A3D0, file "src\pdf_manager.py", line 20>)
              MAKE_FUNCTION
              SET_FUNCTION_ATTRIBUTE   1 (defaults)
              STORE_NAME               6 (get_page_image)

 38           LOAD_CONST               5 (<code object pil_to_bytes at 0x000001FC0A76D1B0, file "src\pdf_manager.py", line 38>)
              MAKE_FUNCTION
              STORE_NAME               7 (pil_to_bytes)

 44           LOAD_CONST               6 (<code object process_and_save at 0x000001FC0A3726F0, file "src\pdf_manager.py", line 44>)
              MAKE_FUNCTION
              STORE_NAME               8 (process_and_save)
              LOAD_CONST               7 (())
              STORE_NAME               9 (__static_attributes__)
              RETURN_CONST             8 (None)

Disassembly of <code object __init__ at 0x000001FC0A734B90, file "src\pdf_manager.py", line 6>:
  6           RESUME                   0

  7           RETURN_CONST             0 (None)

Disassembly of <code object load_pdf at 0x000001FC0A5D2290, file "src\pdf_manager.py", line 9>:
   9           RESUME                   0

  13           NOP

  14   L1:     LOAD_GLOBAL              0 (fitz)
               LOAD_ATTR                2 (open)
               PUSH_NULL
               LOAD_FAST                1 (pdf_path)
               CALL                     1
               STORE_FAST               2 (doc)

  15           LOAD_FAST                2 (doc)
               LOAD_GLOBAL              5 (len + NULL)
               LOAD_FAST                2 (doc)
               CALL                     1
               BUILD_TUPLE              2
       L2:     RETURN_VALUE

  --   L3:     PUSH_EXC_INFO

  16           LOAD_GLOBAL              6 (Exception)
               CHECK_EXC_MATCH
               POP_JUMP_IF_FALSE       24 (to L7)
               STORE_FAST               3 (e)

  17   L4:     LOAD_GLOBAL              9 (print + NULL)
               LOAD_CONST               1 ('Error cargando PDF: ')
               LOAD_FAST                3 (e)
               FORMAT_SIMPLE
               BUILD_STRING             2
               CALL                     1
               POP_TOP

  18   L5:     POP_EXCEPT
               LOAD_CONST               2 (None)
               STORE_FAST               3 (e)
               DELETE_FAST              3 (e)
               RETURN_CONST             3 ((None, 0))

  --   L6:     LOAD_CONST               2 (None)
               STORE_FAST               3 (e)
               DELETE_FAST              3 (e)
               RERAISE                  1

  16   L7:     RERAISE                  0

  --   L8:     COPY                     3
               POP_EXCEPT
               RERAISE                  1
ExceptionTable:
  L1 to L2 -> L3 [0]
  L3 to L4 -> L8 [1] lasti
  L4 to L5 -> L6 [1] lasti
  L6 to L8 -> L8 [1] lasti

Disassembly of <code object get_page_image at 0x000001FC0A61A3D0, file "src\pdf_manager.py", line 20>:
  20           RESUME                   0

  26           NOP

  27   L1:     LOAD_FAST_LOAD_FAST     18 (doc, page_num)
               BINARY_SUBSCR
               STORE_FAST               4 (page)

  28           LOAD_GLOBAL              0 (fitz)
               LOAD_ATTR                2 (Matrix)
               PUSH_NULL
               LOAD_FAST_LOAD_FAST     51 (zoom, zoom)
               CALL                     2
               STORE_FAST               5 (mat)

  29           LOAD_FAST                4 (page)
               LOAD_ATTR                5 (get_pixmap + NULL|self)
               LOAD_FAST                5 (mat)
               LOAD_CONST               1 (('matrix',))
               CALL_KW                  1
               STORE_FAST               6 (pix)

  32           LOAD_GLOBAL              6 (Image)
               LOAD_ATTR                8 (frombytes)
               PUSH_NULL
               LOAD_CONST               2 ('RGB')
               LOAD_FAST                6 (pix)
               LOAD_ATTR               10 (width)
               LOAD_FAST                6 (pix)
               LOAD_ATTR               12 (height)
               BUILD_LIST               2
               LOAD_FAST                6 (pix)
               LOAD_ATTR               14 (samples)
               CALL                     3
               STORE_FAST               7 (img)

  33           LOAD_FAST                7 (img)
       L2:     RETURN_VALUE

  --   L3:     PUSH_EXC_INFO

  34           LOAD_GLOBAL             16 (Exception)
               CHECK_EXC_MATCH
               POP_JUMP_IF_FALSE       24 (to L7)
               STORE_FAST               8 (e)

  35   L4:     LOAD_GLOBAL             19 (print + NULL)
               LOAD_CONST               3 ('Error generando imagen de página: ')
               LOAD_FAST                8 (e)
               FORMAT_SIMPLE
               BUILD_STRING             2
               CALL                     1
               POP_TOP

  36   L5:     POP_EXCEPT
               LOAD_CONST               4 (None)
               STORE_FAST               8 (e)
               DELETE_FAST              8 (e)
               RETURN_CONST             4 (None)

  --   L6:     LOAD_CONST               4 (None)
               STORE_FAST               8 (e)
               DELETE_FAST              8 (e)
               RERAISE                  1

  34   L7:     RERAISE                  0

  --   L8:     COPY                     3
               POP_EXCEPT
               RERAISE                  1
ExceptionTable:
  L1 to L2 -> L3 [0]
  L3 to L4 -> L8 [1] lasti
  L4 to L5 -> L6 [1] lasti
  L6 to L8 -> L8 [1] lasti

Disassembly of <code object pil_to_bytes at 0x000001FC0A76D1B0, file "src\pdf_manager.py", line 38>:
 38           RESUME                   0

 40           LOAD_GLOBAL              0 (io)
              LOAD_ATTR                2 (BytesIO)
              PUSH_NULL
              CALL                     0
              STORE_FAST               2 (img_byte_arr)

 41           LOAD_FAST                1 (pil_image)
              LOAD_ATTR                5 (save + NULL|self)
              LOAD_FAST                2 (img_byte_arr)
              LOAD_CONST               1 ('PNG')
              LOAD_CONST               2 (('format',))
              CALL_KW                  2
              POP_TOP

 42           LOAD_FAST                2 (img_byte_arr)
              LOAD_ATTR                7 (getvalue + NULL|self)
              CALL                     0
              RETURN_VALUE

Disassembly of <code object process_and_save at 0x000001FC0A3726F0, file "src\pdf_manager.py", line 44>:
  --            MAKE_CELL               26 (total_pages)

  44            RESUME                   0

  55            NOP

  56    L1:     LOAD_FAST                2 (cover_img)
                TO_BOOL
                POP_JUMP_IF_FALSE       17 (to L2)
                LOAD_FAST                0 (self)
                LOAD_ATTR                1 (pil_to_bytes + NULL|self)
                LOAD_FAST                2 (cover_img)
                CALL                     1
                JUMP_FORWARD             1 (to L3)
        L2:     LOAD_CONST               1 (None)
        L3:     STORE_FAST               6 (cover_bytes)

  57            LOAD_FAST                3 (body_img)
                TO_BOOL
                POP_JUMP_IF_FALSE       17 (to L4)
                LOAD_FAST                0 (self)
                LOAD_ATTR                1 (pil_to_bytes + NULL|self)
                LOAD_FAST                3 (body_img)
                CALL                     1
                JUMP_FORWARD             1 (to L5)
        L4:     LOAD_CONST               1 (None)
        L5:     STORE_FAST               7 (body_bytes)

  59            LOAD_GLOBAL              3 (len + NULL)
                LOAD_FAST                1 (doc)
                CALL                     1
                STORE_DEREF             26 (total_pages)

  61            LOAD_FAST                4 (config_data)
                LOAD_ATTR                5 (get + NULL|self)
                LOAD_CONST               2 ('body_ranges')
                BUILD_LIST               0
                CALL                     2
                STORE_FAST               8 (body_ranges)

  62            LOAD_FAST                4 (config_data)
                LOAD_ATTR                5 (get + NULL|self)
                LOAD_CONST               3 ('cover_ranges')
                LOAD_CONST               4 ('1')
                LOAD_CONST               4 ('1')
                LOAD_CONST               5 (('start', 'end'))
                BUILD_CONST_KEY_MAP      2
                BUILD_LIST               1
                CALL                     2
                STORE_FAST               9 (cover_ranges)

  64            LOAD_GLOBAL              7 (int + NULL)
                LOAD_FAST                4 (config_data)
                LOAD_ATTR                5 (get + NULL|self)
                LOAD_CONST               6 ('cover_scale')
                LOAD_CONST               7 (100)
                CALL                     2
                CALL                     1
                STORE_FAST              10 (cover_scale)

  65            LOAD_GLOBAL              7 (int + NULL)
                LOAD_FAST                4 (config_data)
                LOAD_ATTR                5 (get + NULL|self)
                LOAD_CONST               8 ('body_scale')
                LOAD_CONST               7 (100)
                CALL                     2
                CALL                     1
                STORE_FAST              11 (body_scale)

  67            LOAD_FAST                4 (config_data)
                LOAD_ATTR                5 (get + NULL|self)
                LOAD_CONST               9 ('body_exceptions')
                LOAD_CONST              10 ('')
                CALL                     2
                STORE_FAST              12 (body_exceptions_str)

  69            BUILD_LIST               0
                STORE_FAST              13 (exceptions)

  70            LOAD_FAST               12 (body_exceptions_str)
                TO_BOOL
                POP_JUMP_IF_FALSE       68 (to L11)

  71            LOAD_FAST               12 (body_exceptions_str)
                LOAD_ATTR                9 (split + NULL|self)
                LOAD_CONST              11 (',')
                CALL                     1
                GET_ITER
        L6:     FOR_ITER                47 (to L10)
                STORE_FAST              14 (x)

  72    L7:     NOP

  73    L8:     LOAD_FAST               13 (exceptions)
                LOAD_ATTR               11 (append + NULL|self)
                LOAD_GLOBAL              7 (int + NULL)
                LOAD_FAST               14 (x)
                LOAD_ATTR               13 (strip + NULL|self)
                CALL                     0
                CALL                     1
                LOAD_CONST              12 (1)
                BINARY_OP               10 (-)
                CALL                     1
                POP_TOP
        L9:     JUMP_BACKWARD           49 (to L6)

  71   L10:     END_FOR
                POP_TOP

  76   L11:     LOAD_FAST               26 (total_pages)
                BUILD_TUPLE              1
                LOAD_CONST              13 (<code object is_in_ranges at 0x000001FC0A7FD2A0, file "src\pdf_manager.py", line 76>)
                MAKE_FUNCTION
                SET_FUNCTION_ATTRIBUTE   8 (closure)
                STORE_FAST              15 (is_in_ranges)

  92            LOAD_GLOBAL             15 (range + NULL)
                LOAD_DEREF              26 (total_pages)
                CALL                     1
                GET_ITER
       L12:     EXTENDED_ARG             1
                FOR_ITER               307 (to L20)
                STORE_FAST              16 (i)

  93            LOAD_FAST                1 (doc)
                LOAD_FAST               16 (i)
                BINARY_SUBSCR
                STORE_FAST              17 (page)

  96            LOAD_FAST                6 (cover_bytes)
                POP_JUMP_IF_NONE       140 (to L13)
                LOAD_FAST               15 (is_in_ranges)
                PUSH_NULL
                LOAD_FAST               16 (i)
                LOAD_FAST                9 (cover_ranges)
                CALL                     2
                TO_BOOL
                POP_JUMP_IF_FALSE      126 (to L13)

  97            LOAD_CONST              14 (0.35)
                STORE_FAST              18 (BASE_FACTOR)

  98            LOAD_FAST                4 (config_data)
                LOAD_ATTR                5 (get + NULL|self)
                LOAD_CONST              15 ('cover_coords')
                LOAD_CONST              16 ((0, 0))
                CALL                     2
                UNPACK_SEQUENCE          2
                STORE_FAST              14 (x)
                STORE_FAST              19 (y)

  99            LOAD_FAST                2 (cover_img)
                LOAD_ATTR               16 (size)
                UNPACK_SEQUENCE          2
                STORE_FAST              20 (orig_w)
                STORE_FAST              21 (orig_h)

 100            LOAD_GLOBAL              7 (int + NULL)
                LOAD_FAST               20 (orig_w)
                LOAD_FAST               18 (BASE_FACTOR)
                BINARY_OP                5 (*)
                LOAD_FAST               10 (cover_scale)
                LOAD_CONST              17 (100.0)
                BINARY_OP               11 (/)
                BINARY_OP                5 (*)
                CALL                     1
                STORE_FAST              22 (w)

 101            LOAD_GLOBAL              7 (int + NULL)
                LOAD_FAST               21 (orig_h)
                LOAD_FAST               18 (BASE_FACTOR)
                BINARY_OP                5 (*)
                LOAD_FAST               10 (cover_scale)
                LOAD_CONST              17 (100.0)
                BINARY_OP               11 (/)
                BINARY_OP                5 (*)
                CALL                     1
                STORE_FAST              23 (h)

 102            LOAD_GLOBAL             18 (fitz)
                LOAD_ATTR               20 (Rect)
                PUSH_NULL
                LOAD_FAST               14 (x)
                LOAD_FAST               19 (y)
                LOAD_FAST               14 (x)
                LOAD_FAST               22 (w)
                BINARY_OP                0 (+)
                LOAD_FAST               19 (y)
                LOAD_FAST               23 (h)
                BINARY_OP                0 (+)
                CALL                     4
                STORE_FAST              24 (rect)

 103            LOAD_FAST               17 (page)
                LOAD_ATTR               23 (insert_image + NULL|self)
                LOAD_FAST               24 (rect)
                LOAD_FAST                6 (cover_bytes)
                LOAD_CONST              18 (True)
                LOAD_CONST              19 (('stream', 'keep_proportion'))
                CALL_KW                  3
                POP_TOP

 106   L13:     LOAD_FAST                7 (body_bytes)
       L14:     POP_JUMP_IF_NOT_NONE     2 (to L15)
                JUMP_BACKWARD          157 (to L12)
       L15:     LOAD_FAST               15 (is_in_ranges)
                PUSH_NULL
                LOAD_FAST               16 (i)
                LOAD_FAST                8 (body_ranges)
                CALL                     2
                TO_BOOL
       L16:     POP_JUMP_IF_TRUE         2 (to L17)
                JUMP_BACKWARD          173 (to L12)
       L17:     LOAD_FAST               16 (i)
                LOAD_FAST               13 (exceptions)
                CONTAINS_OP              1
       L18:     POP_JUMP_IF_TRUE         2 (to L19)
                JUMP_BACKWARD          181 (to L12)

 107   L19:     LOAD_CONST              14 (0.35)
                STORE_FAST              18 (BASE_FACTOR)

 108            LOAD_FAST                4 (config_data)
                LOAD_ATTR                5 (get + NULL|self)
                LOAD_CONST              20 ('body_coords')
                LOAD_CONST              16 ((0, 0))
                CALL                     2
                UNPACK_SEQUENCE          2
                STORE_FAST              14 (x)
                STORE_FAST              19 (y)

 109            LOAD_FAST                3 (body_img)
                LOAD_ATTR               16 (size)
                UNPACK_SEQUENCE          2
                STORE_FAST              20 (orig_w)
                STORE_FAST              21 (orig_h)

 110            LOAD_GLOBAL              7 (int + NULL)
                LOAD_FAST               20 (orig_w)
                LOAD_FAST               18 (BASE_FACTOR)
                BINARY_OP                5 (*)
                LOAD_FAST               11 (body_scale)
                LOAD_CONST              17 (100.0)
                BINARY_OP               11 (/)
                BINARY_OP                5 (*)
                CALL                     1
                STORE_FAST              22 (w)

 111            LOAD_GLOBAL              7 (int + NULL)
                LOAD_FAST               21 (orig_h)
                LOAD_FAST               18 (BASE_FACTOR)
                BINARY_OP                5 (*)
                LOAD_FAST               11 (body_scale)
                LOAD_CONST              17 (100.0)
                BINARY_OP               11 (/)
                BINARY_OP                5 (*)
                CALL                     1
                STORE_FAST              23 (h)

 112            LOAD_GLOBAL             18 (fitz)
                LOAD_ATTR               20 (Rect)
                PUSH_NULL
                LOAD_FAST               14 (x)
                LOAD_FAST               19 (y)
                LOAD_FAST               14 (x)
                LOAD_FAST               22 (w)
                BINARY_OP                0 (+)
                LOAD_FAST               19 (y)
                LOAD_FAST               23 (h)
                BINARY_OP                0 (+)
                CALL                     4
                STORE_FAST              24 (rect)

 113            LOAD_FAST               17 (page)
                LOAD_ATTR               23 (insert_image + NULL|self)
                LOAD_FAST               24 (rect)
                LOAD_FAST                7 (body_bytes)
                LOAD_CONST              18 (True)
                LOAD_CONST              19 (('stream', 'keep_proportion'))
                CALL_KW                  3
                POP_TOP
                EXTENDED_ARG             1
                JUMP_BACKWARD          310 (to L12)

  92   L20:     END_FOR
                POP_TOP

 115            LOAD_FAST                1 (doc)
                LOAD_ATTR               25 (save + NULL|self)
                LOAD_FAST                5 (output_path)
                CALL                     1
                POP_TOP

 116   L21:     RETURN_CONST            21 ((True, 'El PDF se guardó correctamente.'))

  --   L22:     PUSH_EXC_INFO

  74            POP_TOP
       L23:     POP_EXCEPT
                EXTENDED_ARG             1
                JUMP_BACKWARD          404 (to L6)

  --   L24:     COPY                     3
                POP_EXCEPT
                RERAISE                  1
       L25:     PUSH_EXC_INFO

 117            LOAD_GLOBAL             26 (Exception)
                CHECK_EXC_MATCH
                POP_JUMP_IF_FALSE       17 (to L30)
                STORE_FAST              25 (e)

 118   L26:     LOAD_CONST              22 (False)
                LOAD_CONST              23 ('Error al procesar y guardar: ')
                LOAD_FAST               25 (e)
                FORMAT_SIMPLE
                BUILD_STRING             2
                BUILD_TUPLE              2
       L27:     SWAP                     2
       L28:     POP_EXCEPT
                LOAD_CONST               1 (None)
                STORE_FAST              25 (e)
                DELETE_FAST             25 (e)
                RETURN_VALUE

  --   L29:     LOAD_CONST               1 (None)
                STORE_FAST              25 (e)
                DELETE_FAST             25 (e)
                RERAISE                  1

 117   L30:     RERAISE                  0

  --   L31:     COPY                     3
                POP_EXCEPT
                RERAISE                  1
ExceptionTable:
  L1 to L7 -> L25 [0]
  L8 to L9 -> L22 [1]
  L9 to L14 -> L25 [0]
  L15 to L16 -> L25 [0]
  L17 to L18 -> L25 [0]
  L19 to L21 -> L25 [0]
  L22 to L23 -> L24 [2] lasti
  L23 to L25 -> L25 [0]
  L25 to L26 -> L31 [1] lasti
  L26 to L27 -> L29 [1] lasti
  L27 to L28 -> L31 [1] lasti
  L29 to L31 -> L31 [1] lasti

Disassembly of <code object is_in_ranges at 0x000001FC0A7FD2A0, file "src\pdf_manager.py", line 76>:
  --            COPY_FREE_VARS           1

  76            RESUME                   0

  77            LOAD_FAST                1 (ranges_list)
                TO_BOOL
                POP_JUMP_IF_TRUE         1 (to L1)
                RETURN_CONST             1 (False)

  78    L1:     LOAD_FAST                1 (ranges_list)
                GET_ITER
        L2:     FOR_ITER               140 (to L11)
                STORE_FAST               2 (rng)

  79            NOP

  80    L3:     LOAD_GLOBAL              1 (int + NULL)
                LOAD_FAST                2 (rng)
                LOAD_ATTR                3 (get + NULL|self)
                LOAD_CONST               2 ('start')
                LOAD_CONST               3 (1)
                CALL                     2
                CALL                     1
                LOAD_CONST               3 (1)
                BINARY_OP               10 (-)
                STORE_FAST               3 (start)

  81            LOAD_GLOBAL              5 (str + NULL)
                LOAD_FAST                2 (rng)
                LOAD_ATTR                3 (get + NULL|self)
                LOAD_CONST               4 ('end')
                LOAD_CONST               5 ('final')
                CALL                     2
                CALL                     1
                LOAD_ATTR                7 (lower + NULL|self)
                CALL                     0
                STORE_FAST               4 (end_str)

  82            LOAD_FAST                4 (end_str)
                LOAD_CONST               5 ('final')
                COMPARE_OP              88 (bool(==))
                POP_JUMP_IF_TRUE        21 (to L4)
                LOAD_FAST                4 (end_str)
                LOAD_ATTR                9 (isdigit + NULL|self)
                CALL                     0
                TO_BOOL
                POP_JUMP_IF_TRUE         6 (to L5)

  83    L4:     LOAD_DEREF               6 (total_pages)
                LOAD_CONST               3 (1)
                BINARY_OP               10 (-)
                STORE_FAST               5 (end)
                JUMP_FORWARD            14 (to L6)

  85    L5:     LOAD_GLOBAL              1 (int + NULL)
                LOAD_FAST                4 (end_str)
                CALL                     1
                LOAD_CONST               3 (1)
                BINARY_OP               10 (-)
                STORE_FAST               5 (end)

  87    L6:     LOAD_FAST_LOAD_FAST     48 (start, page_idx)
                SWAP                     2
                COPY                     2
                COMPARE_OP              58 (bool(<=))
                POP_JUMP_IF_FALSE        6 (to L7)
                LOAD_FAST                5 (end)
                COMPARE_OP              58 (bool(<=))
                POP_JUMP_IF_FALSE        6 (to L10)
                JUMP_FORWARD             3 (to L9)
        L7:     POP_TOP
        L8:     JUMP_BACKWARD          138 (to L2)

  88    L9:     POP_TOP
                RETURN_CONST             6 (True)

  87   L10:     JUMP_BACKWARD          142 (to L2)

  78   L11:     END_FOR
                POP_TOP

  90            RETURN_CONST             1 (False)

  --   L12:     PUSH_EXC_INFO

  89            POP_TOP
       L13:     POP_EXCEPT
                JUMP_BACKWARD          150 (to L2)

  --   L14:     COPY                     3
                POP_EXCEPT
                RERAISE                  1
ExceptionTable:
  L3 to L8 -> L12 [1]
  L12 to L13 -> L14 [2] lasti

  --- CODE OBJ: <module> ---
  CONSTANTS: (0, None, ('Image',), <code object PDFManager at 0x000001FC0A712D30, file "src\pdf_manager.py", line 5>, 'PDFManager')
  NAMES: ('fitz', 'io', 'PIL', 'Image', 'PDFManager')
  VARNAMES: ()
  FREEVARS: ()

    --- CODE OBJ: PDFManager ---
    CONSTANTS: ('PDFManager', 5, <code object __init__ at 0x000001FC0A734B90, file "src\pdf_manager.py", line 6>, <code object load_pdf at 0x000001FC0A5D2290, file "src\pdf_manager.py", line 9>, <code object get_page_image at 0x000001FC0A61A3D0, file "src\pdf_manager.py", line 20>, <code object pil_to_bytes at 0x000001FC0A76D1B0, file "src\pdf_manager.py", line 38>, <code object process_and_save at 0x000001FC0A3726F0, file "src\pdf_manager.py", line 44>, (), None, (1.0,))
    NAMES: ('__name__', '__module__', '__qualname__', '__firstlineno__', '__init__', 'load_pdf', 'get_page_image', 'pil_to_bytes', 'process_and_save', '__static_attributes__')
    VARNAMES: ()
    FREEVARS: ()

      --- CODE OBJ: __init__ ---
      CONSTANTS: (None,)
      NAMES: ()
      VARNAMES: ('self',)
      FREEVARS: ()

      --- CODE OBJ: load_pdf ---
      CONSTANTS: ('\nCarga el PDF y devuelve el objeto documento y el número de páginas.\n', 'Error cargando PDF: ', None, (None, 0))
      NAMES: ('fitz', 'open', 'len', 'Exception', 'print')
      VARNAMES: ('self', 'pdf_path', 'doc', 'e')
      FREEVARS: ()

      --- CODE OBJ: get_page_image ---
      CONSTANTS: ('\nObtiene la imagen de una página específica para usar en CustomTkinter previsualización.\npage_num es 0-indexed en PyMuPDF.\nDevuelve un objeto PIL.Image\n', ('matrix',), 'RGB', 'Error generando imagen de página: ', None)
      NAMES: ('fitz', 'Matrix', 'get_pixmap', 'Image', 'frombytes', 'width', 'height', 'samples', 'Exception', 'print')
      VARNAMES: ('self', 'doc', 'page_num', 'zoom', 'page', 'mat', 'pix', 'img', 'e')
      FREEVARS: ()

      --- CODE OBJ: pil_to_bytes ---
      CONSTANTS: ('Convierte PIL Image a bytes para insertarlo en PDF. ', 'PNG', ('format',))
      NAMES: ('io', 'BytesIO', 'save', 'getvalue')
      VARNAMES: ('self', 'pil_image', 'img_byte_arr')
      FREEVARS: ()

      --- CODE OBJ: process_and_save ---
      CONSTANTS: ("\nAplica los sellos en el PDF original.\nconfig_data = dict con {\n    cover_page: <int>,\n    body_page_start: <int>,\n    body_page_end: <int o 'final'>,\n    cover_coords: (x, y),\n    body_coords: (x, y)\n}\n", None, 'body_ranges', 'cover_ranges', '1', ('start', 'end'), 'cover_scale', 100, 'body_scale', 'body_exceptions', '', ',', 1, <code object is_in_ranges at 0x000001FC0A7FD2A0, file "src\pdf_manager.py", line 76>, 0.35, 'cover_coords', (0, 0), 100.0, True, ('stream', 'keep_proportion'), 'body_coords', (True, 'El PDF se guardó correctamente.'), False, 'Error al procesar y guardar: ')
      NAMES: ('pil_to_bytes', 'len', 'get', 'int', 'split', 'append', 'strip', 'range', 'size', 'fitz', 'Rect', 'insert_image', 'save', 'Exception')
      VARNAMES: ('self', 'doc', 'cover_img', 'body_img', 'config_data', 'output_path', 'cover_bytes', 'body_bytes', 'body_ranges', 'cover_ranges', 'cover_scale', 'body_scale', 'body_exceptions_str', 'exceptions', 'x', 'is_in_ranges', 'i', 'page', 'BASE_FACTOR', 'y', 'orig_w', 'orig_h', 'w', 'h', 'rect', 'e')
      FREEVARS: ()

        --- CODE OBJ: is_in_ranges ---
        CONSTANTS: (None, False, 'start', 1, 'end', 'final', True)
        NAMES: ('int', 'get', 'str', 'lower', 'isdigit')
        VARNAMES: ('page_idx', 'ranges_list', 'rng', 'start', 'end_str', 'end')
        FREEVARS: ('total_pages',)
