  0           RESUME                   0

  1           LOAD_CONST               0 (0)
              LOAD_CONST               1 (('Image', 'ImageDraw', 'ImageFont'))
              IMPORT_NAME              0 (PIL)
              IMPORT_FROM              1 (Image)
              STORE_NAME               1 (Image)
              IMPORT_FROM              2 (ImageDraw)
              STORE_NAME               2 (ImageDraw)
              IMPORT_FROM              3 (ImageFont)
              STORE_NAME               3 (ImageFont)
              POP_TOP

  2           LOAD_CONST               0 (0)
              LOAD_CONST               2 (None)
              IMPORT_NAME              4 (os)
              STORE_NAME               4 (os)

  3           LOAD_CONST               0 (0)
              LOAD_CONST               2 (None)
              IMPORT_NAME              5 (re)
              STORE_NAME               5 (re)

  4           LOAD_CONST               0 (0)
              LOAD_CONST               3 (('relativedelta',))
              IMPORT_NAME              6 (dateutil.relativedelta)
              IMPORT_FROM              7 (relativedelta)
              STORE_NAME               7 (relativedelta)
              POP_TOP

  5           LOAD_CONST               0 (0)
              LOAD_CONST               4 (('datetime',))
              IMPORT_NAME              8 (datetime)
              IMPORT_FROM              8 (datetime)
              STORE_NAME               8 (datetime)
              POP_TOP

  7           LOAD_BUILD_CLASS
              PUSH_NULL
              LOAD_CONST               5 (<code object StampEngine at 0x000001FC0A723990, file "src\stamp_engine.py", line 7>)
              MAKE_FUNCTION
              LOAD_CONST               6 ('StampEngine')
              CALL                     2
              STORE_NAME               9 (StampEngine)
              RETURN_CONST             2 (None)

Disassembly of <code object StampEngine at 0x000001FC0A723990, file "src\stamp_engine.py", line 7>:
  7           RESUME                   0
              LOAD_NAME                0 (__name__)
              STORE_NAME               1 (__module__)
              LOAD_CONST               0 ('StampEngine')
              STORE_NAME               2 (__qualname__)
              LOAD_CONST               1 (7)
              STORE_NAME               3 (__firstlineno__)

  8           LOAD_CONST               2 (<code object __init__ at 0x000001FC0A734B90, file "src\stamp_engine.py", line 8>)
              MAKE_FUNCTION
              STORE_NAME               4 (__init__)

 11           LOAD_CONST               9 ((20, False))
              LOAD_CONST               3 (<code object _get_font at 0x000001FC0A5D2290, file "src\stamp_engine.py", line 11>)
              MAKE_FUNCTION
              SET_FUNCTION_ATTRIBUTE   1 (defaults)
              STORE_NAME               5 (_get_font)

 18           LOAD_CONST              10 ((None,))
              LOAD_CONST               5 (<code object generate_cover_stamp at 0x000001FC0A80B480, file "src\stamp_engine.py", line 18>)
              MAKE_FUNCTION
              SET_FUNCTION_ATTRIBUTE   1 (defaults)
              STORE_NAME               6 (generate_cover_stamp)

 80           LOAD_CONST              11 (('Ingeniero Electricista',))
              LOAD_CONST               6 (<code object generate_body_stamp at 0x000001FC0A3726F0, file "src\stamp_engine.py", line 80>)
              MAKE_FUNCTION
              SET_FUNCTION_ATTRIBUTE   1 (defaults)
              STORE_NAME               7 (generate_body_stamp)

138           LOAD_CONST              11 (('Ingeniero Electricista',))
              LOAD_CONST               7 (<code object get_body_stamp_size at 0x000001FC0A7FEAD0, file "src\stamp_engine.py", line 138>)
              MAKE_FUNCTION
              SET_FUNCTION_ATTRIBUTE   1 (defaults)
              STORE_NAME               8 (get_body_stamp_size)
              LOAD_CONST               8 (())
              STORE_NAME               9 (__static_attributes__)
              RETURN_CONST             4 (None)

Disassembly of <code object __init__ at 0x000001FC0A734B90, file "src\stamp_engine.py", line 8>:
  8           RESUME                   0

  9           RETURN_CONST             0 (None)

Disassembly of <code object _get_font at 0x000001FC0A5D2290, file "src\stamp_engine.py", line 11>:
  11           RESUME                   0

  12           LOAD_FAST                2 (bold)
               TO_BOOL
               POP_JUMP_IF_FALSE        2 (to L1)
               LOAD_CONST               1 ('C:/Windows/Fonts/arialbd.ttf')
               JUMP_FORWARD             1 (to L2)
       L1:     LOAD_CONST               2 ('C:/Windows/Fonts/arial.ttf')
       L2:     STORE_FAST               3 (font_path)

  13           NOP

  14   L3:     LOAD_GLOBAL              0 (ImageFont)
               LOAD_ATTR                2 (truetype)
               PUSH_NULL
               LOAD_FAST_LOAD_FAST     49 (font_path, size)
               CALL                     2
       L4:     RETURN_VALUE

  --   L5:     PUSH_EXC_INFO

  15           LOAD_GLOBAL              4 (IOError)
               CHECK_EXC_MATCH
               POP_JUMP_IF_FALSE       24 (to L7)
               POP_TOP

  16           LOAD_GLOBAL              0 (ImageFont)
               LOAD_ATTR                6 (load_default)
               PUSH_NULL
               CALL                     0
               SWAP                     2
       L6:     POP_EXCEPT
               RETURN_VALUE

  15   L7:     RERAISE                  0

  --   L8:     COPY                     3
               POP_EXCEPT
               RERAISE                  1
ExceptionTable:
  L3 to L4 -> L5 [0]
  L5 to L6 -> L8 [1] lasti
  L7 to L8 -> L8 [1] lasti

Disassembly of <code object generate_cover_stamp at 0x000001FC0A80B480, file "src\stamp_engine.py", line 18>:
  18            RESUME                   0

  23            LOAD_GLOBAL              0 (os)
                LOAD_ATTR                2 (path)
                LOAD_ATTR                5 (exists + NULL|self)
                LOAD_FAST                1 (base_img_path)
                CALL                     1
                TO_BOOL
                POP_JUMP_IF_TRUE        14 (to L1)

  24            LOAD_GLOBAL              7 (FileNotFoundError + NULL)
                LOAD_CONST               1 ('No se encontró la plantilla base: ')
                LOAD_FAST                1 (base_img_path)
                FORMAT_SIMPLE
                BUILD_STRING             2
                CALL                     1
                RAISE_VARARGS            1

  26    L1:     LOAD_GLOBAL              8 (Image)
                LOAD_ATTR               10 (open)
                PUSH_NULL
                LOAD_FAST                1 (base_img_path)
                CALL                     1
                LOAD_ATTR               13 (convert + NULL|self)
                LOAD_CONST               2 ('RGBA')
                CALL                     1
                STORE_FAST               5 (base_img)

  27            LOAD_GLOBAL             14 (ImageDraw)
                LOAD_ATTR               16 (Draw)
                PUSH_NULL
                LOAD_FAST                5 (base_img)
                CALL                     1
                STORE_FAST               6 (draw)

  28            LOAD_FAST                5 (base_img)
                LOAD_ATTR               18 (size)
                UNPACK_SEQUENCE          2
                STORE_FAST_STORE_FAST  120 (w, h)

  31            LOAD_CONST               3 ('')
                STORE_FAST               9 (end_date_str)

  32            NOP

  33    L2:     LOAD_GLOBAL             20 (datetime)
                LOAD_ATTR               22 (strptime)
                PUSH_NULL
                LOAD_FAST                3 (start_date_str)
                LOAD_CONST               4 ('%d/%m/%Y')
                CALL                     2
                STORE_FAST              10 (start_date)

  34            LOAD_FAST               10 (start_date)
                LOAD_GLOBAL             25 (relativedelta + NULL)
                LOAD_CONST               5 (2)
                LOAD_CONST               6 (('years',))
                CALL_KW                  1
                BINARY_OP                0 (+)
                STORE_FAST              11 (end_date)

  35            LOAD_FAST               11 (end_date)
                LOAD_ATTR               27 (strftime + NULL|self)
                LOAD_CONST               4 ('%d/%m/%Y')
                CALL                     1
                STORE_FAST               9 (end_date_str)

  47    L3:     LOAD_FAST                4 (layout_coords)
                POP_JUMP_IF_NOT_NONE     2 (to L4)
                BUILD_MAP                0
                STORE_FAST               4 (layout_coords)

  49    L4:     LOAD_FAST                4 (layout_coords)
                LOAD_ATTR               43 (get + NULL|self)
                LOAD_CONST              10 ('date_scale')
                CALL                     1
                COPY                     1
                TO_BOOL
                POP_JUMP_IF_TRUE         2 (to L5)
                POP_TOP
                LOAD_CONST              11 (100)
        L5:     STORE_FAST              14 (date_scale)

  50            LOAD_FAST                4 (layout_coords)
                LOAD_ATTR               43 (get + NULL|self)
                LOAD_CONST              12 ('sig_scale')
                CALL                     1
                COPY                     1
                TO_BOOL
                POP_JUMP_IF_TRUE         2 (to L6)
                POP_TOP
                LOAD_CONST              11 (100)
        L6:     STORE_FAST              15 (sig_scale)

  53            LOAD_FAST                4 (layout_coords)
                LOAD_ATTR               43 (get + NULL|self)
                LOAD_CONST              13 ('date1')
                CALL                     1
                COPY                     1
                TO_BOOL
                POP_JUMP_IF_TRUE        28 (to L7)
                POP_TOP
                LOAD_GLOBAL             35 (int + NULL)
                LOAD_FAST                7 (w)
                LOAD_CONST              14 (0.55)
                BINARY_OP                5 (*)
                CALL                     1
                LOAD_GLOBAL             35 (int + NULL)
                LOAD_FAST                8 (h)
                LOAD_CONST              15 (0.53)
                BINARY_OP                5 (*)
                CALL                     1
                BUILD_TUPLE              2
        L7:     STORE_FAST              16 (fecha_ini_coords)

  54            LOAD_FAST                4 (layout_coords)
                LOAD_ATTR               43 (get + NULL|self)
                LOAD_CONST              16 ('date2')
                CALL                     1
                COPY                     1
                TO_BOOL
                POP_JUMP_IF_TRUE        28 (to L8)
                POP_TOP
                LOAD_GLOBAL             35 (int + NULL)
                LOAD_FAST                7 (w)
                LOAD_CONST              14 (0.55)
                BINARY_OP                5 (*)
                CALL                     1
                LOAD_GLOBAL             35 (int + NULL)
                LOAD_FAST                8 (h)
                LOAD_CONST              17 (0.69)
                BINARY_OP                5 (*)
                CALL                     1
                BUILD_TUPLE              2
        L8:     STORE_FAST              17 (fecha_fin_coords)

  57            LOAD_GLOBAL             35 (int + NULL)
                LOAD_FAST                8 (h)
                LOAD_CONST              18 (0.08)
                BINARY_OP                5 (*)
                LOAD_FAST               14 (date_scale)
                LOAD_CONST              19 (100.0)
                BINARY_OP               11 (/)
                BINARY_OP                5 (*)
                CALL                     1
                STORE_FAST              18 (font_size)

  58            LOAD_FAST                0 (self)
                LOAD_ATTR               45 (_get_font + NULL|self)
                LOAD_FAST               18 (font_size)
                LOAD_CONST              20 (True)
                LOAD_CONST              21 (('bold',))
                CALL_KW                  2
                STORE_FAST              19 (font)

  59            LOAD_FAST                6 (draw)
                LOAD_ATTR               47 (text + NULL|self)
                LOAD_FAST               16 (fecha_ini_coords)
                LOAD_FAST                3 (start_date_str)
                LOAD_CONST              22 ('black')
                LOAD_FAST               19 (font)
                LOAD_CONST              23 (('fill', 'font'))
                CALL_KW                  4
                POP_TOP

  60            LOAD_FAST                6 (draw)
                LOAD_ATTR               47 (text + NULL|self)
                LOAD_FAST               17 (fecha_fin_coords)
                LOAD_FAST                9 (end_date_str)
                LOAD_CONST              22 ('black')
                LOAD_FAST               19 (font)
                LOAD_CONST              23 (('fill', 'font'))
                CALL_KW                  4
                POP_TOP

  63            LOAD_FAST                2 (signature_path)
                TO_BOOL
                EXTENDED_ARG             1
                POP_JUMP_IF_FALSE      280 (to L12)
                LOAD_GLOBAL              0 (os)
                LOAD_ATTR                2 (path)
                LOAD_ATTR                5 (exists + NULL|self)
                LOAD_FAST                2 (signature_path)
                CALL                     1
                TO_BOOL
                POP_JUMP_IF_FALSE      244 (to L12)

  64            NOP

  65    L9:     LOAD_GLOBAL              8 (Image)
                LOAD_ATTR               10 (open)
                PUSH_NULL
                LOAD_FAST                2 (signature_path)
                CALL                     1
                LOAD_ATTR               13 (convert + NULL|self)
                LOAD_CONST               2 ('RGBA')
                CALL                     1
                STORE_FAST              20 (signature)

  67            LOAD_GLOBAL             35 (int + NULL)
                LOAD_FAST                7 (w)
                LOAD_CONST              24 (0.35)
                BINARY_OP                5 (*)
                LOAD_FAST               15 (sig_scale)
                LOAD_CONST              19 (100.0)
                BINARY_OP               11 (/)
                BINARY_OP                5 (*)
                CALL                     1
                STORE_FAST              21 (max_width)

  68            LOAD_FAST               21 (max_width)
                LOAD_GLOBAL             49 (float + NULL)
                LOAD_FAST               20 (signature)
                LOAD_ATTR               18 (size)
                LOAD_CONST              25 (0)
                BINARY_SUBSCR
                CALL                     1
                BINARY_OP               11 (/)
                STORE_FAST              22 (ratio)

  69            LOAD_GLOBAL             35 (int + NULL)
                LOAD_GLOBAL             49 (float + NULL)
                LOAD_FAST               20 (signature)
                LOAD_ATTR               18 (size)
                LOAD_CONST              26 (1)
                BINARY_SUBSCR
                CALL                     1
                LOAD_GLOBAL             49 (float + NULL)
                LOAD_FAST               22 (ratio)
                CALL                     1
                BINARY_OP                5 (*)
                CALL                     1
                STORE_FAST              23 (new_height)

  70            LOAD_FAST               20 (signature)
                LOAD_ATTR               51 (resize + NULL|self)
                LOAD_FAST               21 (max_width)
                LOAD_GLOBAL             35 (int + NULL)
                LOAD_FAST               23 (new_height)
                CALL                     1
                BUILD_TUPLE              2
                LOAD_GLOBAL              8 (Image)
                LOAD_ATTR               52 (LANCZOS)
                CALL                     2
                STORE_FAST              20 (signature)

  73            LOAD_FAST                4 (layout_coords)
                LOAD_ATTR               43 (get + NULL|self)
                LOAD_CONST              27 ('sig')
                CALL                     1
                COPY                     1
                TO_BOOL
                POP_JUMP_IF_TRUE        28 (to L10)
                POP_TOP
                LOAD_GLOBAL             35 (int + NULL)
                LOAD_FAST                7 (w)
                LOAD_CONST              28 (0.1)
                BINARY_OP                5 (*)
                CALL                     1
                LOAD_GLOBAL             35 (int + NULL)
                LOAD_FAST                8 (h)
                LOAD_CONST              29 (0.7)
                BINARY_OP                5 (*)
                CALL                     1
                BUILD_TUPLE              2
       L10:     STORE_FAST              24 (sig_coords)

  74            LOAD_FAST                5 (base_img)
                LOAD_ATTR               55 (paste + NULL|self)
                LOAD_FAST               20 (signature)
                LOAD_FAST               24 (sig_coords)
                LOAD_FAST               20 (signature)
                LOAD_CONST              30 (('mask',))
                CALL_KW                  3
                POP_TOP

  78   L11:     LOAD_FAST                5 (base_img)
                RETURN_VALUE
       L12:     LOAD_FAST                5 (base_img)
                RETURN_VALUE

  --   L13:     PUSH_EXC_INFO

  36            LOAD_GLOBAL             28 (ValueError)
                CHECK_EXC_MATCH
                POP_JUMP_IF_FALSE      118 (to L23)
                POP_TOP

  37   L14:     NOP

  38   L15:     LOAD_GLOBAL             30 (re)
                LOAD_ATTR               32 (search)
                PUSH_NULL
                LOAD_CONST               7 ('\\d{4}')
                LOAD_FAST                3 (start_date_str)
                CALL                     2
                STORE_FAST              12 (match)

  39            LOAD_FAST               12 (match)
                TO_BOOL
                POP_JUMP_IF_FALSE       67 (to L17)

  40            LOAD_GLOBAL             35 (int + NULL)
                LOAD_FAST               12 (match)
                LOAD_ATTR               37 (group + NULL|self)
                CALL                     0
                CALL                     1
                STORE_FAST              13 (year)

  41            LOAD_FAST                3 (start_date_str)
                LOAD_ATTR               39 (replace + NULL|self)
                LOAD_GLOBAL             41 (str + NULL)
                LOAD_FAST               13 (year)
                CALL                     1
                LOAD_GLOBAL             41 (str + NULL)
                LOAD_FAST               13 (year)
                LOAD_CONST               5 (2)
                BINARY_OP                0 (+)
                CALL                     1
                CALL                     2
                STORE_FAST               9 (end_date_str)
       L16:     POP_EXCEPT
                EXTENDED_ARG             2
                JUMP_BACKWARD_NO_INTERRUPT 631 (to L3)

  43   L17:     LOAD_FAST                3 (start_date_str)
                LOAD_CONST               8 (' + 2 años')
                BINARY_OP                0 (+)
                STORE_FAST               9 (end_date_str)
       L18:     POP_EXCEPT
                EXTENDED_ARG             2
                JUMP_BACKWARD_NO_INTERRUPT 639 (to L3)

  --   L19:     PUSH_EXC_INFO

  44            POP_TOP

  45            LOAD_CONST               3 ('')
                STORE_FAST               9 (end_date_str)
       L20:     POP_EXCEPT
       L21:     POP_EXCEPT
                EXTENDED_ARG             2
                JUMP_BACKWARD_NO_INTERRUPT 647 (to L3)

  --   L22:     COPY                     3
                POP_EXCEPT
                RERAISE                  1

  36   L23:     RERAISE                  0

  --   L24:     COPY                     3
                POP_EXCEPT
                RERAISE                  1
       L25:     PUSH_EXC_INFO

  75            LOAD_GLOBAL             56 (Exception)
                CHECK_EXC_MATCH
                POP_JUMP_IF_FALSE       25 (to L29)
                STORE_FAST              25 (e)

  76   L26:     LOAD_GLOBAL             59 (print + NULL)
                LOAD_CONST              31 ('Error procesando firma para carátula: ')
                LOAD_FAST               25 (e)
                FORMAT_SIMPLE
                BUILD_STRING             2
                CALL                     1
                POP_TOP
       L27:     POP_EXCEPT
                LOAD_CONST               9 (None)
                STORE_FAST              25 (e)
                DELETE_FAST             25 (e)

  78            LOAD_FAST                5 (base_img)
                RETURN_VALUE

  --   L28:     LOAD_CONST               9 (None)
                STORE_FAST              25 (e)
                DELETE_FAST             25 (e)
                RERAISE                  1

  75   L29:     RERAISE                  0

  --   L30:     COPY                     3
                POP_EXCEPT
                RERAISE                  1
ExceptionTable:
  L2 to L3 -> L13 [0]
  L9 to L11 -> L25 [0]
  L13 to L14 -> L24 [1] lasti
  L15 to L16 -> L19 [1]
  L17 to L18 -> L19 [1]
  L19 to L20 -> L22 [2] lasti
  L20 to L21 -> L24 [1] lasti
  L22 to L24 -> L24 [1] lasti
  L25 to L26 -> L30 [1] lasti
  L26 to L27 -> L28 [1] lasti
  L28 to L30 -> L30 [1] lasti

Disassembly of <code object generate_body_stamp at 0x000001FC0A3726F0, file "src\stamp_engine.py", line 80>:
  --            MAKE_CELL               20 (canvas_width)
                MAKE_CELL               21 (draw)

  80            RESUME                   0

  85            LOAD_CONST               1 (800)
                STORE_DEREF             20 (canvas_width)

  86            LOAD_CONST               2 (500)
                STORE_FAST               5 (canvas_height)

  87            LOAD_GLOBAL              0 (Image)
                LOAD_ATTR                2 (new)
                PUSH_NULL
                LOAD_CONST               3 ('RGBA')
                LOAD_DEREF              20 (canvas_width)
                LOAD_FAST                5 (canvas_height)
                BUILD_TUPLE              2
                LOAD_CONST               4 ((255, 255, 255, 0))
                CALL                     3
                STORE_FAST               6 (stamp)

  88            LOAD_GLOBAL              4 (ImageDraw)
                LOAD_ATTR                6 (Draw)
                PUSH_NULL
                LOAD_FAST                6 (stamp)
                CALL                     1
                STORE_DEREF             21 (draw)

  90            LOAD_FAST                0 (self)
                LOAD_ATTR                9 (_get_font + NULL|self)
                LOAD_CONST               5 (40)
                LOAD_CONST               6 (True)
                LOAD_CONST               7 (('bold',))
                CALL_KW                  2
                STORE_FAST               7 (font_name)

  91            LOAD_FAST                0 (self)
                LOAD_ATTR                9 (_get_font + NULL|self)
                LOAD_CONST               8 (35)
                LOAD_CONST               6 (True)
                LOAD_CONST               7 (('bold',))
                CALL_KW                  2
                STORE_FAST               8 (font_title)

  92            LOAD_FAST                0 (self)
                LOAD_ATTR                9 (_get_font + NULL|self)
                LOAD_CONST               8 (35)
                LOAD_CONST               6 (True)
                LOAD_CONST               7 (('bold',))
                CALL_KW                  2
                STORE_FAST               9 (font_cip)

  94            LOAD_CONST               9 (20)
                STORE_FAST              10 (y_offset)

  96            LOAD_FAST                1 (signature_path)
                TO_BOOL
                POP_JUMP_IF_FALSE      250 (to L2)
                LOAD_GLOBAL             10 (os)
                LOAD_ATTR               12 (path)
                LOAD_ATTR               15 (exists + NULL|self)
                LOAD_FAST                1 (signature_path)
                CALL                     1
                TO_BOOL
                POP_JUMP_IF_FALSE      214 (to L2)

  97            NOP

  98    L1:     LOAD_GLOBAL              0 (Image)
                LOAD_ATTR               16 (open)
                PUSH_NULL
                LOAD_FAST                1 (signature_path)
                CALL                     1
                LOAD_ATTR               19 (convert + NULL|self)
                LOAD_CONST               3 ('RGBA')
                CALL                     1
                STORE_FAST              11 (signature)

  99            LOAD_CONST              10 (400)
                STORE_FAST              12 (max_width)

 100            LOAD_FAST               12 (max_width)
                LOAD_GLOBAL             21 (float + NULL)
                LOAD_FAST               11 (signature)
                LOAD_ATTR               22 (size)
                LOAD_CONST              11 (0)
                BINARY_SUBSCR
                CALL                     1
                BINARY_OP               11 (/)
                STORE_FAST              13 (ratio)

 101            LOAD_GLOBAL             25 (int + NULL)
                LOAD_GLOBAL             21 (float + NULL)
                LOAD_FAST               11 (signature)
                LOAD_ATTR               22 (size)
                LOAD_CONST              12 (1)
                BINARY_SUBSCR
                CALL                     1
                LOAD_GLOBAL             21 (float + NULL)
                LOAD_FAST               13 (ratio)
                CALL                     1
                BINARY_OP                5 (*)
                CALL                     1
                STORE_FAST              14 (new_height)

 102            LOAD_FAST               11 (signature)
                LOAD_ATTR               27 (resize + NULL|self)
                LOAD_FAST               12 (max_width)
                LOAD_GLOBAL             25 (int + NULL)
                LOAD_FAST               14 (new_height)
                CALL                     1
                BUILD_TUPLE              2
                LOAD_GLOBAL              0 (Image)
                LOAD_ATTR               28 (LANCZOS)
                CALL                     2
                STORE_FAST              11 (signature)

 104            LOAD_DEREF              20 (canvas_width)
                LOAD_FAST               11 (signature)
                LOAD_ATTR               22 (size)
                LOAD_CONST              11 (0)
                BINARY_SUBSCR
                BINARY_OP               10 (-)
                LOAD_CONST              13 (2)
                BINARY_OP                2 (//)
                STORE_FAST              15 (x_pos)

 105            LOAD_FAST                6 (stamp)
                LOAD_ATTR               31 (paste + NULL|self)
                LOAD_FAST_LOAD_FAST    191 (signature, x_pos)
                LOAD_FAST               10 (y_offset)
                BUILD_TUPLE              2
                LOAD_FAST               11 (signature)
                LOAD_CONST              14 (('mask',))
                CALL_KW                  3
                POP_TOP

 106            LOAD_FAST_LOAD_FAST    171 (y_offset, signature)
                LOAD_ATTR               22 (size)
                LOAD_CONST              12 (1)
                BINARY_SUBSCR
                LOAD_CONST               9 (20)
                BINARY_OP                0 (+)
                BINARY_OP               13 (+=)
                STORE_FAST              10 (y_offset)

 112    L2:     LOAD_FAST               20 (canvas_width)
                LOAD_FAST               21 (draw)
                BUILD_TUPLE              2
                LOAD_CONST              18 (<code object draw_centered_text at 0x000001FC0A5D3CB0, file "src\stamp_engine.py", line 112>)
                MAKE_FUNCTION
                SET_FUNCTION_ATTRIBUTE   8 (closure)
                STORE_FAST              17 (draw_centered_text)

 119            LOAD_FAST                2 (name)
                TO_BOOL
                POP_JUMP_IF_FALSE       12 (to L3)

 120            LOAD_FAST               10 (y_offset)
                LOAD_FAST               17 (draw_centered_text)
                PUSH_NULL
                LOAD_FAST_LOAD_FAST     39 (name, font_name)
                LOAD_FAST               10 (y_offset)
                CALL                     3
                BINARY_OP               13 (+=)
                STORE_FAST              10 (y_offset)

 122    L3:     LOAD_FAST                4 (tipo)
                TO_BOOL
                POP_JUMP_IF_FALSE       13 (to L4)

 123            LOAD_FAST               10 (y_offset)
                LOAD_FAST               17 (draw_centered_text)
                PUSH_NULL
                LOAD_FAST_LOAD_FAST     72 (tipo, font_title)
                LOAD_FAST               10 (y_offset)
                CALL                     3
                BINARY_OP               13 (+=)
                STORE_FAST              10 (y_offset)
                JUMP_FORWARD            12 (to L5)

 125    L4:     LOAD_FAST               10 (y_offset)
                LOAD_FAST               17 (draw_centered_text)
                PUSH_NULL
                LOAD_CONST              19 ('Ingeniero Electricista')
                LOAD_FAST_LOAD_FAST    138 (font_title, y_offset)
                CALL                     3
                BINARY_OP               13 (+=)
                STORE_FAST              10 (y_offset)

 127    L5:     LOAD_FAST                3 (cip)
                TO_BOOL
                POP_JUMP_IF_FALSE       17 (to L6)

 128            LOAD_CONST              20 ('N° CIP ')
                LOAD_FAST                3 (cip)
                FORMAT_SIMPLE
                BUILD_STRING             2
                STORE_FAST              18 (cip_text)

 129            LOAD_FAST               10 (y_offset)
                LOAD_FAST               17 (draw_centered_text)
                PUSH_NULL
                LOAD_FAST               18 (cip_text)
                LOAD_FAST_LOAD_FAST    154 (font_cip, y_offset)
                CALL                     3
                BINARY_OP               13 (+=)
                STORE_FAST              10 (y_offset)

 132    L6:     LOAD_FAST                6 (stamp)
                LOAD_ATTR               37 (getbbox + NULL|self)
                CALL                     0
                STORE_FAST              19 (bbox)

 133            LOAD_FAST               19 (bbox)
                TO_BOOL
                POP_JUMP_IF_FALSE       17 (to L7)

 134            LOAD_FAST                6 (stamp)
                LOAD_ATTR               39 (crop + NULL|self)
                LOAD_FAST               19 (bbox)
                CALL                     1
                STORE_FAST               6 (stamp)

 136    L7:     LOAD_FAST                6 (stamp)
                RETURN_VALUE

  --    L8:     PUSH_EXC_INFO

 107            LOAD_GLOBAL             32 (Exception)
                CHECK_EXC_MATCH
                POP_JUMP_IF_FALSE       29 (to L12)
                STORE_FAST              16 (e)

 108    L9:     LOAD_GLOBAL             35 (print + NULL)
                LOAD_CONST              15 ('Error cargando firma Sello 2: ')
                LOAD_FAST               16 (e)
                FORMAT_SIMPLE
                BUILD_STRING             2
                CALL                     1
                POP_TOP

 109            LOAD_FAST               10 (y_offset)
                LOAD_CONST              16 (50)
                BINARY_OP               13 (+=)
                STORE_FAST              10 (y_offset)
       L10:     POP_EXCEPT
                LOAD_CONST              17 (None)
                STORE_FAST              16 (e)
                DELETE_FAST             16 (e)
                JUMP_BACKWARD_NO_INTERRUPT 158 (to L2)

  --   L11:     LOAD_CONST              17 (None)
                STORE_FAST              16 (e)
                DELETE_FAST             16 (e)
                RERAISE                  1

 107   L12:     RERAISE                  0

  --   L13:     COPY                     3
                POP_EXCEPT
                RERAISE                  1
ExceptionTable:
  L1 to L2 -> L8 [0]
  L8 to L9 -> L13 [1] lasti
  L9 to L10 -> L11 [1] lasti
  L11 to L13 -> L13 [1] lasti

Disassembly of <code object draw_centered_text at 0x000001FC0A5D3CB0, file "src\stamp_engine.py", line 112>:
  --           COPY_FREE_VARS           2

 112           RESUME                   0

 113           LOAD_DEREF               7 (draw)
               LOAD_ATTR                1 (textbbox + NULL|self)
               LOAD_CONST               1 ((0, 0))
               LOAD_FAST_LOAD_FAST      1 (text, font)
               LOAD_CONST               2 (('font',))
               CALL_KW                  3
               STORE_FAST               3 (bbox)

 114           LOAD_FAST                3 (bbox)
               LOAD_CONST               3 (2)
               BINARY_SUBSCR
               LOAD_FAST                3 (bbox)
               LOAD_CONST               4 (0)
               BINARY_SUBSCR
               BINARY_OP               10 (-)
               STORE_FAST               4 (w)

 115           LOAD_DEREF               6 (canvas_width)
               LOAD_FAST                4 (w)
               BINARY_OP               10 (-)
               LOAD_CONST               3 (2)
               BINARY_OP                2 (//)
               STORE_FAST               5 (x)

 116           LOAD_DEREF               7 (draw)
               LOAD_ATTR                3 (text + NULL|self)
               LOAD_FAST_LOAD_FAST     82 (x, y)
               BUILD_TUPLE              2
               LOAD_FAST                0 (text)
               LOAD_CONST               5 ('black')
               LOAD_FAST                1 (font)
               LOAD_CONST               6 (('fill', 'font'))
               CALL_KW                  4
               POP_TOP

 117           LOAD_FAST                3 (bbox)
               LOAD_CONST               7 (3)
               BINARY_SUBSCR
               LOAD_FAST                3 (bbox)
               LOAD_CONST               8 (1)
               BINARY_SUBSCR
               BINARY_OP               10 (-)
               LOAD_CONST               9 (15)
               BINARY_OP                0 (+)
               RETURN_VALUE

Disassembly of <code object get_body_stamp_size at 0x000001FC0A7FEAD0, file "src\stamp_engine.py", line 138>:
 138            RESUME                   0

 144            LOAD_CONST               1 (800)
                STORE_FAST               5 (canvas_width)

 145            LOAD_CONST               2 (20)
                STORE_FAST               6 (y_offset)

 146            LOAD_CONST               3 (0)
                STORE_FAST               7 (max_content_width)

 149            LOAD_FAST                1 (signature_path)
                TO_BOOL
                POP_JUMP_IF_FALSE      139 (to L4)
                LOAD_GLOBAL              0 (os)
                LOAD_ATTR                2 (path)
                LOAD_ATTR                5 (exists + NULL|self)
                LOAD_FAST                1 (signature_path)
                CALL                     1
                TO_BOOL
                POP_JUMP_IF_FALSE      103 (to L4)

 150            NOP

 152    L1:     LOAD_GLOBAL              6 (Image)
                LOAD_ATTR                8 (open)
                PUSH_NULL
                LOAD_FAST                1 (signature_path)
                CALL                     1
                BEFORE_WITH
        L2:     STORE_FAST               8 (tmp_sig)

 153            LOAD_FAST                8 (tmp_sig)
                LOAD_ATTR               10 (size)
                UNPACK_SEQUENCE          2
                STORE_FAST_STORE_FAST  154 (sig_w, sig_h)

 154            LOAD_CONST               4 (400)
                STORE_FAST              11 (max_width)

 155            LOAD_FAST               11 (max_width)
                LOAD_GLOBAL             13 (float + NULL)
                LOAD_FAST                9 (sig_w)
                CALL                     1
                BINARY_OP               11 (/)
                STORE_FAST              12 (ratio)

 156            LOAD_GLOBAL             15 (int + NULL)
                LOAD_GLOBAL             13 (float + NULL)
                LOAD_FAST               10 (sig_h)
                CALL                     1
                LOAD_FAST               12 (ratio)
                BINARY_OP                5 (*)
                CALL                     1
                STORE_FAST              13 (new_height)

 157            LOAD_FAST_LOAD_FAST    109 (y_offset, new_height)
                LOAD_CONST               2 (20)
                BINARY_OP                0 (+)
                BINARY_OP               13 (+=)
                STORE_FAST               6 (y_offset)

 158            LOAD_GLOBAL             17 (max + NULL)
                LOAD_FAST_LOAD_FAST    123 (max_content_width, max_width)
                CALL                     2
                STORE_FAST               7 (max_content_width)

 152    L3:     LOAD_CONST               5 (None)
                LOAD_CONST               5 (None)
                LOAD_CONST               5 (None)
                CALL                     2
                POP_TOP

 163    L4:     LOAD_FAST                0 (self)
                LOAD_ATTR               19 (_get_font + NULL|self)
                LOAD_CONST               7 (40)
                LOAD_CONST               8 (True)
                LOAD_CONST               9 (('bold',))
                CALL_KW                  2
                STORE_FAST              14 (font_name)

 164            LOAD_FAST                0 (self)
                LOAD_ATTR               19 (_get_font + NULL|self)
                LOAD_CONST              10 (35)
                LOAD_CONST               8 (True)
                LOAD_CONST               9 (('bold',))
                CALL_KW                  2
                STORE_FAST              15 (font_title)

 165            LOAD_FAST                0 (self)
                LOAD_ATTR               19 (_get_font + NULL|self)
                LOAD_CONST              10 (35)
                LOAD_CONST               8 (True)
                LOAD_CONST               9 (('bold',))
                CALL_KW                  2
                STORE_FAST              16 (font_cip)

 169            LOAD_CONST              11 (<code object get_text_size at 0x000001FC0A5D3310, file "src\stamp_engine.py", line 169>)
                MAKE_FUNCTION
                STORE_FAST              17 (get_text_size)

 175            LOAD_FAST                2 (name)
                TO_BOOL
                POP_JUMP_IF_FALSE       31 (to L5)

 176            LOAD_FAST               17 (get_text_size)
                PUSH_NULL
                LOAD_FAST_LOAD_FAST     46 (name, font_name)
                CALL                     2
                UNPACK_SEQUENCE          2
                STORE_FAST              18 (tw)
                STORE_FAST              19 (th)

 177            LOAD_GLOBAL             17 (max + NULL)
                LOAD_FAST                7 (max_content_width)
                LOAD_FAST               18 (tw)
                CALL                     2
                STORE_FAST               7 (max_content_width)

 178            LOAD_FAST                6 (y_offset)
                LOAD_FAST               19 (th)
                LOAD_CONST              12 (15)
                BINARY_OP                0 (+)
                BINARY_OP               13 (+=)
                STORE_FAST               6 (y_offset)

 180    L5:     LOAD_FAST                4 (tipo)
                TO_BOOL
                POP_JUMP_IF_FALSE       12 (to L6)

 181            LOAD_FAST               17 (get_text_size)
                PUSH_NULL
                LOAD_FAST_LOAD_FAST     79 (tipo, font_title)
                CALL                     2
                UNPACK_SEQUENCE          2
                STORE_FAST              18 (tw)
                STORE_FAST              19 (th)
                JUMP_FORWARD            12 (to L7)

 183    L6:     LOAD_FAST               17 (get_text_size)
                PUSH_NULL
                LOAD_CONST              13 ('Ingeniero Electricista')
                LOAD_FAST               15 (font_title)
                CALL                     2
                UNPACK_SEQUENCE          2
                STORE_FAST              18 (tw)
                STORE_FAST              19 (th)

 185    L7:     LOAD_GLOBAL             17 (max + NULL)
                LOAD_FAST                7 (max_content_width)
                LOAD_FAST               18 (tw)
                CALL                     2
                STORE_FAST               7 (max_content_width)

 186            LOAD_FAST                6 (y_offset)
                LOAD_FAST               19 (th)
                LOAD_CONST              12 (15)
                BINARY_OP                0 (+)
                BINARY_OP               13 (+=)
                STORE_FAST               6 (y_offset)

 188            LOAD_FAST                3 (cip)
                TO_BOOL
                POP_JUMP_IF_FALSE       35 (to L8)

 189            LOAD_FAST               17 (get_text_size)
                PUSH_NULL
                LOAD_CONST              14 ('N° CIP ')
                LOAD_FAST                3 (cip)
                FORMAT_SIMPLE
                BUILD_STRING             2
                LOAD_FAST               16 (font_cip)
                CALL                     2
                UNPACK_SEQUENCE          2
                STORE_FAST              18 (tw)
                STORE_FAST              19 (th)

 190            LOAD_GLOBAL             17 (max + NULL)
                LOAD_FAST                7 (max_content_width)
                LOAD_FAST               18 (tw)
                CALL                     2
                STORE_FAST               7 (max_content_width)

 191            LOAD_FAST                6 (y_offset)
                LOAD_FAST               19 (th)
                LOAD_CONST              12 (15)
                BINARY_OP                0 (+)
                BINARY_OP               13 (+=)
                STORE_FAST               6 (y_offset)

 193    L8:     LOAD_FAST                6 (y_offset)
                STORE_FAST              20 (final_height)

 194            LOAD_FAST                7 (max_content_width)
                LOAD_FAST               20 (final_height)
                BUILD_TUPLE              2
                RETURN_VALUE

 152    L9:     PUSH_EXC_INFO
                WITH_EXCEPT_START
                TO_BOOL
                POP_JUMP_IF_TRUE         1 (to L10)
                RERAISE                  2
       L10:     POP_TOP
       L11:     POP_EXCEPT
                POP_TOP
                POP_TOP
       L12:     JUMP_BACKWARD_NO_INTERRUPT 202 (to L4)

  --   L13:     COPY                     3
                POP_EXCEPT
                RERAISE                  1
       L14:     PUSH_EXC_INFO

 159            POP_TOP

 160            LOAD_FAST                6 (y_offset)
                LOAD_CONST               6 (50)
                BINARY_OP               13 (+=)
                STORE_FAST               6 (y_offset)
       L15:     POP_EXCEPT
                JUMP_BACKWARD_NO_INTERRUPT 214 (to L4)

  --   L16:     COPY                     3
                POP_EXCEPT
                RERAISE                  1
ExceptionTable:
  L1 to L2 -> L14 [0]
  L2 to L3 -> L9 [1] lasti
  L3 to L4 -> L14 [0]
  L9 to L11 -> L13 [3] lasti
  L11 to L12 -> L14 [0]
  L13 to L14 -> L14 [0]
  L14 to L15 -> L16 [1] lasti

Disassembly of <code object get_text_size at 0x000001FC0A5D3310, file "src\stamp_engine.py", line 169>:
169           RESUME                   0

170           LOAD_GLOBAL              1 (hasattr + NULL)
              LOAD_FAST                1 (font)
              LOAD_CONST               1 ('getbbox')
              CALL                     2
              TO_BOOL
              POP_JUMP_IF_FALSE       39 (to L1)

171           LOAD_FAST                1 (font)
              LOAD_ATTR                3 (getbbox + NULL|self)
              LOAD_FAST                0 (text)
              CALL                     1
              STORE_FAST               2 (bbox)

172           LOAD_FAST                2 (bbox)
              LOAD_CONST               2 (2)
              BINARY_SUBSCR
              LOAD_FAST                2 (bbox)
              LOAD_CONST               3 (0)
              BINARY_SUBSCR
              BINARY_OP               10 (-)
              LOAD_FAST                2 (bbox)
              LOAD_CONST               4 (3)
              BINARY_SUBSCR
              LOAD_FAST                2 (bbox)
              LOAD_CONST               5 (1)
              BINARY_SUBSCR
              BINARY_OP               10 (-)
              BUILD_TUPLE              2
              RETURN_VALUE

173   L1:     LOAD_FAST                1 (font)
              LOAD_ATTR                5 (getsize + NULL|self)
              LOAD_FAST                0 (text)
              CALL                     1
              RETURN_VALUE

  --- CODE OBJ: <module> ---
  CONSTANTS: (0, ('Image', 'ImageDraw', 'ImageFont'), None, ('relativedelta',), ('datetime',), <code object StampEngine at 0x000001FC0A723990, file "src\stamp_engine.py", line 7>, 'StampEngine')
  NAMES: ('PIL', 'Image', 'ImageDraw', 'ImageFont', 'os', 're', 'dateutil.relativedelta', 'relativedelta', 'datetime', 'StampEngine')
  VARNAMES: ()
  FREEVARS: ()

    --- CODE OBJ: StampEngine ---
    CONSTANTS: ('StampEngine', 7, <code object __init__ at 0x000001FC0A734B90, file "src\stamp_engine.py", line 8>, <code object _get_font at 0x000001FC0A5D2290, file "src\stamp_engine.py", line 11>, None, <code object generate_cover_stamp at 0x000001FC0A80B480, file "src\stamp_engine.py", line 18>, <code object generate_body_stamp at 0x000001FC0A3726F0, file "src\stamp_engine.py", line 80>, <code object get_body_stamp_size at 0x000001FC0A7FEAD0, file "src\stamp_engine.py", line 138>, (), (20, False), (None,), ('Ingeniero Electricista',))
    NAMES: ('__name__', '__module__', '__qualname__', '__firstlineno__', '__init__', '_get_font', 'generate_cover_stamp', 'generate_body_stamp', 'get_body_stamp_size', '__static_attributes__')
    VARNAMES: ()
    FREEVARS: ()

      --- CODE OBJ: __init__ ---
      CONSTANTS: (None,)
      NAMES: ()
      VARNAMES: ('self',)
      FREEVARS: ()

      --- CODE OBJ: _get_font ---
      CONSTANTS: (None, 'C:/Windows/Fonts/arialbd.ttf', 'C:/Windows/Fonts/arial.ttf')
      NAMES: ('ImageFont', 'truetype', 'IOError', 'load_default')
      VARNAMES: ('self', 'size', 'bold', 'font_path')
      FREEVARS: ()

      --- CODE OBJ: generate_cover_stamp ---
      CONSTANTS: ('\nSello 1: Carátula\nCombina la base_img_path con la signature_path, y dibuja fechas de inicio y fin.\n', 'No se encontró la plantilla base: ', 'RGBA', '', '%d/%m/%Y', 2, ('years',), '\\d{4}', ' + 2 años', None, 'date_scale', 100, 'sig_scale', 'date1', 0.55, 0.53, 'date2', 0.69, 0.08, 100.0, True, ('bold',), 'black', ('fill', 'font'), 0.35, 0, 1, 'sig', 0.1, 0.7, ('mask',), 'Error procesando firma para carátula: ')
      NAMES: ('os', 'path', 'exists', 'FileNotFoundError', 'Image', 'open', 'convert', 'ImageDraw', 'Draw', 'size', 'datetime', 'strptime', 'relativedelta', 'strftime', 'ValueError', 're', 'search', 'int', 'group', 'replace', 'str', 'get', '_get_font', 'text', 'float', 'resize', 'LANCZOS', 'paste', 'Exception', 'print')
      VARNAMES: ('self', 'base_img_path', 'signature_path', 'start_date_str', 'layout_coords', 'base_img', 'draw', 'w', 'h', 'end_date_str', 'start_date', 'end_date', 'match', 'year', 'date_scale', 'sig_scale', 'fecha_ini_coords', 'fecha_fin_coords', 'font_size', 'font', 'signature', 'max_width', 'ratio', 'new_height', 'sig_coords', 'e')
      FREEVARS: ()

      --- CODE OBJ: generate_body_stamp ---
      CONSTANTS: ('\nSello 2: Resto de hojas (Composición Libre)\n', 800, 500, 'RGBA', (255, 255, 255, 0), 40, True, ('bold',), 35, 20, 400, 0, 1, 2, ('mask',), 'Error cargando firma Sello 2: ', 50, None, <code object draw_centered_text at 0x000001FC0A5D3CB0, file "src\stamp_engine.py", line 112>, 'Ingeniero Electricista', 'N° CIP ')
      NAMES: ('Image', 'new', 'ImageDraw', 'Draw', '_get_font', 'os', 'path', 'exists', 'open', 'convert', 'float', 'size', 'int', 'resize', 'LANCZOS', 'paste', 'Exception', 'print', 'getbbox', 'crop')
      VARNAMES: ('self', 'signature_path', 'name', 'cip', 'tipo', 'canvas_height', 'stamp', 'font_name', 'font_title', 'font_cip', 'y_offset', 'signature', 'max_width', 'ratio', 'new_height', 'x_pos', 'e', 'draw_centered_text', 'cip_text', 'bbox')
      FREEVARS: ()

        --- CODE OBJ: draw_centered_text ---
        CONSTANTS: (None, (0, 0), ('font',), 2, 0, 'black', ('fill', 'font'), 3, 1, 15)
        NAMES: ('textbbox', 'text')
        VARNAMES: ('text', 'font', 'y', 'bbox', 'w', 'x')
        FREEVARS: ('canvas_width', 'draw')

      --- CODE OBJ: get_body_stamp_size ---
      CONSTANTS: ('\nVersión optimizada que simula el cálculo matemático del ancho x alto\npara el Sello 2 sin renderizar gráficos en Pillow.\nAhorra sobrecarga de CPU en GUI Canvas previsualizaciones.\n', 800, 20, 0, 400, None, 50, 40, True, ('bold',), 35, <code object get_text_size at 0x000001FC0A5D3310, file "src\stamp_engine.py", line 169>, 15, 'Ingeniero Electricista', 'N° CIP ')
      NAMES: ('os', 'path', 'exists', 'Image', 'open', 'size', 'float', 'int', 'max', '_get_font')
      VARNAMES: ('self', 'signature_path', 'name', 'cip', 'tipo', 'canvas_width', 'y_offset', 'max_content_width', 'tmp_sig', 'sig_w', 'sig_h', 'max_width', 'ratio', 'new_height', 'font_name', 'font_title', 'font_cip', 'get_text_size', 'tw', 'th', 'final_height')
      FREEVARS: ()

        --- CODE OBJ: get_text_size ---
        CONSTANTS: (None, 'getbbox', 2, 0, 3, 1)
        NAMES: ('hasattr', 'getbbox', 'getsize')
        VARNAMES: ('text', 'font', 'bbox')
        FREEVARS: ()
